Workbook

Sheet Instrucciones
B2: Simulador de empresa de bolsos de cuero — Catalogo maestro de decisiones
B4: Como esta organizado este archivo:
B6: 1) Catalogo_Decisiones: TODAS las opciones posibles del juego. Cada opcion es una fila y cada dato (costo, aporte a cada puntaje) tiene su propia celda — nada esta combinado en una sola celda.
B7: 2) Seleccion_Ciclo0: aqui el jugador elige, por cada grupo de decision (maquinas, personal, canal, etc.), el codigo de la opcion que quiere (lista desplegable en la columna B). Las demas columnas se completan solas con formulas.
B8: 2b) Lotes_Produccion: aqui se decide la calidad POR LOTE, no como promedio de toda la empresa. Cada lote (hasta 3 por ciclo) tiene su propia cantidad de unidades, su propio cuero/accesorios/hilo/molde y su propio segmento de venta. El sistema calcula el Puntaje de Calidad de CADA lote y lo compara contra el segmento elegido (si vendes 'Premium' con insumos bajos, el lote sale 'No alcanza el segmento').
B9: 3) Motor_Puntajes: el Puntaje de Calidad de la empresa es el promedio de los lotes PONDERADO por las unidades de cada uno (un lote de 500 unidades pesa mas que uno de 50). Los otros 3 puntajes (Eficiencia, Reputacion, Salud Financiera) suman los aportes de Seleccion_Ciclo0.
B10: 4) Matriz_Consecuencias: reglas de negocio — que pasa (efecto numerico) y que mensaje ve el jugador segun el valor de cada puntaje.
B12: Celdas amarillas = donde se elige/edita (inputs). Celdas verdes = puntajes/aportes calculados. Celdas grises = fijas u obligatorias.
B14: Para agregar una opcion nueva: agrega una fila en Catalogo_Decisiones con su Codigo unico y sus aportes, y aparecera disponible para elegir en Seleccion_Ciclo0 (agregando el codigo a la lista desplegable del grupo correspondiente).

Sheet DECISIONES
B2: DECISIONES | C2: Puntaje
B3: Depreciación
B4: Garantía del producto
B5: Mantenimiento de maquinaria
B6: Política de inventarios

Sheet Seleccion_Ciclo0
A1: Grupo de decision | B1: Codigo elegido (elige de la lista) | C1: Opcion / Nivel (auto) | D1: Descripcion (auto) | E1: Costo referencial (auto) | F1: Aporte Calidad (auto) | G1: Aporte Eficiencia (auto) | H1: Aporte Reputacion (auto) | I1: Aporte Financiero (auto)
A2: Maquina de ensamblado | C2: {=IFERROR(INDEX(Catalogo_Decisiones!$D$2:$D$57,MATCH($B2,Catalogo_Decisiones!$A$2:$A$57,0)),"")} | D2: {=IFERROR(INDEX(Catalogo_Decisiones!$F$2:$F$57,MATCH($B2,Catalogo_Decisiones!$A$2:$A$57,0)),"")} | E2: {=IFERROR(INDEX(Catalogo_Decisiones!$G$2:$G$57,MATCH($B2,Catalogo_Decisiones!$A$2:$A$57,0)),0)} -> 0 | F2: {=IFERROR(INDEX(Catalogo_Decisiones!$H$2:$H$57,MATCH($B2,Catalogo_Decisiones!$A$2:$A$57,0)),0)} -> 0 | G2: {=IFERROR(INDEX(Catalogo_Decisiones!$I$2:$I$57,MATCH($B2,Catalogo_Decisiones!$A$2:$A$57,0)),0)} -> 0 | H2: {=IFERROR(INDEX(Catalogo_Decisiones!$J$2:$J$57,MATCH($B2,Catalogo_Decisiones!$A$2:$A$57,0)),0)} -> 0 | I2: {=IFERROR(INDEX(Catalogo_Decisiones!$K$2:$K$57,MATCH($B2,Catalogo_Decisiones!$A$2:$A$57,0)),0)} -> 0
A3: Maquina de acabados | C3: {=IFERROR(INDEX(Catalogo_Decisiones!$D$2:$D$57,MATCH($B3,Catalogo_Decisiones!$A$2:$A$57,0)),"")} | D3: {=IFERROR(INDEX(Catalogo_Decisiones!$F$2:$F$57,MATCH($B3,Catalogo_Decisiones!$A$2:$A$57,0)),"")} | E3: {=IFERROR(INDEX(Catalogo_Decisiones!$G$2:$G$57,MATCH($B3,Catalogo_Decisiones!$A$2:$A$57,0)),0)} -> 0 | F3: {=IFERROR(INDEX(Catalogo_Decisiones!$H$2:$H$57,MATCH($B3,Catalogo_Decisiones!$A$2:$A$57,0)),0)} -> 0 | G3: {=IFERROR(INDEX(Catalogo_Decisiones!$I$2:$I$57,MATCH($B3,Catalogo_Decisiones!$A$2:$A$57,0)),0)} -> 0 | H3: {=IFERROR(INDEX(Catalogo_Decisiones!$J$2:$J$57,MATCH($B3,Catalogo_Decisiones!$A$2:$A$57,0)),0)} -> 0 | I3: {=IFERROR(INDEX(Catalogo_Decisiones!$K$2:$K$57,MATCH($B3,Catalogo_Decisiones!$A$2:$A$57,0)),0)} -> 0
A4: Molde | C4: {=IFERROR(INDEX(Catalogo_Decisiones!$D$2:$D$57,MATCH($B4,Catalogo_Decisiones!$A$2:$A$57,0)),"")} | D4: {=IFERROR(INDEX(Catalogo_Decisiones!$F$2:$F$57,MATCH($B4,Catalogo_Decisiones!$A$2:$A$57,0)),"")} | E4: {=IFERROR(INDEX(Catalogo_Decisiones!$G$2:$G$57,MATCH($B4,Catalogo_Decisiones!$A$2:$A$57,0)),0)} -> 0 | F4: {=IFERROR(INDEX(Catalogo_Decisiones!$H$2:$H$57,MATCH($B4,Catalogo_Decisiones!$A$2:$A$57,0)),0)} -> 0 | G4: {=IFERROR(INDEX(Catalogo_Decisiones!$I$2:$I$57,MATCH($B4,Catalogo_Decisiones!$A$2:$A$57,0)),0)} -> 0 | H4: {=IFERROR(INDEX(Catalogo_Decisiones!$J$2:$J$57,MATCH($B4,Catalogo_Decisiones!$A$2:$A$57,0)),0)} -> 0 | I4: {=IFERROR(INDEX(Catalogo_Decisiones!$K$2:$K$57,MATCH($B4,Catalogo_Decisiones!$A$2:$A$57,0)),0)} -> 0
A5: Personal de corte | C5: {=IFERROR(INDEX(Catalogo_Decisiones!$D$2:$D$57,MATCH($B5,Catalogo_Decisiones!$A$2:$A$57,0)),"")} | D5: {=IFERROR(INDEX(Catalogo_Decisiones!$F$2:$F$57,MATCH($B5,Catalogo_Decisiones!$A$2:$A$57,0)),"")} | E5: {=IFERROR(INDEX(Catalogo_Decisiones!$G$2:$G$57,MATCH($B5,Catalogo_Decisiones!$A$2:$A$57,0)),0)} -> 0 | F5: {=IFERROR(INDEX(Catalogo_Decisiones!$H$2:$H$57,MATCH($B5,Catalogo_Decisiones!$A$2:$A$57,0)),0)} -> 0 | G5: {=IFERROR(INDEX(Catalogo_Decisiones!$I$2:$I$57,MATCH($B5,Catalogo_Decisiones!$A$2:$A$57,0)),0)} -> 0 | H5: {=IFERROR(INDEX(Catalogo_Decisiones!$J$2:$J$57,MATCH($B5,Catalogo_Decisiones!$A$2:$A$57,0)),0)} -> 0 | I5: {=IFERROR(INDEX(Catalogo_Decisiones!$K$2:$K$57,MATCH($B5,Catalogo_Decisiones!$A$2:$A$57,0)),0)} -> 0
A6: Personal de ensamble | C6: {=IFERROR(INDEX(Catalogo_Decisiones!$D$2:$D$57,MATCH($B6,Catalogo_Decisiones!$A$2:$A$57,0)),"")} | D6: {=IFERROR(INDEX(Catalogo_Decisiones!$F$2:$F$57,MATCH($B6,Catalogo_Decisiones!$A$2:$A$57,0)),"")} | E6: {=IFERROR(INDEX(Catalogo_Decisiones!$G$2:$G$57,MATCH($B6,Catalogo_Decisiones!$A$2:$A$57,0)),0)} -> 0 | F6: {=IFERROR(INDEX(Catalogo_Decisiones!$H$2:$H$57,MATCH($B6,Catalogo_Decisiones!$A$2:$A$57,0)),0)} -> 0 | G6: {=IFERROR(INDEX(Catalogo_Decisiones!$I$2:$I$57,MATCH($B6,Catalogo_Decisiones!$A$2:$A$57,0)),0)} -> 0 | H6: {=IFERROR(INDEX(Catalogo_Decisiones!$J$2:$J$57,MATCH($B6,Catalogo_Decisiones!$A$2:$A$57,0)),0)} -> 0 | I6: {=IFERROR(INDEX(Catalogo_Decisiones!$K$2:$K$57,MATCH($B6,Catalogo_Decisiones!$A$2:$A$57,0)),0)} -> 0
A7: Personal de acabados | C7: {=IFERROR(INDEX(Catalogo_Decisiones!$D$2:$D$57,MATCH($B7,Catalogo_Decisiones!$A$2:$A$57,0)),"")} | D7: {=IFERROR(INDEX(Catalogo_Decisiones!$F$2:$F$57,MATCH($B7,Catalogo_Decisiones!$A$2:$A$57,0)),"")} | E7: {=IFERROR(INDEX(Catalogo_Decisiones!$G$2:$G$57,MATCH($B7,Catalogo_Decisiones!$A$2:$A$57,0)),0)} -> 0 | F7: {=IFERROR(INDEX(Catalogo_Decisiones!$H$2:$H$57,MATCH($B7,Catalogo_Decisiones!$A$2:$A$57,0)),0)} -> 0 | G7: {=IFERROR(INDEX(Catalogo_Decisiones!$I$2:$I$57,MATCH($B7,Catalogo_Decisiones!$A$2:$A$57,0)),0)} -> 0 | H7: {=IFERROR(INDEX(Catalogo_Decisiones!$J$2:$J$57,MATCH($B7,Catalogo_Decisiones!$A$2:$A$57,0)),0)} -> 0 | I7: {=IFERROR(INDEX(Catalogo_Decisiones!$K$2:$K$57,MATCH($B7,Catalogo_Decisiones!$A$2:$A$57,0)),0)} -> 0
A8: Jefatura | C8: {=IFERROR(INDEX(Catalogo_Decisiones!$D$2:$D$57,MATCH($B8,Catalogo_Decisiones!$A$2:$A$57,0)),"")} | D8: {=IFERROR(INDEX(Catalogo_Decisiones!$F$2:$F$57,MATCH($B8,Catalogo_Decisiones!$A$2:$A$57,0)),"")} | E8: {=IFERROR(INDEX(Catalogo_Decisiones!$G$2:$G$57,MATCH($B8,Catalogo_Decisiones!$A$2:$A$57,0)),0)} -> 0 | F8: {=IFERROR(INDEX(Catalogo_Decisiones!$H$2:$H$57,MATCH($B8,Catalogo_Decisiones!$A$2:$A$57,0)),0)} -> 0 | G8: {=IFERROR(INDEX(Catalogo_Decisiones!$I$2:$I$57,MATCH($B8,Catalogo_Decisiones!$A$2:$A$57,0)),0)} -> 0 | H8: {=IFERROR(INDEX(Catalogo_Decisiones!$J$2:$J$57,MATCH($B8,Catalogo_Decisiones!$A$2:$A$57,0)),0)} -> 0 | I8: {=IFERROR(INDEX(Catalogo_Decisiones!$K$2:$K$57,MATCH($B8,Catalogo_Decisiones!$A$2:$A$57,0)),0)} -> 0
A9: Canal de venta | C9: {=IFERROR(INDEX(Catalogo_Decisiones!$D$2:$D$57,MATCH($B9,Catalogo_Decisiones!$A$2:$A$57,0)),"")} | D9: {=IFERROR(INDEX(Catalogo_Decisiones!$F$2:$F$57,MATCH($B9,Catalogo_Decisiones!$A$2:$A$57,0)),"")} | E9: {=IFERROR(INDEX(Catalogo_Decisiones!$G$2:$G$57,MATCH($B9,Catalogo_Decisiones!$A$2:$A$57,0)),0)} -> 0 | F9: {=IFERROR(INDEX(Catalogo_Decisiones!$H$2:$H$57,MATCH($B9,Catalogo_Decisiones!$A$2:$A$57,0)),0)} -> 0 | G9: {=IFERROR(INDEX(Catalogo_Decisiones!$I$2:$I$57,MATCH($B9,Catalogo_Decisiones!$A$2:$A$57,0)),0)} -> 0 | H9: {=IFERROR(INDEX(Catalogo_Decisiones!$J$2:$J$57,MATCH($B9,Catalogo_Decisiones!$A$2:$A$57,0)),0)} -> 0 | I9: {=IFERROR(INDEX(Catalogo_Decisiones!$K$2:$K$57,MATCH($B9,Catalogo_Decisiones!$A$2:$A$57,0)),0)} -> 0
A10: Acceso a prestamo bancario | C10: {=IFERROR(INDEX(Catalogo_Decisiones!$D$2:$D$57,MATCH($B10,Catalogo_Decisiones!$A$2:$A$57,0)),"")} | D10: {=IFERROR(INDEX(Catalogo_Decisiones!$F$2:$F$57,MATCH($B10,Catalogo_Decisiones!$A$2:$A$57,0)),"")} | E10: {=IFERROR(INDEX(Catalogo_Decisiones!$G$2:$G$57,MATCH($B10,Catalogo_Decisiones!$A$2:$A$57,0)),0)} -> 0 | F10: {=IFERROR(INDEX(Catalogo_Decisiones!$H$2:$H$57,MATCH($B10,Catalogo_Decisiones!$A$2:$A$57,0)),0)} -> 0 | G10: {=IFERROR(INDEX(Catalogo_Decisiones!$I$2:$I$57,MATCH($B10,Catalogo_Decisiones!$A$2:$A$57,0)),0)} -> 0 | H10: {=IFERROR(INDEX(Catalogo_Decisiones!$J$2:$J$57,MATCH($B10,Catalogo_Decisiones!$A$2:$A$57,0)),0)} -> 0 | I10: {=IFERROR(INDEX(Catalogo_Decisiones!$K$2:$K$57,MATCH($B10,Catalogo_Decisiones!$A$2:$A$57,0)),0)} -> 0
A11: Numero de proveedores | C11: {=IFERROR(INDEX(Catalogo_Decisiones!$D$2:$D$57,MATCH($B11,Catalogo_Decisiones!$A$2:$A$57,0)),"")} | D11: {=IFERROR(INDEX(Catalogo_Decisiones!$F$2:$F$57,MATCH($B11,Catalogo_Decisiones!$A$2:$A$57,0)),"")} | E11: {=IFERROR(INDEX(Catalogo_Decisiones!$G$2:$G$57,MATCH($B11,Catalogo_Decisiones!$A$2:$A$57,0)),0)} -> 0 | F11: {=IFERROR(INDEX(Catalogo_Decisiones!$H$2:$H$57,MATCH($B11,Catalogo_Decisiones!$A$2:$A$57,0)),0)} -> 0 | G11: {=IFERROR(INDEX(Catalogo_Decisiones!$I$2:$I$57,MATCH($B11,Catalogo_Decisiones!$A$2:$A$57,0)),0)} -> 0 | H11: {=IFERROR(INDEX(Catalogo_Decisiones!$J$2:$J$57,MATCH($B11,Catalogo_Decisiones!$A$2:$A$57,0)),0)} -> 0 | I11: {=IFERROR(INDEX(Catalogo_Decisiones!$K$2:$K$57,MATCH($B11,Catalogo_Decisiones!$A$2:$A$57,0)),0)} -> 0
A12: Politica de pago a proveedores | C12: {=IFERROR(INDEX(Catalogo_Decisiones!$D$2:$D$57,MATCH($B12,Catalogo_Decisiones!$A$2:$A$57,0)),"")} | D12: {=IFERROR(INDEX(Catalogo_Decisiones!$F$2:$F$57,MATCH($B12,Catalogo_Decisiones!$A$2:$A$57,0)),"")} | E12: {=IFERROR(INDEX(Catalogo_Decisiones!$G$2:$G$57,MATCH($B12,Catalogo_Decisiones!$A$2:$A$57,0)),0)} -> 0 | F12: {=IFERROR(INDEX(Catalogo_Decisiones!$H$2:$H$57,MATCH($B12,Catalogo_Decisiones!$A$2:$A$57,0)),0)} -> 0 | G12: {=IFERROR(INDEX(Catalogo_Decisiones!$I$2:$I$57,MATCH($B12,Catalogo_Decisiones!$A$2:$A$57,0)),0)} -> 0 | H12: {=IFERROR(INDEX(Catalogo_Decisiones!$J$2:$J$57,MATCH($B12,Catalogo_Decisiones!$A$2:$A$57,0)),0)} -> 0 | I12: {=IFERROR(INDEX(Catalogo_Decisiones!$K$2:$K$57,MATCH($B12,Catalogo_Decisiones!$A$2:$A$57,0)),0)} -> 0
A13: Lead time | C13: {=IFERROR(INDEX(Catalogo_Decisiones!$D$2:$D$57,MATCH($B13,Catalogo_Decisiones!$A$2:$A$57,0)),"")} | D13: {=IFERROR(INDEX(Catalogo_Decisiones!$F$2:$F$57,MATCH($B13,Catalogo_Decisiones!$A$2:$A$57,0)),"")} | E13: {=IFERROR(INDEX(Catalogo_Decisiones!$G$2:$G$57,MATCH($B13,Catalogo_Decisiones!$A$2:$A$57,0)),0)} -> 0 | F13: {=IFERROR(INDEX(Catalogo_Decisiones!$H$2:$H$57,MATCH($B13,Catalogo_Decisiones!$A$2:$A$57,0)),0)} -> 0 | G13: {=IFERROR(INDEX(Catalogo_Decisiones!$I$2:$I$57,MATCH($B13,Catalogo_Decisiones!$A$2:$A$57,0)),0)} -> 0 | H13: {=IFERROR(INDEX(Catalogo_Decisiones!$J$2:$J$57,MATCH($B13,Catalogo_Decisiones!$A$2:$A$57,0)),0)} -> 0 | I13: {=IFERROR(INDEX(Catalogo_Decisiones!$K$2:$K$57,MATCH($B13,Catalogo_Decisiones!$A$2:$A$57,0)),0)} -> 0
... A15: Inversion en marketing | C15: {=IFERROR(INDEX(Catalogo_Decisiones!$D$2:$D$57,MATCH($B15,Catalogo_Decisiones!$A$2:$A$57,0)),"")} | D15: {=IFERROR(INDEX(Catalogo_Decisiones!$F$2:$F$57,MATCH($B15,Catalogo_Decisiones!$A$2:$A$57,0)),"")} | E15: {=IFERROR(INDEX(Catalogo_Decisiones!$G$2:$G$57,MATCH($B15,Catalogo_Decisiones!$A$2:$A$57,0)),0)} -> 0 | F15: {=IFERROR(INDEX(Catalogo_Decisiones!$H$2:$H$57,MATCH($B15,Catalogo_Decisiones!$A$2:$A$57,0)),0)} -> 0 | G15: {=IFERROR(INDEX(Catalogo_Decisiones!$I$2:$I$57,MATCH($B15,Catalogo_Decisiones!$A$2:$A$57,0)),0)} -> 0 | H15: {=IFERROR(INDEX(Catalogo_Decisiones!$J$2:$J$57,MATCH($B15,Catalogo_Decisiones!$A$2:$A$57,0)),0)} -> 0 | I15: {=IFERROR(INDEX(Catalogo_Decisiones!$K$2:$K$57,MATCH($B15,Catalogo_Decisiones!$A$2:$A$57,0)),0)} -> 0
A16: --- Otras decisiones numericas ---
A17: PRO-01 - Cantidad inicial a producir (unidades) | B17: 0
A18: COM-02 - N° de tiendas en zona alta (Miraflores) | B18: 0
A19: COM-03 - N° de tiendas en zona media (Los Olivos / San Miguel) | B19: 0
A20: COM-04 - N° de tiendas en zona baja (SJL / SMP) | B20: 0
A21: COM-05N - % de ventas a credito (0-100) | B21: 0
A22: FIN-01M - Monto de prestamo solicitado (S/) | B22: 0

Sheet Catalogo_Decisiones
A1: Codigo | B1: Bloque | C1: Grupo de decision | D1: Opcion / Nivel | E1: Permanencia | F1: Descripcion | G1: Costo referencial (S/) | H1: Aporte Calidad | I1: Aporte Eficiencia | J1: Aporte Reputacion | K1: Aporte Financiero | L1: Notas
A2: GEN-01 | B2: A. Empresa | C2: Razon social | D2: Texto libre | E2: Fija | F2: Nombre legal de la empresa (texto) | G2: 0 | H2: 0 | I2: 0 | J2: 0 | K2: 0 | L2: Sin efecto en puntajes
A3: GEN-02 | B3: A. Empresa | C3: Nombre comercial / marca | D3: Texto libre | E3: Fija | F3: Marca comercial (texto) | G3: 0 | H3: 0 | I3: 0 | J3: 0 | K3: 0 | L3: Sin efecto en puntajes
A4: GEN-04 | B4: A. Empresa | C4: Tipos de bolsos | D4: Texto libre | E4: Fija | F4: Linea de productos que fabrica (tote, cartera, mochila, etc.) | G4: 0 | H4: 0 | I4: 0 | J4: 0 | K4: 0 | L4: Sin efecto en puntajes
A5: SEG-01 | B5: A. Empresa | C5: Segmento / linea | D5: Economico | E5: Fija | F5: Precio bajo, prioriza volumen y costo | G5: 0 | H5: 0 | I5: 0 | J5: 1 | K5: 0 | L5: Exige coherencia con Calidad real
A6: SEG-02 | B6: A. Empresa | C6: Segmento / linea | D6: Estandar | E6: Fija | F6: Equilibra costo, calidad, demanda y margen | G6: 0 | H6: 1 | I6: 0 | J6: 1 | K6: 0
A7: SEG-03 | B7: A. Empresa | C7: Segmento / linea | D7: Premium | E7: Fija | F7: Precio alto; requiere Calidad>=7 para sostenerse | G7: 0 | H7: 2 | I7: 0 | J7: 2 | K7: 0 | L7: Riesgo si Calidad interna es baja (ver Matriz)
A8: INF-01 | B8: B. Infraestructura | C8: Mesa de corte | D8: Unica (obligatoria) | E8: Fija | F8: Inversion fija para todos; habilita la etapa de corte | G8: 2500 | H8: 0 | I8: 1 | J8: 0 | K8: 0 | L8: Obligatoria, no otorga niveles
A9: INF-02 | B9: B. Infraestructura | C9: Maquina de ensamblado | D9: Nivel 1: manual/basica | E9: Fija | F9: Costura Singer 4423 Heavy Duty; desbastadora a mano con cuchilla o lija | G9: 3500 | H9: 1 | I9: 1 | J9: 0 | K9: 0
A10: INF-03 | B10: B. Infraestructura | C10: Maquina de ensamblado | D10: Nivel 2: semi-industrial | E10: Fija | F10: Maquina de coser de columna/brazo (poste) Typical TB-801 | G10: 7500 | H10: 2 | I10: 2 | J10: 0 | K10: 0
A11: INF-04 | B11: B. Infraestructura | C11: Maquina de ensamblado | D11: Nivel 3: industrial | E11: Fija | F11: Juki de triple accionamiento; desbastadora automatica de alta precision, servomotor | G11: 15000 | H11: 3 | I11: 3 | J11: 0 | K11: 0
A12: INF-05 | B12: B. Infraestructura | C12: Maquina de acabados | D12: Nivel 1: manual/basica | E12: Fija | F12: Acabado a mano con cera/tinte de bordes, bruñido manual. Lento, variable en calidad | G12: 1200 | H12: 1 | I12: 1 | J12: 0 | K12: 0
A13: INF-06 | B13: B. Infraestructura | C13: Maquina de acabados | D13: Nivel 2: semi-industrial | E13: Fija | F13: Maquina de pulido de bordes (edge burnisher) electrica, tinte con pincel/aerografo | G13: 4500 | H13: 2 | I13: 2 | J13: 0 | K13: 0
A14: INF-07 | B14: B. Infraestructura | C14: Maquina de acabados | D14: Nivel 3: industrial | E14: Fija | F14: Linea de acabado con teñido automatico + pulido, control de temperatura y velocidad | G14: 9500 | H14: 3 | I14: 3 | J14: 0 | K14: 0
A15: INF-08 | B15: B. Infraestructura | C15: Molde | D15: Nivel 1 - Generico basico | E15: Fija | F15: Patrones simples, tipo plantilla estandar de internet o catalogo generico | G15: 300 | H15: 1 | I15: 1 | J15: 0 | K15: 0 | L15: Bajo aprovechamiento de cuero
A16: INF-09 | B16: B. Infraestructura | C16: Molde | D16: Nivel 2 - Generico mejorado | E16: Fija | F16: Patron tecnico mas elaborado, con lineas de corte, marcado y perforaciones bien definidas | G16: 1200 | H16: 2 | I16: 2 | J16: 1 | K16: 0 | L16: Aprovechamiento medio-alto
A17: INF-10 | B17: B. Infraestructura | C17: Molde | D17: Nivel 3 - Premium | E17: Fija | F17: La empresa desarrolla su propio patron desde cero, adaptado a su propuesta de marca | G17: 3500 | H17: 4 | I17: 2 | J17: 2 | K17: 0 | L17: Maximo aprovechamiento y diferenciacion
A18: RH-01 | B18: C. RRHH | C18: Personal de corte | D18: Nivel 1 - Operario basico | E18: Revisable con costo | F18: Corta con plantilla simple, sin experiencia previa. Mas lento, mas margen de error | G18: 1500 | H18: 0 | I18: 1 | J18: 0 | K18: 0
A19: RH-02 | B19: C. RRHH | C19: Personal de corte | D19: Nivel 2 - Cortador con experiencia | E19: Revisable con costo | F19: Optimiza el aprovechamiento del cuero, reduce desperdicio, mas rapido | G19: 2500 | H19: 1 | I19: 2 | J19: 0 | K19: 0
A20: RH-03 | B20: C. RRHH | C20: Personal de corte | D20: Nivel 3 - Maestro cortador | E20: Revisable con costo | F20: Trabaja cueros irregulares/premium, maximo aprovechamiento, minimo desperdicio | G20: 4000 | H20: 2 | I20: 3 | J20: 0 | K20: 0
A21: RH-04 | B21: C. RRHH | C21: Personal de ensamble | D21: Nivel 1 - Costurero basico | E21: Revisable con costo | F21: Maquina domestica, puntadas rectas simples, funciona con diseños sencillos | G21: 1500 | H21: 0 | I21: 1 | J21: 0 | K21: 0
A22: RH-05 | B22: C. RRHH | C22: Personal de ensamble | D22: Nivel 2 - Maquinista industrial | E22: Revisable con costo | F22: Maquina semi-industrial/industrial, costuras reforzadas, mayor velocidad | G22: 2800 | H22: 1 | I22: 2 | J22: 0 | K22: 0
A23: RH-06 | B23: C. RRHH | C23: Personal de ensamble | D23: Nivel 3 - Marroquinero especializado | E23: Revisable con costo | F23: Costura a mano de alta gama, ejecuta moldes exclusivos complejos, ideal linea premium | G23: 4500 | H23: 2 | I23: 3 | J23: 1 | K23: 0
A24: RH-07 | B24: C. RRHH | C24: Personal de acabados | D24: Nivel 1 - Operario de acabado basico | E24: Revisable con costo | F24: Aplica tinte y cera de forma simple, resultado variable | G24: 1500 | H24: 0 | I24: 1 | J24: 0 | K24: 0
A25: RH-08 | B25: C. RRHH | C25: Personal de acabados | D25: Nivel 2 - Tecnico en acabados | E25: Revisable con costo | F25: Maneja maquina de pulido de bordes, tinte con aerografo, resultado consistente | G25: 2800 | H25: 1 | I25: 2 | J25: 0 | K25: 0
A26: RH-09 | B26: C. RRHH | C26: Personal de acabados | D26: Nivel 3 - Artesano acabador | E26: Revisable con costo | F26: Bruñido fino, dorado, decoracion compleja (pedreria, herrajes especiales) | G26: 4500 | H26: 2 | I26: 3 | J26: 1 | K26: 0
A27: RH-10A | B27: C. RRHH | C27: Jefatura | D27: Contratar jefatura | E27: Revisable con costo | F27: Coordina el equipo, reduce riesgo de descoordinacion | G27: 3000 | H27: 0 | I27: 2 | J27: 1 | K27: 0
A28: RH-10B | B28: C. RRHH | C28: Jefatura | D28: No contratar jefatura | E28: Revisable con costo | F28: Ahorra costo fijo, pero aumenta el riesgo de descoordinacion | G28: 0 | H28: 0 | I28: -1 | J28: 0 | K28: 1 | L28: Ahorro de caja pero baja Eficiencia
A29: RH-11 | B29: C. RRHH | C29: Limpieza y servicios generales | D29: Unica (obligatoria) | E29: Fija | F29: Monto fijo obligatorio para mantener la operacion | G29: 600 | H29: 0 | I29: 0 | J29: 0 | K29: 0
A30: RH-12 | B30: C. RRHH | C30: Local de produccion | D30: Estandar (unico) | E30: Fija | F30: Local de produccion estandar; alquiler fijo igual para todos los equipos | G30: 2000 | H30: 0 | I30: 0 | J30: 0 | K30: 0
A31: COM-01A | B31: D. Canales | C31: Canal de venta | D31: Solo tienda fisica | E31: Revisable cada ciclo | F31: Menor cobertura y demanda; menor complejidad y costo | G31: 0 | H31: 0 | I31: 0 | J31: 0 | K31: 1
A32: COM-01B | B32: D. Canales | C32: Canal de venta | D32: Solo web | E32: Revisable cada ciclo | F32: Cobertura amplia con menor costo fijo; depende de marketing digital | G32: 500 | H32: 0 | I32: 0 | J32: 1 | K32: 0
A33: COM-01C | B33: D. Canales | C33: Canal de venta | D33: Web y fisico | E33: Revisable cada ciclo | F33: Mayor cobertura y demanda; incrementa complejidad y costo | G33: 1500 | H33: 0 | I33: 0 | J33: 2 | K33: -1
A34: FIN-01A | B34: D. Canales | C34: Acceso a prestamo bancario | D34: Solicitar prestamo | E34: Fija: habilita | F34: Habilita apalancamiento; permite invertir mas rapido | G34: 0 | H34: 0 | I34: 0 | J34: 0 | K34: -1 | L34: Aumenta apalancamiento
A35: FIN-01B | B35: D. Canales | C35: Acceso a prestamo bancario | D35: No solicitar prestamo | E35: Fija: habilita | F35: Evita intereses; la expansion depende del capital propio | G35: 0 | H35: 0 | I35: 0 | J35: 1 | K35: 1
A36: INS-01 | B36: E. Insumos | C36: Calidad del cuero | D36: Nivel 1 - Cuero sintetico | E36: Revisable cada ciclo | F36: Bajo costo, menor durabilidad, acabado menos premium | G36: 25 | H36: 1 | I36: 0 | J36: 0 | K36: 1 | L36: por unidad, referencial
A37: INS-02 | B37: E. Insumos | C37: Calidad del cuero | D37: Nivel 2 - Cuero genuino estandar | E37: Revisable cada ciclo | F37: Costo medio, durabilidad media | G37: 45 | H37: 2 | I37: 0 | J37: 0 | K37: 0 | L37: por unidad, referencial
A38: INS-03 | B38: E. Insumos | C38: Calidad del cuero | D38: Nivel 3 - Cuero genuino premium | E38: Revisable cada ciclo | F38: Full grain / curtido vegetal: alto costo, alta durabilidad, mejor acabado | G38: 80 | H38: 3 | I38: 0 | J38: 1 | K38: -1 | L38: por unidad, referencial
A39: INS-04 | B39: E. Insumos | C39: Calidad de accesorios | D39: Nivel 1 - Aleacion economica | E39: Revisable cada ciclo | F39: Bajo costo, se oxida/desgasta mas rapido | G39: 4 | H39: 1 | I39: 0 | J39: 0 | K39: 1 | L39: por unidad, referencial
A40: INS-05 | B40: E. Insumos | C40: Calidad de accesorios | D40: Nivel 2 - Metal premium | E40: Revisable cada ciclo | F40: Laton macizo o acero inoxidable, alto costo, mayor durabilidad y brillo | G40: 9 | H40: 2 | I40: 0 | J40: 1 | K40: -1 | L40: por unidad, referencial
A41: INS-06 | B41: E. Insumos | C41: Calidad del hilo | D41: Nivel 1 - Poliester estandar | E41: Revisable cada ciclo | F41: Economico, resistencia media | G41: 2 | H41: 1 | I41: 0 | J41: 0 | K41: 1 | L41: por unidad, referencial
A42: INS-07 | B42: E. Insumos | C42: Calidad del hilo | D42: Nivel 2 - Encerado reforzado | E42: Revisable cada ciclo | F42: Costo medio, mayor resistencia a tension | G42: 4 | H42: 2 | I42: 0 | J42: 0 | K42: 0 | L42: por unidad, referencial
A43: INS-08 | B43: E. Insumos | C43: Calidad del hilo | D43: Nivel 3 - Alta tenacidad (nylon trenzado) | E43: Revisable cada ciclo | F43: Costoso, maxima durabilidad, ideal para costura visible/detalle | G43: 7 | H43: 3 | I43: 0 | J43: 1 | K43: -1 | L43: por unidad, referencial
A44: INS-09A | B44: E. Insumos | C44: Numero de proveedores | D44: Proveedor unico | E44: Revisable cada ciclo | F44: Obtiene 2% adicional de descuento, pero concentra el riesgo de abastecimiento | G44: 0 | H44: 0 | I44: 0 | J44: 0 | K44: 1 | L44: Riesgo de desabastecimiento
A45: INS-09B | B45: E. Insumos | C45: Numero de proveedores | D45: Varios proveedores | E45: Revisable cada ciclo | F45: Menor descuento, pero reduce el riesgo de desabastecimiento | G45: 0 | H45: 0 | I45: 1 | J45: 0 | K45: 0
A46: INS-10A | B46: E. Insumos | C46: Politica de pago a proveedores | D46: Contado | E46: Revisable cada ciclo | F46: Obtiene 3% de descuento; reduce la caja inmediatamente | G46: 0 | H46: 0 | I46: 0 | J46: 0 | K46: -1
A47: INS-10B | B47: E. Insumos | C47: Politica de pago a proveedores | D47: Credito | E47: Revisable cada ciclo | F47: Sin descuento; conserva liquidez en el ciclo | G47: 0 | H47: 0 | I47: 0 | J47: 0 | K47: 1
A48: INS-11A | B48: E. Insumos | C48: Lead time | D48: Rapido (urgente, con sobrecosto) | E48: Revisable cada ciclo | F48: Entrega en menos dias, pero con sobrecosto | G48: 0 | H48: 0 | I48: 1 | J48: 0 | K48: -1
A49: INS-11B | B49: E. Insumos | C49: Lead time | D49: Normal - 7 dias | E49: Revisable cada ciclo | F49: Equilibrio entre costo y disponibilidad | G49: 0 | H49: 0 | I49: 0 | J49: 0 | K49: 0
A50: INS-11C | B50: E. Insumos | C50: Lead time | D50: Lento (economico) | E50: Revisable cada ciclo | F50: Menor costo, mayor riesgo de quiebre de stock | G50: 0 | H50: 0 | I50: -1 | J50: 0 | K50: 1
A51: COM-05 | B51: D. Canales | C51: % de ventas a credito | D51: 20% a credito (referencia) | E51: Revisable cada ciclo | F51: Balancea liquidez y ventas; riesgo de cobranza bajo | G51: 0 | H51: 0 | I51: 0 | J51: 1 | K51: -1 | L51: Valor ingresado por el jugador en hoja Seleccion
A52: INV-01A | B52: F. Inversiones | C52: Inversion en RR.HH. | D52: Baja | E52: Revisable cada ciclo | F52: Poca capacitacion tecnica | G52: 1000 | H52: 0 | I52: 1 | J52: 0 | K52: -1
A53: INV-01B | B53: F. Inversiones | C53: Inversion en RR.HH. | D53: Media | E53: Revisable cada ciclo | F53: Capacitacion tecnica: +8% de capacidad y mejor reputacion | G53: 6000 | H53: 0 | I53: 2 | J53: 1 | K53: -1
A54: INV-01C | B54: F. Inversiones | C54: Inversion en RR.HH. | D54: Alta | E54: Revisable cada ciclo | F54: Capacitacion avanzada: mayor capacidad y reputacion, alto costo | G54: 12000 | H54: 0 | I54: 3 | J54: 2 | K54: -2
A55: INV-02A | B55: F. Inversiones | C55: Inversion en marketing | D55: Baja | E55: Revisable cada ciclo | F55: Poca visibilidad de marca | G55: 1500 | H55: 0 | I55: 0 | J55: 1 | K55: -1
A56: INV-02B | B56: F. Inversiones | C56: Inversion en marketing | D56: Media | E56: Revisable cada ciclo | F56: S/ 6,000 por ciclo; aumenta demanda estimada 12% y reputacion | G56: 6000 | H56: 0 | I56: 0 | J56: 2 | K56: -1
A57: INV-02C | B57: F. Inversiones | C57: Inversion en marketing | D57: Alta | E57: Revisable cada ciclo | F57: Alto costo; mayor aumento de demanda y reputacion | G57: 12000 | H57: 0 | I57: 0 | J57: 3 | K57: -2
A58: FIN-02A | B58: G. Finanzas | C58: Método de depreciación | D58: Línea recta | E58: Fija en Ciclo 0 | F58: Distribuye el valor depreciable de la maquinaria en cuotas iguales durante su vida útil | G58: S/0 | H58: 0 | I58: 0 | J58: 0 | K58: 0 | L58: Gasto contable constante; no representa una salida de efectivo
A59: FIN-02B | B59: G. Finanzas | C59: Método de depreciación | D59: Unidades producidas | E59: Fija en Ciclo 0 | F59: Calcula la depreciación según el uso real de la maquinaria y las unidades fabricadas | G59: S/0 | H59: 0 | I59: 0 | J59: 0 | K59: =+1 -> 1 | L59: Mejora la asignación del costo por unidad; no representa una salida de efectivo
A60: FIN-02C | B60: G. Finanzas | C60: Método de depreciación | D60: Acelerada | E60: Fija en Ciclo 0 | F60: Reconoce una mayor depreciación durante los primeros ciclos y una menor depreciación después | G60: S/0 | H60: 0 | I60: 0 | J60: 0 | K60: -1 | L60: Reduce la utilidad contable inicial; no representa una salida de efectivo
A61: COM-06A | B61: D. Canales | C61: Garantía del producto | D61: Sin garantía | E61: Revisable cada ciclo | F61: No cubre fallas posteriores a la venta; reduce el costo inmediato, pero genera desconfianza | G61: S/0 | H61: 0 | I61: 0 | J61: -1 | K61: =+1 -> 1 | L61: Mayor riesgo de reclamos y pérdida de clientes
A62: COM-06B | B62: D. Canales | C62: Garantía del producto | D62: Garantía de 30 días | E62: Revisable cada ciclo | F62: Cubre defectos de fabricación durante 30 días y brinda seguridad básica al cliente | G62: S/5 | H62: 0 | I62: 0 | J62: =+1 -> 1 | K62: 0 | L62: Costo referencial por unidad vendida para atender cambios o reparaciones
A63: COM-06C | B63: D. Canales | C63: Garantía del producto | D63: Garantía de 90 días | E63: Revisable cada ciclo | F63: Cubre defectos durante 90 días; aumenta la confianza, pero exige una mayor provisión | G63: S/10 | H63: 0 | I63: 0 | J63: =+2 -> 2 | K63: -1 | L63: Costo referencial por unidad vendida; mayor exposición a devoluciones
A64: INF-11A | B64: B. Infraestructura | C64: Mantenimiento de maquinaria | D64: Solo correctivo | E64: Revisable cada ciclo | F64: La empresa repara las máquinas únicamente cuando presentan una falla | G64: S/0 | H64: 0 | I64: -1 | J64: 0 | K64: =+1 -> 1 | L64: Ahorra al inicio, pero aumenta el riesgo de paradas y retrasos
A65: INF-11B | B65: B. Infraestructura | C65: Mantenimiento de maquinaria | D65: Preventivo básico | E65: Revisable cada ciclo | F65: Incluye revisión, limpieza, lubricación y ajustes básicos para prevenir fallas | G65: S/1,500 | H65: 0 | I65: =+1 -> 1 | J65: 0 | K65: 0 | L65: Costo referencial por ciclo; reduce parcialmente las averías
A66: INF-11C | B66: B. Infraestructura | C66: Mantenimiento de maquinaria | D66: Preventivo integral | E66: Revisable cada ciclo | F66: Incluye mantenimiento programado, cambio de piezas críticas y calibración de equipos | G66: S/3,000 | H66: =+1 -> 1 | I66: =+2 -> 2 | J66: 0 | K66: -1 | L66: Costo referencial por ciclo; minimiza paradas y defectos de fabricación
A67: INS-12A | B67: E. Insumos | C67: Política de inventarios | D67: Justo a tiempo | E67: Revisable cada ciclo | F67: Mantiene inventario mínimo y compra cerca de la fecha de producción | G67: S/0 | H67: 0 | I67: -1 | J67: 0 | K67: =+1 -> 1 | L67: Menor dinero inmovilizado, pero mayor riesgo de quedarse sin insumos
A68: INS-12B | B68: E. Insumos | C68: Política de inventarios | D68: Stock de seguridad medio | E68: Revisable cada ciclo | F68: Mantiene una reserva moderada para cubrir retrasos del proveedor o cambios de demanda | G68: S/1,000 | H68: 0 | I68: =+1 -> 1 | J68: 0 | K68: 0 | L68: Costo referencial de almacenamiento por ciclo; alternativa equilibrada
A69: INS-12C | B69: E. Insumos | C69: Política de inventarios | D69: Stock de seguridad alto | E69: Revisable cada ciclo | F69: Mantiene una reserva amplia de materiales para evitar interrupciones de producción | G69: S/2,500 | H69: 0 | I69: =+2 -> 2 | J69: 0 | K69: -1 | L69: Reduce quiebres de stock, pero inmoviliza más efectivo y aumenta el almacenaje

Sheet FlujoWeb
B3: Flujo
B4: Steps | C4: Docente | D4: Jugadores | H4: Valeria y Gonzalo
B5: 1 | C5: Launcher | H5: Erick y Miguel
B6: 2 | C6: Login | E6: Se valida el codigo de sala y el nombre empresa(usuario)
B7: 3 | C7: Configuracion del juego (incluye Creacion de Sala)
B8: 4 | D8: Launcher
B9: 5 | D9: Login
B10: 6 | D10: Tutorial | E10: Indicaciones en un carrusel.
A11: Ciclo 1 | B11: 7 | D11: Decisiones
B12: 8 | D12: Espera (Fin de ciclo) | E12: El docente define si se hace automatico o manual
B13: 9 | C13: Información en vivo de las decisiones de los jugadores (Manual: Cierra el ciclo)
B14: 10 | C14: Estados financieros Generales | D14: Estados financieros Individuales e Informacion del mercado | E14: Descargables en pdf
A15: Ciclo 2 | B15: 11 | D15: Decisiones
B16: 12 | D16: Espera (Fin de ciclo)
B17: 13 | C17: Información en vivo de las decisiones de los jugadores (Manual: Cierra el ciclo)
B18: 14 | C18: Estados financieros Generales | D18: Estados financieros Individuales e Informacion del mercado | E18: Descargables en pdf
A19: Ciclo 3 | B19: 15 | D19: Decisiones
B20: 16 | D20: Espera (Fin de ciclo)
B21: 17 | C21: Información en vivo de las decisiones de los jugadores (Manual: Cierra el ciclo)
B22: 18 | C22: Estados financieros Generales | D22: Estados financieros Individuales e Informacion del mercado | E22: Descargables en pdf
A23: Ciclo N | B23: 15 | D23: Decisiones
B24: 16 | D24: Espera (Fin de ciclo)
B25: 17 | C25: Información en vivo de las decisiones de los jugadores (Manual: Cierra el ciclo)
B26: 18 | C26: Estados financieros Generales | D26: Estados financieros Individuales e Informacion del mercado
B27: 23 | C27: Resumen General - Indicar podio | D27: Estados financieros Individuales y Consolidado Final | E27: Descargables en pdf
B28: 24 | D28: Mostrar Podio | E28: Agregar disclaimer indicando que los datos se guardaran un maximo de 24 horas
B37: Si el jugador no tomo decision dentro del tiempo establecido y es la primera decisión se le elimina del juego
B38: El Docente tiene la opcion de eliminar jugadores en cualquier momento. Sin importar si es manual o automatico
B39: Si el jugador no tomo decisiones dentro del tiempo establecido y no es la primera decisión el sistema replica las decisiones del ciclo anterior.

Sheet CANTIDAD DE PRODUCCIÓN
A1: Calculo de MO
A3: AREA DE CORTE
E4: Bolsas por día | F4: Mesa de corte | K4: Producción por día | L4: AL MES | M4: Eficiencia | N4: Produccion Real
C5: Nivel 1 - Operario basico | E5: 5 | F5: 1 | I5: =E5*F5 -> 5 | K5: =MIN(I8,I14,I20) -> 17.2 | L5: =K5*24 -> 412.8 | M5: =K7+(F7+F13+F19)/100+4%*F21 -> 0.96 | N5: =ROUND(L5*M5,0) -> 396 | O5: Esta produccion no puede ser superior a lo que permite el material
C6: Nivel 2 - Cortador con experiencia | E6: 7 | F6: 1 | I6: =E6*F6 -> 7 | K6: Eficiencia BASE
C7: Nivel 3 - Maestro cortador | E7: 9 | F7: 1 | I7: =E7*F7 -> 9 | K7: 0.9
A8: AREA DE ENSAMBLADO | I8: =SUM(I5:I7) -> 21
C9: Operarios | F9: MAQUINARIA MANUAL | G9: MAQUINARIA SEMIINDUSTRIAL | H9: MAQUINARIA INDUSTRIAL | K9: Total de trabajadores | L9: =SUM(F5:F7,F11:H13,F17:H19) -> 8
F10: 1 | G10: 1.2 | H10: 1.5 | K10: total de trabajadores N3 | L10: =SUM(F7,F13:H13,F19:H19) -> 3 | M10: =L10/L9 -> 0.375
C11: Nivel 1 | E11: 6 | H11: 1 | I11: =SUM(F11*E11*$F$10,G11*E11*$G$10,H11*E11*$H$10) -> 9
C12: Nivel 2 | E12: 8 | F12: 1 | G12: 0 | I12: =SUM(F12*E12*$F$10,G12*E12*$G$10,H12*E12*$H$10) -> 8
C13: Nivel 3 | E13: 12 | G13: 1 | I13: =SUM(F13*E13*$F$10,G13*E13*$G$10,H13*E13*$H$10) -> 14.4
A14: AREA DE ACABADO | I14: =SUM(I11:I13) -> 31.4
C15: Operarios | F15: MAQUINARIA MANUAL | G15: MAQUINARIA SEMIINDUSTRIAL | H15: MAQUINARIA INDUSTRIAL
F16: 1 | G16: 1.2 | H16: 1.5
C17: Nivel 1 | E17: 6 | G17: 1 | I17: =SUM(F17*E17*$F$16,G17*E17*$G$16,H17*E17*$H$16) -> 7.2
C18: Nivel 2 | E18: 7 | G18: 0 | H18: 0 | I18: =SUM(F18*E18*$F$16,G18*E18*$G$16,H18*E18*$H$16) -> 0
C19: Nivel 3 | E19: 10 | F19: 1 | I19: =SUM(F19*E19*$F$16,G19*E19*$G$16,H19*E19*$H$16) -> 10
I20: =SUM(I17:I19) -> 17.2
A21: Jefe de Produccion | F21: 1
B23: NOTA: EL PROCETANJE DE TRABAJADORES DE NIVEL 3 AFECTA POSITIVAMENTE A LA EFICIENCIA
A25: Calculo de MP
D27: Calidad del cuero | E27: Calidad del cuero | F27: Calidad del cuero | G27: Calidad de accesorios | H27: Calidad de accesorios | I27: Calidad de accesorios | J27: Calidad del hilo | K27: Calidad del hilo | L27: Calidad del hilo
D28: Nivel 1 - Cuero sintetico | E28: Nivel 2 - Cuero genuino estandar | F28: Nivel 3 - Cuero genuino premium | G28: Nivel 1 - Aleacion economica | H28: Nivel 2 - Metal premium | I28: Nivel 3 - Metal Deluxe | J28: Nivel 1 - Poliester estandar | K28: Nivel 2 - Encerado reforzado | L28: Nivel 3 - Alta tenacidad (nylon trenzado)
C29: UM Compra | D29: rollo | E29: Piel completa | F29: Piel completa | G29: Juego | H29: Juego | I29: Juego | J29: Carrete | K29: Carrete | L29: Carrete
C30: UM Produccion | D30: m2 | E30: m2 | F30: m2 | G30: unidad | H30: unidad | I30: unidad | J30: metro | K30: metro | L30: metro
C31: Nivel 1 - Generico basico | D31: 0.3 | G31: 1 | J31: 6
C32: Nivel 2 - Generico mejorado | E32: 0.4 | H32: 1 | K32: 7
C33: Nivel 3 - Premium | F33: 0.7 | I33: 1 | L33: 13
E35: =N5 -> 396
C36: Cantidad que desea producir | D36: =SUM(D37:D39) -> 520 | E36: =SUM(E37:E39) -> 395
C37: Nivel 1 - Generico basico | D37: 250 | E37: =ROUNDDOWN(D37*E35/D36,0) -> 190
C38: Nivel 2 - Generico mejorado | D38: 180 | E38: =ROUNDDOWN(D38*E35/D36,0) -> 137
C39: Nivel 3 - Premium | D39: 90 | E39: =ROUNDDOWN(D39*E35/D36,0) -> 68
D40: Calidad del cuero | E40: Calidad del cuero | F40: Calidad del cuero | G40: Calidad de accesorios | H40: Calidad de accesorios | I40: Calidad de accesorios | J40: Calidad del hilo | K40: Calidad del hilo | L40: Calidad del hilo
D41: Nivel 1 - Cuero sintetico | E41: Nivel 2 - Cuero genuino estandar | F41: Nivel 3 - Cuero genuino premium | G41: Nivel 1 - Aleacion economica | H41: Nivel 2 - Metal premium | I41: Nivel 3 - Metal Deluxe | J41: Nivel 1 - Poliester estandar | K41: Nivel 2 - Encerado reforzado | L41: Nivel 3 - Alta tenacidad (nylon trenzado)
C42: Nivel 1 - Generico basico | D42: =$D37*D31 -> 75 | E42: =$D37*E31 -> 0 | F42: =$D37*F31 -> 0 | G42: =$D37*G31 -> 250 | H42: =$D37*H31 -> 0 | I42: =$D37*I31 -> 0 | J42: =$D37*J31 -> 1500 | K42: =$D37*K31 -> 0 | L42: =$D37*L31 -> 0
C43: Nivel 2 - Generico mejorado | D43: =$D38*D32 -> 0 | E43: =$D38*E32 -> 72 | F43: =$D38*F32 -> 0 | G43: =$D38*G32 -> 0 | H43: =$D38*H32 -> 180 | I43: =$D38*I32 -> 0 | J43: =$D38*J32 -> 0 | K43: =$D38*K32 -> 1260 | L43: =$D38*L32 -> 0
C44: Nivel 3 - Premium | D44: =$D39*D33 -> 0 | E44: =$D39*E33 -> 0 | F44: =$D39*F33 -> 63 | G44: =$D39*G33 -> 0 | H44: =$D39*H33 -> 0 | I44: =$D39*I33 -> 90 | J44: =$D39*J33 -> 0 | K44: =$D39*K33 -> 0 | L44: =$D39*L33 -> 1170
D47: Calidad del cuero | E47: Calidad del cuero | F47: Calidad del cuero | G47: Calidad de accesorios | H47: Calidad de accesorios | I47: Calidad de accesorios | J47: Calidad del hilo | K47: Calidad del hilo | L47: Calidad del hilo
C48: Ejecucion de produccion | D48: Nivel 1 - Cuero sintetico | E48: Nivel 2 - Cuero genuino estandar | F48: Nivel 3 - Cuero genuino premium | G48: Nivel 1 - Aleacion economica | H48: Nivel 2 - Metal premium | I48: Nivel 3 - Metal Deluxe | J48: Nivel 1 - Poliester estandar | K48: Nivel 2 - Encerado reforzado | L48: Nivel 3 - Alta tenacidad (nylon trenzado)
C49: Nivel 1 - Generico basico | D49: 60 | E49: 10 | H49: 200 | J49: 1600
C50: Nivel 2 - Generico mejorado | E50: 50 | H50: 150 | L50: 1200
C51: Nivel 3 - Premium | F51: 70 | H51: 50 | L51: 1100
D53: =D49/D31 -> 200 | G53: =G49/G31 -> 0 | J53: =J49/J31 -> 266.66667
C55: TOTAL PRODUCIDO REAL | G55: Cuero empleado | H55: Accesorios empleados | I55: Hilo empleado | K55: Calidad por Materiales
C56: Nivel 1 - Generico basico | D56: =MIN(SUM(D49:F49)/D31,SUM(G49:I49)/G31,SUM(J49:L49)/J31,E37,D37) -> 190 | E56: =ROUNDDOWN(D56,0) -> 190 | G56: =E56*D31 -> 57 | H56: =E56*G31 -> 190 | I56: =E56*J31 -> 1140 | K56: 46143
C57: Nivel 2 - Generico mejorado | D57: =MIN(SUM(D50:F50)/E32,SUM(G50:I50)/H32,SUM(J50:L50)/K32,E38,D38) -> 125 | E57: =ROUNDDOWN(D57,0) -> 125 | G57: =E57*E32 -> 50 | H57: =E57*H32 -> 125 | I57: =E57*K32 -> 875 | K57: 46082
C58: Nivel 3 - Premium | D58: =MIN(SUM(D51:F51)/F33,SUM(G51:I51)/I33,SUM(J51:L51)/L33,E39,D39) -> 50 | E58: =ROUNDDOWN(D58,0) -> 50 | G58: =E58*F33 -> 35 | H58: =E58*I33 -> 50 | I58: =E58*L33 -> 650 | K58: 46054
D62: Inventario Inicial | E62: Compras | F62: Produccion | G62: Inventario Final | H62: InventarioFinal = InventarioInicial + compras - produccido
C63: Nivel 1 - Cuero sintetico | D63: 15 | E63: 60 | F63: 75 | G63: =D63+E63-F63 -> 0
C64: Nivel 2 - Cuero genuino estandar | D64: 17 | E64: 55 | F64: 72 | G64: =D64+E64-F64 -> 0
C65: Nivel 3 - Cuero genuino premium | D65: 48 | E65: 15 | F65: 63 | G65: =D65+E65-F65 -> 0
C66: Nivel 1 - Aleacion economica | D66: 50 | E66: 200 | F66: 250 | G66: =D66+E66-F66 -> 0
C67: Nivel 2 - Metal premium | D67: 0 | E67: 190 | F67: 180 | G67: =D67+E67-F67 -> 10
C68: Nivel 3 - Metal Deluxe | D68: 90 | E68: 0 | F68: 90 | G68: =D68+E68-F68 -> 0
C69: Nivel 1 - Poliester estandar | D69: 1494 | E69: 6 | F69: 1500 | G69: =D69+E69-F69 -> 0
C70: Nivel 2 - Encerado reforzado | D70: 1253 | E70: 7 | F70: 1260 | G70: =D70+E70-F70 -> 0
C71: Nivel 3 - Alta tenacidad (nylon trenzado) | D71: 1170 | E71: 0 | F71: 1170 | G71: =D71+E71-F71 -> 0
B72: 0 - 10,000(rango en soles)
A73: Gastos del ciclo en publicidad | B73: 3000
A75: Calculo de Reputacion | C75: =F51*10 -> 700 | D75: =M10*10 -> 3.75 | F75: =B73/10000*10 -> 3 | G75: =SUM(C75:F75) -> 706.75 | H75: ptos de reputación
C76: Factor de producción | D76: Factor de MO | E76: Factor de MP (utilizacion) | F76: Factor de Publicidad
B82: EJEMPLO de distribución de Ventas (Bolsos Economicos) | C82: Reputacion | D82: Precio | E82: Puntaje del precio | F82: Puntaje total | G82: Porcentaje parcial | H82: Unidades Vendidas
B83: Empresa A | C83: 7 | D83: 40 | E83: =(MAX($D$83:$D$86)*2-D83)/10 -> 5 | F83: =SUM(C83,E83) -> 12 | G83: =F83/$F$87 -> 0.2238806 | H83: =ROUND(G83*$B$91,0) -> 784
B84: Empresa B | C84: 8.3 | D84: 45 | E84: =(MAX($D$83:$D$86)*2-D84)/10 -> 4.5 | F84: =SUM(C84,E84) -> 12.8 | G84: =F84/$F$87 -> 0.23880597 | H84: =ROUND(G84*$B$91,0) -> 836
B85: Empresa C | C85: 10.2 | D85: 43 | E85: =(MAX($D$83:$D$86)*2-D85)/10 -> 4.7 | F85: =SUM(C85,E85) -> 14.9 | G85: =F85/$F$87 -> 0.27798507 | H85: =ROUND(G85*$B$91,0) -> 973
B86: Empresa D | C86: 9 | D86: 41 | E86: =(MAX($D$83:$D$86)*2-D86)/10 -> 4.9 | F86: =SUM(C86,E86) -> 13.9 | G86: =F86/$F$87 -> 0.25932836 | H86: =ROUND(G86*$B$91,0) -> 908
E87: Total | F87: =SUM(F83:F86) -> 53.6 | H87: =SUM(H83:H86) -> 3501
B89: 7000 | C89: unidades mercado
B90: 0.5
B91: =B89*B90 -> 3500 | C91: unidades mercado real
B96: EJEMPLO de distribución de Ventas (Bolsos promedio) | C96: Reputacion | D96: Precio | E96: Puntaje del precio | F96: Puntaje total | G96: Porcentaje parcial | H96: Unidades Vendidas
B97: Empresa A | C97: 7 | D97: 120 | E97: =(MAX($D$97:$D$100)*2-D97)/10 -> 28 | F97: =SUM(C97,E97) -> 35 | G97: =F97/$F$101 -> 0.27237354 | H97: =ROUND(G97*$B$91,0) -> 953
B98: Empresa B | C98: 8.3 | D98: 150 | E98: =(MAX($D$97:$D$100)*2-D98)/10 -> 25 | F98: =SUM(C98,E98) -> 33.3 | G98: =F98/$F$101 -> 0.25914397 | H98: =ROUND(G98*$B$91,0) -> 907
B99: Empresa C | C99: 10.2 | D99: 190 | E99: =(MAX($D$97:$D$100)*2-D99)/10 -> 21 | F99: =SUM(C99,E99) -> 31.2 | G99: =F99/$F$101 -> 0.24280156 | H99: =ROUND(G99*$B$91,0) -> 850
B100: Empresa D | C100: 9 | D100: 200 | E100: =(MAX($D$97:$D$100)*2-D100)/10 -> 20 | F100: =SUM(C100,E100) -> 29 | G100: =F100/$F$101 -> 0.22568093 | H100: =ROUND(G100*$B$91,0) -> 790
E101: Total | F101: =SUM(F97:F100) -> 128.5
B103: 5000 | C103: unidades mercado
B104: 0.7
B105: =B103*B104 -> 3500 | C105: unidades mercado real
B110: EJEMPLO de distribución de Ventas (Bolsos Premium) | C110: Reputacion | D110: Precio | E110: Puntaje del precio | F110: Puntaje total | G110: Porcentaje parcial | H110: Unidades Vendidas
B111: Empresa A | C111: 7 | D111: 250 | E111: =(MAX($D$111:$D$114)*2-D111)/10 -> 55 | F111: =SUM(C111,E111) -> 62 | G111: =F111/$F$115 -> 0.26105263 | H111: =ROUND(G111*$B$119,0) -> 209
B112: Empresa B | C112: 8.3 | D112: 300 | E112: =(MAX($D$111:$D$114)*2-D112)/10 -> 50 | F112: =SUM(C112,E112) -> 58.3 | G112: =F112/$F$115 -> 0.24547368 | H112: =ROUND(G112*$B$119,0) -> 196
B113: Empresa C | C113: 10.2 | D113: 220 | E113: =(MAX($D$111:$D$114)*2-D113)/10 -> 58 | F113: =SUM(C113,E113) -> 68.2 | G113: =F113/$F$115 -> 0.28715789 | H113: =ROUND(G113*$B$119,0) -> 230
B114: Empresa D | C114: 9 | D114: 400 | E114: =(MAX($D$111:$D$114)*2-D114)/10 -> 40 | F114: =SUM(C114,E114) -> 49 | G114: =F114/$F$115 -> 0.20631579 | H114: =ROUND(G114*$B$119,0) -> 165
E115: Total | F115: =SUM(F111:F114) -> 237.5
B117: 2000 | C117: unidades mercado
B118: 0.4
B119: =B117*B118 -> 800 | C119: unidades mercado real
A123: Calculo de Reputacion | C123: =F51*10 -> 700 | D123: =M10*10 -> 3.75 | F123: =B73/10000*10 -> 3 | G123: =SUM(C123:F123) -> 706.75 | H123: ptos de reputación
C124: Factor de producción | D124: Factor de MO | E124: Factor de MP (utilizacion) | F124: Factor de Publicidad | L124: Peso precio | M124: 0.7
L125: peso reputación | M125: 0.2
L126: Peso calidad | M126: 0.1
B127: EJEMPLO de distribución de Ventas (Bolsos Economicos) | C127: Precio | D127: Reputación (0-10) | E127: Calidad (0-100) | F127: Precio Económico (0-100) | G127: Reputación (0-100) | H127: Puntaje total | I127: Porcentaje parcial | J127: Unidades Vendidas
B128: Empresa A | C128: 40 | D128: 7 | E128: =ROUND((D128/$D$132)*100,0) -> 20 | F128: =100*(MAX($C$128:$C$131)-C128)/(MAX($C$128:$C$131)-MIN($C$128:$C$131)) -> 100 | G128: =D128*10 -> 70 | H128: =$M$124*F128+$M$125*G128+$M$126*E128 -> 86 | I128: =H128/$H$132 -> 0.36909871 | J128: =ROUND(I128*$B$136,0) -> 1292
B129: Empresa B | C129: 45 | D129: 8.3 | E129: =ROUND((D129/$D$132)*100,0) -> 24 | F129: =100*(MAX($C$128:$C$131)-C129)/(MAX($C$128:$C$131)-MIN($C$128:$C$131)) -> 0 | G129: =D129*10 -> 83 | H129: =$M$124*F129+$M$125*G129+$M$126*E129 -> 19 | I129: =H129/$H$132 -> 0.081545064 | J129: =ROUND(I129*$B$136,0) -> 285
B130: Empresa C | C130: 43 | D130: 10.2 | E130: =ROUND((D130/$D$132)*100,0) -> 30 | F130: =100*(MAX($C$128:$C$131)-C130)/(MAX($C$128:$C$131)-MIN($C$128:$C$131)) -> 40 | G130: =D130*10 -> 102 | H130: =$M$124*F130+$M$125*G130+$M$126*E130 -> 51.4 | I130: =H130/$H$132 -> 0.22060086 | J130: =ROUND(I130*$B$136,0) -> 772
B131: Empresa D | C131: 41 | D131: 9 | E131: =ROUND((D131/$D$132)*100,0) -> 26 | F131: =100*(MAX($C$128:$C$131)-C131)/(MAX($C$128:$C$131)-MIN($C$128:$C$131)) -> 80 | G131: =D131*10 -> 90 | H131: =$M$124*F131+$M$125*G131+$M$126*E131 -> 76.6 | I131: =H131/$H$132 -> 0.32875536 | J131: =ROUND(I131*$B$136,0) -> 1151
C132: SUMA | D132: =SUM(D128:D131) -> 34.5 | G132: TOTAL | H132: =SUM(H128:H131) -> 233 | J132: =SUM(J128:J131) -> 3500
...

Sheet Costos De Producción
A1: Calculo de MO
T2: Costos: MO
A3: AREA DE CORTE
E4: Bolsas por día | F4: Mesa de corte | K4: Producción por día | L4: AL MES | M4: Eficiencia | N4: Produccion Real | T4: O.Basico | U4: MYPE | V4: NoMype | X4: Costurero básico | Y4: MYPE | Z4: NoMype | AB4: Operario de acabado clásico | AC4: MYPE | AD4: NoMype
C5: Nivel 1 - Operario basico | E5: 6 | F5: 1 | I5: =E5*F5 -> 6 | K5: =MIN(I8,I14,I20) -> 14 | L5: =K5*30 -> 420 | M5: =K7+(F7+F13+F19)/100+4%*F21 -> 0.91 | N5: =ROUND(L5*M5,0) -> 382 | O5: Esta produccion no puede ser superior a lo que permite el material | T5: Sueldo base | U5: 1500 | V5: 1500 | X5: Sueldo base | Y5: 1500 | Z5: 1500 | AB5: Sueldo base | AC5: 1500 | AD5: 1500
C6: Nivel 2 - Cortador con experiencia | E6: 8 | F6: 1 | I6: =E6*F6 -> 8 | K6: Eficiencia BASE | T6: Essalud | U6: =U5*0.09 -> 135 | V6: =V5*0.09 -> 135 | X6: Essalud | Y6: =Y5*0.09 -> 135 | Z6: =Z5*0.09 -> 135 | AB6: Essalud | AC6: =AC5*0.09 -> 135 | AD6: =AD5*0.09 -> 135
C7: Nivel 3 - Maestro cortador | E7: 12 | F7: 0 | I7: =E7*F7 -> 0 | K7: 0.9 | T7: Grati | U7: =U5 -> 1500 | V7: =V5*2 -> 3000 | X7: Grati | Y7: =Y5 -> 1500 | Z7: =Z5*2 -> 3000 | AB7: Grati | AC7: =AC5 -> 1500 | AD7: =AD5*2 -> 3000
A8: AREA DE ENSAMBLADO | I8: =SUM(I5:I7) -> 14 | T8: CTS | U8: 750 | V8: 1500 | X8: CTS | Y8: 750 | Z8: 1500 | AB8: CTS | AC8: 750 | AD8: 1500
C9: Operarios | F9: MAQUINARIA MANUAL | G9: MAQUINARIA SEMIINDUSTRIAL | H9: MAQUINARIA INDUSTRIAL | K9: Total de trabajadores | L9: =SUM(F5:F7,F11:H13,F17:H19) -> 7 | T9: vacaciones | U9: =U5/2 -> 750 | V9: =V5 -> 1500 | X9: vacaciones | Y9: =Y5/2 -> 750 | Z9: =Z5 -> 1500 | AB9: vacaciones | AC9: =AC5/2 -> 750 | AD9: =AD5 -> 1500
F10: 1 | G10: 1.2 | H10: 1.5 | K10: total de trabajadores N3 | L10: =SUM(F7,F13:H13,F19:H19) -> 2 | M10: =L10/L9 -> 0.28571429 | T10: Suma anual | U10: =SUM(U6:U9)+U5*12 -> 21135 | V10: =SUM(V6:V9)+V5*12 -> 24135 | X10: Suma anual | Y10: =SUM(Y6:Y9)+Y5*12 -> 21135 | Z10: =SUM(Z6:Z9)+Z5*12 -> 24135 | AB10: Suma anual | AC10: =SUM(AC6:AC9)+AC5*12 -> 21135 | AD10: =SUM(AD6:AD9)+AD5*12 -> 24135
C11: Nivel 1 | E11: 6 | H11: 1 | I11: =SUM(F11*E11*$F$10,G11*E11*$G$10,H11*E11*$H$10) -> 9 | T11: Pago mensual | U11: =U10/12.5 -> 1690.8 | V11: =V10/13 -> 1856.5385 | X11: Pago mensual | Y11: =Y10/12.5 -> 1690.8 | Z11: =Z10/13 -> 1856.5385 | AB11: Pago mensual | AC11: =AC10/12.5 -> 1690.8 | AD11: =AD10/13 -> 1856.5385
C12: Nivel 2 | E12: 8 | F12: 1 | I12: =SUM(F12*E12*$F$10,G12*E12*$G$10,H12*E12*$H$10) -> 8
C13: Nivel 3 | E13: 12 | G13: 1 | I13: =SUM(F13*E13*$F$10,G13*E13*$G$10,H13*E13*$H$10) -> 14.4 | T13: Cortador con experiencia | U13: MYPE | V13: NoMype | X13: Maquinista industrial | Y13: MYPE | Z13: NoMype | AB13: Técnico de acabado | AC13: MYPE | AD13: NoMype
A14: AREA DE ACABADO | I14: =SUM(I11:I13) -> 31.4 | T14: Sueldo base | U14: 2000 | V14: 2000 | X14: Sueldo base | Y14: 2800 | Z14: 2800 | AB14: Sueldo base | AC14: 2800 | AD14: 2800
C15: Operarios | F15: MAQUINARIA MANUAL | G15: MAQUINARIA SEMIINDUSTRIAL | H15: MAQUINARIA INDUSTRIAL | T15: Essalud | U15: =U14*0.09 -> 180 | V15: =V14*0.09 -> 180 | X15: Essalud | Y15: =Y14*0.09 -> 252 | Z15: =Z14*0.09 -> 252 | AB15: Essalud | AC15: =AC14*0.09 -> 252 | AD15: =AD14*0.09 -> 252
F16: 1 | G16: 1.2 | H16: 1.5 | T16: Grati | U16: =U14 -> 2000 | V16: =V14*2 -> 4000 | X16: Grati | Y16: =Y14 -> 2800 | Z16: =Z14*2 -> 5600 | AB16: Grati | AC16: =AC14 -> 2800 | AD16: =AD14*2 -> 5600
C17: Nivel 1 | E17: 6 | I17: =SUM(F17*E17*$F$16,G17*E17*$G$16,H17*E17*$H$16) -> 0 | T17: CTS | U17: =U14/2 -> 1000 | V17: =V14 -> 2000 | X17: CTS | Y17: 750 | Z17: 1500 | AB17: CTS | AC17: 750 | AD17: 1500
C18: Nivel 2 | E18: 8 | H18: 1 | I18: =SUM(F18*E18*$F$16,G18*E18*$G$16,H18*E18*$H$16) -> 12 | T18: vacaciones | U18: =U14/2 -> 1000 | V18: =V14 -> 2000 | X18: vacaciones | Y18: =Y14/2 -> 1400 | Z18: =Z14 -> 2800 | AB18: vacaciones | AC18: =AC14/2 -> 1400 | AD18: =AD14 -> 2800
C19: Nivel 3 | E19: 12 | F19: 1 | I19: =SUM(F19*E19*$F$16,G19*E19*$G$16,H19*E19*$H$16) -> 12 | T19: Suma anual | U19: =SUM(U15:U18)+U14*12 -> 28180 | V19: =SUM(V15:V18)+V14*12 -> 32180 | X19: Suma anual | Y19: =SUM(Y15:Y18)+Y14*12 -> 38802 | Z19: =SUM(Z15:Z18)+Z14*12 -> 43752 | AB19: Suma anual | AC19: =SUM(AC15:AC18)+AC14*12 -> 38802 | AD19: =SUM(AD15:AD18)+AD14*12 -> 43752
I20: =SUM(I17:I19) -> 24 | T20: Pago mensual | U20: =U19/12.5 -> 2254.4 | V20: =V19/13 -> 2475.3846 | X20: Pago mensual | Y20: =Y19/12.5 -> 3104.16 | Z20: =Z19/13 -> 3365.5385 | AB20: Pago mensual | AC20: =AC19/12.5 -> 3104.16 | AD20: =AD19/13 -> 3365.5385
A21: Jefe de Produccion | F21: 0
T22: Maestro cortador | U22: MYPE | V22: NoMype | X22: Marroquinero especializado | Y22: MYPE | Z22: NoMype | AB22: Artesano acabador | AC22: MYPE | AD22: NoMype
B23: NOTA: EL PROCETANJE DE TRABAJADORES DE NIVEL 3 AFECTA POSITIVAMENTE A LA EFICIENCIA | T23: Sueldo base | U23: 3800 | V23: 3800 | X23: Sueldo base | Y23: 4500 | Z23: 4500 | AB23: Sueldo base | AC23: 4500 | AD23: 4500
T24: Essalud | U24: =U23*0.09 -> 342 | V24: =V23*0.09 -> 342 | X24: Essalud | Y24: =Y23*0.09 -> 405 | Z24: =Z23*0.09 -> 405 | AB24: Essalud | AC24: =AC23*0.09 -> 405 | AD24: =AD23*0.09 -> 405
A25: Calculo de MP | T25: Grati | U25: =U23 -> 3800 | V25: =V23*2 -> 7600 | X25: Grati | Y25: =Y23 -> 4500 | Z25: =Z23*2 -> 9000 | AB25: Grati | AC25: =AC23 -> 4500 | AD25: =AD23*2 -> 9000
T26: CTS | U26: 750 | V26: 1500 | X26: CTS | Y26: 750 | Z26: 1500 | AB26: CTS | AC26: 750 | AD26: 1500
D27: Calidad del cuero | E27: Calidad del cuero | F27: Calidad del cuero | G27: Calidad de accesorios | H27: Calidad de accesorios | I27: Calidad del hilo | J27: Calidad del hilo | K27: Calidad del hilo | T27: vacaciones | U27: =U23/2 -> 1900 | V27: =V23 -> 3800 | X27: vacaciones | Y27: =Y23/2 -> 2250 | Z27: =Z23 -> 4500 | AB27: vacaciones | AC27: =AC23/2 -> 2250 | AD27: =AD23 -> 4500
D28: Nivel 1 - Cuero sintetico | E28: Nivel 2 - Cuero genuino estandar | F28: Nivel 3 - Cuero genuino premium | G28: Nivel 1 - Aleacion economica | H28: Nivel 2 - Metal premium | I28: Nivel 1 - Poliester estandar | J28: Nivel 2 - Encerado reforzado | K28: Nivel 3 - Alta tenacidad (nylon trenzado) | T28: Suma anual | U28: =SUM(U24:U27)+U23*12 -> 52392 | V28: =SUM(V24:V27)+V23*12 -> 58842 | X28: Suma anual | Y28: =SUM(Y24:Y27)+Y23*12 -> 61905 | Z28: =SUM(Z24:Z27)+Z23*12 -> 69405 | AB28: Suma anual | AC28: =SUM(AC24:AC27)+AC23*12 -> 61905 | AD28: =SUM(AD24:AD27)+AD23*12 -> 69405
C29: UM Compra | D29: rollo | E29: Piel completa | F29: Piel completa | G29: Juego | H29: Juego | I29: Carrete | J29: Carrete | K29: Carrete | T29: Pago mensual | U29: =U28/12.5 -> 4191.36 | V29: =V28/13 -> 4526.3077 | X29: Pago mensual | Y29: =Y28/12.5 -> 4952.4 | Z29: =Z28/13 -> 5338.8462 | AB29: Pago mensual | AC29: =AC28/12.5 -> 4952.4 | AD29: =AD28/13 -> 5338.8462
C30: UM Produccion | D30: m2 | E30: m2 | F30: m2 | G30: unidad | H30: unidad | I30: metro | J30: metro | K30: metro
B31: Cantidad necesaria | C31: Compra Jugador | D31: 60 | E31: 55 | F31: 15 | G31: 200 | H31: 190 | I31: 0 | J31: 6 | K31: 7
C32: Cantidad Produccion | D32: 1 | E32: 2 | F32: 2 | G32: 1 | H32: 1 | I32: 270 | J32: 250 | K32: 200 | T32: Jefatura | U32: MYPE | V32: NoMype | X32: Limpieza | Y32: MYPE | Z32: NoMype | AB32: Local de producción | AC32: MYPE | AD32: NoMype
D33: =D31*D32 -> 60 | E33: =E31*E32 -> 110 | F33: =F31*F32 -> 30 | G33: =G31*G32 -> 200 | H33: =H31*H32 -> 190 | I33: =I31*I32 -> 0 | J33: =J31*J32 -> 1500 | K33: =K31*K32 -> 1400 | T33: Sueldo base | U33: 3000 | V33: 3000 | X33: Sueldo base | Y33: 600 | Z33: 600 | AB33: Costo fijo | AC33: 2000 | AD33: 2000
T34: Essalud | U34: =U33*0.09 -> 270 | V34: =V33*0.09 -> 270 | X34: Essalud | Y34: =Y33*0.09 -> 54 | Z34: =Z33*0.09 -> 54
H35: InventarioFinal = InventarioInicial + compras - produccido | T35: Grati | U35: =U33 -> 3000 | V35: =V33*2 -> 6000 | X35: Grati | Y35: =Y33 -> 600 | Z35: =Z33*2 -> 1200
D36: m2 | E36: unidad | F36: metro | H36: Almacen | T36: CTS | U36: 750 | V36: 1500 | X36: CTS | Y36: 750 | Z36: 1500
C37: Moldes (siempre debe comprar al menos uno) | D37: Cuero | E37: Accesorios | F37: Hilos | H37: Cuero | I37: Accesorios | J37: Hilos | T37: vacaciones | U37: =U33/2 -> 1500 | V37: =V33 -> 3000 | X37: vacaciones | Y37: =Y33/2 -> 300 | Z37: =Z33 -> 600
C38: Nivel 1 - Generico basico | D38: 0.3 | E38: 1 | F38: 6 | H38: =SUM(D33:F33) -> 200 | I38: =SUM(G33:H33) -> 390 | J38: =SUM(I33:K33) -> 2900 | T38: Suma anual | U38: =SUM(U34:U37)+U33*12 -> 41520 | V38: =SUM(V34:V37)+V33*12 -> 46770 | X38: Suma anual | Y38: =SUM(Y34:Y37)+Y33*12 -> 8904 | Z38: =SUM(Z34:Z37)+Z33*12 -> 10554
C39: Nivel 2 - Generico mejorado | D39: 0.4 | E39: 1 | F39: 7 | T39: Pago mensual | U39: =U38/12.5 -> 3321.6 | V39: =V38/13 -> 3597.6923 | X39: Pago mensual | Y39: =Y38/12.5 -> 712.32 | Z39: =Z38/13 -> 811.84615
C40: Nivel 3 - Premium | D40: 0.7 | E40: 1 | F40: 13
B42: como estamos trabajando los hilos, po rmetro? pero cuando compramos compramos metros o carretes? si es carretes cuantos metros tiene | T42: Costos: Maquinaria
B43: es mas sencillo trabajarlo como unidad y establecer valores mas pequeños de hilo necesario, bajarle el precio al hilo
T44: Mesa de corte | U44: MYPE | V44: NoMype | X44: Maquina de Ensamblado N1 | Y44: MYPE | Z44: NoMype | AB44: Maquina de acabado N1 | AC44: MYPE | AD44: NoMype
C45: Cuantos Bolso deseas producir ? | E45: Producido luego del termino del ciclo | H45: Total Cuero Necesario | I45: Total Accesorios Necesario | J45: Total Hilo Necesario | L45: Total Cuero Utilizado | M45: Total Accesorios Utilizado | N45: Total Hilo Utilizado | T45: Costo de adquisición | U45: 2500 | V45: 2500 | X45: Costo de adquisición | Y45: 3500 | Z45: 3500 | AB45: Costo de adquisición | AC45: 1200 | AD45: 1200
C46: Nivel 1 - Generico basico | D46: 150 | E46: 150 | F46: =E46/E49 -> 0.4076087 | H46: =D38*D46 -> 45 | I46: =D46*E38 -> 150 | J46: =F38*D46 -> 900 | L46: =E46*D38 -> 45 | M46: =E46*E38 -> 150 | N46: =F38*E46 -> 900 | T46: Instalación | U46: =U45*3% -> 75 | V46: =V45*5% -> 125 | X46: Instalación | Y46: =Y45*3% -> 105 | Z46: =Z45*5% -> 175 | AB46: Instalación | AC46: =AC45*3% -> 36 | AD46: =AD45*5% -> 60
C47: Nivel 2 - Generico mejorado | D47: 140 | E47: 140 | F47: =E47/E49 -> 0.38043478 | H47: =D39*D47 -> 56 | I47: =D47*E39 -> 140 | J47: =F39*D47 -> 980 | L47: =E47*D39 -> 56 | M47: =E47*E39 -> 140 | N47: =F39*E47 -> 980 | T47: Capacitación | U47: =U45*2% -> 50 | V47: =V45*3% -> 75 | X47: Capacitación | Y47: =Y45*2% -> 70 | Z47: =Z45*3% -> 105 | AB47: Capacitación | AC47: =AC45*2% -> 24 | AD47: =AD45*3% -> 36
C48: Nivel 3 - Premium | D48: 95 | E48: 78 | F48: =E48/E49 -> 0.21195652 | H48: =D40*D48 -> 66.5 | I48: =D48*E40 -> 95 | J48: =F40*D48 -> 1235 | L48: =D40*E48 -> 54.6 | M48: =E48*E40 -> 78 | N48: =F40*E48 -> 1014 | T48: Mantenimiento anual | U48: =U45*5% -> 125 | V48: =V45*8% -> 200 | X48: Mantenimiento anual | Y48: =Y45*5% -> 175 | Z48: =Z45*8% -> 280 | AB48: Mantenimiento anual | AC48: =AC45*5% -> 60 | AD48: =AD45*8% -> 96
D49: =SUM(D46:D48) -> 385 | E49: =SUM(E46:E48) -> 368 | F49: =SUM(F46:F48) -> 1 | H49: =SUM(H46:H48) -> 167.5 | I49: =SUM(I46:I48) -> 385 | J49: =SUM(J46:J48) -> 3115 | L49: =SUM(L46:L48) -> 155.6 | M49: =SUM(M46:M48) -> 368 | N49: =SUM(N46:N48) -> 2894 | T49: Depreciación anual | U49: =-((U45-U45*5%)/10) -> -237.5 | V49: =-((V45-V45*10%)/10) -> -225 | X49: Depreciación anual | Y49: =-(Y45-Y45*5%)/10 -> -332.5 | Z49: =-(Z45-Z45*10%)/10 -> -315 | AB49: Depreciación anual | AC49: =-(AC45-AC45*5%)/8 -> -142.5 | AD49: =-(AD45-AD45*10%)/8 -> -135
T50: Suma anual | U50: =SUM(U46:U49)+U45 -> 2512.5 | V50: =SUM(V46:V49)+V45 -> 2675 | X50: Suma anual | Y50: =SUM(Y46:Y49)+Y45 -> 3517.5 | Z50: =SUM(Z46:Z49)+Z45 -> 3745 | AB50: Suma anual | AC50: =SUM(AC46:AC49)+AC45 -> 1177.5 | AD50: =SUM(AD46:AD49)+AD45 -> 1257
C52: ALMACEN | T52: Molde 1 | U52: MYPE | V52: NoMype | X52: Maquina de Ensamblado N2 | Y52: MYPE | Z52: NoMype | AB52: Maquina de acabado N2 | AC52: MYPE | AD52: NoMype
D53: Inventario Inicial | E53: Compras | F53: Produccion | G53: Inventario Final | T53: Costo de adquisición | U53: 300 | V53: 300 | X53: Costo de adquisición | Y53: 7500 | Z53: 7500 | AB53: Costo de adquisición | AC53: 4500 | AD53: 4500
C54: Nivel 1 - Cuero sintetico | D54: 0 | E54: =D33 -> 60 | F54: =MIN(E54,H49) -> 60 | G54: =D54+E54-F54 -> 0 | T54: Capacitación | U54: =U53*1% -> 3 | V54: =V53*2% -> 6 | X54: Instalación | Y54: =Y53*3% -> 225 | Z54: =Z53*5% -> 375 | AB54: Instalación | AC54: =AC53*3% -> 135 | AD54: =AD53*5% -> 225
C55: Nivel 2 - Cuero genuino estandar | D55: 0 | E55: =E33 -> 110 | F55: =min(E55,H49-F54) -> 107.5 | G55: =D55+E55-F55 -> 2.5 | T55: Mantenimiento anual | U55: =U53*5% -> 15 | V55: =V53*8% -> 24 | X55: Capacitación | Y55: =Y53*2% -> 150 | Z55: =Z53*3% -> 225 | AB55: Capacitación | AC55: =AC53*2% -> 90 | AD55: =AD53*3% -> 135
C56: Nivel 3 - Cuero genuino premium | D56: 0 | E56: =F33 -> 30 | F56: =MIN(E56,H49-F54-F55) -> 0 | G56: =D56+E56-F56 -> 30 | H56: =F56/SUM(F54:F56) -> 0 | T56: Depreciación anual | U56: =-((U53-U53*5%)/5) -> -57 | V56: =-((V53-V53*10%)/5) -> -54 | X56: Mantenimiento anual | Y56: =Y53*5% -> 375 | Z56: =Z53*8% -> 600 | AB56: Mantenimiento anual | AC56: =AC53*5% -> 225 | AD56: =AD53*8% -> 360
C57: Nivel 1 - Aleacion economica | D57: 0 | E57: =G33 -> 200 | F57: =MIN(E57,I49) -> 200 | G57: =D57+E57-F57 -> 0 | T57: Suma anual | U57: =SUM(U54:U56)+U53 -> 261 | V57: =SUM(V54:V56)+V53 -> 276 | X57: Depreciación anual | Y57: =-(Y53-Y53*5%)/10 -> -712.5 | Z57: =-(Z53-Z53*10%)/10 -> -675 | AB57: Depreciación anual | AC57: =-(AC53-AC53*5%)/8 -> -534.375 | AD57: =-(AD53-AD53*10%)/8 -> -506.25
C58: Nivel 2 - Metal premium | D58: 0 | E58: =H33 -> 190 | F58: =MIN(E58,I49-F57) -> 185 | G58: =D58+E58-F58 -> 5 | H58: =F58/SUM(F57:F58) -> 0.48051948 | X58: Suma anual | Y58: =SUM(Y54:Y57)+Y53 -> 7537.5 | Z58: =SUM(Z54:Z57)+Z53 -> 8025 | AB58: Suma anual | AC58: =SUM(AC54:AC57)+AC53 -> 4415.625 | AD58: =SUM(AD54:AD57)+AD53 -> 4713.75
C59: Nivel 1 - Poliester estandar | D59: 0 | E59: =I33 -> 0 | F59: =MIN(E59,J49) -> 0 | G59: =D59+E59-F59 -> 0 | T59: Molde 2 | U59: MYPE | V59: NoMype
C60: Nivel 2 - Encerado reforzado | D60: 0 | E60: =J33 -> 1500 | F60: =MIN(E60,J49-F59) -> 1500 | G60: =D60+E60-F60 -> 0 | T60: Costo de adquisición | U60: 1200 | V60: 1200 | X60: Maquina de Ensamblado N3 | Y60: MYPE | Z60: NoMype | AB60: Maquina de acabado N3 | AC60: MYPE | AD60: NoMype
C61: Nivel 3 - Alta tenacidad (nylon trenzado) | D61: 0 | E61: =K33 -> 1400 | F61: =MIN(E61,J49-F59-F60) -> 1400 | G61: =D61+E61-F61 -> 0 | H61: =F61/(SUM(F60:F61)) -> 0.48275862 | T61: Capacitación | U61: =U60*1% -> 12 | V61: =V60*2% -> 24 | X61: Costo de adquisición | Y61: 15000 | Z61: 15000 | AB61: Costo de adquisición | AC61: 9500 | AD61: 9500
B62: 0 - 10,000(rango en soles) | T62: Mantenimiento anual | U62: =U60*5% -> 60 | V62: =V60*8% -> 96 | X62: Instalación | Y62: =Y61*3% -> 450 | Z62: =Z61*5% -> 750 | AB62: Instalación | AC62: =AC61*3% -> 285 | AD62: =AD61*5% -> 475
A63: Gastos del ciclo en publicidad | B63: 3000 | T63: Depreciación anual | U63: =-((U60-U60*5%)/5) -> -228 | V63: =-((V60-V60*10%)/5) -> -216 | X63: Capacitación | Y63: =Y61*2% -> 300 | Z63: =Z61*3% -> 450 | AB63: Capacitación | AC63: =AC61*2% -> 190 | AD63: =AD61*3% -> 285
T64: Suma anual | U64: =SUM(U61:U63)+U60 -> 1044 | V64: =SUM(V61:V63)+V60 -> 1104 | X64: Mantenimiento anual | Y64: =Y61*5% -> 750 | Z64: =Z61*8% -> 1200 | AB64: Mantenimiento anual | AC64: =AC61*5% -> 475 | AD64: =AD61*8% -> 760
A65: Calculo de Reputacion | C65: =F48*10 -> 2.1195652 | D65: =M10*10 -> 2.8571429 | E65: =AVERAGE(H56,H58,H61)*10 -> 3.210927 | F65: =B63/10000*10 -> 3 | G65: =SUM(C65:F65) -> 11.187635 | H65: ptos de reputación | X65: Depreciación anual | Y65: =-(Y61-Y61*5%)/10 -> -1425 | Z65: =-(Z61-Z61*10%)/10 -> -1350 | AB65: Depreciación anual | AC65: =-(AC61-AC61*5%)/8 -> -1128.125 | AD65: =-(AD61-AD61*10%)/8 -> -1068.75
C66: Factor de producción | D66: Factor de MO | E66: Factor de MP (utilizacion) | F66: Factor de Publicidad | T66: Moldes 3 | U66: MYPE | V66: NoMype | X66: Suma anual | Y66: =SUM(Y62:Y65)+Y61 -> 15075 | Z66: =SUM(Z62:Z65)+Z61 -> 16050 | AB66: Suma anual | AC66: =SUM(AC62:AC65)+AC61 -> 9321.875 | AD66: =SUM(AD62:AD65)+AD61 -> 9951.25
T67: Costo de adquisición | U67: 3500 | V67: 3500
T68: Capacitación | U68: =U67*1% -> 35 | V68: =V67*2% -> 70
T69: Mantenimiento anual | U69: =U67*5% -> 175 | V69: =V67*8% -> 280
T70: Depreciación anual | U70: =-((U67-U67*5%)/5) -> -665 | V70: =-((V67-V67*10%)/5) -> -630
T71: Suma anual | U71: =SUM(U68:U70)+U67 -> 3045 | V71: =SUM(V68:V70)+V67 -> 3220
B72: EJEMPLO de distribución de Ventas (Bolsos Economicos) | C72: Reputacion | D72: Precio | E72: Puntaje del precio | F72: Puntaje total | G72: Porcentaje parcial | H72: Unidades Vendidas
B73: Empresa A | C73: 7 | D73: 40 | E73: =(MAX($D$73:$D$76)*2-D73)/10 -> 5 | F73: =SUM(C73,E73) -> 12 | G73: =F73/$F$77 -> 0.2238806 | H73: =ROUND(G73*$B$81,0) -> 784 | T73: Costos: MP
B74: Empresa B | C74: 8.3 | D74: 45 | E74: =(MAX($D$73:$D$76)*2-D74)/10 -> 4.5 | F74: =SUM(C74,E74) -> 12.8 | G74: =F74/$F$77 -> 0.23880597 | H74: =ROUND(G74*$B$81,0) -> 836 | T74: Tabla de materia base. | Z74: Lo que sea comprado por un equipo:
B75: Empresa C | C75: 10.2 | D75: 43 | E75: =(MAX($D$73:$D$76)*2-D75)/10 -> 4.7 | F75: =SUM(C75,E75) -> 14.9 | G75: =F75/$F$77 -> 0.27798507 | H75: =ROUND(G75*$B$81,0) -> 973 | T75: Grupo de decisión | U75: Opción/Nivel | V75: Precio de lista | W75: Descontado por cantidad | X75: Unidad | Z75: Grupo de decisión | AA75: Opción/Nivel | AB75: Precio de lista | AC75: Descontado por cantidad | AD75: Unidad
B76: Empresa D | C76: 9 | D76: 41 | E76: =(MAX($D$73:$D$76)*2-D76)/10 -> 4.9 | F76: =SUM(C76,E76) -> 13.9 | G76: =F76/$F$77 -> 0.25932836 | H76: =ROUND(G76*$B$81,0) -> 908 | T76: Calidad del cuero | U76: 1- Cuero sintético | V76: 25 | W76: =V76-V76*8% -> 23 | X76: m² | Z76: Calidad del cuero | AA76: 1- Cuero sintético | AB76: =25*60 -> 1500 | AC76: =AB76-AB76*8% -> 1380 | AD76: 60m²
E77: Total | F77: =SUM(F73:F76) -> 53.6 | H77: =SUM(H73:H76) -> 3501 | T77: Calidad del cuero | U77: 2- Cuero genuino estándar | V77: 45 | W77: =V77-V77*8% -> 41.4 | X77: m² | Z77: Calidad del cuero | AA77: 2- Cuero genuino estándar | AB77: =45*55 -> 2475 | AC77: =AB77-AB77*8% -> 2277 | AD77: 55m²
T78: Calidad del cuero | U78: 3-Cuero genuino premium | V78: 80 | W78: =V78-V78*8% -> 73.6 | X78: m² | Z78: Calidad del cuero | AA78: 3-Cuero genuino premium | AB78: =80*15 -> 1200 | AC78: =AB78-AB78*8% -> 1104 | AD78: 15m²
B79: 7000 | C79: unidades mercado | T79: Calidad de accesorios | U79: 1- Aleación económica | V79: 4 | W79: =V79-V79*8% -> 3.68 | X79: unidad | Z79: Calidad de accesorios | AA79: 1- Aleación económica | AB79: =4*200 -> 800 | AC79: =AB79-AB79*8% -> 736 | AD79: 200 unidad
B80: 0.5 | T80: Calidad de accesorios | U80: 2- Metal premium | V80: 9 | W80: =V80-V80*8% -> 8.28 | X80: unidad | Z80: Calidad de accesorios | AA80: 2- Metal premium | AB80: =9*190 -> 1710 | AC80: =AB80-AB80*8% -> 1573.2 | AD80: 190 unidad
B81: =B79*B80 -> 3500 | C81: unidades mercado real | T81: Calidad del hilo | U81: 1- Poliéster estándar | V81: 2 | W81: =V81-V81*8% -> 1.84 | X81: m | Z81: Calidad del hilo | AA81: 1- Poliéster estándar | AB81: =2*0 -> 0 | AC81: =AB81-AB81*8% -> 0 | AD81: 0 m
T82: Calidad del hilo | U82: 2- Encerado reforzado | V82: 4 | W82: =V82-V82*8% -> 3.68 | X82: m | Z82: Calidad del hilo | AA82: 2- Encerado reforzado | AB82: =4*6 -> 24 | AC82: =AB82-AB82*8% -> 22.08 | AD82: 6 m
T83: Calidad del hilo | U83: 3- Alta tenacidad | V83: 7 | W83: =V83-V83*8% -> 6.44 | X83: m | Z83: Calidad del hilo | AA83: 3- Alta tenacidad | AB83: =7*7 -> 49 | AC83: =AB83-AB83*8% -> 45.08 | AD83: 7 m
Z84: Total | AB84: =SUM(AB76:AB83) -> 7758 | AC84: =SUM(AC76:AC83) -> 7137.36
T85: Inventario Inicial:
B86: EJEMPLO de distribución de Ventas (Bolsos promedio) | C86: Reputacion | D86: Precio | E86: Puntaje del precio | F86: Puntaje total | G86: Porcentaje parcial | H86: Unidades Vendidas | T86: Grupo de decisión | U86: Opción/Nivel | V86: Precio de lista | W86: Descontado por cantidad | X86: Unidad*cant. producida | Z86: Producción:
B87: Empresa A | C87: 7 | D87: 120 | E87: =(MAX($D$87:$D$90)*2-D87)/10 -> 28 | F87: =SUM(C87,E87) -> 35 | G87: =F87/$F$91 -> 0.27237354 | H87: =ROUND(G87*$B$81,0) -> 953 | T87: Calidad del cuero | U87: 1- Cuero sintético | V87: =25*60 -> 1500 | W87: =V87-V87*8% -> 1380 | X87: 60m² | Z87: Grupo de decisión | AA87: Opción/Nivel | AB87: Precio de lista | AC87: Descontado por cantidad | AD87: Unidad*cant. producida
B88: Empresa B | C88: 8.3 | D88: 150 | E88: =(MAX($D$87:$D$90)*2-D88)/10 -> 25 | F88: =SUM(C88,E88) -> 33.3 | G88: =F88/$F$91 -> 0.25914397 | H88: =ROUND(G88*$B$81,0) -> 907 | T88: Calidad del cuero | U88: 2- Cuero genuino estándar | V88: =45*110 -> 4950 | W88: =V88-V88*8% -> 4554 | X88: 110m² | Z88: Calidad del cuero | AA88: 1- Cuero sintético | AB88: =25*60 -> 1500 | AC88: =AB88-AB88*8% -> 1380 | AD88: 60m²
B89: Empresa C | C89: 10.2 | D89: 190 | E89: =(MAX($D$87:$D$90)*2-D89)/10 -> 21 | F89: =SUM(C89,E89) -> 31.2 | G89: =F89/$F$91 -> 0.24280156 | H89: =ROUND(G89*$B$81,0) -> 850 | T89: Calidad del cuero | U89: 3-Cuero genuino premium | V89: =80*30 -> 2400 | W89: =V89-V89*8% -> 2208 | X89: 30m² | Z89: Calidad del cuero | AA89: 2- Cuero genuino estándar | AB89: =45*107 -> 4815 | AC89: =AB89-AB89*8% -> 4429.8 | AD89: 107m²
B90: Empresa D | C90: 9 | D90: 200 | E90: =(MAX($D$87:$D$90)*2-D90)/10 -> 20 | F90: =SUM(C90,E90) -> 29 | G90: =F90/$F$91 -> 0.22568093 | H90: =ROUND(G90*$B$81,0) -> 790 | T90: Calidad de accesorios | U90: 1- Aleación económica | V90: =4*200 -> 800 | W90: =V90-V90*8% -> 736 | X90: 200 unidad | Z90: Calidad del cuero | AA90: 3-Cuero genuino premium | AB90: =80*0 -> 0 | AC90: =AB90-AB90*8% -> 0 | AD90: 0m²
E91: Total | F91: =SUM(F87:F90) -> 128.5 | T91: Calidad de accesorios | U91: 2- Metal premium | V91: =9*190 -> 1710 | W91: =V91-V91*8% -> 1573.2 | X91: 190 unidad | Z91: Calidad de accesorios | AA91: 1- Aleación económica | AB91: =4*200 -> 800 | AC91: =AB91-AB91*8% -> 736 | AD91: 200 unidad
T92: Calidad del hilo | U92: 1- Poliéster estándar | V92: =2*0 -> 0 | W92: =V92-V92*8% -> 0 | X92: 0 m | Z92: Calidad de accesorios | AA92: 2- Metal premium | AB92: =9*185 -> 1665 | AC92: =AB92-AB92*8% -> 1531.8 | AD92: 185 unidad
B93: 5000 | C93: unidades mercado | T93: Calidad del hilo | U93: 2- Encerado reforzado | V93: =4*1500 -> 6000 | W93: =V93-V93*8% -> 5520 | X93: 1500 m | Z93: Calidad del hilo | AA93: 1- Poliéster estándar | AB93: =2*0 -> 0 | AC93: =AB93-AB93*8% -> 0 | AD93: 0 m
B94: 0.7 | T94: Calidad del hilo | U94: 3- Alta tenacidad | V94: =7*1400 -> 9800 | W94: =V94-V94*8% -> 9016 | X94: 1400 m | Z94: Calidad del hilo | AA94: 2- Encerado reforzado | AB94: =4*1500 -> 6000 | AC94: =AB94-AB94*8% -> 5520 | AD94: 1500 m
B95: =B93*B94 -> 3500 | C95: unidades mercado real | T95: Total | V95: =SUM(V87:V94) -> 27160 | W95: =SUM(W87:W94) -> 24987.2 | Z95: Calidad del hilo | AA95: 3- Alta tenacidad | AB95: =7*1400 -> 9800 | AC95: =AB95-AB95*8% -> 9016 | AD95: 1400 m
Z96: Total | AB96: =SUM(AB88:AB95) -> 24580 | AC96: =SUM(AC88:AC95) -> 22613.6
T98: Inventario final: Inventario inicial - Producción
B100: EJEMPLO de distribución de Ventas (Bolsos Premium) | C100: Reputacion | D100: Precio | E100: Puntaje del precio | F100: Puntaje total | G100: Porcentaje parcial | H100: Unidades Vendidas | T100: Total | V100: =V95-AB96 -> 2580 | W100: =W95-AC96 -> 2373.6
B101: Empresa A | C101: 7 | D101: 250 | E101: =(MAX($D$101:$D$104)*2-D101)/10 -> 55 | F101: =SUM(C101,E101) -> 62 | G101: =F101/$F$105 -> 0.26105263 | H101: =ROUND(G101*$B$109,0) -> 209
B102: Empresa B | C102: 8.3 | D102: 300 | E102: =(MAX($D$101:$D$104)*2-D102)/10 -> 50 | F102: =SUM(C102,E102) -> 58.3 | G102: =F102/$F$105 -> 0.24547368 | H102: =ROUND(G102*$B$109,0) -> 196
B103: Empresa C | C103: 10.2 | D103: 220 | E103: =(MAX($D$101:$D$104)*2-D103)/10 -> 58 | F103: =SUM(C103,E103) -> 68.2 | G103: =F103/$F$105 -> 0.28715789 | H103: =ROUND(G103*$B$109,0) -> 230
B104: Empresa D | C104: 9 | D104: 400 | E104: =(MAX($D$101:$D$104)*2-D104)/10 -> 40 | F104: =SUM(C104,E104) -> 49 | G104: =F104/$F$105 -> 0.20631579 | H104: =ROUND(G104*$B$109,0) -> 165
...

Sheet Copia de Costos De Producción
A1: Calculo de MO
T2: Costos: MO
A3: AREA DE CORTE
E4: Bolsas por día | F4: Mesa de corte | K4: Producción por día | L4: AL MES | M4: Eficiencia | N4: Produccion Real | T4: O.Basico | U4: MYPE | V4: NoMype | X4: Costurero básico | Y4: MYPE | Z4: NoMype | AB4: Operario de acabado clásico | AC4: MYPE | AD4: NoMype
C5: Nivel 1 - Operario basico | E5: 6 | F5: 1 | I5: =E5*F5 -> 6 | K5: =MIN(I8,I14,I20) -> 14 | L5: =K5*30 -> 420 | M5: =K7+(F7+F13+F19)/100+4%*F21 -> 0.91 | N5: =ROUND(L5*M5,0) -> 382 | O5: Esta produccion no puede ser superior a lo que permite el material | T5: Sueldo base | U5: 1500 | V5: 1500 | X5: Sueldo base | Y5: 1500 | Z5: 1500 | AB5: Sueldo base | AC5: 1500 | AD5: 1500
C6: Nivel 2 - Cortador con experiencia | E6: 8 | F6: 1 | I6: =E6*F6 -> 8 | K6: Eficiencia BASE | T6: Essalud | U6: =U5*0.09 -> 135 | V6: =V5*0.09 -> 135 | X6: Essalud | Y6: =Y5*0.09 -> 135 | Z6: =Z5*0.09 -> 135 | AB6: Essalud | AC6: =AC5*0.09 -> 135 | AD6: =AD5*0.09 -> 135
C7: Nivel 3 - Maestro cortador | E7: 12 | F7: 0 | I7: =E7*F7 -> 0 | K7: 0.9 | T7: Grati | U7: =U5 -> 1500 | V7: =V5*2 -> 3000 | X7: Grati | Y7: =Y5 -> 1500 | Z7: =Z5*2 -> 3000 | AB7: Grati | AC7: =AC5 -> 1500 | AD7: =AD5*2 -> 3000
A8: AREA DE ENSAMBLADO | I8: =SUM(I5:I7) -> 14 | T8: CTS | U8: 750 | V8: 1500 | X8: CTS | Y8: 750 | Z8: 1500 | AB8: CTS | AC8: 750 | AD8: 1500
C9: Operarios | F9: MAQUINARIA MANUAL | G9: MAQUINARIA SEMIINDUSTRIAL | H9: MAQUINARIA INDUSTRIAL | K9: Total de trabajadores | L9: =SUM(F5:F7,F11:H13,F17:H19) -> 7 | T9: vacaciones | U9: =U5/2 -> 750 | V9: =V5 -> 1500 | X9: vacaciones | Y9: =Y5/2 -> 750 | Z9: =Z5 -> 1500 | AB9: vacaciones | AC9: =AC5/2 -> 750 | AD9: =AD5 -> 1500
F10: 1 | G10: 1.2 | H10: 1.5 | K10: total de trabajadores N3 | L10: =SUM(F7,F13:H13,F19:H19) -> 2 | M10: =L10/L9 -> 0.28571429 | T10: Suma anual | U10: =SUM(U6:U9)+U5*12 -> 21135 | V10: =SUM(V6:V9)+V5*12 -> 24135 | X10: Suma anual | Y10: =SUM(Y6:Y9)+Y5*12 -> 21135 | Z10: =SUM(Z6:Z9)+Z5*12 -> 24135 | AB10: Suma anual | AC10: =SUM(AC6:AC9)+AC5*12 -> 21135 | AD10: =SUM(AD6:AD9)+AD5*12 -> 24135
C11: Nivel 1 | E11: 6 | H11: 1 | I11: =SUM(F11*E11*$F$10,G11*E11*$G$10,H11*E11*$H$10) -> 9 | T11: Pago mensual | U11: =U10/12.5 -> 1690.8 | V11: =V10/13 -> 1856.5385 | X11: Pago mensual | Y11: =Y10/12.5 -> 1690.8 | Z11: =Z10/13 -> 1856.5385 | AB11: Pago mensual | AC11: =AC10/12.5 -> 1690.8 | AD11: =AD10/13 -> 1856.5385
C12: Nivel 2 | E12: 8 | F12: 1 | I12: =SUM(F12*E12*$F$10,G12*E12*$G$10,H12*E12*$H$10) -> 8
C13: Nivel 3 | E13: 12 | G13: 1 | I13: =SUM(F13*E13*$F$10,G13*E13*$G$10,H13*E13*$H$10) -> 14.4 | T13: Cortador con experiencia | U13: MYPE | V13: NoMype | X13: Maquinista industrial | Y13: MYPE | Z13: NoMype | AB13: Técnico de acabado | AC13: MYPE | AD13: NoMype
A14: AREA DE ACABADO | I14: =SUM(I11:I13) -> 31.4 | T14: Sueldo base | U14: 2000 | V14: 2000 | X14: Sueldo base | Y14: 2800 | Z14: 2800 | AB14: Sueldo base | AC14: 2800 | AD14: 2800
C15: Operarios | F15: MAQUINARIA MANUAL | G15: MAQUINARIA SEMIINDUSTRIAL | H15: MAQUINARIA INDUSTRIAL | T15: Essalud | U15: =U14*0.09 -> 180 | V15: =V14*0.09 -> 180 | X15: Essalud | Y15: =Y14*0.09 -> 252 | Z15: =Z14*0.09 -> 252 | AB15: Essalud | AC15: =AC14*0.09 -> 252 | AD15: =AD14*0.09 -> 252
F16: 1 | G16: 1.2 | H16: 1.5 | T16: Grati | U16: =U14 -> 2000 | V16: =V14*2 -> 4000 | X16: Grati | Y16: =Y14 -> 2800 | Z16: =Z14*2 -> 5600 | AB16: Grati | AC16: =AC14 -> 2800 | AD16: =AD14*2 -> 5600
C17: Nivel 1 | E17: 6 | I17: =SUM(F17*E17*$F$16,G17*E17*$G$16,H17*E17*$H$16) -> 0 | T17: CTS | U17: =U14/2 -> 1000 | V17: =V14 -> 2000 | X17: CTS | Y17: 750 | Z17: 1500 | AB17: CTS | AC17: 750 | AD17: 1500
C18: Nivel 2 | E18: 8 | H18: 1 | I18: =SUM(F18*E18*$F$16,G18*E18*$G$16,H18*E18*$H$16) -> 12 | T18: vacaciones | U18: =U14/2 -> 1000 | V18: =V14 -> 2000 | X18: vacaciones | Y18: =Y14/2 -> 1400 | Z18: =Z14 -> 2800 | AB18: vacaciones | AC18: =AC14/2 -> 1400 | AD18: =AD14 -> 2800
C19: Nivel 3 | E19: 12 | F19: 1 | I19: =SUM(F19*E19*$F$16,G19*E19*$G$16,H19*E19*$H$16) -> 12 | T19: Suma anual | U19: =SUM(U15:U18)+U14*12 -> 28180 | V19: =SUM(V15:V18)+V14*12 -> 32180 | X19: Suma anual | Y19: =SUM(Y15:Y18)+Y14*12 -> 38802 | Z19: =SUM(Z15:Z18)+Z14*12 -> 43752 | AB19: Suma anual | AC19: =SUM(AC15:AC18)+AC14*12 -> 38802 | AD19: =SUM(AD15:AD18)+AD14*12 -> 43752
I20: =SUM(I17:I19) -> 24 | T20: Pago mensual | U20: =U19/12.5 -> 2254.4 | V20: =V19/13 -> 2475.3846 | X20: Pago mensual | Y20: =Y19/12.5 -> 3104.16 | Z20: =Z19/13 -> 3365.5385 | AB20: Pago mensual | AC20: =AC19/12.5 -> 3104.16 | AD20: =AD19/13 -> 3365.5385
A21: Jefe de Produccion | F21: 0
T22: Maestro cortador | U22: MYPE | V22: NoMype | X22: Marroquinero especializado | Y22: MYPE | Z22: NoMype | AB22: Artesano acabador | AC22: MYPE | AD22: NoMype
B23: NOTA: EL PROCETANJE DE TRABAJADORES DE NIVEL 3 AFECTA POSITIVAMENTE A LA EFICIENCIA | T23: Sueldo base | U23: 3800 | V23: 3800 | X23: Sueldo base | Y23: 4500 | Z23: 4500 | AB23: Sueldo base | AC23: 4500 | AD23: 4500
T24: Essalud | U24: =U23*0.09 -> 342 | V24: =V23*0.09 -> 342 | X24: Essalud | Y24: =Y23*0.09 -> 405 | Z24: =Z23*0.09 -> 405 | AB24: Essalud | AC24: =AC23*0.09 -> 405 | AD24: =AD23*0.09 -> 405
A25: Calculo de MP | T25: Grati | U25: =U23 -> 3800 | V25: =V23*2 -> 7600 | X25: Grati | Y25: =Y23 -> 4500 | Z25: =Z23*2 -> 9000 | AB25: Grati | AC25: =AC23 -> 4500 | AD25: =AD23*2 -> 9000
T26: CTS | U26: 750 | V26: 1500 | X26: CTS | Y26: 750 | Z26: 1500 | AB26: CTS | AC26: 750 | AD26: 1500
D27: Calidad del cuero | E27: Calidad del cuero | F27: Calidad del cuero | G27: Calidad de accesorios | H27: Calidad de accesorios | I27: Calidad del hilo | J27: Calidad del hilo | K27: Calidad del hilo | T27: vacaciones | U27: =U23/2 -> 1900 | V27: =V23 -> 3800 | X27: vacaciones | Y27: =Y23/2 -> 2250 | Z27: =Z23 -> 4500 | AB27: vacaciones | AC27: =AC23/2 -> 2250 | AD27: =AD23 -> 4500
D28: Nivel 1 - Cuero sintetico | E28: Nivel 2 - Cuero genuino estandar | F28: Nivel 3 - Cuero genuino premium | G28: Nivel 1 - Aleacion economica | H28: Nivel 2 - Metal premium | I28: Nivel 1 - Poliester estandar | J28: Nivel 2 - Encerado reforzado | K28: Nivel 3 - Alta tenacidad (nylon trenzado) | T28: Suma anual | U28: =SUM(U24:U27)+U23*12 -> 52392 | V28: =SUM(V24:V27)+V23*12 -> 58842 | X28: Suma anual | Y28: =SUM(Y24:Y27)+Y23*12 -> 61905 | Z28: =SUM(Z24:Z27)+Z23*12 -> 69405 | AB28: Suma anual | AC28: =SUM(AC24:AC27)+AC23*12 -> 61905 | AD28: =SUM(AD24:AD27)+AD23*12 -> 69405
C29: UM Compra | D29: rollo | E29: Piel completa | F29: Piel completa | G29: Juego | H29: Juego | I29: Carrete | J29: Carrete | K29: Carrete | T29: Pago mensual | U29: =U28/12.5 -> 4191.36 | V29: =V28/13 -> 4526.3077 | X29: Pago mensual | Y29: =Y28/12.5 -> 4952.4 | Z29: =Z28/13 -> 5338.8462 | AB29: Pago mensual | AC29: =AC28/12.5 -> 4952.4 | AD29: =AD28/13 -> 5338.8462
C30: UM Produccion | D30: m2 | E30: m2 | F30: m2 | G30: unidad | H30: unidad | I30: metro | J30: metro | K30: metro
B31: Cantidad necesaria | C31: Compra Jugador | D31: 60 | E31: 55 | F31: 15 | G31: 200 | H31: 190 | I31: 0 | J31: 6 | K31: 7
C32: Cantidad Produccion | D32: 1 | E32: 2 | F32: 2 | G32: 1 | H32: 1 | I32: 270 | J32: 250 | K32: 200 | T32: Jefatura | U32: MYPE | V32: NoMype | X32: Limpieza | Y32: MYPE | Z32: NoMype | AB32: Local de producción | AC32: MYPE | AD32: NoMype
D33: =D31*D32 -> 60 | E33: =E31*E32 -> 110 | F33: =F31*F32 -> 30 | G33: =G31*G32 -> 200 | H33: =H31*H32 -> 190 | I33: =I31*I32 -> 0 | J33: =J31*J32 -> 1500 | K33: =K31*K32 -> 1400 | T33: Sueldo base | U33: 3000 | V33: 3000 | X33: Sueldo base | Y33: 600 | Z33: 600 | AB33: Costo fijo | AC33: 2000 | AD33: 2000
T34: Essalud | U34: =U33*0.09 -> 270 | V34: =V33*0.09 -> 270 | X34: Essalud | Y34: =Y33*0.09 -> 54 | Z34: =Z33*0.09 -> 54
H35: InventarioFinal = InventarioInicial + compras - produccido | T35: Grati | U35: =U33 -> 3000 | V35: =V33*2 -> 6000 | X35: Grati | Y35: =Y33 -> 600 | Z35: =Z33*2 -> 1200
D36: m2 | E36: unidad | F36: metro | H36: Almacen | T36: CTS | U36: 750 | V36: 1500 | X36: CTS | Y36: 750 | Z36: 1500
C37: Moldes (siempre debe comprar al menos uno) | D37: Cuero | E37: Accesorios | F37: Hilos | H37: Cuero | I37: Accesorios | J37: Hilos | T37: vacaciones | U37: =U33/2 -> 1500 | V37: =V33 -> 3000 | X37: vacaciones | Y37: =Y33/2 -> 300 | Z37: =Z33 -> 600
C38: Nivel 1 - Generico basico | D38: 0.3 | E38: 1 | F38: 6 | H38: =SUM(D33:F33) -> 200 | I38: =SUM(G33:H33) -> 390 | J38: =SUM(I33:K33) -> 2900 | T38: Suma anual | U38: =SUM(U34:U37)+U33*12 -> 41520 | V38: =SUM(V34:V37)+V33*12 -> 46770 | X38: Suma anual | Y38: =SUM(Y34:Y37)+Y33*12 -> 8904 | Z38: =SUM(Z34:Z37)+Z33*12 -> 10554
C39: Nivel 2 - Generico mejorado | D39: 0.4 | E39: 1 | F39: 7 | T39: Pago mensual | U39: =U38/12.5 -> 3321.6 | V39: =V38/13 -> 3597.6923 | X39: Pago mensual | Y39: =Y38/12.5 -> 712.32 | Z39: =Z38/13 -> 811.84615
C40: Nivel 3 - Premium | D40: 0.7 | E40: 1 | F40: 13
B42: como estamos trabajando los hilos, po rmetro? pero cuando compramos compramos metros o carretes? si es carretes cuantos metros tiene | T42: Costos: Maquinaria
B43: es mas sencillo trabajarlo como unidad y establecer valores mas pequeños de hilo necesario, bajarle el precio al hilo
T44: Mesa de corte | U44: MYPE | V44: NoMype | X44: Maquina de Ensamblado N1 | Y44: MYPE | Z44: NoMype | AB44: Maquina de acabado N1 | AC44: MYPE | AD44: NoMype
C45: Cuantos Bolso deseas producir ? | E45: Producido luego del termino del ciclo | H45: Total Cuero Necesario | I45: Total Accesorios Necesario | J45: Total Hilo Necesario | L45: Total Cuero Utilizado | M45: Total Accesorios Utilizado | N45: Total Hilo Utilizado | T45: Costo de adquisición | U45: 2500 | V45: 2500 | X45: Costo de adquisición | Y45: 3500 | Z45: 3500 | AB45: Costo de adquisición | AC45: 1200 | AD45: 1200
C46: Nivel 1 - Generico basico | D46: 150 | E46: 150 | F46: =E46/E49 -> 0.4076087 | H46: =D38*D46 -> 45 | I46: =D46*E38 -> 150 | J46: =F38*D46 -> 900 | L46: =E46*D38 -> 45 | M46: =E46*E38 -> 150 | N46: =F38*E46 -> 900 | T46: Instalación | U46: =U45*3% -> 75 | V46: =V45*5% -> 125 | X46: Instalación | Y46: =Y45*3% -> 105 | Z46: =Z45*5% -> 175 | AB46: Instalación | AC46: =AC45*3% -> 36 | AD46: =AD45*5% -> 60
C47: Nivel 2 - Generico mejorado | D47: 140 | E47: 140 | F47: =E47/E49 -> 0.38043478 | H47: =D39*D47 -> 56 | I47: =D47*E39 -> 140 | J47: =F39*D47 -> 980 | L47: =E47*D39 -> 56 | M47: =E47*E39 -> 140 | N47: =F39*E47 -> 980 | T47: Capacitación | U47: =U45*2% -> 50 | V47: =V45*3% -> 75 | X47: Capacitación | Y47: =Y45*2% -> 70 | Z47: =Z45*3% -> 105 | AB47: Capacitación | AC47: =AC45*2% -> 24 | AD47: =AD45*3% -> 36
C48: Nivel 3 - Premium | D48: 95 | E48: 78 | F48: =E48/E49 -> 0.21195652 | H48: =D40*D48 -> 66.5 | I48: =D48*E40 -> 95 | J48: =F40*D48 -> 1235 | L48: =D40*E48 -> 54.6 | M48: =E48*E40 -> 78 | N48: =F40*E48 -> 1014 | T48: Mantenimiento anual | U48: =U45*5% -> 125 | V48: =V45*8% -> 200 | X48: Mantenimiento anual | Y48: =Y45*5% -> 175 | Z48: =Z45*8% -> 280 | AB48: Mantenimiento anual | AC48: =AC45*5% -> 60 | AD48: =AD45*8% -> 96
D49: =SUM(D46:D48) -> 385 | E49: =SUM(E46:E48) -> 368 | F49: =SUM(F46:F48) -> 1 | H49: =SUM(H46:H48) -> 167.5 | I49: =SUM(I46:I48) -> 385 | J49: =SUM(J46:J48) -> 3115 | L49: =SUM(L46:L48) -> 155.6 | M49: =SUM(M46:M48) -> 368 | N49: =SUM(N46:N48) -> 2894 | T49: Depreciación anual | U49: =-((U45-U45*5%)/10) -> -237.5 | V49: =-((V45-V45*10%)/10) -> -225 | X49: Depreciación anual | Y49: =-(Y45-Y45*5%)/10 -> -332.5 | Z49: =-(Z45-Z45*10%)/10 -> -315 | AB49: Depreciación anual | AC49: =-(AC45-AC45*5%)/8 -> -142.5 | AD49: =-(AD45-AD45*10%)/8 -> -135
T50: Suma anual | U50: =SUM(U46:U49)+U45 -> 2512.5 | V50: =SUM(V46:V49)+V45 -> 2675 | X50: Suma anual | Y50: =SUM(Y46:Y49)+Y45 -> 3517.5 | Z50: =SUM(Z46:Z49)+Z45 -> 3745 | AB50: Suma anual | AC50: =SUM(AC46:AC49)+AC45 -> 1177.5 | AD50: =SUM(AD46:AD49)+AD45 -> 1257
C52: ALMACEN | T52: Molde 1 | U52: MYPE | V52: NoMype | X52: Maquina de Ensamblado N2 | Y52: MYPE | Z52: NoMype | AB52: Maquina de acabado N2 | AC52: MYPE | AD52: NoMype
D53: Inventario Inicial | E53: Compras | F53: Produccion | G53: Inventario Final | T53: Costo de adquisición | U53: 300 | V53: 300 | X53: Costo de adquisición | Y53: 7500 | Z53: 7500 | AB53: Costo de adquisición | AC53: 4500 | AD53: 4500
C54: Nivel 1 - Cuero sintetico | D54: 0 | E54: =D33 -> 60 | F54: =MIN(E54,H49) -> 60 | G54: =D54+E54-F54 -> 0 | T54: Capacitación | U54: =U53*1% -> 3 | V54: =V53*2% -> 6 | X54: Instalación | Y54: =Y53*3% -> 225 | Z54: =Z53*5% -> 375 | AB54: Instalación | AC54: =AC53*3% -> 135 | AD54: =AD53*5% -> 225
C55: Nivel 2 - Cuero genuino estandar | D55: 0 | E55: =E33 -> 110 | F55: =min(E55,H49-F54) -> 107.5 | G55: =D55+E55-F55 -> 2.5 | T55: Mantenimiento anual | U55: =U53*5% -> 15 | V55: =V53*8% -> 24 | X55: Capacitación | Y55: =Y53*2% -> 150 | Z55: =Z53*3% -> 225 | AB55: Capacitación | AC55: =AC53*2% -> 90 | AD55: =AD53*3% -> 135
C56: Nivel 3 - Cuero genuino premium | D56: 0 | E56: =F33 -> 30 | F56: =MIN(E56,H49-F54-F55) -> 0 | G56: =D56+E56-F56 -> 30 | H56: =F56/SUM(F54:F56) -> 0 | T56: Depreciación anual | U56: =-((U53-U53*5%)/5) -> -57 | V56: =-((V53-V53*10%)/5) -> -54 | X56: Mantenimiento anual | Y56: =Y53*5% -> 375 | Z56: =Z53*8% -> 600 | AB56: Mantenimiento anual | AC56: =AC53*5% -> 225 | AD56: =AD53*8% -> 360
C57: Nivel 1 - Aleacion economica | D57: 0 | E57: =G33 -> 200 | F57: =MIN(E57,I49) -> 200 | G57: =D57+E57-F57 -> 0 | T57: Suma anual | U57: =SUM(U54:U56)+U53 -> 261 | V57: =SUM(V54:V56)+V53 -> 276 | X57: Depreciación anual | Y57: =-(Y53-Y53*5%)/10 -> -712.5 | Z57: =-(Z53-Z53*10%)/10 -> -675 | AB57: Depreciación anual | AC57: =-(AC53-AC53*5%)/8 -> -534.375 | AD57: =-(AD53-AD53*10%)/8 -> -506.25
C58: Nivel 2 - Metal premium | D58: 0 | E58: =H33 -> 190 | F58: =MIN(E58,I49-F57) -> 185 | G58: =D58+E58-F58 -> 5 | H58: =F58/SUM(F57:F58) -> 0.48051948 | X58: Suma anual | Y58: =SUM(Y54:Y57)+Y53 -> 7537.5 | Z58: =SUM(Z54:Z57)+Z53 -> 8025 | AB58: Suma anual | AC58: =SUM(AC54:AC57)+AC53 -> 4415.625 | AD58: =SUM(AD54:AD57)+AD53 -> 4713.75
C59: Nivel 1 - Poliester estandar | D59: 0 | E59: =I33 -> 0 | F59: =MIN(E59,J49) -> 0 | G59: =D59+E59-F59 -> 0 | T59: Molde 2 | U59: MYPE | V59: NoMype
C60: Nivel 2 - Encerado reforzado | D60: 0 | E60: =J33 -> 1500 | F60: =MIN(E60,J49-F59) -> 1500 | G60: =D60+E60-F60 -> 0 | T60: Costo de adquisición | U60: 1200 | V60: 1200 | X60: Maquina de Ensamblado N3 | Y60: MYPE | Z60: NoMype | AB60: Maquina de acabado N3 | AC60: MYPE | AD60: NoMype
C61: Nivel 3 - Alta tenacidad (nylon trenzado) | D61: 0 | E61: =K33 -> 1400 | F61: =MIN(E61,J49-F59-F60) -> 1400 | G61: =D61+E61-F61 -> 0 | H61: =F61/(SUM(F60:F61)) -> 0.48275862 | T61: Capacitación | U61: =U60*1% -> 12 | V61: =V60*2% -> 24 | X61: Costo de adquisición | Y61: 15000 | Z61: 15000 | AB61: Costo de adquisición | AC61: 9500 | AD61: 9500
B62: 0 - 10,000(rango en soles) | T62: Mantenimiento anual | U62: =U60*5% -> 60 | V62: =V60*8% -> 96 | X62: Instalación | Y62: =Y61*3% -> 450 | Z62: =Z61*5% -> 750 | AB62: Instalación | AC62: =AC61*3% -> 285 | AD62: =AD61*5% -> 475
A63: Gastos del ciclo en publicidad | B63: 3000 | T63: Depreciación anual | U63: =-((U60-U60*5%)/5) -> -228 | V63: =-((V60-V60*10%)/5) -> -216 | X63: Capacitación | Y63: =Y61*2% -> 300 | Z63: =Z61*3% -> 450 | AB63: Capacitación | AC63: =AC61*2% -> 190 | AD63: =AD61*3% -> 285
T64: Suma anual | U64: =SUM(U61:U63)+U60 -> 1044 | V64: =SUM(V61:V63)+V60 -> 1104 | X64: Mantenimiento anual | Y64: =Y61*5% -> 750 | Z64: =Z61*8% -> 1200 | AB64: Mantenimiento anual | AC64: =AC61*5% -> 475 | AD64: =AD61*8% -> 760
A65: Calculo de Reputacion | C65: =F48*10 -> 2.1195652 | D65: =M10*10 -> 2.8571429 | E65: =AVERAGE(H56,H58,H61)*10 -> 3.210927 | F65: =B63/10000*10 -> 3 | G65: =SUM(C65:F65) -> 11.187635 | H65: ptos de reputación | X65: Depreciación anual | Y65: =-(Y61-Y61*5%)/10 -> -1425 | Z65: =-(Z61-Z61*10%)/10 -> -1350 | AB65: Depreciación anual | AC65: =-(AC61-AC61*5%)/8 -> -1128.125 | AD65: =-(AD61-AD61*10%)/8 -> -1068.75
C66: Factor de producción | D66: Factor de MO | E66: Factor de MP (utilizacion) | F66: Factor de Publicidad | T66: Moldes 3 | U66: MYPE | V66: NoMype | X66: Suma anual | Y66: =SUM(Y62:Y65)+Y61 -> 15075 | Z66: =SUM(Z62:Z65)+Z61 -> 16050 | AB66: Suma anual | AC66: =SUM(AC62:AC65)+AC61 -> 9321.875 | AD66: =SUM(AD62:AD65)+AD61 -> 9951.25
T67: Costo de adquisición | U67: 3500 | V67: 3500
T68: Capacitación | U68: =U67*1% -> 35 | V68: =V67*2% -> 70
T69: Mantenimiento anual | U69: =U67*5% -> 175 | V69: =V67*8% -> 280
T70: Depreciación anual | U70: =-((U67-U67*5%)/5) -> -665 | V70: =-((V67-V67*10%)/5) -> -630
T71: Suma anual | U71: =SUM(U68:U70)+U67 -> 3045 | V71: =SUM(V68:V70)+V67 -> 3220
B72: EJEMPLO de distribución de Ventas (Bolsos Economicos) | C72: Reputacion | D72: Precio | E72: Puntaje del precio | F72: Puntaje total | G72: Porcentaje parcial | H72: Unidades Vendidas
B73: Empresa A | C73: 7 | D73: 40 | E73: =(MAX($D$73:$D$76)*2-D73)/10 -> 5 | F73: =SUM(C73,E73) -> 12 | G73: =F73/$F$77 -> 0.2238806 | H73: =ROUND(G73*$B$81,0) -> 784 | T73: Costos: MP
B74: Empresa B | C74: 8.3 | D74: 45 | E74: =(MAX($D$73:$D$76)*2-D74)/10 -> 4.5 | F74: =SUM(C74,E74) -> 12.8 | G74: =F74/$F$77 -> 0.23880597 | H74: =ROUND(G74*$B$81,0) -> 836 | T74: Tabla de materia base. | Z74: Lo que sea comprado por un equipo:
B75: Empresa C | C75: 10.2 | D75: 43 | E75: =(MAX($D$73:$D$76)*2-D75)/10 -> 4.7 | F75: =SUM(C75,E75) -> 14.9 | G75: =F75/$F$77 -> 0.27798507 | H75: =ROUND(G75*$B$81,0) -> 973 | T75: Grupo de decisión | U75: Opción/Nivel | V75: Precio de lista | W75: Descontado por cantidad | X75: Unidad | Z75: Grupo de decisión | AA75: Opción/Nivel | AB75: Precio de lista | AC75: Descontado por cantidad | AD75: Unidad
B76: Empresa D | C76: 9 | D76: 41 | E76: =(MAX($D$73:$D$76)*2-D76)/10 -> 4.9 | F76: =SUM(C76,E76) -> 13.9 | G76: =F76/$F$77 -> 0.25932836 | H76: =ROUND(G76*$B$81,0) -> 908 | T76: Calidad del cuero | U76: 1- Cuero sintético | V76: 25 | W76: =V76-V76*8% -> 23 | X76: m² | Z76: Calidad del cuero | AA76: 1- Cuero sintético | AB76: =25*60 -> 1500 | AC76: =AB76-AB76*8% -> 1380 | AD76: 60m²
E77: Total | F77: =SUM(F73:F76) -> 53.6 | H77: =SUM(H73:H76) -> 3501 | T77: Calidad del cuero | U77: 2- Cuero genuino estándar | V77: 45 | W77: =V77-V77*8% -> 41.4 | X77: m² | Z77: Calidad del cuero | AA77: 2- Cuero genuino estándar | AB77: =45*55 -> 2475 | AC77: =AB77-AB77*8% -> 2277 | AD77: 55m²
T78: Calidad del cuero | U78: 3-Cuero genuino premium | V78: 80 | W78: =V78-V78*8% -> 73.6 | X78: m² | Z78: Calidad del cuero | AA78: 3-Cuero genuino premium | AB78: =80*15 -> 1200 | AC78: =AB78-AB78*8% -> 1104 | AD78: 15m²
B79: 7000 | C79: unidades mercado | T79: Calidad de accesorios | U79: 1- Aleación económica | V79: 4 | W79: =V79-V79*8% -> 3.68 | X79: unidad | Z79: Calidad de accesorios | AA79: 1- Aleación económica | AB79: =4*200 -> 800 | AC79: =AB79-AB79*8% -> 736 | AD79: 200 unidad
B80: 0.5 | T80: Calidad de accesorios | U80: 2- Metal premium | V80: 9 | W80: =V80-V80*8% -> 8.28 | X80: unidad | Z80: Calidad de accesorios | AA80: 2- Metal premium | AB80: =9*190 -> 1710 | AC80: =AB80-AB80*8% -> 1573.2 | AD80: 190 unidad
B81: =B79*B80 -> 3500 | C81: unidades mercado real | T81: Calidad del hilo | U81: 1- Poliéster estándar | V81: 2 | W81: =V81-V81*8% -> 1.84 | X81: m | Z81: Calidad del hilo | AA81: 1- Poliéster estándar | AB81: =2*0 -> 0 | AC81: =AB81-AB81*8% -> 0 | AD81: 0 m
T82: Calidad del hilo | U82: 2- Encerado reforzado | V82: 4 | W82: =V82-V82*8% -> 3.68 | X82: m | Z82: Calidad del hilo | AA82: 2- Encerado reforzado | AB82: =4*6 -> 24 | AC82: =AB82-AB82*8% -> 22.08 | AD82: 6 m
T83: Calidad del hilo | U83: 3- Alta tenacidad | V83: 7 | W83: =V83-V83*8% -> 6.44 | X83: m | Z83: Calidad del hilo | AA83: 3- Alta tenacidad | AB83: =7*7 -> 49 | AC83: =AB83-AB83*8% -> 45.08 | AD83: 7 m
Z84: Total | AB84: =SUM(AB76:AB83) -> 7758 | AC84: =SUM(AC76:AC83) -> 7137.36
T85: Inventario Inicial:
B86: EJEMPLO de distribución de Ventas (Bolsos promedio) | C86: Reputacion | D86: Precio | E86: Puntaje del precio | F86: Puntaje total | G86: Porcentaje parcial | H86: Unidades Vendidas | T86: Grupo de decisión | U86: Opción/Nivel | V86: Precio de lista | W86: Descontado por cantidad | X86: Unidad*cant. producida | Z86: Producción:
B87: Empresa A | C87: 7 | D87: 120 | E87: =(MAX($D$87:$D$90)*2-D87)/10 -> 28 | F87: =SUM(C87,E87) -> 35 | G87: =F87/$F$91 -> 0.27237354 | H87: =ROUND(G87*$B$81,0) -> 953 | T87: Calidad del cuero | U87: 1- Cuero sintético | V87: =25*60 -> 1500 | W87: =V87-V87*8% -> 1380 | X87: 60m² | Z87: Grupo de decisión | AA87: Opción/Nivel | AB87: Precio de lista | AC87: Descontado por cantidad | AD87: Unidad*cant. producida
B88: Empresa B | C88: 8.3 | D88: 150 | E88: =(MAX($D$87:$D$90)*2-D88)/10 -> 25 | F88: =SUM(C88,E88) -> 33.3 | G88: =F88/$F$91 -> 0.25914397 | H88: =ROUND(G88*$B$81,0) -> 907 | T88: Calidad del cuero | U88: 2- Cuero genuino estándar | V88: =45*110 -> 4950 | W88: =V88-V88*8% -> 4554 | X88: 110m² | Z88: Calidad del cuero | AA88: 1- Cuero sintético | AB88: =25*60 -> 1500 | AC88: =AB88-AB88*8% -> 1380 | AD88: 60m²
B89: Empresa C | C89: 10.2 | D89: 190 | E89: =(MAX($D$87:$D$90)*2-D89)/10 -> 21 | F89: =SUM(C89,E89) -> 31.2 | G89: =F89/$F$91 -> 0.24280156 | H89: =ROUND(G89*$B$81,0) -> 850 | T89: Calidad del cuero | U89: 3-Cuero genuino premium | V89: =80*30 -> 2400 | W89: =V89-V89*8% -> 2208 | X89: 30m² | Z89: Calidad del cuero | AA89: 2- Cuero genuino estándar | AB89: =45*107 -> 4815 | AC89: =AB89-AB89*8% -> 4429.8 | AD89: 107m²
B90: Empresa D | C90: 9 | D90: 200 | E90: =(MAX($D$87:$D$90)*2-D90)/10 -> 20 | F90: =SUM(C90,E90) -> 29 | G90: =F90/$F$91 -> 0.22568093 | H90: =ROUND(G90*$B$81,0) -> 790 | T90: Calidad de accesorios | U90: 1- Aleación económica | V90: =4*200 -> 800 | W90: =V90-V90*8% -> 736 | X90: 200 unidad | Z90: Calidad del cuero | AA90: 3-Cuero genuino premium | AB90: =80*0 -> 0 | AC90: =AB90-AB90*8% -> 0 | AD90: 0m²
E91: Total | F91: =SUM(F87:F90) -> 128.5 | T91: Calidad de accesorios | U91: 2- Metal premium | V91: =9*190 -> 1710 | W91: =V91-V91*8% -> 1573.2 | X91: 190 unidad | Z91: Calidad de accesorios | AA91: 1- Aleación económica | AB91: =4*200 -> 800 | AC91: =AB91-AB91*8% -> 736 | AD91: 200 unidad
T92: Calidad del hilo | U92: 1- Poliéster estándar | V92: =2*0 -> 0 | W92: =V92-V92*8% -> 0 | X92: 0 m | Z92: Calidad de accesorios | AA92: 2- Metal premium | AB92: =9*185 -> 1665 | AC92: =AB92-AB92*8% -> 1531.8 | AD92: 185 unidad
B93: 5000 | C93: unidades mercado | T93: Calidad del hilo | U93: 2- Encerado reforzado | V93: =4*1500 -> 6000 | W93: =V93-V93*8% -> 5520 | X93: 1500 m | Z93: Calidad del hilo | AA93: 1- Poliéster estándar | AB93: =2*0 -> 0 | AC93: =AB93-AB93*8% -> 0 | AD93: 0 m
B94: 0.7 | T94: Calidad del hilo | U94: 3- Alta tenacidad | V94: =7*1400 -> 9800 | W94: =V94-V94*8% -> 9016 | X94: 1400 m | Z94: Calidad del hilo | AA94: 2- Encerado reforzado | AB94: =4*1500 -> 6000 | AC94: =AB94-AB94*8% -> 5520 | AD94: 1500 m
B95: =B93*B94 -> 3500 | C95: unidades mercado real | T95: Total | V95: =SUM(V87:V94) -> 27160 | W95: =SUM(W87:W94) -> 24987.2 | Z95: Calidad del hilo | AA95: 3- Alta tenacidad | AB95: =7*1400 -> 9800 | AC95: =AB95-AB95*8% -> 9016 | AD95: 1400 m
Z96: Total | AB96: =SUM(AB88:AB95) -> 24580 | AC96: =SUM(AC88:AC95) -> 22613.6
T98: Inventario final: Inventario inicial - Producción
B100: EJEMPLO de distribución de Ventas (Bolsos Premium) | C100: Reputacion | D100: Precio | E100: Puntaje del precio | F100: Puntaje total | G100: Porcentaje parcial | H100: Unidades Vendidas | T100: Total | V100: =V95-AB96 -> 2580 | W100: =W95-AC96 -> 2373.6
B101: Empresa A | C101: 7 | D101: 250 | E101: =(MAX($D$101:$D$104)*2-D101)/10 -> 55 | F101: =SUM(C101,E101) -> 62 | G101: =F101/$F$105 -> 0.26105263 | H101: =ROUND(G101*$B$109,0) -> 209
B102: Empresa B | C102: 8.3 | D102: 300 | E102: =(MAX($D$101:$D$104)*2-D102)/10 -> 50 | F102: =SUM(C102,E102) -> 58.3 | G102: =F102/$F$105 -> 0.24547368 | H102: =ROUND(G102*$B$109,0) -> 196
B103: Empresa C | C103: 10.2 | D103: 220 | E103: =(MAX($D$101:$D$104)*2-D103)/10 -> 58 | F103: =SUM(C103,E103) -> 68.2 | G103: =F103/$F$105 -> 0.28715789 | H103: =ROUND(G103*$B$109,0) -> 230
B104: Empresa D | C104: 9 | D104: 400 | E104: =(MAX($D$101:$D$104)*2-D104)/10 -> 40 | F104: =SUM(C104,E104) -> 49 | G104: =F104/$F$105 -> 0.20631579 | H104: =ROUND(G104*$B$109,0) -> 165
...

Sheet Lotes_Produccion
A1: Lote | B1: Segmento de venta (elige) | C1: Cantidad de unidades (input) | D1: Codigo Cuero (elige) | E1: Codigo Accesorios (elige) | F1: Codigo Hilo (elige) | G1: Codigo Molde (elige) | H1: Costo unitario insumos (auto) | I1: Puntaje Calidad del lote (auto) | J1: Umbral requerido por segmento (auto) | K1: Resultado (auto) | L1: Mensaje para el jugador (auto)
A2: Lote 1 | C2: 0 | H2: {=IFERROR(INDEX(Catalogo_Decisiones!$G$2:$G$57,MATCH($D2,Catalogo_Decisiones!$A$2:$A$57,0)),0)+IFERROR(INDEX(Catalogo_Decisiones!$G$2:$G$57,MATCH($E2,Catalogo_Decisiones!$A$2:$A$57,0)),0)+IFERROR(INDEX(Catalogo_Decisiones!$G$2:$G$57,MATCH($F2,Catalogo_Decisiones!$A$2:$A$57,0)),0)} -> 0 | I2: {=IFERROR(INDEX(Catalogo_Decisiones!$H$2:$H$57,MATCH($D2,Catalogo_Decisiones!$A$2:$A$57,0)),0)+IFERROR(INDEX(Catalogo_Decisiones!$H$2:$H$57,MATCH($E2,Catalogo_Decisiones!$A$2:$A$57,0)),0)+IFERROR(INDEX(Catalogo_Decisiones!$H$2:$H$57,MATCH($F2,Catalogo_Decisiones!$A$2:$A$57,0)),0)+IFERROR(INDEX(Catalogo_Decisiones!$H$2:$H$57,MATCH($G2,Catalogo_Decisiones!$A$2:$A$57,0)),0)} -> 0 | J2: =IFS($B2="SEG-01",0,$B2="SEG-02",4,$B2="SEG-03",7,TRUE(),0) -> 0 | K2: =IF(B2="","",IF(I2>=J2,"Coherente","No alcanza el segmento")) | L2: =IF(B2="","Elige un segmento y los insumos del lote",IF(K2="Coherente","Este lote cumple con la calidad esperada para su segmento. Los clientes perciben el valor y el precio se sostiene.","Este lote no alcanza la calidad que su segmento promete. Los clientes se sienten enganados: baja el precio efectivo y la reputacion.")) -> Elige un segmento y los insumos del lote
A3: Lote 2 | C3: 0 | H3: {=IFERROR(INDEX(Catalogo_Decisiones!$G$2:$G$57,MATCH($D3,Catalogo_Decisiones!$A$2:$A$57,0)),0)+IFERROR(INDEX(Catalogo_Decisiones!$G$2:$G$57,MATCH($E3,Catalogo_Decisiones!$A$2:$A$57,0)),0)+IFERROR(INDEX(Catalogo_Decisiones!$G$2:$G$57,MATCH($F3,Catalogo_Decisiones!$A$2:$A$57,0)),0)} -> 0 | I3: {=IFERROR(INDEX(Catalogo_Decisiones!$H$2:$H$57,MATCH($D3,Catalogo_Decisiones!$A$2:$A$57,0)),0)+IFERROR(INDEX(Catalogo_Decisiones!$H$2:$H$57,MATCH($E3,Catalogo_Decisiones!$A$2:$A$57,0)),0)+IFERROR(INDEX(Catalogo_Decisiones!$H$2:$H$57,MATCH($F3,Catalogo_Decisiones!$A$2:$A$57,0)),0)+IFERROR(INDEX(Catalogo_Decisiones!$H$2:$H$57,MATCH($G3,Catalogo_Decisiones!$A$2:$A$57,0)),0)} -> 0 | J3: =IFS($B3="SEG-01",0,$B3="SEG-02",4,$B3="SEG-03",7,TRUE(),0) -> 0 | K3: =IF(B3="","",IF(I3>=J3,"Coherente","No alcanza el segmento")) | L3: =IF(B3="","Elige un segmento y los insumos del lote",IF(K3="Coherente","Este lote cumple con la calidad esperada para su segmento. Los clientes perciben el valor y el precio se sostiene.","Este lote no alcanza la calidad que su segmento promete. Los clientes se sienten enganados: baja el precio efectivo y la reputacion.")) -> Elige un segmento y los insumos del lote
A4: Lote 3 | C4: 0 | H4: {=IFERROR(INDEX(Catalogo_Decisiones!$G$2:$G$57,MATCH($D4,Catalogo_Decisiones!$A$2:$A$57,0)),0)+IFERROR(INDEX(Catalogo_Decisiones!$G$2:$G$57,MATCH($E4,Catalogo_Decisiones!$A$2:$A$57,0)),0)+IFERROR(INDEX(Catalogo_Decisiones!$G$2:$G$57,MATCH($F4,Catalogo_Decisiones!$A$2:$A$57,0)),0)} -> 0 | I4: {=IFERROR(INDEX(Catalogo_Decisiones!$H$2:$H$57,MATCH($D4,Catalogo_Decisiones!$A$2:$A$57,0)),0)+IFERROR(INDEX(Catalogo_Decisiones!$H$2:$H$57,MATCH($E4,Catalogo_Decisiones!$A$2:$A$57,0)),0)+IFERROR(INDEX(Catalogo_Decisiones!$H$2:$H$57,MATCH($F4,Catalogo_Decisiones!$A$2:$A$57,0)),0)+IFERROR(INDEX(Catalogo_Decisiones!$H$2:$H$57,MATCH($G4,Catalogo_Decisiones!$A$2:$A$57,0)),0)} -> 0 | J4: =IFS($B4="SEG-01",0,$B4="SEG-02",4,$B4="SEG-03",7,TRUE(),0) -> 0 | K4: =IF(B4="","",IF(I4>=J4,"Coherente","No alcanza el segmento")) | L4: =IF(B4="","Elige un segmento y los insumos del lote",IF(K4="Coherente","Este lote cumple con la calidad esperada para su segmento. Los clientes perciben el valor y el precio se sostiene.","Este lote no alcanza la calidad que su segmento promete. Los clientes se sienten enganados: baja el precio efectivo y la reputacion.")) -> Elige un segmento y los insumos del lote
A5: TOTAL CICLO | C5: =SUM(C2:C4) -> 0 | H5: =SUMPRODUCT(C2:C4,H2:H4) -> 0
A7: Nota: cada lote se evalua por separado. El costo unitario de insumos (col H) NO incluye el molde (es inversion fija de Ciclo 0), solo cuero+accesorios+hilo por unidad.

Sheet Motor_Puntajes
A1: Puntaje interno | B1: Valor (suma de aportes) | C1: Escala | D1: Nivel resultante
A2: CALIDAD POR LOTE (detalle)
A3: Puntaje Calidad - Lote 1 | B3: =Lotes_Produccion!I2 -> 0 | C3: =IF(Lotes_Produccion!B2="","","Segmento: "&Lotes_Produccion!B2) | D3: =Lotes_Produccion!K2
A4: Puntaje Calidad - Lote 2 | B4: =Lotes_Produccion!I3 -> 0 | C4: =IF(Lotes_Produccion!B3="","","Segmento: "&Lotes_Produccion!B3) | D4: =Lotes_Produccion!K3
A5: Puntaje Calidad - Lote 3 | B5: =Lotes_Produccion!I4 -> 0 | C5: =IF(Lotes_Produccion!B4="","","Segmento: "&Lotes_Produccion!B4) | D5: =Lotes_Produccion!K4
A6: Puntaje Calidad EMPRESA (promedio ponderado por unidades) | B6: =IFERROR(SUMPRODUCT(Lotes_Produccion!C2:C4,Lotes_Produccion!I2:I4)/SUM(Lotes_Produccion!C2:C4),0) -> 0 | C6: 0 - 10 (referencial) | D6: =IF(B6>=7,"Alto",IF(B6>=4,"Medio","Bajo")) -> Bajo
A8: OTROS PUNTAJES DE EMPRESA
A9: Puntaje de Eficiencia | B9: =SUM(Seleccion_Ciclo0!G2:G15) -> 0 | C9: 0 - 10 (referencial) | D9: =IF(B9>=7,"Alto",IF(B9>=4,"Medio","Bajo")) -> Bajo
A10: Puntaje de Reputacion | B10: =SUM(Seleccion_Ciclo0!H2:H15) -> 0 | C10: 0 - 10 (referencial) | D10: =IF(B10>=7,"Alto",IF(B10>=4,"Medio","Bajo")) -> Bajo
A11: Puntaje de Salud Financiera | B11: =SUM(Seleccion_Ciclo0!I2:I15) -> 0 | C11: 0 - 10 (referencial) | D11: =IF(B11>=7,"Alto",IF(B11>=4,"Medio","Bajo")) -> Bajo
A13: Nota: cada 'Aporte' se define en la hoja Catalogo_Decisiones (columnas H-K) y se suma automaticamente segun lo elegido en Seleccion_Ciclo0.

Sheet Matriz_Consecuencias
A1: ID | B1: Puntaje evaluado | C1: Condicion | D1: Efecto numerico en el juego | E1: Mensaje textual para el jugador
A2: CONS-01 | B2: Calidad | C2: < 4 y Segmento = Premium | D2: Precio de venta -35%, Reputacion -2 | E2: Posicionaste tu marca como premium, pero tus materiales e insumos no lo respaldan. Los clientes se sienten enganados y las devoluciones aumentan.
A3: CONS-02 | B3: Calidad | C3: >= 7 y Segmento = Premium | D3: Precio de venta +40%, Reputacion +2 | E3: Tu producto cumple con los estandares premium. Los clientes perciben el valor y pagan sin problema el precio elevado.
A4: CONS-03 | B4: Eficiencia | C4: < 4 | D4: Produccion real = 70% de lo planeado (retrasos) | E4: Tu equipo no dio abasto con el volumen que planeaste. Hubo retrasos y entregaste menos de lo prometido.
A5: CONS-04 | B5: Reputacion | C5: < 3 durante 2 ciclos seguidos | D5: Demanda -20% | E5: Tu marca empieza a perder terreno. Los clientes prefieren a la competencia.
A6: CONS-05 | B6: Salud Financiera | C6: < 3 | D6: El banco sube la tasa de interes del proximo prestamo | E6: Tu situacion financiera es riesgosa. El banco te ofrece condiciones menos favorables la proxima vez.
A7: CONS-06 | B7: Produccion vs Capacidad | C7: Cantidad producida > capacidad instalada | D7: Retraso de entrega, costo extra por horas extra | E7: Intentaste producir mas de lo que tu planta soporta. Hubo cuellos de botella y tuviste que pagar horas extra para cumplir.
A8: CONS-07 | B8: Produccion vs Demanda | C8: Cantidad producida > demanda real del mercado | D8: Inventario sin vender, costo de almacenaje | E8: Produjiste mas de lo que el mercado te pidio. Te quedaste con inventario sin vender.
A9: CONS-08 | B9: Eficiencia | C9: Jefatura = No y Eficiencia < 5 | D9: Riesgo de descoordinacion: -5% produccion adicional | E9: Sin jefatura que coordine, tu equipo perdio tiempo resolviendo conflictos de tareas.
