Workbook

Sheet Resumen
A1: Verificación manual · SIDE vs Excel
A4: Tolerancia absoluta | B4: 0.01
A6: Edite solo Obtenido (amarillo) al repetir los casos; Esperado conserva la evidencia del Excel original.
A7: NO COMPARABLE: falta de oráculo numérico o fórmula original con error. PENDIENTE: no existe observación SIDE.
A9: Tema | B9: Total | C9: OK | D9: DIFERENCIA | E9: PENDIENTE | F9: NO COMPARABLE | G9: % OK comparables
A10: DOP por cantidad | B10: =COUNTA('DOP por cantidad'!A8:A97) -> 90 | C10: =COUNTIF('DOP por cantidad'!I8:I97,"OK") -> 90 | D10: =COUNTIF('DOP por cantidad'!I8:I97,"DIFERENCIA") -> 0 | E10: =COUNTIF('DOP por cantidad'!I8:I97,"PENDIENTE") -> 0 | F10: =COUNTIF('DOP por cantidad'!I8:I97,"NO COMPARABLE") -> 0 | G10: =IFERROR(C10/(C10+D10),0) -> 1
A11: costo de producción | B11: =COUNTA('costo de producción'!A8:A17) -> 10 | C11: =COUNTIF('costo de producción'!I8:I17,"OK") -> 10 | D11: =COUNTIF('costo de producción'!I8:I17,"DIFERENCIA") -> 0 | E11: =COUNTIF('costo de producción'!I8:I17,"PENDIENTE") -> 0 | F11: =COUNTIF('costo de producción'!I8:I17,"NO COMPARABLE") -> 0 | G11: =IFERROR(C11/(C11+D11),0) -> 1
A12: caja | B12: =COUNTA(caja!A8:A8) -> 1 | C12: =COUNTIF(caja!I8:I8,"OK") -> 0 | D12: =COUNTIF(caja!I8:I8,"DIFERENCIA") -> 0 | E12: =COUNTIF(caja!I8:I8,"PENDIENTE") -> 0 | F12: =COUNTIF(caja!I8:I8,"NO COMPARABLE") -> 1 | G12: =IFERROR(C12/(C12+D12),0) -> 0
A13: consecuencias | B13: =COUNTA(consecuencias!A8:A11) -> 4 | C13: =COUNTIF(consecuencias!I8:I11,"OK") -> 4 | D13: =COUNTIF(consecuencias!I8:I11,"DIFERENCIA") -> 0 | E13: =COUNTIF(consecuencias!I8:I11,"PENDIENTE") -> 0 | F13: =COUNTIF(consecuencias!I8:I11,"NO COMPARABLE") -> 0 | G13: =IFERROR(C13/(C13+D13),0) -> 1
A14: puntajes | B14: =COUNTA(puntajes!A8:A14) -> 7 | C14: =COUNTIF(puntajes!I8:I14,"OK") -> 7 | D14: =COUNTIF(puntajes!I8:I14,"DIFERENCIA") -> 0 | E14: =COUNTIF(puntajes!I8:I14,"PENDIENTE") -> 0 | F14: =COUNTIF(puntajes!I8:I14,"NO COMPARABLE") -> 0 | G14: =IFERROR(C14/(C14+D14),0) -> 1
A15: TOTAL | B15: =SUM(B10:B14) -> 112 | C15: =SUM(C10:C14) -> 111 | D15: =SUM(D10:D14) -> 0 | E15: =SUM(E10:E14) -> 0 | F15: =SUM(F10:F14) -> 1 | G15: =IFERROR(C15/(C15+D15),0) -> 1
A18: Escenarios únicos | B18: 15
A19: Fuente de esperados | B19: .codex-work\DECISIONES_SIDE_16.xlsx
A20: Celdas amarillas | B20: Obtenido: escriba lo observado en SIDE. B4: tolerancia elegida.
A21: Diferencia porcentual | B21: (Obtenido − Esperado) / ABS(Esperado). Si Esperado = 0 y Obtenido ≠ 0: N/A.
A22: Estado OK | B22: No equivale a auditoría del juego completo. Se limita al resultado y entradas de la fila.
A23: Errores del original | B23: Un error como #DIV/0! se conserva como texto para evidenciarlo; no se transforma en cero.
A24: Caja y faltante | B24: Las reglas del juego sin celda equivalente en el original quedan NO COMPARABLE.
A25: Cómo añadir casos | B25: Duplique una fila del tema; anote entradas y celda fuente. Amplíe filtros y rangos del resumen.

Sheet DOP por cantidad
A1: Dop por cantidad
A4: Tolerancia numérica: Resumen!B4. Diferencia = Obtenido − Esperado. Sin oráculo: NO COMPARABLE.
A5: Entradas y fuentes completas en Fuentes originales. DOP se compara para la cantidad solicitada; el inventario es otro dato.
A7: Caso | B7: Resultado / unidad | C7: Entradas concretas SIDE | D7: Fuente Excel | E7: Esperado (Excel) | F7: Obtenido (SIDE) | G7: Diferencia | H7: % diferencia | I7: Estado | J7: Fuente SIDE / pantalla
A8: E01 | B8: Cantidad deseada total [unidad] | C8: {"quantities": [0, 0, 0], "stock": 0, "cash": 1000000} | D8: CANTIDAD DE PRODUCCIÓN!D36 | E8: 0 | F8: 0 | G8: =IF(ISNUMBER(F8),F8-E8,"") -> 0 | H8: =IF(ISNUMBER(F8),IF(E8=0,IF(F8=0,0,"N/A"),G8/ABS(E8)),"") -> 0 | I8: =IF(ISNUMBER(F8),IF(ABS(G8)<=Resumen!$B$4,"OK","DIFERENCIA"),"PENDIENTE") -> OK | J8: js/production_model.js y navegador local index.html, productionPlan(); capital=100000, tras fijos=97287.68 | Captura: tests/output/verificacion/E01-necesidades.png
A9: E01 | B9: Cuero, molde 1 [m²] | C9: {"quantities": [0, 0, 0], "stock": 0, "cash": 1000000} | D9: CANTIDAD DE PRODUCCIÓN!D42 | E9: 0 | F9: 0 | G9: =IF(ISNUMBER(F9),F9-E9,"") -> 0 | H9: =IF(ISNUMBER(F9),IF(E9=0,IF(F9=0,0,"N/A"),G9/ABS(E9)),"") -> 0 | I9: =IF(ISNUMBER(F9),IF(ABS(G9)<=Resumen!$B$4,"OK","DIFERENCIA"),"PENDIENTE") -> OK | J9: js/production_model.js y navegador local index.html, productionPlan(); capital=100000, tras fijos=97287.68 | Captura: tests/output/verificacion/E01-necesidades.png
A10: E01 | B10: Accesorios, molde 1 [unidad] | C10: {"quantities": [0, 0, 0], "stock": 0, "cash": 1000000} | D10: CANTIDAD DE PRODUCCIÓN!G42 | E10: 0 | F10: 0 | G10: =IF(ISNUMBER(F10),F10-E10,"") -> 0 | H10: =IF(ISNUMBER(F10),IF(E10=0,IF(F10=0,0,"N/A"),G10/ABS(E10)),"") -> 0 | I10: =IF(ISNUMBER(F10),IF(ABS(G10)<=Resumen!$B$4,"OK","DIFERENCIA"),"PENDIENTE") -> OK | J10: js/production_model.js y navegador local index.html, productionPlan(); capital=100000, tras fijos=97287.68 | Captura: tests/output/verificacion/E01-necesidades.png
A11: E01 | B11: Hilo, molde 1 [m] | C11: {"quantities": [0, 0, 0], "stock": 0, "cash": 1000000} | D11: CANTIDAD DE PRODUCCIÓN!J42 | E11: 0 | F11: 0 | G11: =IF(ISNUMBER(F11),F11-E11,"") -> 0 | H11: =IF(ISNUMBER(F11),IF(E11=0,IF(F11=0,0,"N/A"),G11/ABS(E11)),"") -> 0 | I11: =IF(ISNUMBER(F11),IF(ABS(G11)<=Resumen!$B$4,"OK","DIFERENCIA"),"PENDIENTE") -> OK | J11: js/production_model.js y navegador local index.html, productionPlan(); capital=100000, tras fijos=97287.68 | Captura: tests/output/verificacion/E01-necesidades.png
A12: E01 | B12: Cuero, molde 2 [m²] | C12: {"quantities": [0, 0, 0], "stock": 0, "cash": 1000000} | D12: CANTIDAD DE PRODUCCIÓN!E43 | E12: 0 | F12: 0 | G12: =IF(ISNUMBER(F12),F12-E12,"") -> 0 | H12: =IF(ISNUMBER(F12),IF(E12=0,IF(F12=0,0,"N/A"),G12/ABS(E12)),"") -> 0 | I12: =IF(ISNUMBER(F12),IF(ABS(G12)<=Resumen!$B$4,"OK","DIFERENCIA"),"PENDIENTE") -> OK | J12: js/production_model.js y navegador local index.html, productionPlan(); capital=100000, tras fijos=97287.68 | Captura: tests/output/verificacion/E01-necesidades.png
A13: E01 | B13: Accesorios, molde 2 [unidad] | C13: {"quantities": [0, 0, 0], "stock": 0, "cash": 1000000} | D13: CANTIDAD DE PRODUCCIÓN!H43 | E13: 0 | F13: 0 | G13: =IF(ISNUMBER(F13),F13-E13,"") -> 0 | H13: =IF(ISNUMBER(F13),IF(E13=0,IF(F13=0,0,"N/A"),G13/ABS(E13)),"") -> 0 | I13: =IF(ISNUMBER(F13),IF(ABS(G13)<=Resumen!$B$4,"OK","DIFERENCIA"),"PENDIENTE") -> OK | J13: js/production_model.js y navegador local index.html, productionPlan(); capital=100000, tras fijos=97287.68 | Captura: tests/output/verificacion/E01-necesidades.png
A14: E01 | B14: Hilo, molde 2 [m] | C14: {"quantities": [0, 0, 0], "stock": 0, "cash": 1000000} | D14: CANTIDAD DE PRODUCCIÓN!K43 | E14: 0 | F14: 0 | G14: =IF(ISNUMBER(F14),F14-E14,"") -> 0 | H14: =IF(ISNUMBER(F14),IF(E14=0,IF(F14=0,0,"N/A"),G14/ABS(E14)),"") -> 0 | I14: =IF(ISNUMBER(F14),IF(ABS(G14)<=Resumen!$B$4,"OK","DIFERENCIA"),"PENDIENTE") -> OK | J14: js/production_model.js y navegador local index.html, productionPlan(); capital=100000, tras fijos=97287.68 | Captura: tests/output/verificacion/E01-necesidades.png
A15: E01 | B15: Cuero, molde 3 [m²] | C15: {"quantities": [0, 0, 0], "stock": 0, "cash": 1000000} | D15: CANTIDAD DE PRODUCCIÓN!F44 | E15: 0 | F15: 0 | G15: =IF(ISNUMBER(F15),F15-E15,"") -> 0 | H15: =IF(ISNUMBER(F15),IF(E15=0,IF(F15=0,0,"N/A"),G15/ABS(E15)),"") -> 0 | I15: =IF(ISNUMBER(F15),IF(ABS(G15)<=Resumen!$B$4,"OK","DIFERENCIA"),"PENDIENTE") -> OK | J15: js/production_model.js y navegador local index.html, productionPlan(); capital=100000, tras fijos=97287.68 | Captura: tests/output/verificacion/E01-necesidades.png
A16: E01 | B16: Accesorios, molde 3 [unidad] | C16: {"quantities": [0, 0, 0], "stock": 0, "cash": 1000000} | D16: CANTIDAD DE PRODUCCIÓN!I44 | E16: 0 | F16: 0 | G16: =IF(ISNUMBER(F16),F16-E16,"") -> 0 | H16: =IF(ISNUMBER(F16),IF(E16=0,IF(F16=0,0,"N/A"),G16/ABS(E16)),"") -> 0 | I16: =IF(ISNUMBER(F16),IF(ABS(G16)<=Resumen!$B$4,"OK","DIFERENCIA"),"PENDIENTE") -> OK | J16: js/production_model.js y navegador local index.html, productionPlan(); capital=100000, tras fijos=97287.68 | Captura: tests/output/verificacion/E01-necesidades.png
A17: E01 | B17: Hilo, molde 3 [m] | C17: {"quantities": [0, 0, 0], "stock": 0, "cash": 1000000} | D17: CANTIDAD DE PRODUCCIÓN!L44 | E17: 0 | F17: 0 | G17: =IF(ISNUMBER(F17),F17-E17,"") -> 0 | H17: =IF(ISNUMBER(F17),IF(E17=0,IF(F17=0,0,"N/A"),G17/ABS(E17)),"") -> 0 | I17: =IF(ISNUMBER(F17),IF(ABS(G17)<=Resumen!$B$4,"OK","DIFERENCIA"),"PENDIENTE") -> OK | J17: js/production_model.js y navegador local index.html, productionPlan(); capital=100000, tras fijos=97287.68 | Captura: tests/output/verificacion/E01-necesidades.png
A18: E02 | B18: Cantidad deseada total [unidad] | C18: {"quantities": [1, 0, 0], "stock": 0, "cash": 1000000} | D18: CANTIDAD DE PRODUCCIÓN!D36 | E18: 1 | F18: 1 | G18: =IF(ISNUMBER(F18),F18-E18,"") -> 0 | H18: =IF(ISNUMBER(F18),IF(E18=0,IF(F18=0,0,"N/A"),G18/ABS(E18)),"") -> 0 | I18: =IF(ISNUMBER(F18),IF(ABS(G18)<=Resumen!$B$4,"OK","DIFERENCIA"),"PENDIENTE") -> OK | J18: js/production_model.js y navegador local index.html, productionPlan(); capital=100000, tras fijos=97287.68 | Captura: tests/output/verificacion/E02-necesidades.png
A19: E02 | B19: Cuero, molde 1 [m²] | C19: {"quantities": [1, 0, 0], "stock": 0, "cash": 1000000} | D19: CANTIDAD DE PRODUCCIÓN!D42 | E19: 0.3 | F19: 0.3 | G19: =IF(ISNUMBER(F19),F19-E19,"") -> 0 | H19: =IF(ISNUMBER(F19),IF(E19=0,IF(F19=0,0,"N/A"),G19/ABS(E19)),"") -> 0 | I19: =IF(ISNUMBER(F19),IF(ABS(G19)<=Resumen!$B$4,"OK","DIFERENCIA"),"PENDIENTE") -> OK | J19: js/production_model.js y navegador local index.html, productionPlan(); capital=100000, tras fijos=97287.68 | Captura: tests/output/verificacion/E02-necesidades.png
... A97: E09 | B97: Hilo, molde 3 [m] | C97: {"quantities": [0, 0, 10], "stock": 0, "cash": 1000000} | D97: CANTIDAD DE PRODUCCIÓN!L44 | E97: 130 | F97: 130 | G97: =IF(ISNUMBER(F97),F97-E97,"") -> 0 | H97: =IF(ISNUMBER(F97),IF(E97=0,IF(F97=0,0,"N/A"),G97/ABS(E97)),"") -> 0 | I97: =IF(ISNUMBER(F97),IF(ABS(G97)<=Resumen!$B$4,"OK","DIFERENCIA"),"PENDIENTE") -> OK | J97: js/production_model.js y navegador local index.html, productionPlan(); capital=100000, tras fijos=97287.68 | Captura: tests/output/verificacion/E09-necesidades.png

Sheet costo de producción
A1: Costo de producción
A4: Tolerancia numérica: Resumen!B4. Diferencia = Obtenido − Esperado. Sin oráculo: NO COMPARABLE.
A5: Entradas y fuentes completas en Fuentes originales. DOP se compara para la cantidad solicitada; el inventario es otro dato.
A7: Caso | B7: Resultado / unidad | C7: Entradas concretas SIDE | D7: Fuente Excel | E7: Esperado (Excel) | F7: Obtenido (SIDE) | G7: Diferencia | H7: % diferencia | I7: Estado | J7: Fuente SIDE / pantalla
A8: E10 | B8: Costo mensual corte nivel 1 [S/] | C8: {"regimen": "MYPE"} | D8: Costos De Producción!U11 | E8: 1690.8 | F8: 1690.8 | G8: =IF(ISNUMBER(F8),F8-E8,"") -> 0 | H8: =IF(ISNUMBER(F8),IF(E8=0,IF(F8=0,0,"N/A"),G8/ABS(E8)),"") -> 0 | I8: =IF(ISNUMBER(F8),IF(ABS(G8)<=Resumen!$B$4,"OK","DIFERENCIA"),"PENDIENTE") -> OK | J8: js/engine/costos.js costoLaboral y precioCompraMateriaPrima (motor Node); control adicional Chromium componente ui_excel montado aislado: valor navegador=1690.8; revisar diferenciasNavegador | Captura: tests/output/verificacion/E10-editor.png
A9: E10 | B9: Costo mensual ensamble nivel 1 [S/] | C9: {"regimen": "MYPE"} | D9: Costos De Producción!Y11 | E9: 1690.8 | F9: 1690.8 | G9: =IF(ISNUMBER(F9),F9-E9,"") -> 0 | H9: =IF(ISNUMBER(F9),IF(E9=0,IF(F9=0,0,"N/A"),G9/ABS(E9)),"") -> 0 | I9: =IF(ISNUMBER(F9),IF(ABS(G9)<=Resumen!$B$4,"OK","DIFERENCIA"),"PENDIENTE") -> OK | J9: js/engine/costos.js costoLaboral y precioCompraMateriaPrima (motor Node); control adicional Chromium componente ui_excel montado aislado: valor navegador=1690.8; revisar diferenciasNavegador | Captura: tests/output/verificacion/E10-editor.png
A10: E10 | B10: Costo mensual acabado nivel 1 [S/] | C10: {"regimen": "MYPE"} | D10: Costos De Producción!AC11 | E10: 1690.8 | F10: 1690.8 | G10: =IF(ISNUMBER(F10),F10-E10,"") -> 0 | H10: =IF(ISNUMBER(F10),IF(E10=0,IF(F10=0,0,"N/A"),G10/ABS(E10)),"") -> 0 | I10: =IF(ISNUMBER(F10),IF(ABS(G10)<=Resumen!$B$4,"OK","DIFERENCIA"),"PENDIENTE") -> OK | J10: js/engine/costos.js costoLaboral y precioCompraMateriaPrima (motor Node); control adicional Chromium componente ui_excel montado aislado: valor navegador=1690.8; revisar diferenciasNavegador | Captura: tests/output/verificacion/E10-editor.png
A11: E10 | B11: Local de producción mensual [S/] | C11: {"regimen": "MYPE"} | D11: Costos De Producción!AC33 | E11: 2000 | F11: 2000 | G11: =IF(ISNUMBER(F11),F11-E11,"") -> 0 | H11: =IF(ISNUMBER(F11),IF(E11=0,IF(F11=0,0,"N/A"),G11/ABS(E11)),"") -> 0 | I11: =IF(ISNUMBER(F11),IF(ABS(G11)<=Resumen!$B$4,"OK","DIFERENCIA"),"PENDIENTE") -> OK | J11: js/engine/costos.js costoLaboral y precioCompraMateriaPrima (motor Node); control adicional Chromium componente ui_excel montado aislado: valor navegador=2000; revisar diferenciasNavegador | Captura: tests/output/verificacion/E10-editor.png
A12: E10 | B12: Precio neto cuero sintético [S//m²] | C12: {"regimen": "MYPE"} | D12: Costos De Producción!W76 | E12: 23 | F12: 23 | G12: =IF(ISNUMBER(F12),F12-E12,"") -> 0 | H12: =IF(ISNUMBER(F12),IF(E12=0,IF(F12=0,0,"N/A"),G12/ABS(E12)),"") -> 0 | I12: =IF(ISNUMBER(F12),IF(ABS(G12)<=Resumen!$B$4,"OK","DIFERENCIA"),"PENDIENTE") -> OK | J12: js/engine/costos.js costoLaboral y precioCompraMateriaPrima (motor Node); control adicional Chromium componente ui_excel montado aislado: valor navegador=23; revisar diferenciasNavegador | Captura: tests/output/verificacion/E10-editor.png
A13: E11 | B13: Costo mensual corte nivel 1 [S/] | C13: {"regimen": "NO_MYPE"} | D13: Costos De Producción!V11 | E13: 1856.5385 | F13: 1856.5385 | G13: =IF(ISNUMBER(F13),F13-E13,"") -> 0 | H13: =IF(ISNUMBER(F13),IF(E13=0,IF(F13=0,0,"N/A"),G13/ABS(E13)),"") -> 0 | I13: =IF(ISNUMBER(F13),IF(ABS(G13)<=Resumen!$B$4,"OK","DIFERENCIA"),"PENDIENTE") -> OK | J13: js/engine/costos.js costoLaboral y precioCompraMateriaPrima (motor Node); control adicional Chromium componente ui_excel montado aislado: valor navegador=1856.5384615384614; revisar diferenciasNavegador | Captura: tests/output/verificacion/E11-editor.png
A14: E11 | B14: Costo mensual ensamble nivel 1 [S/] | C14: {"regimen": "NO_MYPE"} | D14: Costos De Producción!Z11 | E14: 1856.5385 | F14: 1856.5385 | G14: =IF(ISNUMBER(F14),F14-E14,"") -> 0 | H14: =IF(ISNUMBER(F14),IF(E14=0,IF(F14=0,0,"N/A"),G14/ABS(E14)),"") -> 0 | I14: =IF(ISNUMBER(F14),IF(ABS(G14)<=Resumen!$B$4,"OK","DIFERENCIA"),"PENDIENTE") -> OK | J14: js/engine/costos.js costoLaboral y precioCompraMateriaPrima (motor Node); control adicional Chromium componente ui_excel montado aislado: valor navegador=1856.5384615384614; revisar diferenciasNavegador | Captura: tests/output/verificacion/E11-editor.png
A15: E11 | B15: Costo mensual acabado nivel 1 [S/] | C15: {"regimen": "NO_MYPE"} | D15: Costos De Producción!AD11 | E15: 1856.5385 | F15: 1856.5385 | G15: =IF(ISNUMBER(F15),F15-E15,"") -> 0 | H15: =IF(ISNUMBER(F15),IF(E15=0,IF(F15=0,0,"N/A"),G15/ABS(E15)),"") -> 0 | I15: =IF(ISNUMBER(F15),IF(ABS(G15)<=Resumen!$B$4,"OK","DIFERENCIA"),"PENDIENTE") -> OK | J15: js/engine/costos.js costoLaboral y precioCompraMateriaPrima (motor Node); control adicional Chromium componente ui_excel montado aislado: valor navegador=1856.5384615384614; revisar diferenciasNavegador | Captura: tests/output/verificacion/E11-editor.png
A16: E11 | B16: Local de producción mensual [S/] | C16: {"regimen": "NO_MYPE"} | D16: Costos De Producción!AC33 | E16: 2000 | F16: 2000 | G16: =IF(ISNUMBER(F16),F16-E16,"") -> 0 | H16: =IF(ISNUMBER(F16),IF(E16=0,IF(F16=0,0,"N/A"),G16/ABS(E16)),"") -> 0 | I16: =IF(ISNUMBER(F16),IF(ABS(G16)<=Resumen!$B$4,"OK","DIFERENCIA"),"PENDIENTE") -> OK | J16: js/engine/costos.js costoLaboral y precioCompraMateriaPrima (motor Node); control adicional Chromium componente ui_excel montado aislado: valor navegador=2000; revisar diferenciasNavegador | Captura: tests/output/verificacion/E11-editor.png
A17: E11 | B17: Precio neto cuero sintético [S//m²] | C17: {"regimen": "NO_MYPE"} | D17: Costos De Producción!W76 | E17: 23 | F17: 23 | G17: =IF(ISNUMBER(F17),F17-E17,"") -> 0 | H17: =IF(ISNUMBER(F17),IF(E17=0,IF(F17=0,0,"N/A"),G17/ABS(E17)),"") -> 0 | I17: =IF(ISNUMBER(F17),IF(ABS(G17)<=Resumen!$B$4,"OK","DIFERENCIA"),"PENDIENTE") -> OK | J17: js/engine/costos.js costoLaboral y precioCompraMateriaPrima (motor Node); control adicional Chromium componente ui_excel montado aislado: valor navegador=23; revisar diferenciasNavegador | Captura: tests/output/verificacion/E11-editor.png

Sheet caja
A1: Caja
A4: Tolerancia numérica: Resumen!B4. Diferencia = Obtenido − Esperado. Sin oráculo: NO COMPARABLE.
A5: Entradas y fuentes completas en Fuentes originales. DOP se compara para la cantidad solicitada; el inventario es otro dato.
A7: Caso | B7: Resultado / unidad | C7: Entradas concretas SIDE | D7: Fuente Excel | E7: Esperado (Excel) | F7: Obtenido (SIDE) | G7: Diferencia | H7: % diferencia | I7: Estado | J7: Fuente SIDE / pantalla
A8: E12 | B8: Caja observada con capital cero tras fijos [S/] | C8: {"cash": 0, "regimen": "MYPE", "quantity": 10} | D8: None!None | F8: -2712.32 | I8: NO COMPARABLE | J8: Navegador local con capital=0; meta 10 sin compra ni confirmacion. No prueba rechazo por saldo insuficiente | Captura: tests/output/verificacion/E12-produccion.png

Sheet consecuencias
A1: Consecuencias
A4: Tolerancia numérica: Resumen!B4. Diferencia = Obtenido − Esperado. Sin oráculo: NO COMPARABLE.
A5: Entradas y fuentes completas en Fuentes originales. DOP se compara para la cantidad solicitada; el inventario es otro dato.
A7: Caso | B7: Resultado / unidad | C7: Entradas concretas SIDE | D7: Fuente Excel | E7: Esperado (Excel) | F7: Obtenido (SIDE) | G7: Diferencia | H7: % diferencia | I7: Estado | J7: Fuente SIDE / pantalla
A8: E14 | B8: Factor sobre precio de venta [factor] | C8: {"calidad": 4, "segmento": "SEG-03", "eficiencia": 7, "reputacion": 7, "saludFinanciera": 7, "jefes": 1, "planeado": 10, "capacidad": 396, "producido": 10, "demanda": 100, "costoMOciclo": 0, "lotes_manuales": [{"segmento": "SEG-03", "cantidad": 10, "cuero": "INS-01", "accesorios": "INS-04", "hilo": "INS-06", "molde": "INF-08"}]} | D8: Matriz_Consecuencias!C2:D3 | E8: 1 | F8: 1 | G8: =IF(ISNUMBER(F8),F8-E8,"") -> 0 | H8: =IF(ISNUMBER(F8),IF(E8=0,IF(F8=0,0,"N/A"),G8/ABS(E8)),"") -> 0 | I8: =IF(ISNUMBER(F8),IF(ABS(G8)<=Resumen!$B$4,"OK","DIFERENCIA"),"PENDIENTE") -> OK | J8: js/engine/consecuencias.js evaluarConsecuencias (motor Node); calidad controlada, regla textual; control adicional Chromium componente ui_excel montado aislado: valor navegador=1; revisar diferenciasNavegador | Captura: tests/output/verificacion/E14-editor.png
A9: E14 | B9: Cambio reputación [puntos] | C9: {"calidad": 4, "segmento": "SEG-03", "eficiencia": 7, "reputacion": 7, "saludFinanciera": 7, "jefes": 1, "planeado": 10, "capacidad": 396, "producido": 10, "demanda": 100, "costoMOciclo": 0, "lotes_manuales": [{"segmento": "SEG-03", "cantidad": 10, "cuero": "INS-01", "accesorios": "INS-04", "hilo": "INS-06", "molde": "INF-08"}]} | D9: Matriz_Consecuencias!C2:D3 | E9: 0 | F9: 0 | G9: =IF(ISNUMBER(F9),F9-E9,"") -> 0 | H9: =IF(ISNUMBER(F9),IF(E9=0,IF(F9=0,0,"N/A"),G9/ABS(E9)),"") -> 0 | I9: =IF(ISNUMBER(F9),IF(ABS(G9)<=Resumen!$B$4,"OK","DIFERENCIA"),"PENDIENTE") -> OK | J9: js/engine/consecuencias.js evaluarConsecuencias (motor Node); calidad controlada, regla textual; control adicional Chromium componente ui_excel montado aislado: valor navegador=0; revisar diferenciasNavegador | Captura: tests/output/verificacion/E14-editor.png
A10: E15 | B10: Factor sobre precio de venta [factor] | C10: {"calidad": 12, "segmento": "SEG-03", "eficiencia": 7, "reputacion": 7, "saludFinanciera": 7, "jefes": 1, "planeado": 10, "capacidad": 396, "producido": 10, "demanda": 100, "costoMOciclo": 0} | D10: Matriz_Consecuencias!D3 | E10: 1.4 | F10: 1.4 | G10: =IF(ISNUMBER(F10),F10-E10,"") -> 0 | H10: =IF(ISNUMBER(F10),IF(E10=0,IF(F10=0,0,"N/A"),G10/ABS(E10)),"") -> 0 | I10: =IF(ISNUMBER(F10),IF(ABS(G10)<=Resumen!$B$4,"OK","DIFERENCIA"),"PENDIENTE") -> OK | J10: js/engine/consecuencias.js evaluarConsecuencias (motor Node); calidad controlada, regla textual; control adicional Chromium componente ui_excel montado aislado: valor navegador=1.4; revisar diferenciasNavegador | Captura: tests/output/verificacion/E15-editor.png
A11: E15 | B11: Cambio reputación [puntos] | C11: {"calidad": 12, "segmento": "SEG-03", "eficiencia": 7, "reputacion": 7, "saludFinanciera": 7, "jefes": 1, "planeado": 10, "capacidad": 396, "producido": 10, "demanda": 100, "costoMOciclo": 0} | D11: Matriz_Consecuencias!D3 | E11: 2 | F11: 2 | G11: =IF(ISNUMBER(F11),F11-E11,"") -> 0 | H11: =IF(ISNUMBER(F11),IF(E11=0,IF(F11=0,0,"N/A"),G11/ABS(E11)),"") -> 0 | I11: =IF(ISNUMBER(F11),IF(ABS(G11)<=Resumen!$B$4,"OK","DIFERENCIA"),"PENDIENTE") -> OK | J11: js/engine/consecuencias.js evaluarConsecuencias (motor Node); calidad controlada, regla textual; control adicional Chromium componente ui_excel montado aislado: valor navegador=2; revisar diferenciasNavegador | Captura: tests/output/verificacion/E15-editor.png

Sheet puntajes
A1: Puntajes
A4: Tolerancia numérica: Resumen!B4. Diferencia = Obtenido − Esperado. Sin oráculo: NO COMPARABLE.
A5: Entradas y fuentes completas en Fuentes originales. DOP se compara para la cantidad solicitada; el inventario es otro dato.
A7: Caso | B7: Resultado / unidad | C7: Entradas concretas SIDE | D7: Fuente Excel | E7: Esperado (Excel) | F7: Obtenido (SIDE) | G7: Diferencia | H7: % diferencia | I7: Estado | J7: Fuente SIDE / pantalla
A8: E13 | B8: calidad [puntos] | C8: {"seleccion": ["INF-03", "INF-06", "INF-09", "RH-02", "RH-05", "RH-08", "RH-10A", "COM-01C", "FIN-01B", "INV-01B"], "garantiaDias": null, "mantenimientoPreventivo": false, "marketingNivel": null, "analistaCompras": false, "garantiaProveedor": 0, "tiendasPorDistrito": {"los_olivos": 0, "miraflores": 0, "sjl": 0}, "lotes": [{"segmento": "SEG-03", "cantidad": 100, "cuero": "INS-03", "accesorios": "INS-05", "hilo": "INS-08", "molde": "INF-10", "costoUnitario": 96, "calidad": 12, "umbral": 7, "resultado": "Coherente", "precio": 250}, {"segmento": "SEG-02", "cantidad": 300, "cuero": "INS-02", "accesorios": "INS-04", "hilo": "INS-06", "molde": "INF-08", "costoUnitario": 51, "calidad": 5, "umbral": 4, "resultado": "Coherente", "precio": 250}, {"segmento": "SEG-03", "cantidad": 100, "cuero": "INS-01", "accesorios": "INS-04", "hilo": "INS-06", "molde": "INF-08", "costoUnitario": 31, "calidad": 4, "umbral": 7, "resultado": "No alcanza el segmento", "precio": 250}], "personal": {"corte": [[0, 0, 0], [0, 0, 0], [0, 0, 0]], "ensamble": [[0, 0, 0], [0, 0, 0], [0, 0, 0]], "acabado": [[0, 0, 0], [0, 0, 0], [0, 0, 0]]}, "jefes": 1, "regimen": "MYPE", "publicidad": 0, "montoPrestamo": 0, "comprasUnidades": {}, "maquinaria": {}} | D8: Motor_Puntajes!B6 | E8: 6.2 | F8: 6.2 | G8: =IF(ISNUMBER(F8),F8-E8,"") -> 0 | H8: =IF(ISNUMBER(F8),IF(E8=0,IF(F8=0,0,"N/A"),G8/ABS(E8)),"") -> 0 | I8: =IF(ISNUMBER(F8),IF(ABS(G8)<=Resumen!$B$4,"OK","DIFERENCIA"),"PENDIENTE") -> OK | J8: js/engine/puntajes.js calcularPuntajes (motor Node); control adicional Chromium componente ui_excel montado aislado: valor navegador=6.2; revisar diferenciasNavegador | Captura: tests/output/verificacion/E13-editor.png
A9: E13 | B9: eficiencia [puntos] | C9: {"seleccion": ["INF-03", "INF-06", "INF-09", "RH-02", "RH-05", "RH-08", "RH-10A", "COM-01C", "FIN-01B", "INV-01B"], "garantiaDias": null, "mantenimientoPreventivo": false, "marketingNivel": null, "analistaCompras": false, "garantiaProveedor": 0, "tiendasPorDistrito": {"los_olivos": 0, "miraflores": 0, "sjl": 0}, "lotes": [{"segmento": "SEG-03", "cantidad": 100, "cuero": "INS-03", "accesorios": "INS-05", "hilo": "INS-08", "molde": "INF-10", "costoUnitario": 96, "calidad": 12, "umbral": 7, "resultado": "Coherente", "precio": 250}, {"segmento": "SEG-02", "cantidad": 300, "cuero": "INS-02", "accesorios": "INS-04", "hilo": "INS-06", "molde": "INF-08", "costoUnitario": 51, "calidad": 5, "umbral": 4, "resultado": "Coherente", "precio": 250}, {"segmento": "SEG-03", "cantidad": 100, "cuero": "INS-01", "accesorios": "INS-04", "hilo": "INS-06", "molde": "INF-08", "costoUnitario": 31, "calidad": 4, "umbral": 7, "resultado": "No alcanza el segmento", "precio": 250}], "personal": {"corte": [[0, 0, 0], [0, 0, 0], [0, 0, 0]], "ensamble": [[0, 0, 0], [0, 0, 0], [0, 0, 0]], "acabado": [[0, 0, 0], [0, 0, 0], [0, 0, 0]]}, "jefes": 1, "regimen": "MYPE", "publicidad": 0, "montoPrestamo": 0, "comprasUnidades": {}, "maquinaria": {}} | D9: Motor_Puntajes!B9 | E9: 16 | F9: 16 | G9: =IF(ISNUMBER(F9),F9-E9,"") -> 0 | H9: =IF(ISNUMBER(F9),IF(E9=0,IF(F9=0,0,"N/A"),G9/ABS(E9)),"") -> 0 | I9: =IF(ISNUMBER(F9),IF(ABS(G9)<=Resumen!$B$4,"OK","DIFERENCIA"),"PENDIENTE") -> OK | J9: js/engine/puntajes.js calcularPuntajes (motor Node); control adicional Chromium componente ui_excel montado aislado: valor navegador=16; revisar diferenciasNavegador | Captura: tests/output/verificacion/E13-editor.png
A10: E13 | B10: reputacion [puntos] | C10: {"seleccion": ["INF-03", "INF-06", "INF-09", "RH-02", "RH-05", "RH-08", "RH-10A", "COM-01C", "FIN-01B", "INV-01B"], "garantiaDias": null, "mantenimientoPreventivo": false, "marketingNivel": null, "analistaCompras": false, "garantiaProveedor": 0, "tiendasPorDistrito": {"los_olivos": 0, "miraflores": 0, "sjl": 0}, "lotes": [{"segmento": "SEG-03", "cantidad": 100, "cuero": "INS-03", "accesorios": "INS-05", "hilo": "INS-08", "molde": "INF-10", "costoUnitario": 96, "calidad": 12, "umbral": 7, "resultado": "Coherente", "precio": 250}, {"segmento": "SEG-02", "cantidad": 300, "cuero": "INS-02", "accesorios": "INS-04", "hilo": "INS-06", "molde": "INF-08", "costoUnitario": 51, "calidad": 5, "umbral": 4, "resultado": "Coherente", "precio": 250}, {"segmento": "SEG-03", "cantidad": 100, "cuero": "INS-01", "accesorios": "INS-04", "hilo": "INS-06", "molde": "INF-08", "costoUnitario": 31, "calidad": 4, "umbral": 7, "resultado": "No alcanza el segmento", "precio": 250}], "personal": {"corte": [[0, 0, 0], [0, 0, 0], [0, 0, 0]], "ensamble": [[0, 0, 0], [0, 0, 0], [0, 0, 0]], "acabado": [[0, 0, 0], [0, 0, 0], [0, 0, 0]]}, "jefes": 1, "regimen": "MYPE", "publicidad": 0, "montoPrestamo": 0, "comprasUnidades": {}, "maquinaria": {}} | D10: Motor_Puntajes!B10 | E10: 6 | F10: 6 | G10: =IF(ISNUMBER(F10),F10-E10,"") -> 0 | H10: =IF(ISNUMBER(F10),IF(E10=0,IF(F10=0,0,"N/A"),G10/ABS(E10)),"") -> 0 | I10: =IF(ISNUMBER(F10),IF(ABS(G10)<=Resumen!$B$4,"OK","DIFERENCIA"),"PENDIENTE") -> OK | J10: js/engine/puntajes.js calcularPuntajes (motor Node); control adicional Chromium componente ui_excel montado aislado: valor navegador=6; revisar diferenciasNavegador | Captura: tests/output/verificacion/E13-editor.png
A11: E13 | B11: saludFinanciera [puntos] | C11: {"seleccion": ["INF-03", "INF-06", "INF-09", "RH-02", "RH-05", "RH-08", "RH-10A", "COM-01C", "FIN-01B", "INV-01B"], "garantiaDias": null, "mantenimientoPreventivo": false, "marketingNivel": null, "analistaCompras": false, "garantiaProveedor": 0, "tiendasPorDistrito": {"los_olivos": 0, "miraflores": 0, "sjl": 0}, "lotes": [{"segmento": "SEG-03", "cantidad": 100, "cuero": "INS-03", "accesorios": "INS-05", "hilo": "INS-08", "molde": "INF-10", "costoUnitario": 96, "calidad": 12, "umbral": 7, "resultado": "Coherente", "precio": 250}, {"segmento": "SEG-02", "cantidad": 300, "cuero": "INS-02", "accesorios": "INS-04", "hilo": "INS-06", "molde": "INF-08", "costoUnitario": 51, "calidad": 5, "umbral": 4, "resultado": "Coherente", "precio": 250}, {"segmento": "SEG-03", "cantidad": 100, "cuero": "INS-01", "accesorios": "INS-04", "hilo": "INS-06", "molde": "INF-08", "costoUnitario": 31, "calidad": 4, "umbral": 7, "resultado": "No alcanza el segmento", "precio": 250}], "personal": {"corte": [[0, 0, 0], [0, 0, 0], [0, 0, 0]], "ensamble": [[0, 0, 0], [0, 0, 0], [0, 0, 0]], "acabado": [[0, 0, 0], [0, 0, 0], [0, 0, 0]]}, "jefes": 1, "regimen": "MYPE", "publicidad": 0, "montoPrestamo": 0, "comprasUnidades": {}, "maquinaria": {}} | D11: Motor_Puntajes!B11 | E11: -1 | F11: -1 | G11: =IF(ISNUMBER(F11),F11-E11,"") -> 0 | H11: =IF(ISNUMBER(F11),IF(E11=0,IF(F11=0,0,"N/A"),G11/ABS(E11)),"") -> 0 | I11: =IF(ISNUMBER(F11),IF(ABS(G11)<=Resumen!$B$4,"OK","DIFERENCIA"),"PENDIENTE") -> OK | J11: js/engine/puntajes.js calcularPuntajes (motor Node); control adicional Chromium componente ui_excel montado aislado: valor navegador=-1; revisar diferenciasNavegador | Captura: tests/output/verificacion/E13-editor.png
A12: E13 | B12: Costo unitario lote 1 [S/] | C12: {"seleccion": ["INF-03", "INF-06", "INF-09", "RH-02", "RH-05", "RH-08", "RH-10A", "COM-01C", "FIN-01B", "INV-01B"], "garantiaDias": null, "mantenimientoPreventivo": false, "marketingNivel": null, "analistaCompras": false, "garantiaProveedor": 0, "tiendasPorDistrito": {"los_olivos": 0, "miraflores": 0, "sjl": 0}, "lotes": [{"segmento": "SEG-03", "cantidad": 100, "cuero": "INS-03", "accesorios": "INS-05", "hilo": "INS-08", "molde": "INF-10", "costoUnitario": 96, "calidad": 12, "umbral": 7, "resultado": "Coherente", "precio": 250}, {"segmento": "SEG-02", "cantidad": 300, "cuero": "INS-02", "accesorios": "INS-04", "hilo": "INS-06", "molde": "INF-08", "costoUnitario": 51, "calidad": 5, "umbral": 4, "resultado": "Coherente", "precio": 250}, {"segmento": "SEG-03", "cantidad": 100, "cuero": "INS-01", "accesorios": "INS-04", "hilo": "INS-06", "molde": "INF-08", "costoUnitario": 31, "calidad": 4, "umbral": 7, "resultado": "No alcanza el segmento", "precio": 250}], "personal": {"corte": [[0, 0, 0], [0, 0, 0], [0, 0, 0]], "ensamble": [[0, 0, 0], [0, 0, 0], [0, 0, 0]], "acabado": [[0, 0, 0], [0, 0, 0], [0, 0, 0]]}, "jefes": 1, "regimen": "MYPE", "publicidad": 0, "montoPrestamo": 0, "comprasUnidades": {}, "maquinaria": {}} | D12: Lotes_Produccion!H2 | E12: 96 | F12: 96 | G12: =IF(ISNUMBER(F12),F12-E12,"") -> 0 | H12: =IF(ISNUMBER(F12),IF(E12=0,IF(F12=0,0,"N/A"),G12/ABS(E12)),"") -> 0 | I12: =IF(ISNUMBER(F12),IF(ABS(G12)<=Resumen!$B$4,"OK","DIFERENCIA"),"PENDIENTE") -> OK | J12: js/engine/puntajes.js calcularPuntajes (motor Node); control adicional Chromium componente ui_excel montado aislado: valor navegador=96; revisar diferenciasNavegador | Captura: tests/output/verificacion/E13-editor.png
A13: E13 | B13: Costo unitario lote 2 [S/] | C13: {"seleccion": ["INF-03", "INF-06", "INF-09", "RH-02", "RH-05", "RH-08", "RH-10A", "COM-01C", "FIN-01B", "INV-01B"], "garantiaDias": null, "mantenimientoPreventivo": false, "marketingNivel": null, "analistaCompras": false, "garantiaProveedor": 0, "tiendasPorDistrito": {"los_olivos": 0, "miraflores": 0, "sjl": 0}, "lotes": [{"segmento": "SEG-03", "cantidad": 100, "cuero": "INS-03", "accesorios": "INS-05", "hilo": "INS-08", "molde": "INF-10", "costoUnitario": 96, "calidad": 12, "umbral": 7, "resultado": "Coherente", "precio": 250}, {"segmento": "SEG-02", "cantidad": 300, "cuero": "INS-02", "accesorios": "INS-04", "hilo": "INS-06", "molde": "INF-08", "costoUnitario": 51, "calidad": 5, "umbral": 4, "resultado": "Coherente", "precio": 250}, {"segmento": "SEG-03", "cantidad": 100, "cuero": "INS-01", "accesorios": "INS-04", "hilo": "INS-06", "molde": "INF-08", "costoUnitario": 31, "calidad": 4, "umbral": 7, "resultado": "No alcanza el segmento", "precio": 250}], "personal": {"corte": [[0, 0, 0], [0, 0, 0], [0, 0, 0]], "ensamble": [[0, 0, 0], [0, 0, 0], [0, 0, 0]], "acabado": [[0, 0, 0], [0, 0, 0], [0, 0, 0]]}, "jefes": 1, "regimen": "MYPE", "publicidad": 0, "montoPrestamo": 0, "comprasUnidades": {}, "maquinaria": {}} | D13: Lotes_Produccion!H3 | E13: 51 | F13: 51 | G13: =IF(ISNUMBER(F13),F13-E13,"") -> 0 | H13: =IF(ISNUMBER(F13),IF(E13=0,IF(F13=0,0,"N/A"),G13/ABS(E13)),"") -> 0 | I13: =IF(ISNUMBER(F13),IF(ABS(G13)<=Resumen!$B$4,"OK","DIFERENCIA"),"PENDIENTE") -> OK | J13: js/engine/puntajes.js calcularPuntajes (motor Node); control adicional Chromium componente ui_excel montado aislado: valor navegador=51; revisar diferenciasNavegador | Captura: tests/output/verificacion/E13-editor.png
A14: E13 | B14: Costo unitario lote 3 [S/] | C14: {"seleccion": ["INF-03", "INF-06", "INF-09", "RH-02", "RH-05", "RH-08", "RH-10A", "COM-01C", "FIN-01B", "INV-01B"], "garantiaDias": null, "mantenimientoPreventivo": false, "marketingNivel": null, "analistaCompras": false, "garantiaProveedor": 0, "tiendasPorDistrito": {"los_olivos": 0, "miraflores": 0, "sjl": 0}, "lotes": [{"segmento": "SEG-03", "cantidad": 100, "cuero": "INS-03", "accesorios": "INS-05", "hilo": "INS-08", "molde": "INF-10", "costoUnitario": 96, "calidad": 12, "umbral": 7, "resultado": "Coherente", "precio": 250}, {"segmento": "SEG-02", "cantidad": 300, "cuero": "INS-02", "accesorios": "INS-04", "hilo": "INS-06", "molde": "INF-08", "costoUnitario": 51, "calidad": 5, "umbral": 4, "resultado": "Coherente", "precio": 250}, {"segmento": "SEG-03", "cantidad": 100, "cuero": "INS-01", "accesorios": "INS-04", "hilo": "INS-06", "molde": "INF-08", "costoUnitario": 31, "calidad": 4, "umbral": 7, "resultado": "No alcanza el segmento", "precio": 250}], "personal": {"corte": [[0, 0, 0], [0, 0, 0], [0, 0, 0]], "ensamble": [[0, 0, 0], [0, 0, 0], [0, 0, 0]], "acabado": [[0, 0, 0], [0, 0, 0], [0, 0, 0]]}, "jefes": 1, "regimen": "MYPE", "publicidad": 0, "montoPrestamo": 0, "comprasUnidades": {}, "maquinaria": {}} | D14: Lotes_Produccion!H4 | E14: 31 | F14: 31 | G14: =IF(ISNUMBER(F14),F14-E14,"") -> 0 | H14: =IF(ISNUMBER(F14),IF(E14=0,IF(F14=0,0,"N/A"),G14/ABS(E14)),"") -> 0 | I14: =IF(ISNUMBER(F14),IF(ABS(G14)<=Resumen!$B$4,"OK","DIFERENCIA"),"PENDIENTE") -> OK | J14: js/engine/puntajes.js calcularPuntajes (motor Node); control adicional Chromium componente ui_excel montado aislado: valor navegador=31; revisar diferenciasNavegador | Captura: tests/output/verificacion/E13-editor.png

Sheet Fuentes originales
A1: Trazabilidad · Excel original
A7: Caso | B7: Tema | C7: Resultado | D7: Entradas Excel (editar solo copia) | E7: Hoja | F7: Celda | G7: Fórmula original (texto) | H7: Valor Excel original | I7: Observación / alcance
A8: E01 | B8: DOP por cantidad | C8: Cantidad deseada total | D8: {"CANTIDAD DE PRODUCCIÓN": {"D37": 0, "D38": 0, "D39": 0}} | E8: CANTIDAD DE PRODUCCIÓN | F8: D36 | G8: =SUM(D37:D39) | H8: 0 | I8: ["396 es capacidad del ejemplo, no máximo global. No existe máximo definido en Excel.", "E37:E39 muestran #DIV/0!; las necesidades D42:L44 sí son cero."]
A9: E01 | B9: DOP por cantidad | C9: Cuero, molde 1 | D9: {"CANTIDAD DE PRODUCCIÓN": {"D37": 0, "D38": 0, "D39": 0}} | E9: CANTIDAD DE PRODUCCIÓN | F9: D42 | G9: =$D37*D31 | H9: 0 | I9: ["396 es capacidad del ejemplo, no máximo global. No existe máximo definido en Excel.", "E37:E39 muestran #DIV/0!; las necesidades D42:L44 sí son cero."]
A10: E01 | B10: DOP por cantidad | C10: Accesorios, molde 1 | D10: {"CANTIDAD DE PRODUCCIÓN": {"D37": 0, "D38": 0, "D39": 0}} | E10: CANTIDAD DE PRODUCCIÓN | F10: G42 | G10: =$D37*G31 | H10: 0 | I10: ["396 es capacidad del ejemplo, no máximo global. No existe máximo definido en Excel.", "E37:E39 muestran #DIV/0!; las necesidades D42:L44 sí son cero."]
A11: E01 | B11: DOP por cantidad | C11: Hilo, molde 1 | D11: {"CANTIDAD DE PRODUCCIÓN": {"D37": 0, "D38": 0, "D39": 0}} | E11: CANTIDAD DE PRODUCCIÓN | F11: J42 | G11: =$D37*J31 | H11: 0 | I11: ["396 es capacidad del ejemplo, no máximo global. No existe máximo definido en Excel.", "E37:E39 muestran #DIV/0!; las necesidades D42:L44 sí son cero."]
A12: E01 | B12: DOP por cantidad | C12: Cuero, molde 2 | D12: {"CANTIDAD DE PRODUCCIÓN": {"D37": 0, "D38": 0, "D39": 0}} | E12: CANTIDAD DE PRODUCCIÓN | F12: E43 | G12: =$D38*E32 | H12: 0 | I12: ["396 es capacidad del ejemplo, no máximo global. No existe máximo definido en Excel.", "E37:E39 muestran #DIV/0!; las necesidades D42:L44 sí son cero."]
A13: E01 | B13: DOP por cantidad | C13: Accesorios, molde 2 | D13: {"CANTIDAD DE PRODUCCIÓN": {"D37": 0, "D38": 0, "D39": 0}} | E13: CANTIDAD DE PRODUCCIÓN | F13: H43 | G13: =$D38*H32 | H13: 0 | I13: ["396 es capacidad del ejemplo, no máximo global. No existe máximo definido en Excel.", "E37:E39 muestran #DIV/0!; las necesidades D42:L44 sí son cero."]
A14: E01 | B14: DOP por cantidad | C14: Hilo, molde 2 | D14: {"CANTIDAD DE PRODUCCIÓN": {"D37": 0, "D38": 0, "D39": 0}} | E14: CANTIDAD DE PRODUCCIÓN | F14: K43 | G14: =$D38*K32 | H14: 0 | I14: ["396 es capacidad del ejemplo, no máximo global. No existe máximo definido en Excel.", "E37:E39 muestran #DIV/0!; las necesidades D42:L44 sí son cero."]
A15: E01 | B15: DOP por cantidad | C15: Cuero, molde 3 | D15: {"CANTIDAD DE PRODUCCIÓN": {"D37": 0, "D38": 0, "D39": 0}} | E15: CANTIDAD DE PRODUCCIÓN | F15: F44 | G15: =$D39*F33 | H15: 0 | I15: ["396 es capacidad del ejemplo, no máximo global. No existe máximo definido en Excel.", "E37:E39 muestran #DIV/0!; las necesidades D42:L44 sí son cero."]
A16: E01 | B16: DOP por cantidad | C16: Accesorios, molde 3 | D16: {"CANTIDAD DE PRODUCCIÓN": {"D37": 0, "D38": 0, "D39": 0}} | E16: CANTIDAD DE PRODUCCIÓN | F16: I44 | G16: =$D39*I33 | H16: 0 | I16: ["396 es capacidad del ejemplo, no máximo global. No existe máximo definido en Excel.", "E37:E39 muestran #DIV/0!; las necesidades D42:L44 sí son cero."]
A17: E01 | B17: DOP por cantidad | C17: Hilo, molde 3 | D17: {"CANTIDAD DE PRODUCCIÓN": {"D37": 0, "D38": 0, "D39": 0}} | E17: CANTIDAD DE PRODUCCIÓN | F17: L44 | G17: =$D39*L33 | H17: 0 | I17: ["396 es capacidad del ejemplo, no máximo global. No existe máximo definido en Excel.", "E37:E39 muestran #DIV/0!; las necesidades D42:L44 sí son cero."]
A18: E02 | B18: DOP por cantidad | C18: Cantidad deseada total | D18: {"CANTIDAD DE PRODUCCIÓN": {"D37": 1, "D38": 0, "D39": 0}} | E18: CANTIDAD DE PRODUCCIÓN | F18: D36 | G18: =SUM(D37:D39) | H18: 1 | I18: ["396 es capacidad del ejemplo, no máximo global. No existe máximo definido en Excel."]
A19: E02 | B19: DOP por cantidad | C19: Cuero, molde 1 | D19: {"CANTIDAD DE PRODUCCIÓN": {"D37": 1, "D38": 0, "D39": 0}} | E19: CANTIDAD DE PRODUCCIÓN | F19: D42 | G19: =$D37*D31 | H19: 0.3 | I19: ["396 es capacidad del ejemplo, no máximo global. No existe máximo definido en Excel."]
... A100: E10 | B100: costo de producción | C100: Costo mensual acabado nivel 1 | D100: {} | E100: Costos De Producción | F100: AC11 | G100: =AC10/12.5 | H100: 1690.8 | I100: ["Componentes de costos comparables; no equivalen a caja final completa del ciclo."]
A101: E10 | B101: costo de producción | C101: Local de producción mensual | D101: {} | E101: Costos De Producción | F101: AC33 | G101: 2000 | H101: 2000 | I101: ["Componentes de costos comparables; no equivalen a caja final completa del ciclo."]
A102: E10 | B102: costo de producción | C102: Precio neto cuero sintético | D102: {} | E102: Costos De Producción | F102: W76 | G102: =V76-V76*8% | H102: 23 | I102: ["Componentes de costos comparables; no equivalen a caja final completa del ciclo."]
A103: E11 | B103: costo de producción | C103: Costo mensual corte nivel 1 | D103: {} | E103: Costos De Producción | F103: V11 | G103: =V10/13 | H103: 1856.5385 | I103: ["Componentes de costos comparables; no equivalen a caja final completa del ciclo."]
A104: E11 | B104: costo de producción | C104: Costo mensual ensamble nivel 1 | D104: {} | E104: Costos De Producción | F104: Z11 | G104: =Z10/13 | H104: 1856.5385 | I104: ["Componentes de costos comparables; no equivalen a caja final completa del ciclo."]
A105: E11 | B105: costo de producción | C105: Costo mensual acabado nivel 1 | D105: {} | E105: Costos De Producción | F105: AD11 | G105: =AD10/13 | H105: 1856.5385 | I105: ["Componentes de costos comparables; no equivalen a caja final completa del ciclo."]
A106: E11 | B106: costo de producción | C106: Local de producción mensual | D106: {} | E106: Costos De Producción | F106: AC33 | G106: 2000 | H106: 2000 | I106: ["Componentes de costos comparables; no equivalen a caja final completa del ciclo."]
A107: E11 | B107: costo de producción | C107: Precio neto cuero sintético | D107: {} | E107: Costos De Producción | F107: W76 | G107: =V76-V76*8% | H107: 23 | I107: ["Componentes de costos comparables; no equivalen a caja final completa del ciclo."]
A108: E12 | B108: caja | C108: Caja observada con capital cero tras fijos | D108: {} | I108: ["El Excel original no contiene caja inicial ni transición completa por ciclo; no puede fijarse esperado ni declararse igualdad.", "La prueba controla capital cero y observa reaplicación de fijos: no intenta confirmar una compra ni demuestra rechazo por fondos insuficientes."]
A109: E13 | B109: puntajes | C109: calidad | D109: {"Seleccion_Ciclo0": {"B2": "INF-03", "B3": "INF-06", "B4": "INF-09", "B5": "RH-02", "B6": "RH-05", "B7": "RH-08", "B8": "RH-10A", "B9": "COM-01C", "B10": "FIN-01B", "B11": "INV-01B", "B12": null, "B13": null, "B14": null, "B15": null}, "Lotes_Produccion": {"B2": "SEG-03", "C2": 100, "D2": "INS-03", "E2": "INS-05", "F2": "INS-08", "G2": "INF-10", "B3": "SEG-02", "C3": 300, "D3": "INS-02", "E3": "INS-04", "F3": "INS-06", "G3": "INF-08", "B4": "SEG-03", "C4": 100, "D4": "INS-01", "E4": "INS-04", "F4": "INS-06", "G4": "INF-08"}} | E109: Motor_Puntajes | F109: B6 | G109: =IFERROR(SUMPRODUCT(Lotes_Produccion!C2:C4,Lotes_Produccion!I2:I4)/SUM(Lotes_Produccion!C2:C4),0) | H109: 6.2 | I109: ["La selección B2:B15 y lotes B2:G4 se introducen sin tocar fórmulas.", "Caso original con selección histórica no era equivalente al plan actual: UI normaliza códigos. Se sustituyen las entradas por selección efectivamente guardada, esperando recálculo COM; ningún esperado se toma del código SIDE.", "Selección efectiva vigente capturada en navegador; se recalculó de nuevo la copia original E13.xlsx modificando solo entradas. La selección histórica no equivale a la pantalla actual."]
A110: E13 | B110: puntajes | C110: eficiencia | D110: {"Seleccion_Ciclo0": {"B2": "INF-03", "B3": "INF-06", "B4": "INF-09", "B5": "RH-02", "B6": "RH-05", "B7": "RH-08", "B8": "RH-10A", "B9": "COM-01C", "B10": "FIN-01B", "B11": "INV-01B", "B12": null, "B13": null, "B14": null, "B15": null}, "Lotes_Produccion": {"B2": "SEG-03", "C2": 100, "D2": "INS-03", "E2": "INS-05", "F2": "INS-08", "G2": "INF-10", "B3": "SEG-02", "C3": 300, "D3": "INS-02", "E3": "INS-04", "F3": "INS-06", "G3": "INF-08", "B4": "SEG-03", "C4": 100, "D4": "INS-01", "E4": "INS-04", "F4": "INS-06", "G4": "INF-08"}} | E110: Motor_Puntajes | F110: B9 | G110: =SUM(Seleccion_Ciclo0!G2:G15) | H110: 16 | I110: ["La selección B2:B15 y lotes B2:G4 se introducen sin tocar fórmulas.", "Caso original con selección histórica no era equivalente al plan actual: UI normaliza códigos. Se sustituyen las entradas por selección efectivamente guardada, esperando recálculo COM; ningún esperado se toma del código SIDE.", "Selección efectiva vigente capturada en navegador; se recalculó de nuevo la copia original E13.xlsx modificando solo entradas. La selección histórica no equivale a la pantalla actual."]
A111: E13 | B111: puntajes | C111: reputacion | D111: {"Seleccion_Ciclo0": {"B2": "INF-03", "B3": "INF-06", "B4": "INF-09", "B5": "RH-02", "B6": "RH-05", "B7": "RH-08", "B8": "RH-10A", "B9": "COM-01C", "B10": "FIN-01B", "B11": "INV-01B", "B12": null, "B13": null, "B14": null, "B15": null}, "Lotes_Produccion": {"B2": "SEG-03", "C2": 100, "D2": "INS-03", "E2": "INS-05", "F2": "INS-08", "G2": "INF-10", "B3": "SEG-02", "C3": 300, "D3": "INS-02", "E3": "INS-04", "F3": "INS-06", "G3": "INF-08", "B4": "SEG-03", "C4": 100, "D4": "INS-01", "E4": "INS-04", "F4": "INS-06", "G4": "INF-08"}} | E111: Motor_Puntajes | F111: B10 | G111: =SUM(Seleccion_Ciclo0!H2:H15) | H111: 6 | I111: ["La selección B2:B15 y lotes B2:G4 se introducen sin tocar fórmulas.", "Caso original con selección histórica no era equivalente al plan actual: UI normaliza códigos. Se sustituyen las entradas por selección efectivamente guardada, esperando recálculo COM; ningún esperado se toma del código SIDE.", "Selección efectiva vigente capturada en navegador; se recalculó de nuevo la copia original E13.xlsx modificando solo entradas. La selección histórica no equivale a la pantalla actual."]
A112: E13 | B112: puntajes | C112: saludFinanciera | D112: {"Seleccion_Ciclo0": {"B2": "INF-03", "B3": "INF-06", "B4": "INF-09", "B5": "RH-02", "B6": "RH-05", "B7": "RH-08", "B8": "RH-10A", "B9": "COM-01C", "B10": "FIN-01B", "B11": "INV-01B", "B12": null, "B13": null, "B14": null, "B15": null}, "Lotes_Produccion": {"B2": "SEG-03", "C2": 100, "D2": "INS-03", "E2": "INS-05", "F2": "INS-08", "G2": "INF-10", "B3": "SEG-02", "C3": 300, "D3": "INS-02", "E3": "INS-04", "F3": "INS-06", "G3": "INF-08", "B4": "SEG-03", "C4": 100, "D4": "INS-01", "E4": "INS-04", "F4": "INS-06", "G4": "INF-08"}} | E112: Motor_Puntajes | F112: B11 | G112: =SUM(Seleccion_Ciclo0!I2:I15) | H112: -1 | I112: ["La selección B2:B15 y lotes B2:G4 se introducen sin tocar fórmulas.", "Caso original con selección histórica no era equivalente al plan actual: UI normaliza códigos. Se sustituyen las entradas por selección efectivamente guardada, esperando recálculo COM; ningún esperado se toma del código SIDE.", "Selección efectiva vigente capturada en navegador; se recalculó de nuevo la copia original E13.xlsx modificando solo entradas. La selección histórica no equivale a la pantalla actual."]
A113: E13 | B113: puntajes | C113: Costo unitario lote 1 | D113: {"Seleccion_Ciclo0": {"B2": "INF-03", "B3": "INF-06", "B4": "INF-09", "B5": "RH-02", "B6": "RH-05", "B7": "RH-08", "B8": "RH-10A", "B9": "COM-01C", "B10": "FIN-01B", "B11": "INV-01B", "B12": null, "B13": null, "B14": null, "B15": null}, "Lotes_Produccion": {"B2": "SEG-03", "C2": 100, "D2": "INS-03", "E2": "INS-05", "F2": "INS-08", "G2": "INF-10", "B3": "SEG-02", "C3": 300, "D3": "INS-02", "E3": "INS-04", "F3": "INS-06", "G3": "INF-08", "B4": "SEG-03", "C4": 100, "D4": "INS-01", "E4": "INS-04", "F4": "INS-06", "G4": "INF-08"}} | E113: Lotes_Produccion | F113: H2 | G113: =IFERROR(INDEX(Catalogo_Decisiones!$G$2:$G$57,MATCH($D2,Catalogo_Decisiones!$A$2:$A$57,0)),0)+IFERROR(INDEX(Catalogo_Decisiones!$G$2:$G$57,MATCH($E2,Catalogo_Decisiones!$A$2:$A$57,0)),0)+IFERROR(INDEX(Catalogo_Decisiones!$G$2:$G$57,MATCH($F2,Catalogo_Decisiones!$A$2:$A$57,0)),0) | H113: 96 | I113: ["La selección B2:B15 y lotes B2:G4 se introducen sin tocar fórmulas.", "Caso original con selección histórica no era equivalente al plan actual: UI normaliza códigos. Se sustituyen las entradas por selección efectivamente guardada, esperando recálculo COM; ningún esperado se toma del código SIDE.", "Selección efectiva vigente capturada en navegador; se recalculó de nuevo la copia original E13.xlsx modificando solo entradas. La selección histórica no equivale a la pantalla actual."]
A114: E13 | B114: puntajes | C114: Costo unitario lote 2 | D114: {"Seleccion_Ciclo0": {"B2": "INF-03", "B3": "INF-06", "B4": "INF-09", "B5": "RH-02", "B6": "RH-05", "B7": "RH-08", "B8": "RH-10A", "B9": "COM-01C", "B10": "FIN-01B", "B11": "INV-01B", "B12": null, "B13": null, "B14": null, "B15": null}, "Lotes_Produccion": {"B2": "SEG-03", "C2": 100, "D2": "INS-03", "E2": "INS-05", "F2": "INS-08", "G2": "INF-10", "B3": "SEG-02", "C3": 300, "D3": "INS-02", "E3": "INS-04", "F3": "INS-06", "G3": "INF-08", "B4": "SEG-03", "C4": 100, "D4": "INS-01", "E4": "INS-04", "F4": "INS-06", "G4": "INF-08"}} | E114: Lotes_Produccion | F114: H3 | G114: =IFERROR(INDEX(Catalogo_Decisiones!$G$2:$G$57,MATCH($D3,Catalogo_Decisiones!$A$2:$A$57,0)),0)+IFERROR(INDEX(Catalogo_Decisiones!$G$2:$G$57,MATCH($E3,Catalogo_Decisiones!$A$2:$A$57,0)),0)+IFERROR(INDEX(Catalogo_Decisiones!$G$2:$G$57,MATCH($F3,Catalogo_Decisiones!$A$2:$A$57,0)),0) | H114: 51 | I114: ["La selección B2:B15 y lotes B2:G4 se introducen sin tocar fórmulas.", "Caso original con selección histórica no era equivalente al plan actual: UI normaliza códigos. Se sustituyen las entradas por selección efectivamente guardada, esperando recálculo COM; ningún esperado se toma del código SIDE.", "Selección efectiva vigente capturada en navegador; se recalculó de nuevo la copia original E13.xlsx modificando solo entradas. La selección histórica no equivale a la pantalla actual."]
A115: E13 | B115: puntajes | C115: Costo unitario lote 3 | D115: {"Seleccion_Ciclo0": {"B2": "INF-03", "B3": "INF-06", "B4": "INF-09", "B5": "RH-02", "B6": "RH-05", "B7": "RH-08", "B8": "RH-10A", "B9": "COM-01C", "B10": "FIN-01B", "B11": "INV-01B", "B12": null, "B13": null, "B14": null, "B15": null}, "Lotes_Produccion": {"B2": "SEG-03", "C2": 100, "D2": "INS-03", "E2": "INS-05", "F2": "INS-08", "G2": "INF-10", "B3": "SEG-02", "C3": 300, "D3": "INS-02", "E3": "INS-04", "F3": "INS-06", "G3": "INF-08", "B4": "SEG-03", "C4": 100, "D4": "INS-01", "E4": "INS-04", "F4": "INS-06", "G4": "INF-08"}} | E115: Lotes_Produccion | F115: H4 | G115: =IFERROR(INDEX(Catalogo_Decisiones!$G$2:$G$57,MATCH($D4,Catalogo_Decisiones!$A$2:$A$57,0)),0)+IFERROR(INDEX(Catalogo_Decisiones!$G$2:$G$57,MATCH($E4,Catalogo_Decisiones!$A$2:$A$57,0)),0)+IFERROR(INDEX(Catalogo_Decisiones!$G$2:$G$57,MATCH($F4,Catalogo_Decisiones!$A$2:$A$57,0)),0) | H115: 31 | I115: ["La selección B2:B15 y lotes B2:G4 se introducen sin tocar fórmulas.", "Caso original con selección histórica no era equivalente al plan actual: UI normaliza códigos. Se sustituyen las entradas por selección efectivamente guardada, esperando recálculo COM; ningún esperado se toma del código SIDE.", "Selección efectiva vigente capturada en navegador; se recalculó de nuevo la copia original E13.xlsx modificando solo entradas. La selección histórica no equivale a la pantalla actual."]
A116: E14 | B116: consecuencias | C116: Factor sobre precio de venta | D116: {"Lotes_Produccion": {"B2": "SEG-03", "C2": 10, "D2": "INS-01", "E2": "INS-04", "F2": "INS-06", "G2": "INF-08", "C3": 0, "C4": 0}} | E116: Matriz_Consecuencias | F116: C2:D3 | G116: C2: < 4 y Segmento = Premium; C3: >= 7 y Segmento = Premium. Calidad 4 no cumple ninguna condición; no se activa D2 ni D3. | H116: 1 | I116: ["El lote completo más básico suma calidad 4 (1+1+1+1). La condición de castigo exige menos de 4 y la de premio al menos 7; ninguna se activa.", "Calidad 3 se conserva solo como control técnico adicional; no se presenta como lote completo reproducible desde el menú.", "En una copia vacíe las cantidades de los otros lotes y compruebe calidad 4 en Motor_Puntajes!B6 sin tocar fórmulas."]
A117: E14 | B117: consecuencias | C117: Cambio reputación | D117: {"Lotes_Produccion": {"B2": "SEG-03", "C2": 10, "D2": "INS-01", "E2": "INS-04", "F2": "INS-06", "G2": "INF-08", "C3": 0, "C4": 0}} | E117: Matriz_Consecuencias | F117: C2:D3 | G117: C2: < 4 y Segmento = Premium; C3: >= 7 y Segmento = Premium. Calidad 4 no cumple ninguna condición; no se activa D2 ni D3. | H117: 0 | I117: ["El lote completo más básico suma calidad 4 (1+1+1+1). La condición de castigo exige menos de 4 y la de premio al menos 7; ninguna se activa.", "Calidad 3 se conserva solo como control técnico adicional; no se presenta como lote completo reproducible desde el menú.", "En una copia vacíe las cantidades de los otros lotes y compruebe calidad 4 en Motor_Puntajes!B6 sin tocar fórmulas."]
A118: E15 | B118: consecuencias | C118: Factor sobre precio de venta | D118: {} | E118: Matriz_Consecuencias | F118: D3 | G118: Precio de venta +40%, Reputacion +2 | H118: 1.4 | I118: ["Matriz_Consecuencias no contiene fórmulas: leer condición C3 y efecto D3. Calidad controlada para aislar esta consecuencia; no editar fórmulas del Motor."]
A119: E15 | B119: consecuencias | C119: Cambio reputación | D119: {} | E119: Matriz_Consecuencias | F119: D3 | G119: Precio de venta +40%, Reputacion +2 | H119: 2 | I119: ["Matriz_Consecuencias no contiene fórmulas: leer condición C3 y efecto D3. Calidad controlada para aislar esta consecuencia; no editar fórmulas del Motor."]

Sheet Errores del original
A1: Errores heredados · evidencia
A4: Estos errores pertenecen al Excel original recalculado. Son evidencia, no fórmulas con error del comparativo. Se excluyen del conteo de igualdad numérica.
A7: Caso | B7: Hoja | C7: Celda | D7: Error original (texto) | E7: Interpretación
A8: E01 | B8: CANTIDAD DE PRODUCCIÓN | C8: E37 | D8: #DIV/0! | E8: Plan cero: la proporción divide entre cero; comparar necesidades brutas en la hoja DOP.
A9: E01 | B9: CANTIDAD DE PRODUCCIÓN | C9: E38 | D9: #DIV/0! | E9: Plan cero: la proporción divide entre cero; comparar necesidades brutas en la hoja DOP.
A10: E01 | B10: CANTIDAD DE PRODUCCIÓN | C10: E39 | D10: #DIV/0! | E10: Plan cero: la proporción divide entre cero; comparar necesidades brutas en la hoja DOP.
