Workbook

Sheet Instrucciones
B2: Simulador de empresa de bolsos de cuero — Catalogo maestro de decisiones
B4: Como esta organizado este archivo:
B6: 1) Catalogo_Decisiones: TODAS las opciones posibles del juego. Cada opcion es una fila y cada dato (costo, aporte a cada puntaje) tiene su propia celda — nada esta combinado en una sola celda.
B7: 2) Seleccion_Ciclo0: aqui el jugador elige, por cada grupo de decision (maquinas, personal, canal, etc.), el codigo de la opcion que quiere (lista desplegable en la columna B). Las demas columnas se completan solas con formulas.
B8: 2b) Lotes_Produccion: aqui se decide la calidad POR LOTE, no como promedio de toda la empresa. Cada lote (hasta 3 por ciclo) tiene su propia cantidad de unidades, su propio cuero/accesorios/hilo/molde y su propio segmento de venta. El sistema calcula el Puntaje de Calidad de CADA lote y lo compara contra el segmento elegido (si vendes 'Premium' con insumos bajos, el lote sale 'No alcanza el segmento').
B9: 3) Motor_Puntajes: el Puntaje de Calidad de la empresa es el promedio de los lotes PONDERADO por las unidades de cada uno (un lote de 500 unidades pesa mas que uno de 50). Los otros 3 puntajes (Eficiencia, Reputacion, Salud Financiera) suman los aportes de Seleccion_Ciclo0.
B10: 4) Matriz_Consecuencias: reglas de negocio — que pasa (efecto numerico) y que mensaje ve el jugador segun el valor de cada puntaje.
B12: Celdas amarillas = donde se elige/edita (inputs). Celdas verdes = puntajes/aportes calculados. Celdas grises = fijas u obligatorias.
B14: Para agregar una opcion nueva: agrega una fila en Catalogo_Decisiones con su Codigo unico y sus aportes, y aparecera disponible para elegir en Seleccion_Ciclo0 (agregando el codigo a la lista desplegable del grupo correspondiente).

Sheet DECISIONES
B2: DECISIONES | C2: Puntaje
B3: Depreciación
B4: Garantía del producto
B5: Mantenimiento de maquinaria
B6: Política de inventarios

Sheet Seleccion_Ciclo0
A1: Grupo de decision | B1: Codigo elegido (elige de la lista) | C1: Opcion / Nivel (auto) | D1: Descripcion (auto) | E1: Costo referencial (auto) | F1: Aporte Calidad (auto) | G1: Aporte Eficiencia (auto) | H1: Aporte Reputacion (auto) | I1: Aporte Financiero (auto)
A2: Maquina de ensamblado | C2: =IFERROR(INDEX(Catalogo_Decisiones!$D$2:$D$69,MATCH($B2,Catalogo_Decisiones!$A$2:$A$69,0)),"") | D2: =IFERROR(INDEX(Catalogo_Decisiones!$F$2:$F$69,MATCH($B2,Catalogo_Decisiones!$A$2:$A$69,0)),"") | E2: =IFERROR(INDEX(Catalogo_Decisiones!$G$2:$G$69,MATCH($B2,Catalogo_Decisiones!$A$2:$A$69,0)),0) -> 0 | F2: =IFERROR(INDEX(Catalogo_Decisiones!$H$2:$H$69,MATCH($B2,Catalogo_Decisiones!$A$2:$A$69,0)),0) -> 0 | G2: =IFERROR(INDEX(Catalogo_Decisiones!$I$2:$I$69,MATCH($B2,Catalogo_Decisiones!$A$2:$A$69,0)),0) -> 0 | H2: =IFERROR(INDEX(Catalogo_Decisiones!$J$2:$J$69,MATCH($B2,Catalogo_Decisiones!$A$2:$A$69,0)),0) -> 0 | I2: =IFERROR(INDEX(Catalogo_Decisiones!$K$2:$K$69,MATCH($B2,Catalogo_Decisiones!$A$2:$A$69,0)),0) -> 0
A3: Maquina de acabados | C3: =IFERROR(INDEX(Catalogo_Decisiones!$D$2:$D$69,MATCH($B3,Catalogo_Decisiones!$A$2:$A$69,0)),"") | D3: =IFERROR(INDEX(Catalogo_Decisiones!$F$2:$F$69,MATCH($B3,Catalogo_Decisiones!$A$2:$A$69,0)),"") | E3: =IFERROR(INDEX(Catalogo_Decisiones!$G$2:$G$69,MATCH($B3,Catalogo_Decisiones!$A$2:$A$69,0)),0) -> 0 | F3: =IFERROR(INDEX(Catalogo_Decisiones!$H$2:$H$69,MATCH($B3,Catalogo_Decisiones!$A$2:$A$69,0)),0) -> 0 | G3: =IFERROR(INDEX(Catalogo_Decisiones!$I$2:$I$69,MATCH($B3,Catalogo_Decisiones!$A$2:$A$69,0)),0) -> 0 | H3: =IFERROR(INDEX(Catalogo_Decisiones!$J$2:$J$69,MATCH($B3,Catalogo_Decisiones!$A$2:$A$69,0)),0) -> 0 | I3: =IFERROR(INDEX(Catalogo_Decisiones!$K$2:$K$69,MATCH($B3,Catalogo_Decisiones!$A$2:$A$69,0)),0) -> 0
A4: Molde | C4: =IFERROR(INDEX(Catalogo_Decisiones!$D$2:$D$69,MATCH($B4,Catalogo_Decisiones!$A$2:$A$69,0)),"") | D4: =IFERROR(INDEX(Catalogo_Decisiones!$F$2:$F$69,MATCH($B4,Catalogo_Decisiones!$A$2:$A$69,0)),"") | E4: =IFERROR(INDEX(Catalogo_Decisiones!$G$2:$G$69,MATCH($B4,Catalogo_Decisiones!$A$2:$A$69,0)),0) -> 0 | F4: =IFERROR(INDEX(Catalogo_Decisiones!$H$2:$H$69,MATCH($B4,Catalogo_Decisiones!$A$2:$A$69,0)),0) -> 0 | G4: =IFERROR(INDEX(Catalogo_Decisiones!$I$2:$I$69,MATCH($B4,Catalogo_Decisiones!$A$2:$A$69,0)),0) -> 0 | H4: =IFERROR(INDEX(Catalogo_Decisiones!$J$2:$J$69,MATCH($B4,Catalogo_Decisiones!$A$2:$A$69,0)),0) -> 0 | I4: =IFERROR(INDEX(Catalogo_Decisiones!$K$2:$K$69,MATCH($B4,Catalogo_Decisiones!$A$2:$A$69,0)),0) -> 0
A5: Personal de corte | C5: =IFERROR(INDEX(Catalogo_Decisiones!$D$2:$D$69,MATCH($B5,Catalogo_Decisiones!$A$2:$A$69,0)),"") | D5: =IFERROR(INDEX(Catalogo_Decisiones!$F$2:$F$69,MATCH($B5,Catalogo_Decisiones!$A$2:$A$69,0)),"") | E5: =IFERROR(INDEX(Catalogo_Decisiones!$G$2:$G$69,MATCH($B5,Catalogo_Decisiones!$A$2:$A$69,0)),0) -> 0 | F5: =IFERROR(INDEX(Catalogo_Decisiones!$H$2:$H$69,MATCH($B5,Catalogo_Decisiones!$A$2:$A$69,0)),0) -> 0 | G5: =IFERROR(INDEX(Catalogo_Decisiones!$I$2:$I$69,MATCH($B5,Catalogo_Decisiones!$A$2:$A$69,0)),0) -> 0 | H5: =IFERROR(INDEX(Catalogo_Decisiones!$J$2:$J$69,MATCH($B5,Catalogo_Decisiones!$A$2:$A$69,0)),0) -> 0 | I5: =IFERROR(INDEX(Catalogo_Decisiones!$K$2:$K$69,MATCH($B5,Catalogo_Decisiones!$A$2:$A$69,0)),0) -> 0
A6: Personal de ensamble | C6: =IFERROR(INDEX(Catalogo_Decisiones!$D$2:$D$69,MATCH($B6,Catalogo_Decisiones!$A$2:$A$69,0)),"") | D6: =IFERROR(INDEX(Catalogo_Decisiones!$F$2:$F$69,MATCH($B6,Catalogo_Decisiones!$A$2:$A$69,0)),"") | E6: =IFERROR(INDEX(Catalogo_Decisiones!$G$2:$G$69,MATCH($B6,Catalogo_Decisiones!$A$2:$A$69,0)),0) -> 0 | F6: =IFERROR(INDEX(Catalogo_Decisiones!$H$2:$H$69,MATCH($B6,Catalogo_Decisiones!$A$2:$A$69,0)),0) -> 0 | G6: =IFERROR(INDEX(Catalogo_Decisiones!$I$2:$I$69,MATCH($B6,Catalogo_Decisiones!$A$2:$A$69,0)),0) -> 0 | H6: =IFERROR(INDEX(Catalogo_Decisiones!$J$2:$J$69,MATCH($B6,Catalogo_Decisiones!$A$2:$A$69,0)),0) -> 0 | I6: =IFERROR(INDEX(Catalogo_Decisiones!$K$2:$K$69,MATCH($B6,Catalogo_Decisiones!$A$2:$A$69,0)),0) -> 0
A7: Personal de acabados | C7: =IFERROR(INDEX(Catalogo_Decisiones!$D$2:$D$69,MATCH($B7,Catalogo_Decisiones!$A$2:$A$69,0)),"") | D7: =IFERROR(INDEX(Catalogo_Decisiones!$F$2:$F$69,MATCH($B7,Catalogo_Decisiones!$A$2:$A$69,0)),"") | E7: =IFERROR(INDEX(Catalogo_Decisiones!$G$2:$G$69,MATCH($B7,Catalogo_Decisiones!$A$2:$A$69,0)),0) -> 0 | F7: =IFERROR(INDEX(Catalogo_Decisiones!$H$2:$H$69,MATCH($B7,Catalogo_Decisiones!$A$2:$A$69,0)),0) -> 0 | G7: =IFERROR(INDEX(Catalogo_Decisiones!$I$2:$I$69,MATCH($B7,Catalogo_Decisiones!$A$2:$A$69,0)),0) -> 0 | H7: =IFERROR(INDEX(Catalogo_Decisiones!$J$2:$J$69,MATCH($B7,Catalogo_Decisiones!$A$2:$A$69,0)),0) -> 0 | I7: =IFERROR(INDEX(Catalogo_Decisiones!$K$2:$K$69,MATCH($B7,Catalogo_Decisiones!$A$2:$A$69,0)),0) -> 0
A8: Jefatura | C8: =IFERROR(INDEX(Catalogo_Decisiones!$D$2:$D$69,MATCH($B8,Catalogo_Decisiones!$A$2:$A$69,0)),"") | D8: =IFERROR(INDEX(Catalogo_Decisiones!$F$2:$F$69,MATCH($B8,Catalogo_Decisiones!$A$2:$A$69,0)),"") | E8: =IFERROR(INDEX(Catalogo_Decisiones!$G$2:$G$69,MATCH($B8,Catalogo_Decisiones!$A$2:$A$69,0)),0) -> 0 | F8: =IFERROR(INDEX(Catalogo_Decisiones!$H$2:$H$69,MATCH($B8,Catalogo_Decisiones!$A$2:$A$69,0)),0) -> 0 | G8: =IFERROR(INDEX(Catalogo_Decisiones!$I$2:$I$69,MATCH($B8,Catalogo_Decisiones!$A$2:$A$69,0)),0) -> 0 | H8: =IFERROR(INDEX(Catalogo_Decisiones!$J$2:$J$69,MATCH($B8,Catalogo_Decisiones!$A$2:$A$69,0)),0) -> 0 | I8: =IFERROR(INDEX(Catalogo_Decisiones!$K$2:$K$69,MATCH($B8,Catalogo_Decisiones!$A$2:$A$69,0)),0) -> 0
A9: Canal de venta | C9: =IFERROR(INDEX(Catalogo_Decisiones!$D$2:$D$69,MATCH($B9,Catalogo_Decisiones!$A$2:$A$69,0)),"") | D9: =IFERROR(INDEX(Catalogo_Decisiones!$F$2:$F$69,MATCH($B9,Catalogo_Decisiones!$A$2:$A$69,0)),"") | E9: =IFERROR(INDEX(Catalogo_Decisiones!$G$2:$G$69,MATCH($B9,Catalogo_Decisiones!$A$2:$A$69,0)),0) -> 0 | F9: =IFERROR(INDEX(Catalogo_Decisiones!$H$2:$H$69,MATCH($B9,Catalogo_Decisiones!$A$2:$A$69,0)),0) -> 0 | G9: =IFERROR(INDEX(Catalogo_Decisiones!$I$2:$I$69,MATCH($B9,Catalogo_Decisiones!$A$2:$A$69,0)),0) -> 0 | H9: =IFERROR(INDEX(Catalogo_Decisiones!$J$2:$J$69,MATCH($B9,Catalogo_Decisiones!$A$2:$A$69,0)),0) -> 0 | I9: =IFERROR(INDEX(Catalogo_Decisiones!$K$2:$K$69,MATCH($B9,Catalogo_Decisiones!$A$2:$A$69,0)),0) -> 0
A10: Acceso a prestamo bancario | C10: =IFERROR(INDEX(Catalogo_Decisiones!$D$2:$D$69,MATCH($B10,Catalogo_Decisiones!$A$2:$A$69,0)),"") | D10: =IFERROR(INDEX(Catalogo_Decisiones!$F$2:$F$69,MATCH($B10,Catalogo_Decisiones!$A$2:$A$69,0)),"") | E10: =IFERROR(INDEX(Catalogo_Decisiones!$G$2:$G$69,MATCH($B10,Catalogo_Decisiones!$A$2:$A$69,0)),0) -> 0 | F10: =IFERROR(INDEX(Catalogo_Decisiones!$H$2:$H$69,MATCH($B10,Catalogo_Decisiones!$A$2:$A$69,0)),0) -> 0 | G10: =IFERROR(INDEX(Catalogo_Decisiones!$I$2:$I$69,MATCH($B10,Catalogo_Decisiones!$A$2:$A$69,0)),0) -> 0 | H10: =IFERROR(INDEX(Catalogo_Decisiones!$J$2:$J$69,MATCH($B10,Catalogo_Decisiones!$A$2:$A$69,0)),0) -> 0 | I10: =IFERROR(INDEX(Catalogo_Decisiones!$K$2:$K$69,MATCH($B10,Catalogo_Decisiones!$A$2:$A$69,0)),0) -> 0
A11: Numero de proveedores | C11: =IFERROR(INDEX(Catalogo_Decisiones!$D$2:$D$69,MATCH($B11,Catalogo_Decisiones!$A$2:$A$69,0)),"") | D11: =IFERROR(INDEX(Catalogo_Decisiones!$F$2:$F$69,MATCH($B11,Catalogo_Decisiones!$A$2:$A$69,0)),"") | E11: =IFERROR(INDEX(Catalogo_Decisiones!$G$2:$G$69,MATCH($B11,Catalogo_Decisiones!$A$2:$A$69,0)),0) -> 0 | F11: =IFERROR(INDEX(Catalogo_Decisiones!$H$2:$H$69,MATCH($B11,Catalogo_Decisiones!$A$2:$A$69,0)),0) -> 0 | G11: =IFERROR(INDEX(Catalogo_Decisiones!$I$2:$I$69,MATCH($B11,Catalogo_Decisiones!$A$2:$A$69,0)),0) -> 0 | H11: =IFERROR(INDEX(Catalogo_Decisiones!$J$2:$J$69,MATCH($B11,Catalogo_Decisiones!$A$2:$A$69,0)),0) -> 0 | I11: =IFERROR(INDEX(Catalogo_Decisiones!$K$2:$K$69,MATCH($B11,Catalogo_Decisiones!$A$2:$A$69,0)),0) -> 0
A12: Politica de pago a proveedores | C12: =IFERROR(INDEX(Catalogo_Decisiones!$D$2:$D$69,MATCH($B12,Catalogo_Decisiones!$A$2:$A$69,0)),"") | D12: =IFERROR(INDEX(Catalogo_Decisiones!$F$2:$F$69,MATCH($B12,Catalogo_Decisiones!$A$2:$A$69,0)),"") | E12: =IFERROR(INDEX(Catalogo_Decisiones!$G$2:$G$69,MATCH($B12,Catalogo_Decisiones!$A$2:$A$69,0)),0) -> 0 | F12: =IFERROR(INDEX(Catalogo_Decisiones!$H$2:$H$69,MATCH($B12,Catalogo_Decisiones!$A$2:$A$69,0)),0) -> 0 | G12: =IFERROR(INDEX(Catalogo_Decisiones!$I$2:$I$69,MATCH($B12,Catalogo_Decisiones!$A$2:$A$69,0)),0) -> 0 | H12: =IFERROR(INDEX(Catalogo_Decisiones!$J$2:$J$69,MATCH($B12,Catalogo_Decisiones!$A$2:$A$69,0)),0) -> 0 | I12: =IFERROR(INDEX(Catalogo_Decisiones!$K$2:$K$69,MATCH($B12,Catalogo_Decisiones!$A$2:$A$69,0)),0) -> 0
A13: Lead time | C13: =IFERROR(INDEX(Catalogo_Decisiones!$D$2:$D$69,MATCH($B13,Catalogo_Decisiones!$A$2:$A$69,0)),"") | D13: =IFERROR(INDEX(Catalogo_Decisiones!$F$2:$F$69,MATCH($B13,Catalogo_Decisiones!$A$2:$A$69,0)),"") | E13: =IFERROR(INDEX(Catalogo_Decisiones!$G$2:$G$69,MATCH($B13,Catalogo_Decisiones!$A$2:$A$69,0)),0) -> 0 | F13: =IFERROR(INDEX(Catalogo_Decisiones!$H$2:$H$69,MATCH($B13,Catalogo_Decisiones!$A$2:$A$69,0)),0) -> 0 | G13: =IFERROR(INDEX(Catalogo_Decisiones!$I$2:$I$69,MATCH($B13,Catalogo_Decisiones!$A$2:$A$69,0)),0) -> 0 | H13: =IFERROR(INDEX(Catalogo_Decisiones!$J$2:$J$69,MATCH($B13,Catalogo_Decisiones!$A$2:$A$69,0)),0) -> 0 | I13: =IFERROR(INDEX(Catalogo_Decisiones!$K$2:$K$69,MATCH($B13,Catalogo_Decisiones!$A$2:$A$69,0)),0) -> 0
... A15: Inversion en marketing | C15: =IFERROR(INDEX(Catalogo_Decisiones!$D$2:$D$69,MATCH($B15,Catalogo_Decisiones!$A$2:$A$69,0)),"") | D15: =IFERROR(INDEX(Catalogo_Decisiones!$F$2:$F$69,MATCH($B15,Catalogo_Decisiones!$A$2:$A$69,0)),"") | E15: =IFERROR(INDEX(Catalogo_Decisiones!$G$2:$G$69,MATCH($B15,Catalogo_Decisiones!$A$2:$A$69,0)),0) -> 0 | F15: =IFERROR(INDEX(Catalogo_Decisiones!$H$2:$H$69,MATCH($B15,Catalogo_Decisiones!$A$2:$A$69,0)),0) -> 0 | G15: =IFERROR(INDEX(Catalogo_Decisiones!$I$2:$I$69,MATCH($B15,Catalogo_Decisiones!$A$2:$A$69,0)),0) -> 0 | H15: =IFERROR(INDEX(Catalogo_Decisiones!$J$2:$J$69,MATCH($B15,Catalogo_Decisiones!$A$2:$A$69,0)),0) -> 0 | I15: =IFERROR(INDEX(Catalogo_Decisiones!$K$2:$K$69,MATCH($B15,Catalogo_Decisiones!$A$2:$A$69,0)),0) -> 0
A16: --- Otras decisiones numericas ---
A17: PRO-01 - Cantidad inicial a producir (unidades) | B17: 0
A18: COM-02 - N° de tiendas en zona alta (Miraflores) | B18: 0
A19: COM-03 - N° de tiendas en zona media (Los Olivos / San Miguel) | B19: 0
A20: COM-04 - N° de tiendas en zona baja (SJL / SMP) | B20: 0
A21: COM-05N - % de ventas a credito (0-100) | B21: 0
A22: FIN-01M - Monto de prestamo solicitado (S/) | B22: 0
A24: Método de depreciación | C24: =IFERROR(INDEX(Catalogo_Decisiones!$D$2:$D$69,MATCH($B24,Catalogo_Decisiones!$A$2:$A$69,0)),"") | D24: =IFERROR(INDEX(Catalogo_Decisiones!$F$2:$F$69,MATCH($B24,Catalogo_Decisiones!$A$2:$A$69,0)),"") | E24: =IFERROR(INDEX(Catalogo_Decisiones!$G$2:$G$69,MATCH($B24,Catalogo_Decisiones!$A$2:$A$69,0)),0) -> 0 | F24: =IFERROR(INDEX(Catalogo_Decisiones!$H$2:$H$69,MATCH($B24,Catalogo_Decisiones!$A$2:$A$69,0)),0) -> 0 | G24: =IFERROR(INDEX(Catalogo_Decisiones!$I$2:$I$69,MATCH($B24,Catalogo_Decisiones!$A$2:$A$69,0)),0) -> 0 | H24: =IFERROR(INDEX(Catalogo_Decisiones!$J$2:$J$69,MATCH($B24,Catalogo_Decisiones!$A$2:$A$69,0)),0) -> 0 | I24: =IFERROR(INDEX(Catalogo_Decisiones!$K$2:$K$69,MATCH($B24,Catalogo_Decisiones!$A$2:$A$69,0)),0) -> 0
A25: Garantía | C25: =IFERROR(INDEX(Catalogo_Decisiones!$D$2:$D$69,MATCH($B25,Catalogo_Decisiones!$A$2:$A$69,0)),"") | D25: =IFERROR(INDEX(Catalogo_Decisiones!$F$2:$F$69,MATCH($B25,Catalogo_Decisiones!$A$2:$A$69,0)),"") | E25: =IFERROR(INDEX(Catalogo_Decisiones!$G$2:$G$69,MATCH($B25,Catalogo_Decisiones!$A$2:$A$69,0)),0) -> 0 | F25: =IFERROR(INDEX(Catalogo_Decisiones!$H$2:$H$69,MATCH($B25,Catalogo_Decisiones!$A$2:$A$69,0)),0) -> 0 | G25: =IFERROR(INDEX(Catalogo_Decisiones!$I$2:$I$69,MATCH($B25,Catalogo_Decisiones!$A$2:$A$69,0)),0) -> 0 | H25: =IFERROR(INDEX(Catalogo_Decisiones!$J$2:$J$69,MATCH($B25,Catalogo_Decisiones!$A$2:$A$69,0)),0) -> 0 | I25: =IFERROR(INDEX(Catalogo_Decisiones!$K$2:$K$69,MATCH($B25,Catalogo_Decisiones!$A$2:$A$69,0)),0) -> 0
A26: Mantenimiento | C26: =IFERROR(INDEX(Catalogo_Decisiones!$D$2:$D$69,MATCH($B26,Catalogo_Decisiones!$A$2:$A$69,0)),"") | D26: =IFERROR(INDEX(Catalogo_Decisiones!$F$2:$F$69,MATCH($B26,Catalogo_Decisiones!$A$2:$A$69,0)),"") | E26: =IFERROR(INDEX(Catalogo_Decisiones!$G$2:$G$69,MATCH($B26,Catalogo_Decisiones!$A$2:$A$69,0)),0) -> 0 | F26: =IFERROR(INDEX(Catalogo_Decisiones!$H$2:$H$69,MATCH($B26,Catalogo_Decisiones!$A$2:$A$69,0)),0) -> 0 | G26: =IFERROR(INDEX(Catalogo_Decisiones!$I$2:$I$69,MATCH($B26,Catalogo_Decisiones!$A$2:$A$69,0)),0) -> 0 | H26: =IFERROR(INDEX(Catalogo_Decisiones!$J$2:$J$69,MATCH($B26,Catalogo_Decisiones!$A$2:$A$69,0)),0) -> 0 | I26: =IFERROR(INDEX(Catalogo_Decisiones!$K$2:$K$69,MATCH($B26,Catalogo_Decisiones!$A$2:$A$69,0)),0) -> 0
A27: Política de inventarios | C27: =IFERROR(INDEX(Catalogo_Decisiones!$D$2:$D$69,MATCH($B27,Catalogo_Decisiones!$A$2:$A$69,0)),"") | D27: =IFERROR(INDEX(Catalogo_Decisiones!$F$2:$F$69,MATCH($B27,Catalogo_Decisiones!$A$2:$A$69,0)),"") | E27: =IFERROR(INDEX(Catalogo_Decisiones!$G$2:$G$69,MATCH($B27,Catalogo_Decisiones!$A$2:$A$69,0)),0) -> 0 | F27: =IFERROR(INDEX(Catalogo_Decisiones!$H$2:$H$69,MATCH($B27,Catalogo_Decisiones!$A$2:$A$69,0)),0) -> 0 | G27: =IFERROR(INDEX(Catalogo_Decisiones!$I$2:$I$69,MATCH($B27,Catalogo_Decisiones!$A$2:$A$69,0)),0) -> 0 | H27: =IFERROR(INDEX(Catalogo_Decisiones!$J$2:$J$69,MATCH($B27,Catalogo_Decisiones!$A$2:$A$69,0)),0) -> 0 | I27: =IFERROR(INDEX(Catalogo_Decisiones!$K$2:$K$69,MATCH($B27,Catalogo_Decisiones!$A$2:$A$69,0)),0) -> 0

Sheet Catalogo_Decisiones
A1: Codigo | B1: Bloque | C1: Grupo de decision | D1: Opcion / Nivel | E1: Permanencia | F1: Descripcion | G1: Costo referencial (S/) | H1: Aporte Calidad | I1: Aporte Eficiencia | J1: Aporte Reputacion | K1: Aporte Financiero | L1: Notas
A2: GEN-01 | B2: A. Empresa | C2: Razon social | D2: Texto libre | E2: Fija | F2: Nombre legal de la empresa (texto) | G2: 0 | H2: 0 | I2: 0 | J2: 0 | K2: 0 | L2: Sin efecto en puntajes
A3: GEN-02 | B3: A. Empresa | C3: Nombre comercial / marca | D3: Texto libre | E3: Fija | F3: Marca comercial (texto) | G3: 0 | H3: 0 | I3: 0 | J3: 0 | K3: 0 | L3: Sin efecto en puntajes
A4: GEN-04 | B4: A. Empresa | C4: Tipos de bolsos | D4: Texto libre | E4: Fija | F4: Linea de productos que fabrica (tote, cartera, mochila, etc.) | G4: 0 | H4: 0 | I4: 0 | J4: 0 | K4: 0 | L4: Sin efecto en puntajes
A5: SEG-01 | B5: A. Empresa | C5: Segmento / linea | D5: Economico | E5: Fija | F5: Precio bajo, prioriza volumen y costo | G5: 0 | H5: 0 | I5: 0 | J5: 1 | K5: 0 | L5: Exige coherencia con Calidad real
A6: SEG-02 | B6: A. Empresa | C6: Segmento / linea | D6: Estandar | E6: Fija | F6: Equilibra costo, calidad, demanda y margen | G6: 0 | H6: 1 | I6: 0 | J6: 1 | K6: 0
A7: SEG-03 | B7: A. Empresa | C7: Segmento / linea | D7: Premium | E7: Fija | F7: Precio alto; requiere Calidad>=7 para sostenerse | G7: 0 | H7: 2 | I7: 0 | J7: 2 | K7: 0 | L7: Riesgo si Calidad interna es baja (ver Matriz)
A8: INF-01 | B8: B. Infraestructura | C8: Mesa de corte | D8: Unica (obligatoria) | E8: Fija | F8: Inversion fija para todos; habilita la etapa de corte | G8: 2500 | H8: 0 | I8: 1 | J8: 0 | K8: 0 | L8: Obligatoria, no otorga niveles
A9: INF-02 | B9: B. Infraestructura | C9: Maquina de ensamblado | D9: Nivel 1: manual/basica | E9: Fija | F9: Costura Singer 4423 Heavy Duty; desbastadora a mano con cuchilla o lija | G9: 3500 | H9: 1 | I9: 1 | J9: 0 | K9: 0
A10: INF-03 | B10: B. Infraestructura | C10: Maquina de ensamblado | D10: Nivel 2: semi-industrial | E10: Fija | F10: Maquina de coser de columna/brazo (poste) Typical TB-801 | G10: 7500 | H10: 2 | I10: 2 | J10: 0 | K10: 0
A11: INF-04 | B11: B. Infraestructura | C11: Maquina de ensamblado | D11: Nivel 3: industrial | E11: Fija | F11: Juki de triple accionamiento; desbastadora automatica de alta precision, servomotor | G11: 15000 | H11: 3 | I11: 3 | J11: 0 | K11: 0
A12: INF-05 | B12: B. Infraestructura | C12: Maquina de acabados | D12: Nivel 1: manual/basica | E12: Fija | F12: Acabado a mano con cera/tinte de bordes, bruñido manual. Lento, variable en calidad | G12: 1200 | H12: 1 | I12: 1 | J12: 0 | K12: 0
A13: INF-06 | B13: B. Infraestructura | C13: Maquina de acabados | D13: Nivel 2: semi-industrial | E13: Fija | F13: Maquina de pulido de bordes (edge burnisher) electrica, tinte con pincel/aerografo | G13: 4500 | H13: 2 | I13: 2 | J13: 0 | K13: 0
A14: INF-07 | B14: B. Infraestructura | C14: Maquina de acabados | D14: Nivel 3: industrial | E14: Fija | F14: Linea de acabado con teñido automatico + pulido, control de temperatura y velocidad | G14: 9500 | H14: 3 | I14: 3 | J14: 0 | K14: 0
A15: INF-08 | B15: B. Infraestructura | C15: Molde | D15: Nivel 1 - Generico basico | E15: Fija | F15: Patrones simples, tipo plantilla estandar de internet o catalogo generico | G15: 300 | H15: 1 | I15: 1 | J15: 0 | K15: 0 | L15: Bajo aprovechamiento de cuero
A16: INF-09 | B16: B. Infraestructura | C16: Molde | D16: Nivel 2 - Generico mejorado | E16: Fija | F16: Patron tecnico mas elaborado, con lineas de corte, marcado y perforaciones bien definidas | G16: 1200 | H16: 2 | I16: 2 | J16: 1 | K16: 0 | L16: Aprovechamiento medio-alto
A17: INF-10 | B17: B. Infraestructura | C17: Molde | D17: Nivel 3 - Premium | E17: Fija | F17: La empresa desarrolla su propio patron desde cero, adaptado a su propuesta de marca | G17: 3500 | H17: 4 | I17: 2 | J17: 2 | K17: 0 | L17: Maximo aprovechamiento y diferenciacion
A18: RH-01 | B18: C. RRHH | C18: Personal de corte | D18: Nivel 1 - Operario basico | E18: Revisable con costo | F18: Corta con plantilla simple, sin experiencia previa. Mas lento, mas margen de error | G18: 1500 | H18: 0 | I18: 1 | J18: 0 | K18: 0
A19: RH-02 | B19: C. RRHH | C19: Personal de corte | D19: Nivel 2 - Cortador con experiencia | E19: Revisable con costo | F19: Optimiza el aprovechamiento del cuero, reduce desperdicio, mas rapido | G19: 2500 | H19: 1 | I19: 2 | J19: 0 | K19: 0
A20: RH-03 | B20: C. RRHH | C20: Personal de corte | D20: Nivel 3 - Maestro cortador | E20: Revisable con costo | F20: Trabaja cueros irregulares/premium, maximo aprovechamiento, minimo desperdicio | G20: 4000 | H20: 2 | I20: 3 | J20: 0 | K20: 0
A21: RH-04 | B21: C. RRHH | C21: Personal de ensamble | D21: Nivel 1 - Costurero basico | E21: Revisable con costo | F21: Maquina domestica, puntadas rectas simples, funciona con diseños sencillos | G21: 1500 | H21: 0 | I21: 1 | J21: 0 | K21: 0
A22: RH-05 | B22: C. RRHH | C22: Personal de ensamble | D22: Nivel 2 - Maquinista industrial | E22: Revisable con costo | F22: Maquina semi-industrial/industrial, costuras reforzadas, mayor velocidad | G22: 2800 | H22: 1 | I22: 2 | J22: 0 | K22: 0
A23: RH-06 | B23: C. RRHH | C23: Personal de ensamble | D23: Nivel 3 - Marroquinero especializado | E23: Revisable con costo | F23: Costura a mano de alta gama, ejecuta moldes exclusivos complejos, ideal linea premium | G23: 4500 | H23: 2 | I23: 3 | J23: 1 | K23: 0
A24: RH-07 | B24: C. RRHH | C24: Personal de acabados | D24: Nivel 1 - Operario de acabado basico | E24: Revisable con costo | F24: Aplica tinte y cera de forma simple, resultado variable | G24: 1500 | H24: 0 | I24: 1 | J24: 0 | K24: 0
A25: RH-08 | B25: C. RRHH | C25: Personal de acabados | D25: Nivel 2 - Tecnico en acabados | E25: Revisable con costo | F25: Maneja maquina de pulido de bordes, tinte con aerografo, resultado consistente | G25: 2800 | H25: 1 | I25: 2 | J25: 0 | K25: 0
A26: RH-09 | B26: C. RRHH | C26: Personal de acabados | D26: Nivel 3 - Artesano acabador | E26: Revisable con costo | F26: Bruñido fino, dorado, decoracion compleja (pedreria, herrajes especiales) | G26: 4500 | H26: 2 | I26: 3 | J26: 1 | K26: 0
A27: RH-10A | B27: C. RRHH | C27: Jefatura | D27: Contratar jefatura | E27: Revisable con costo | F27: Coordina el equipo, reduce riesgo de descoordinacion | G27: 3000 | H27: 0 | I27: 2 | J27: 1 | K27: 0
A28: RH-10B | B28: C. RRHH | C28: Jefatura | D28: No contratar jefatura | E28: Revisable con costo | F28: Ahorra costo fijo, pero aumenta el riesgo de descoordinacion | G28: 0 | H28: 0 | I28: -1 | J28: 0 | K28: 1 | L28: Ahorro de caja pero baja Eficiencia
A29: RH-11 | B29: C. RRHH | C29: Limpieza y servicios generales | D29: Unica (obligatoria) | E29: Fija | F29: Monto fijo obligatorio para mantener la operacion | G29: 600 | H29: 0 | I29: 0 | J29: 0 | K29: 0
A30: RH-12 | B30: C. RRHH | C30: Local de produccion | D30: Estandar (unico) | E30: Fija | F30: Local de produccion estandar; alquiler fijo igual para todos los equipos | G30: 2000 | H30: 0 | I30: 0 | J30: 0 | K30: 0
A31: COM-01A | B31: D. Canales | C31: Canal de venta | D31: Solo tienda fisica | E31: Revisable cada ciclo | F31: Menor cobertura y demanda; menor complejidad y costo | G31: 0 | H31: 0 | I31: 0 | J31: 0 | K31: 1
A32: COM-01B | B32: D. Canales | C32: Canal de venta | D32: Solo web | E32: Revisable cada ciclo | F32: Cobertura amplia con menor costo fijo; depende de marketing digital | G32: 500 | H32: 0 | I32: 0 | J32: 1 | K32: 0
A33: COM-01C | B33: D. Canales | C33: Canal de venta | D33: Web y fisico | E33: Revisable cada ciclo | F33: Mayor cobertura y demanda; incrementa complejidad y costo | G33: 1500 | H33: 0 | I33: 0 | J33: 2 | K33: -1
A34: FIN-01A | B34: D. Canales | C34: Acceso a prestamo bancario | D34: Solicitar prestamo | E34: Fija: habilita | F34: Habilita apalancamiento; permite invertir mas rapido | G34: 0 | H34: 0 | I34: 0 | J34: 0 | K34: -1 | L34: Aumenta apalancamiento
A35: FIN-01B | B35: D. Canales | C35: Acceso a prestamo bancario | D35: No solicitar prestamo | E35: Fija: habilita | F35: Evita intereses; la expansion depende del capital propio | G35: 0 | H35: 0 | I35: 0 | J35: 1 | K35: 1
A36: INS-01 | B36: E. Insumos | C36: Calidad del cuero | D36: Nivel 1 - Cuero sintetico | E36: Revisable cada ciclo | F36: Bajo costo, menor durabilidad, acabado menos premium | G36: 25 | H36: 1 | I36: 0 | J36: 0 | K36: 1 | L36: por unidad, referencial
A37: INS-02 | B37: E. Insumos | C37: Calidad del cuero | D37: Nivel 2 - Cuero genuino estandar | E37: Revisable cada ciclo | F37: Costo medio, durabilidad media | G37: 45 | H37: 2 | I37: 0 | J37: 0 | K37: 0 | L37: por unidad, referencial
A38: INS-03 | B38: E. Insumos | C38: Calidad del cuero | D38: Nivel 3 - Cuero genuino premium | E38: Revisable cada ciclo | F38: Full grain / curtido vegetal: alto costo, alta durabilidad, mejor acabado | G38: 80 | H38: 3 | I38: 0 | J38: 1 | K38: -1 | L38: por unidad, referencial
A39: INS-04 | B39: E. Insumos | C39: Calidad de accesorios | D39: Nivel 1 - Aleacion economica | E39: Revisable cada ciclo | F39: Bajo costo, se oxida/desgasta mas rapido | G39: 4 | H39: 1 | I39: 0 | J39: 0 | K39: 1 | L39: por unidad, referencial
A40: INS-05 | B40: E. Insumos | C40: Calidad de accesorios | D40: Nivel 2 - Metal premium | E40: Revisable cada ciclo | F40: Laton macizo o acero inoxidable, alto costo, mayor durabilidad y brillo | G40: 9 | H40: 2 | I40: 0 | J40: 1 | K40: -1 | L40: por unidad, referencial
A41: INS-06 | B41: E. Insumos | C41: Calidad del hilo | D41: Nivel 1 - Poliester estandar | E41: Revisable cada ciclo | F41: Economico, resistencia media | G41: 2 | H41: 1 | I41: 0 | J41: 0 | K41: 1 | L41: por unidad, referencial
A42: INS-07 | B42: E. Insumos | C42: Calidad del hilo | D42: Nivel 2 - Encerado reforzado | E42: Revisable cada ciclo | F42: Costo medio, mayor resistencia a tension | G42: 4 | H42: 2 | I42: 0 | J42: 0 | K42: 0 | L42: por unidad, referencial
A43: INS-08 | B43: E. Insumos | C43: Calidad del hilo | D43: Nivel 3 - Alta tenacidad (nylon trenzado) | E43: Revisable cada ciclo | F43: Costoso, maxima durabilidad, ideal para costura visible/detalle | G43: 7 | H43: 3 | I43: 0 | J43: 1 | K43: -1 | L43: por unidad, referencial
A44: INS-09A | B44: E. Insumos | C44: Numero de proveedores | D44: Proveedor unico | E44: Revisable cada ciclo | F44: Obtiene 2% adicional de descuento, pero concentra el riesgo de abastecimiento | G44: 0 | H44: 0 | I44: 0 | J44: 0 | K44: 1 | L44: Riesgo de desabastecimiento
A45: INS-09B | B45: E. Insumos | C45: Numero de proveedores | D45: Varios proveedores | E45: Revisable cada ciclo | F45: Menor descuento, pero reduce el riesgo de desabastecimiento | G45: 0 | H45: 0 | I45: 1 | J45: 0 | K45: 0
A46: INS-10A | B46: E. Insumos | C46: Politica de pago a proveedores | D46: Contado | E46: Revisable cada ciclo | F46: Obtiene 3% de descuento; reduce la caja inmediatamente | G46: 0 | H46: 0 | I46: 0 | J46: 0 | K46: -1
A47: INS-10B | B47: E. Insumos | C47: Politica de pago a proveedores | D47: Credito | E47: Revisable cada ciclo | F47: Sin descuento; conserva liquidez en el ciclo | G47: 0 | H47: 0 | I47: 0 | J47: 0 | K47: 1
A48: INS-11A | B48: E. Insumos | C48: Lead time | D48: Rapido (urgente, con sobrecosto) | E48: Revisable cada ciclo | F48: Entrega en menos dias, pero con sobrecosto | G48: 0 | H48: 0 | I48: 1 | J48: 0 | K48: -1
A49: INS-11B | B49: E. Insumos | C49: Lead time | D49: Normal - 7 dias | E49: Revisable cada ciclo | F49: Equilibrio entre costo y disponibilidad | G49: 0 | H49: 0 | I49: 0 | J49: 0 | K49: 0
A50: INS-11C | B50: E. Insumos | C50: Lead time | D50: Lento (economico) | E50: Revisable cada ciclo | F50: Menor costo, mayor riesgo de quiebre de stock | G50: 0 | H50: 0 | I50: -1 | J50: 0 | K50: 1
A51: COM-05 | B51: D. Canales | C51: % de ventas a credito | D51: 20% a credito (referencia) | E51: Revisable cada ciclo | F51: Balancea liquidez y ventas; riesgo de cobranza bajo | G51: 0 | H51: 0 | I51: 0 | J51: 1 | K51: -1 | L51: Valor ingresado por el jugador en hoja Seleccion
A52: INV-01A | B52: F. Inversiones | C52: Inversion en RR.HH. | D52: Baja | E52: Revisable cada ciclo | F52: Poca capacitacion tecnica | G52: 1000 | H52: 0 | I52: 1 | J52: 0 | K52: -1
A53: INV-01B | B53: F. Inversiones | C53: Inversion en RR.HH. | D53: Media | E53: Revisable cada ciclo | F53: Capacitacion tecnica: +8% de capacidad y mejor reputacion | G53: 6000 | H53: 0 | I53: 2 | J53: 1 | K53: -1
A54: INV-01C | B54: F. Inversiones | C54: Inversion en RR.HH. | D54: Alta | E54: Revisable cada ciclo | F54: Capacitacion avanzada: mayor capacidad y reputacion, alto costo | G54: 12000 | H54: 0 | I54: 3 | J54: 2 | K54: -2
A55: INV-02A | B55: F. Inversiones | C55: Inversion en marketing | D55: Baja | E55: Revisable cada ciclo | F55: Poca visibilidad de marca | G55: 1500 | H55: 0 | I55: 0 | J55: 1 | K55: -1
A56: INV-02B | B56: F. Inversiones | C56: Inversion en marketing | D56: Media | E56: Revisable cada ciclo | F56: S/ 6,000 por ciclo; aumenta demanda estimada 12% y reputacion | G56: 6000 | H56: 0 | I56: 0 | J56: 2 | K56: -1
A57: INV-02C | B57: F. Inversiones | C57: Inversion en marketing | D57: Alta | E57: Revisable cada ciclo | F57: Alto costo; mayor aumento de demanda y reputacion | G57: 12000 | H57: 0 | I57: 0 | J57: 3 | K57: -2
A58: FIN-02A | B58: G. Finanzas | C58: Método de depreciación | D58: Línea recta | E58: Fija en Ciclo 0 | F58: Distribuye el valor depreciable de la maquinaria en cuotas iguales durante su vida útil | G58: 0 | H58: 0 | I58: 0 | J58: 0 | K58: 0 | L58: Gasto contable constante; no representa una salida de efectivo
A59: FIN-02B | B59: G. Finanzas | C59: Método de depreciación | D59: Unidades producidas | E59: Fija en Ciclo 0 | F59: Calcula la depreciación según el uso real de la maquinaria y las unidades fabricadas | G59: 0 | H59: 0 | I59: 0 | J59: 0 | K59: 1 | L59: Mejora la asignación del costo por unidad; no representa una salida de efectivo
A60: FIN-02C | B60: G. Finanzas | C60: Método de depreciación | D60: Acelerada | E60: Fija en Ciclo 0 | F60: Reconoce una mayor depreciación durante los primeros ciclos y una menor depreciación después | G60: 0 | H60: 0 | I60: 0 | J60: 0 | K60: -1 | L60: Reduce la utilidad contable inicial; no representa una salida de efectivo
A61: COM-06A | B61: D. Canales | C61: Garantía del producto | D61: Sin garantía | E61: Revisable cada ciclo | F61: No cubre fallas posteriores a la venta; reduce el costo inmediato, pero genera desconfianza | G61: 0 | H61: 0 | I61: 0 | J61: -1 | K61: 1 | L61: Mayor riesgo de reclamos y pérdida de clientes
A62: COM-06B | B62: D. Canales | C62: Garantía del producto | D62: Garantía de 30 días | E62: Revisable cada ciclo | F62: Cubre defectos de fabricación durante 30 días y brinda seguridad básica al cliente | G62: 5 | H62: 0 | I62: 0 | J62: 1 | K62: 0 | L62: Costo referencial por unidad vendida para atender cambios o reparaciones
A63: COM-06C | B63: D. Canales | C63: Garantía del producto | D63: Garantía de 90 días | E63: Revisable cada ciclo | F63: Cubre defectos durante 90 días; aumenta la confianza, pero exige una mayor provisión | G63: 10 | H63: 0 | I63: 0 | J63: 2 | K63: -1 | L63: Costo referencial por unidad vendida; mayor exposición a devoluciones
A64: INF-11A | B64: B. Infraestructura | C64: Mantenimiento de maquinaria | D64: Solo correctivo | E64: Revisable cada ciclo | F64: La empresa repara las máquinas únicamente cuando presentan una falla | G64: 0 | H64: 0 | I64: -1 | J64: 0 | K64: 1 | L64: Ahorra al inicio, pero aumenta el riesgo de paradas y retrasos
A65: INF-11B | B65: B. Infraestructura | C65: Mantenimiento de maquinaria | D65: Preventivo básico | E65: Revisable cada ciclo | F65: Incluye revisión, limpieza, lubricación y ajustes básicos para prevenir fallas | G65: 1500 | H65: 0 | I65: 1 | J65: 0 | K65: 0 | L65: Costo referencial por ciclo; reduce parcialmente las averías
A66: INF-11C | B66: B. Infraestructura | C66: Mantenimiento de maquinaria | D66: Preventivo integral | E66: Revisable cada ciclo | F66: Incluye mantenimiento programado, cambio de piezas críticas y calibración de equipos | G66: 3000 | H66: 1 | I66: 2 | J66: 0 | K66: -1 | L66: Costo referencial por ciclo; minimiza paradas y defectos de fabricación
A67: INS-12A | B67: E. Insumos | C67: Política de inventarios | D67: Justo a tiempo | E67: Revisable cada ciclo | F67: Mantiene inventario mínimo y compra cerca de la fecha de producción | G67: 0 | H67: 0 | I67: -1 | J67: 0 | K67: 1 | L67: Menor dinero inmovilizado, pero mayor riesgo de quedarse sin insumos
A68: INS-12B | B68: E. Insumos | C68: Política de inventarios | D68: Stock de seguridad medio | E68: Revisable cada ciclo | F68: Mantiene una reserva moderada para cubrir retrasos del proveedor o cambios de demanda | G68: 1000 | H68: 0 | I68: 1 | J68: 0 | K68: 0 | L68: Costo referencial de almacenamiento por ciclo; alternativa equilibrada
A69: INS-12C | B69: E. Insumos | C69: Política de inventarios | D69: Stock de seguridad alto | E69: Revisable cada ciclo | F69: Mantiene una reserva amplia de materiales para evitar interrupciones de producción | G69: 2500 | H69: 0 | I69: 2 | J69: 0 | K69: -1 | L69: Reduce quiebres de stock, pero inmoviliza más efectivo y aumenta el almacenaje

Sheet FlujoWeb
B3: Flujo
B4: Steps | C4: Docente | D4: Jugadores | H4: Valeria y Gonzalo
B5: 1 | C5: Launcher | H5: Erick y Miguel
B6: 2 | C6: Login | E6: Se valida el codigo de sala y el nombre empresa(usuario)
B7: 3 | C7: Configuracion del juego (incluye Creacion de Sala)
B8: 4 | D8: Launcher
B9: 5 | D9: Login
B10: 6 | D10: Tutorial | E10: Indicaciones en un carrusel.
A11: Ciclo 1 | B11: 7 | D11: Decisiones
B12: 8 | D12: Espera (Fin de ciclo) | E12: El docente define si se hace automatico o manual
B13: 9 | C13: Información en vivo de las decisiones de los jugadores (Manual: Cierra el ciclo)
B14: 10 | C14: Estados financieros Generales | D14: Estados financieros Individuales e Informacion del mercado | E14: Descargables en pdf
A15: Ciclo 2 | B15: 11 | D15: Decisiones
B16: 12 | D16: Espera (Fin de ciclo)
B17: 13 | C17: Información en vivo de las decisiones de los jugadores (Manual: Cierra el ciclo)
B18: 14 | C18: Estados financieros Generales | D18: Estados financieros Individuales e Informacion del mercado | E18: Descargables en pdf
A19: Ciclo 3 | B19: 15 | D19: Decisiones
B20: 16 | D20: Espera (Fin de ciclo)
B21: 17 | C21: Información en vivo de las decisiones de los jugadores (Manual: Cierra el ciclo)
B22: 18 | C22: Estados financieros Generales | D22: Estados financieros Individuales e Informacion del mercado | E22: Descargables en pdf
A23: Ciclo N | B23: 15 | D23: Decisiones
B24: 16 | D24: Espera (Fin de ciclo)
B25: 17 | C25: Información en vivo de las decisiones de los jugadores (Manual: Cierra el ciclo)
B26: 18 | C26: Estados financieros Generales | D26: Estados financieros Individuales e Informacion del mercado
B27: 23 | C27: Resumen General - Indicar podio | D27: Estados financieros Individuales y Consolidado Final | E27: Descargables en pdf
B28: 24 | D28: Mostrar Podio | E28: Agregar disclaimer indicando que los datos se guardaran un maximo de 24 horas
B37: Si el jugador no tomo decision dentro del tiempo establecido y es la primera decisión se le elimina del juego
B38: El Docente tiene la opcion de eliminar jugadores en cualquier momento. Sin importar si es manual o automatico
B39: Si el jugador no tomo decisiones dentro del tiempo establecido y no es la primera decisión el sistema replica las decisiones del ciclo anterior.

Sheet CANTIDAD DE PRODUCCIÓN
A1: Calculo de MO
A3: AREA DE CORTE
E4: Bolsas por día | F4: Mesa de corte | K4: Producción por día | L4: AL MES | M4: Eficiencia | N4: Produccion Real
C5: Nivel 1 - Operario basico | E5: 5 | F5: 1 | I5: =E5*F5 -> 5 | K5: =MIN(I8,I14,I20) -> 17.2 | L5: =K5*24 -> 412.8 | M5: =MIN(1,K7+SUM(F7,F13:H13,F19:H19)/100+4%*F21) -> 0.97 | N5: =ROUND(L5*M5,0) -> 400 | O5: Esta produccion no puede ser superior a lo que permite el material
C6: Nivel 2 - Cortador con experiencia | E6: 7 | F6: 1 | I6: =E6*F6 -> 7 | K6: Eficiencia BASE
C7: Nivel 3 - Maestro cortador | E7: 9 | F7: 1 | I7: =E7*F7 -> 9 | K7: 0.9
A8: AREA DE ENSAMBLADO | I8: =SUM(I5:I7) -> 21
C9: Operarios | F9: MAQUINARIA MANUAL | G9: MAQUINARIA SEMIINDUSTRIAL | H9: MAQUINARIA INDUSTRIAL | K9: Total de trabajadores | L9: =SUM(F5:F7,F11:H13,F17:H19) -> 8
F10: 1 | G10: 1.2 | H10: 1.5 | K10: total de trabajadores N3 | L10: =SUM(F7,F13:H13,F19:H19) -> 3 | M10: =IFERROR(L10/L9,0) -> 0.375
C11: Nivel 1 | E11: 6 | H11: 1 | I11: =SUM(F11*E11*$F$10,G11*E11*$G$10,H11*E11*$H$10) -> 9
C12: Nivel 2 | E12: 8 | F12: 1 | G12: 0 | I12: =SUM(F12*E12*$F$10,G12*E12*$G$10,H12*E12*$H$10) -> 8
C13: Nivel 3 | E13: 12 | G13: 1 | I13: =SUM(F13*E13*$F$10,G13*E13*$G$10,H13*E13*$H$10) -> 14.4
A14: AREA DE ACABADO | I14: =SUM(I11:I13) -> 31.4
C15: Operarios | F15: MAQUINARIA MANUAL | G15: MAQUINARIA SEMIINDUSTRIAL | H15: MAQUINARIA INDUSTRIAL
F16: 1 | G16: 1.2 | H16: 1.5
C17: Nivel 1 | E17: 6 | G17: 1 | I17: =SUM(F17*E17*$F$16,G17*E17*$G$16,H17*E17*$H$16) -> 7.2
C18: Nivel 2 | E18: 7 | G18: 0 | H18: 0 | I18: =SUM(F18*E18*$F$16,G18*E18*$G$16,H18*E18*$H$16) -> 0
C19: Nivel 3 | E19: 10 | F19: 1 | I19: =SUM(F19*E19*$F$16,G19*E19*$G$16,H19*E19*$H$16) -> 10
I20: =SUM(I17:I19) -> 17.2
A21: Jefe de Produccion | F21: 1
B23: NOTA: EL PROCETANJE DE TRABAJADORES DE NIVEL 3 AFECTA POSITIVAMENTE A LA EFICIENCIA
A25: Calculo de MP
D27: Calidad del cuero | E27: Calidad del cuero | F27: Calidad del cuero | G27: Calidad de accesorios | H27: Calidad de accesorios | I27: Calidad de accesorios | J27: Calidad del hilo | K27: Calidad del hilo | L27: Calidad del hilo
D28: Nivel 1 - Cuero sintetico | E28: Nivel 2 - Cuero genuino estandar | F28: Nivel 3 - Cuero genuino premium | G28: Nivel 1 - Aleacion economica | H28: Nivel 2 - Metal premium | I28: Nivel 3 - Metal Deluxe | J28: Nivel 1 - Poliester estandar | K28: Nivel 2 - Encerado reforzado | L28: Nivel 3 - Alta tenacidad (nylon trenzado)
C29: UM Compra | D29: rollo | E29: Piel completa | F29: Piel completa | G29: Juego | H29: Juego | I29: Juego | J29: Carrete | K29: Carrete | L29: Carrete
C30: UM Produccion | D30: m2 | E30: m2 | F30: m2 | G30: unidad | H30: unidad | I30: unidad | J30: metro | K30: metro | L30: metro
C31: Nivel 1 - Generico basico | D31: 0.3 | G31: 1 | J31: 6
C32: Nivel 2 - Generico mejorado | E32: 0.4 | H32: 1 | K32: 7
C33: Nivel 3 - Premium | F33: 0.7 | I33: 1 | L33: 13
E35: =N5 -> 400
C36: Cantidad que desea producir | D36: =SUM(D37:D39) -> 520 | E36: =SUM(E37:E39) -> 399
C37: Nivel 1 - Generico basico | D37: 250 | E37: =IFERROR(ROUNDDOWN(D37*E35/D36,0),0) -> 192
C38: Nivel 2 - Generico mejorado | D38: 180 | E38: =IFERROR(ROUNDDOWN(D38*E35/D36,0),0) -> 138
C39: Nivel 3 - Premium | D39: 90 | E39: =IFERROR(ROUNDDOWN(D39*E35/D36,0),0) -> 69
D40: Calidad del cuero | E40: Calidad del cuero | F40: Calidad del cuero | G40: Calidad de accesorios | H40: Calidad de accesorios | I40: Calidad de accesorios | J40: Calidad del hilo | K40: Calidad del hilo | L40: Calidad del hilo
D41: Nivel 1 - Cuero sintetico | E41: Nivel 2 - Cuero genuino estandar | F41: Nivel 3 - Cuero genuino premium | G41: Nivel 1 - Aleacion economica | H41: Nivel 2 - Metal premium | I41: Nivel 3 - Metal Deluxe | J41: Nivel 1 - Poliester estandar | K41: Nivel 2 - Encerado reforzado | L41: Nivel 3 - Alta tenacidad (nylon trenzado)
C42: Nivel 1 - Generico basico | D42: =$D37*D31 -> 75 | E42: =$D37*E31 -> 0 | F42: =$D37*F31 -> 0 | G42: =$D37*G31 -> 250 | H42: =$D37*H31 -> 0 | I42: =$D37*I31 -> 0 | J42: =$D37*J31 -> 1500 | K42: =$D37*K31 -> 0 | L42: =$D37*L31 -> 0
C43: Nivel 2 - Generico mejorado | D43: =$D38*D32 -> 0 | E43: =$D38*E32 -> 72 | F43: =$D38*F32 -> 0 | G43: =$D38*G32 -> 0 | H43: =$D38*H32 -> 180 | I43: =$D38*I32 -> 0 | J43: =$D38*J32 -> 0 | K43: =$D38*K32 -> 1260 | L43: =$D38*L32 -> 0
C44: Nivel 3 - Premium | D44: =$D39*D33 -> 0 | E44: =$D39*E33 -> 0 | F44: =$D39*F33 -> 63 | G44: =$D39*G33 -> 0 | H44: =$D39*H33 -> 0 | I44: =$D39*I33 -> 90 | J44: =$D39*J33 -> 0 | K44: =$D39*K33 -> 0 | L44: =$D39*L33 -> 1170
D47: Calidad del cuero | E47: Calidad del cuero | F47: Calidad del cuero | G47: Calidad de accesorios | H47: Calidad de accesorios | I47: Calidad de accesorios | J47: Calidad del hilo | K47: Calidad del hilo | L47: Calidad del hilo
C48: Ejecucion de produccion | D48: Nivel 1 - Cuero sintetico | E48: Nivel 2 - Cuero genuino estandar | F48: Nivel 3 - Cuero genuino premium | G48: Nivel 1 - Aleacion economica | H48: Nivel 2 - Metal premium | I48: Nivel 3 - Metal Deluxe | J48: Nivel 1 - Poliester estandar | K48: Nivel 2 - Encerado reforzado | L48: Nivel 3 - Alta tenacidad (nylon trenzado)
C49: Nivel 1 - Generico basico | D49: 60 | E49: 10 | H49: 200 | J49: 1600
C50: Nivel 2 - Generico mejorado | E50: 50 | H50: 150 | L50: 1200
C51: Nivel 3 - Premium | F51: 70 | H51: 50 | L51: 1100
D53: =D49/D31 -> 200 | G53: =G49/G31 -> 0 | J53: =J49/J31 -> 266.66667
C55: TOTAL PRODUCIDO REAL | G55: Cuero empleado | H55: Accesorios empleados | I55: Hilo empleado | K55: Calidad por Materiales
C56: Nivel 1 - Generico basico | D56: =MIN(SUM(D49:F49)/D31,SUM(G49:I49)/G31,SUM(J49:L49)/J31,E37,D37) -> 192 | E56: =ROUNDDOWN(D56,0) -> 192 | G56: =E56*D31 -> 57.6 | H56: =E56*G31 -> 192 | I56: =E56*J31 -> 1152 | K56: =Lotes_Produccion!I2 -> 0
C57: Nivel 2 - Generico mejorado | D57: =MIN(SUM(D50:F50)/E32,SUM(G50:I50)/H32,SUM(J50:L50)/K32,E38,D38) -> 125 | E57: =ROUNDDOWN(D57,0) -> 125 | G57: =E57*E32 -> 50 | H57: =E57*H32 -> 125 | I57: =E57*K32 -> 875 | K57: =Lotes_Produccion!I3 -> 0
C58: Nivel 3 - Premium | D58: =MIN(SUM(D51:F51)/F33,SUM(G51:I51)/I33,SUM(J51:L51)/L33,E39,D39) -> 50 | E58: =ROUNDDOWN(D58,0) -> 50 | G58: =E58*F33 -> 35 | H58: =E58*I33 -> 50 | I58: =E58*L33 -> 650 | K58: =Lotes_Produccion!I4 -> 0
D62: Inventario Inicial | E62: Compras | F62: Produccion | G62: Inventario Final | H62: InventarioFinal = InventarioInicial + compras - produccido
C63: Nivel 1 - Cuero sintetico | D63: 15 | E63: 60 | F63: 75 | G63: =D63+E63-F63 -> 0
C64: Nivel 2 - Cuero genuino estandar | D64: 17 | E64: 55 | F64: 72 | G64: =D64+E64-F64 -> 0
C65: Nivel 3 - Cuero genuino premium | D65: 48 | E65: 15 | F65: 63 | G65: =D65+E65-F65 -> 0
C66: Nivel 1 - Aleacion economica | D66: 50 | E66: 200 | F66: 250 | G66: =D66+E66-F66 -> 0
C67: Nivel 2 - Metal premium | D67: 0 | E67: 190 | F67: 180 | G67: =D67+E67-F67 -> 10
C68: Nivel 3 - Metal Deluxe | D68: 90 | E68: 0 | F68: 90 | G68: =D68+E68-F68 -> 0
C69: Nivel 1 - Poliester estandar | D69: 1494 | E69: 6 | F69: 1500 | G69: =D69+E69-F69 -> 0
C70: Nivel 2 - Encerado reforzado | D70: 1253 | E70: 7 | F70: 1260 | G70: =D70+E70-F70 -> 0
C71: Nivel 3 - Alta tenacidad (nylon trenzado) | D71: 1170 | E71: 0 | F71: 1170 | G71: =D71+E71-F71 -> 0
B72: 0 - 10,000(rango en soles)
A73: Gastos del ciclo en publicidad | B73: 3000
A75: Reputación canónica del catálogo (0–10) | C75: 0 | D75: 0 | E75: 0 | F75: 0 | G75: =Motor_Puntajes!B10 -> 0 | H75: ptos de reputación
C76: Factor de producción | D76: Factor de MO | E76: Factor de MP (utilizacion) | F76: Factor de Publicidad
B82: EJEMPLO de distribución de Ventas (Bolsos Economicos) | C82: Reputacion | D82: Precio | E82: Puntaje del precio | F82: Puntaje total | G82: Porcentaje parcial | H82: Unidades Vendidas
B83: Empresa A | C83: 7 | D83: 40 | E83: =(MAX($D$83:$D$86)*2-D83)/10 -> 5 | F83: =SUM(C83,E83) -> 12 | G83: =F83/$F$87 -> 0.2238806 | H83: =ROUND(G83*$B$91,0) -> 784
B84: Empresa B | C84: 8.3 | D84: 45 | E84: =(MAX($D$83:$D$86)*2-D84)/10 -> 4.5 | F84: =SUM(C84,E84) -> 12.8 | G84: =F84/$F$87 -> 0.23880597 | H84: =ROUND(G84*$B$91,0) -> 836
B85: Empresa C | C85: 10.2 | D85: 43 | E85: =(MAX($D$83:$D$86)*2-D85)/10 -> 4.7 | F85: =SUM(C85,E85) -> 14.9 | G85: =F85/$F$87 -> 0.27798507 | H85: =ROUND(G85*$B$91,0) -> 973
B86: Empresa D | C86: 9 | D86: 41 | E86: =(MAX($D$83:$D$86)*2-D86)/10 -> 4.9 | F86: =SUM(C86,E86) -> 13.9 | G86: =F86/$F$87 -> 0.25932836 | H86: =ROUND(G86*$B$91,0) -> 908
E87: Total | F87: =SUM(F83:F86) -> 53.6 | H87: =SUM(H83:H86) -> 3501
B89: 7000 | C89: unidades mercado
B90: 0.5
B91: =B89*B90 -> 3500 | C91: unidades mercado real
B96: EJEMPLO de distribución de Ventas (Bolsos promedio) | C96: Reputacion | D96: Precio | E96: Puntaje del precio | F96: Puntaje total | G96: Porcentaje parcial | H96: Unidades Vendidas
B97: Empresa A | C97: 7 | D97: 120 | E97: =(MAX($D$97:$D$100)*2-D97)/10 -> 28 | F97: =SUM(C97,E97) -> 35 | G97: =F97/$F$101 -> 0.27237354 | H97: =ROUND(G97*$B$91,0) -> 953
B98: Empresa B | C98: 8.3 | D98: 150 | E98: =(MAX($D$97:$D$100)*2-D98)/10 -> 25 | F98: =SUM(C98,E98) -> 33.3 | G98: =F98/$F$101 -> 0.25914397 | H98: =ROUND(G98*$B$91,0) -> 907
B99: Empresa C | C99: 10.2 | D99: 190 | E99: =(MAX($D$97:$D$100)*2-D99)/10 -> 21 | F99: =SUM(C99,E99) -> 31.2 | G99: =F99/$F$101 -> 0.24280156 | H99: =ROUND(G99*$B$91,0) -> 850
B100: Empresa D | C100: 9 | D100: 200 | E100: =(MAX($D$97:$D$100)*2-D100)/10 -> 20 | F100: =SUM(C100,E100) -> 29 | G100: =F100/$F$101 -> 0.22568093 | H100: =ROUND(G100*$B$91,0) -> 790
E101: Total | F101: =SUM(F97:F100) -> 128.5
B103: 5000 | C103: unidades mercado
B104: 0.7
B105: =B103*B104 -> 3500 | C105: unidades mercado real
B110: EJEMPLO de distribución de Ventas (Bolsos Premium) | C110: Reputacion | D110: Precio | E110: Puntaje del precio | F110: Puntaje total | G110: Porcentaje parcial | H110: Unidades Vendidas
B111: Empresa A | C111: 7 | D111: 250 | E111: =(MAX($D$111:$D$114)*2-D111)/10 -> 55 | F111: =SUM(C111,E111) -> 62 | G111: =F111/$F$115 -> 0.26105263 | H111: =ROUND(G111*$B$119,0) -> 209
B112: Empresa B | C112: 8.3 | D112: 300 | E112: =(MAX($D$111:$D$114)*2-D112)/10 -> 50 | F112: =SUM(C112,E112) -> 58.3 | G112: =F112/$F$115 -> 0.24547368 | H112: =ROUND(G112*$B$119,0) -> 196
B113: Empresa C | C113: 10.2 | D113: 220 | E113: =(MAX($D$111:$D$114)*2-D113)/10 -> 58 | F113: =SUM(C113,E113) -> 68.2 | G113: =F113/$F$115 -> 0.28715789 | H113: =ROUND(G113*$B$119,0) -> 230
B114: Empresa D | C114: 9 | D114: 400 | E114: =(MAX($D$111:$D$114)*2-D114)/10 -> 40 | F114: =SUM(C114,E114) -> 49 | G114: =F114/$F$115 -> 0.20631579 | H114: =ROUND(G114*$B$119,0) -> 165
E115: Total | F115: =SUM(F111:F114) -> 237.5
B117: 2000 | C117: unidades mercado
B118: 0.4
B119: =B117*B118 -> 800 | C119: unidades mercado real
A123: Reputación canónica del catálogo (0–10) | C123: 0 | D123: 0 | E123: 0 | F123: 0 | G123: =Motor_Puntajes!B10 -> 0 | H123: ptos de reputación
C124: Factor de producción | D124: Factor de MO | E124: Factor de MP (utilizacion) | F124: Factor de Publicidad | L124: Peso precio | M124: 0.7
L125: peso reputación | M125: 0.2
L126: Peso calidad | M126: 0.1
B127: EJEMPLO de distribución de Ventas (Bolsos Economicos) | C127: Precio | D127: Reputación (0-10) | E127: Calidad (0-100) | F127: Precio Económico (0-100) | G127: Reputación (0-100) | H127: Puntaje total | I127: Porcentaje parcial | J127: Unidades Vendidas | N127: Calidad lote0–10 | O127: Stock disponible | P127: Producción segmento | Q127: Venta MIN stock | R127: Ingresos S/ | S127: Precio efectivo S/
B128: Empresa A | C128: 40 | D128: 7 | E128: =MAX(0,MIN(10,N128))*10 -> 0 | F128: =MAX(0,MIN(100,IF(MAX($C$128:$C$131)=MIN($C$128:$C$131),100,100*(MAX($C$128:$C$131)-C128)/(MAX($C$128:$C$131)-MIN($C$128:$C$131))))) -> 100 | G128: =MAX(0,MIN(10,D128))*10 -> 70 | H128: =IF(P128>0,$M$124*F128+$M$125*G128+$M$126*E128,0) -> 0 | I128: =IFERROR(H128/SUM($H$128:$H$131),0) -> 0 | J128: =ROUND(I128*$B$136,0) -> 0 | N128: =Lotes_Produccion!I2 -> 0 | O128: =Lotes_Produccion!C2 -> 0 | P128: =Lotes_Produccion!C2 -> 0 | Q128: =MIN(MAX(0,O128),J128) -> 0 | R128: =Q128*S128 -> 0 | S128: =C128*1 -> 40
B129: Empresa B | C129: 45 | D129: 8.3 | E129: =MAX(0,MIN(10,N129))*10 -> 0 | F129: =MAX(0,MIN(100,IF(MAX($C$128:$C$131)=MIN($C$128:$C$131),100,100*(MAX($C$128:$C$131)-C129)/(MAX($C$128:$C$131)-MIN($C$128:$C$131))))) -> 0 | G129: =MAX(0,MIN(10,D129))*10 -> 83 | H129: =IF(P129>0,$M$124*F129+$M$125*G129+$M$126*E129,0) -> 0 | I129: =IFERROR(H129/SUM($H$128:$H$131),0) -> 0 | J129: =ROUND(I129*$B$136,0) -> 0 | N129: =Lotes_Produccion!I3 -> 0 | O129: =Lotes_Produccion!C3 -> 0 | P129: =Lotes_Produccion!C3 -> 0 | Q129: =MIN(MAX(0,O129),J129) -> 0 | R129: =Q129*S129 -> 0 | S129: =C129*1 -> 45
B130: Empresa C | C130: 43 | D130: 10.2 | E130: =MAX(0,MIN(10,N130))*10 -> 0 | F130: =MAX(0,MIN(100,IF(MAX($C$128:$C$131)=MIN($C$128:$C$131),100,100*(MAX($C$128:$C$131)-C130)/(MAX($C$128:$C$131)-MIN($C$128:$C$131))))) -> 40 | G130: =MAX(0,MIN(10,D130))*10 -> 100 | H130: =IF(P130>0,$M$124*F130+$M$125*G130+$M$126*E130,0) -> 0 | I130: =IFERROR(H130/SUM($H$128:$H$131),0) -> 0 | J130: =ROUND(I130*$B$136,0) -> 0 | N130: =Lotes_Produccion!I4 -> 0 | O130: =Lotes_Produccion!C4 -> 0 | P130: =Lotes_Produccion!C4 -> 0 | Q130: =MIN(MAX(0,O130),J130) -> 0 | R130: =Q130*S130 -> 0 | S130: =C130*1 -> 43
B131: Empresa D | C131: 41 | D131: 9 | E131: =MAX(0,MIN(10,N131))*10 -> 0 | F131: =MAX(0,MIN(100,IF(MAX($C$128:$C$131)=MIN($C$128:$C$131),100,100*(MAX($C$128:$C$131)-C131)/(MAX($C$128:$C$131)-MIN($C$128:$C$131))))) -> 80 | G131: =MAX(0,MIN(10,D131))*10 -> 90 | H131: =IF(P131>0,$M$124*F131+$M$125*G131+$M$126*E131,0) -> 0 | I131: =IFERROR(H131/SUM($H$128:$H$131),0) -> 0 | J131: =ROUND(I131*$B$136,0) -> 0 | N131: =Lotes_Produccion!I4 -> 0 | O131: =Lotes_Produccion!C4 -> 0 | P131: =Lotes_Produccion!C4 -> 0 | Q131: =MIN(MAX(0,O131),J131) -> 0 | R131: =Q131*S131 -> 0 | S131: =C131*1 -> 41
C132: SUMA | D132: =SUM(D128:D131) -> 34.5 | G132: TOTAL | H132: =SUM(H128:H131) -> 0 | J132: =SUM(J128:J131) -> 0
...

Sheet Costos De Producción
A1: Calculo de MO
T2: Costos: MO
A3: AREA DE CORTE
E4: Bolsas por día | F4: Mesa de corte | K4: Producción por día | L4: AL MES | M4: Eficiencia | N4: Produccion Real | T4: O.Basico | U4: MYPE | V4: NoMype | X4: Costurero básico | Y4: MYPE | Z4: NoMype | AB4: Operario de acabado clásico | AC4: MYPE | AD4: NoMype
C5: Nivel 1 - Operario basico | E5: ='CANTIDAD DE PRODUCCIÓN'!E5 -> 5 | F5: 1 | I5: =E5*F5 -> 5 | K5: =MIN(I8,I14,I20) -> 12 | L5: =K5*24 -> 288 | M5: =MIN(1,K7+SUM(F7,F13:H13,F19:H19)/100+4%*F21) -> 0.92 | N5: =ROUND(L5*M5,0) -> 265 | O5: Esta produccion no puede ser superior a lo que permite el material | T5: Sueldo base | U5: 1500 | V5: 1500 | X5: Sueldo base | Y5: 1500 | Z5: 1500 | AB5: Sueldo base | AC5: 1500 | AD5: 1500
C6: Nivel 2 - Cortador con experiencia | E6: ='CANTIDAD DE PRODUCCIÓN'!E6 -> 7 | F6: 1 | I6: =E6*F6 -> 7 | K6: Eficiencia BASE | T6: Essalud | U6: =U5*0.09 -> 135 | V6: =V5*0.09 -> 135 | X6: Essalud | Y6: =Y5*0.09 -> 135 | Z6: =Z5*0.09 -> 135 | AB6: Essalud | AC6: =AC5*0.09 -> 135 | AD6: =AD5*0.09 -> 135
C7: Nivel 3 - Maestro cortador | E7: ='CANTIDAD DE PRODUCCIÓN'!E7 -> 9 | F7: 0 | I7: =E7*F7 -> 0 | K7: 0.9 | T7: Grati | U7: =U5 -> 1500 | V7: =V5*2 -> 3000 | X7: Grati | Y7: =Y5 -> 1500 | Z7: =Z5*2 -> 3000 | AB7: Grati | AC7: =AC5 -> 1500 | AD7: =AD5*2 -> 3000
A8: AREA DE ENSAMBLADO | I8: =SUM(I5:I7) -> 12 | T8: CTS | U8: 750 | V8: 1500 | X8: CTS | Y8: 750 | Z8: 1500 | AB8: CTS | AC8: 750 | AD8: 1500
C9: Operarios | F9: MAQUINARIA MANUAL | G9: MAQUINARIA SEMIINDUSTRIAL | H9: MAQUINARIA INDUSTRIAL | K9: Total de trabajadores | L9: =SUM(F5:F7,F11:H13,F17:H19) -> 7 | T9: vacaciones | U9: =U5/2 -> 750 | V9: =V5 -> 1500 | X9: vacaciones | Y9: =Y5/2 -> 750 | Z9: =Z5 -> 1500 | AB9: vacaciones | AC9: =AC5/2 -> 750 | AD9: =AD5 -> 1500
F10: 1 | G10: 1.2 | H10: 1.5 | K10: total de trabajadores N3 | L10: =SUM(F7,F13:H13,F19:H19) -> 2 | M10: =IFERROR(L10/L9,0) -> 0.28571429 | T10: Suma anual | U10: =SUM(U6:U9)+U5*12 -> 21135 | V10: =SUM(V6:V9)+V5*12 -> 24135 | X10: Suma anual | Y10: =SUM(Y6:Y9)+Y5*12 -> 21135 | Z10: =SUM(Z6:Z9)+Z5*12 -> 24135 | AB10: Suma anual | AC10: =SUM(AC6:AC9)+AC5*12 -> 21135 | AD10: =SUM(AD6:AD9)+AD5*12 -> 24135
C11: Nivel 1 | E11: ='CANTIDAD DE PRODUCCIÓN'!E11 -> 6 | H11: 1 | I11: =SUM(F11*E11*$F$10,G11*E11*$G$10,H11*E11*$H$10) -> 9 | T11: Pago mensual | U11: =U10/12.5 -> 1690.8 | V11: =V10/13 -> 1856.5385 | X11: Pago mensual | Y11: =Y10/12.5 -> 1690.8 | Z11: =Z10/13 -> 1856.5385 | AB11: Pago mensual | AC11: =AC10/12.5 -> 1690.8 | AD11: =AD10/13 -> 1856.5385
C12: Nivel 2 | E12: ='CANTIDAD DE PRODUCCIÓN'!E12 -> 8 | F12: 1 | I12: =SUM(F12*E12*$F$10,G12*E12*$G$10,H12*E12*$H$10) -> 8
C13: Nivel 3 | E13: ='CANTIDAD DE PRODUCCIÓN'!E13 -> 12 | G13: 1 | I13: =SUM(F13*E13*$F$10,G13*E13*$G$10,H13*E13*$H$10) -> 14.4 | T13: Cortador con experiencia | U13: MYPE | V13: NoMype | X13: Maquinista industrial | Y13: MYPE | Z13: NoMype | AB13: Técnico de acabado | AC13: MYPE | AD13: NoMype
A14: AREA DE ACABADO | I14: =SUM(I11:I13) -> 31.4 | T14: Sueldo base | U14: 2000 | V14: 2000 | X14: Sueldo base | Y14: 2800 | Z14: 2800 | AB14: Sueldo base | AC14: 2800 | AD14: 2800
C15: Operarios | F15: MAQUINARIA MANUAL | G15: MAQUINARIA SEMIINDUSTRIAL | H15: MAQUINARIA INDUSTRIAL | T15: Essalud | U15: =U14*0.09 -> 180 | V15: =V14*0.09 -> 180 | X15: Essalud | Y15: =Y14*0.09 -> 252 | Z15: =Z14*0.09 -> 252 | AB15: Essalud | AC15: =AC14*0.09 -> 252 | AD15: =AD14*0.09 -> 252
F16: 1 | G16: 1.2 | H16: 1.5 | T16: Grati | U16: =U14 -> 2000 | V16: =V14*2 -> 4000 | X16: Grati | Y16: =Y14 -> 2800 | Z16: =Z14*2 -> 5600 | AB16: Grati | AC16: =AC14 -> 2800 | AD16: =AD14*2 -> 5600
C17: Nivel 1 | E17: ='CANTIDAD DE PRODUCCIÓN'!E17 -> 6 | I17: =SUM(F17*E17*$F$16,G17*E17*$G$16,H17*E17*$H$16) -> 0 | T17: CTS | U17: =U14/2 -> 1000 | V17: =V14 -> 2000 | X17: CTS | Y17: 750 | Z17: 1500 | AB17: CTS | AC17: 750 | AD17: 1500
C18: Nivel 2 | E18: ='CANTIDAD DE PRODUCCIÓN'!E18 -> 7 | H18: 1 | I18: =SUM(F18*E18*$F$16,G18*E18*$G$16,H18*E18*$H$16) -> 10.5 | T18: vacaciones | U18: =U14/2 -> 1000 | V18: =V14 -> 2000 | X18: vacaciones | Y18: =Y14/2 -> 1400 | Z18: =Z14 -> 2800 | AB18: vacaciones | AC18: =AC14/2 -> 1400 | AD18: =AD14 -> 2800
C19: Nivel 3 | E19: ='CANTIDAD DE PRODUCCIÓN'!E19 -> 10 | F19: 1 | I19: =SUM(F19*E19*$F$16,G19*E19*$G$16,H19*E19*$H$16) -> 10 | T19: Suma anual | U19: =SUM(U15:U18)+U14*12 -> 28180 | V19: =SUM(V15:V18)+V14*12 -> 32180 | X19: Suma anual | Y19: =SUM(Y15:Y18)+Y14*12 -> 38802 | Z19: =SUM(Z15:Z18)+Z14*12 -> 43752 | AB19: Suma anual | AC19: =SUM(AC15:AC18)+AC14*12 -> 38802 | AD19: =SUM(AD15:AD18)+AD14*12 -> 43752
I20: =SUM(I17:I19) -> 20.5 | T20: Pago mensual | U20: =U19/12.5 -> 2254.4 | V20: =V19/13 -> 2475.3846 | X20: Pago mensual | Y20: =Y19/12.5 -> 3104.16 | Z20: =Z19/13 -> 3365.5385 | AB20: Pago mensual | AC20: =AC19/12.5 -> 3104.16 | AD20: =AD19/13 -> 3365.5385
A21: Jefe de Produccion | F21: 0
T22: Maestro cortador | U22: MYPE | V22: NoMype | X22: Marroquinero especializado | Y22: MYPE | Z22: NoMype | AB22: Artesano acabador | AC22: MYPE | AD22: NoMype
B23: NOTA: EL PROCETANJE DE TRABAJADORES DE NIVEL 3 AFECTA POSITIVAMENTE A LA EFICIENCIA | T23: Sueldo base | U23: 3800 | V23: 3800 | X23: Sueldo base | Y23: 4500 | Z23: 4500 | AB23: Sueldo base | AC23: 4500 | AD23: 4500
T24: Essalud | U24: =U23*0.09 -> 342 | V24: =V23*0.09 -> 342 | X24: Essalud | Y24: =Y23*0.09 -> 405 | Z24: =Z23*0.09 -> 405 | AB24: Essalud | AC24: =AC23*0.09 -> 405 | AD24: =AD23*0.09 -> 405
A25: Calculo de MP | T25: Grati | U25: =U23 -> 3800 | V25: =V23*2 -> 7600 | X25: Grati | Y25: =Y23 -> 4500 | Z25: =Z23*2 -> 9000 | AB25: Grati | AC25: =AC23 -> 4500 | AD25: =AD23*2 -> 9000
T26: CTS | U26: 750 | V26: 1500 | X26: CTS | Y26: 750 | Z26: 1500 | AB26: CTS | AC26: 750 | AD26: 1500
D27: Calidad del cuero | E27: Calidad del cuero | F27: Calidad del cuero | G27: Calidad de accesorios | H27: Calidad de accesorios | I27: Calidad del hilo | J27: Calidad del hilo | K27: Calidad del hilo | T27: vacaciones | U27: =U23/2 -> 1900 | V27: =V23 -> 3800 | X27: vacaciones | Y27: =Y23/2 -> 2250 | Z27: =Z23 -> 4500 | AB27: vacaciones | AC27: =AC23/2 -> 2250 | AD27: =AD23 -> 4500
D28: Nivel 1 - Cuero sintetico | E28: Nivel 2 - Cuero genuino estandar | F28: Nivel 3 - Cuero genuino premium | G28: Nivel 1 - Aleacion economica | H28: Nivel 2 - Metal premium | I28: Nivel 1 - Poliester estandar | J28: Nivel 2 - Encerado reforzado | K28: Nivel 3 - Alta tenacidad (nylon trenzado) | T28: Suma anual | U28: =SUM(U24:U27)+U23*12 -> 52392 | V28: =SUM(V24:V27)+V23*12 -> 58842 | X28: Suma anual | Y28: =SUM(Y24:Y27)+Y23*12 -> 61905 | Z28: =SUM(Z24:Z27)+Z23*12 -> 69405 | AB28: Suma anual | AC28: =SUM(AC24:AC27)+AC23*12 -> 61905 | AD28: =SUM(AD24:AD27)+AD23*12 -> 69405
C29: UM Compra | D29: rollo | E29: Piel completa | F29: Piel completa | G29: Juego | H29: Juego | I29: Carrete | J29: Carrete | K29: Carrete | T29: Pago mensual | U29: =U28/12.5 -> 4191.36 | V29: =V28/13 -> 4526.3077 | X29: Pago mensual | Y29: =Y28/12.5 -> 4952.4 | Z29: =Z28/13 -> 5338.8462 | AB29: Pago mensual | AC29: =AC28/12.5 -> 4952.4 | AD29: =AD28/13 -> 5338.8462
C30: UM Produccion | D30: m2 | E30: m2 | F30: m2 | G30: unidad | H30: unidad | I30: metro | J30: metro | K30: metro
B31: Cantidad necesaria | C31: Compra Jugador | D31: 60 | E31: 55 | F31: 15 | G31: 200 | H31: 190 | I31: 0 | J31: 6 | K31: 7
C32: Cantidad Produccion | D32: 1 | E32: 2 | F32: 2 | G32: 1 | H32: 1 | I32: 270 | J32: 250 | K32: 200 | T32: Jefatura | U32: MYPE | V32: NoMype | X32: Limpieza | Y32: MYPE | Z32: NoMype | AB32: Local de producción | AC32: MYPE | AD32: NoMype
D33: =D31*D32 -> 60 | E33: =E31*E32 -> 110 | F33: =F31*F32 -> 30 | G33: =G31*G32 -> 200 | H33: =H31*H32 -> 190 | I33: =I31*I32 -> 0 | J33: =J31*J32 -> 1500 | K33: =K31*K32 -> 1400 | T33: Sueldo base | U33: 3000 | V33: 3000 | X33: Sueldo base | Y33: 600 | Z33: 600 | AB33: Costo fijo | AC33: 2000 | AD33: 2000
T34: Essalud | U34: =U33*0.09 -> 270 | V34: =V33*0.09 -> 270 | X34: Essalud | Y34: =Y33*0.09 -> 54 | Z34: =Z33*0.09 -> 54
H35: InventarioFinal = InventarioInicial + compras - produccido | T35: Grati | U35: =U33 -> 3000 | V35: =V33*2 -> 6000 | X35: Grati | Y35: =Y33 -> 600 | Z35: =Z33*2 -> 1200
D36: m2 | E36: unidad | F36: metro | H36: Almacen | T36: CTS | U36: 750 | V36: 1500 | X36: CTS | Y36: 750 | Z36: 1500
C37: Moldes (siempre debe comprar al menos uno) | D37: Cuero | E37: Accesorios | F37: Hilos | H37: Cuero | I37: Accesorios | J37: Hilos | T37: vacaciones | U37: =U33/2 -> 1500 | V37: =V33 -> 3000 | X37: vacaciones | Y37: =Y33/2 -> 300 | Z37: =Z33 -> 600
C38: Nivel 1 - Generico basico | D38: 0.3 | E38: 1 | F38: 6 | H38: =SUM(D33:F33) -> 200 | I38: =SUM(G33:H33) -> 390 | J38: =SUM(I33:K33) -> 2900 | T38: Suma anual | U38: =SUM(U34:U37)+U33*12 -> 41520 | V38: =SUM(V34:V37)+V33*12 -> 46770 | X38: Suma anual | Y38: =SUM(Y34:Y37)+Y33*12 -> 8904 | Z38: =SUM(Z34:Z37)+Z33*12 -> 10554
C39: Nivel 2 - Generico mejorado | D39: 0.4 | E39: 1 | F39: 7 | T39: Pago mensual | U39: =U38/12.5 -> 3321.6 | V39: =V38/13 -> 3597.6923 | X39: Pago mensual | Y39: =Y38/12.5 -> 712.32 | Z39: =Z38/13 -> 811.84615
C40: Nivel 3 - Premium | D40: 0.7 | E40: 1 | F40: 13
T42: Costos: Maquinaria
T44: Mesa de corte | U44: MYPE | V44: NoMype | X44: Maquina de Ensamblado N1 | Y44: MYPE | Z44: NoMype | AB44: Maquina de acabado N1 | AC44: MYPE | AD44: NoMype
C45: Cuantos Bolso deseas producir ? | E45: Producido luego del termino del ciclo | H45: Total Cuero Necesario | I45: Total Accesorios Necesario | J45: Total Hilo Necesario | L45: Total Cuero Utilizado | M45: Total Accesorios Utilizado | N45: Total Hilo Utilizado | T45: Costo de adquisición | U45: 2500 | V45: 2500 | X45: Costo de adquisición | Y45: 3500 | Z45: 3500 | AB45: Costo de adquisición | AC45: 1200 | AD45: 1200
C46: Nivel 1 - Generico basico | D46: 150 | E46: 150 | F46: =E46/E49 -> 0.4076087 | H46: =D38*D46 -> 45 | I46: =D46*E38 -> 150 | J46: =F38*D46 -> 900 | L46: =E46*D38 -> 45 | M46: =E46*E38 -> 150 | N46: =F38*E46 -> 900 | T46: Instalación | U46: =U45*3% -> 75 | V46: =V45*5% -> 125 | X46: Instalación | Y46: =Y45*3% -> 105 | Z46: =Z45*5% -> 175 | AB46: Instalación | AC46: =AC45*3% -> 36 | AD46: =AD45*5% -> 60
C47: Nivel 2 - Generico mejorado | D47: 140 | E47: 140 | F47: =E47/E49 -> 0.38043478 | H47: =D39*D47 -> 56 | I47: =D47*E39 -> 140 | J47: =F39*D47 -> 980 | L47: =E47*D39 -> 56 | M47: =E47*E39 -> 140 | N47: =F39*E47 -> 980 | T47: Capacitación | U47: =U45*2% -> 50 | V47: =V45*3% -> 75 | X47: Capacitación | Y47: =Y45*2% -> 70 | Z47: =Z45*3% -> 105 | AB47: Capacitación | AC47: =AC45*2% -> 24 | AD47: =AD45*3% -> 36
C48: Nivel 3 - Premium | D48: 95 | E48: 78 | F48: =E48/E49 -> 0.21195652 | H48: =D40*D48 -> 66.5 | I48: =D48*E40 -> 95 | J48: =F40*D48 -> 1235 | L48: =D40*E48 -> 54.6 | M48: =E48*E40 -> 78 | N48: =F40*E48 -> 1014 | T48: Mantenimiento anual | U48: =U45*5% -> 125 | V48: =V45*8% -> 200 | X48: Mantenimiento anual | Y48: =Y45*5% -> 175 | Z48: =Z45*8% -> 280 | AB48: Mantenimiento anual | AC48: =AC45*5% -> 60 | AD48: =AD45*8% -> 96
D49: =SUM(D46:D48) -> 385 | E49: =SUM(E46:E48) -> 368 | F49: =SUM(F46:F48) -> 1 | H49: =SUM(H46:H48) -> 167.5 | I49: =SUM(I46:I48) -> 385 | J49: =SUM(J46:J48) -> 3115 | L49: =SUM(L46:L48) -> 155.6 | M49: =SUM(M46:M48) -> 368 | N49: =SUM(N46:N48) -> 2894 | T49: Depreciación anual | U49: =-((U45-U45*5%)/10) -> -237.5 | V49: =-((V45-V45*10%)/10) -> -225 | X49: Depreciación anual | Y49: =-(Y45-Y45*5%)/10 -> -332.5 | Z49: =-(Z45-Z45*10%)/10 -> -315 | AB49: Depreciación anual | AC49: =-(AC45-AC45*5%)/8 -> -142.5 | AD49: =-(AD45-AD45*10%)/8 -> -135
T50: Suma anual | U50: =SUM(U46:U49)+U45 -> 2512.5 | V50: =SUM(V46:V49)+V45 -> 2675 | X50: Suma anual | Y50: =SUM(Y46:Y49)+Y45 -> 3517.5 | Z50: =SUM(Z46:Z49)+Z45 -> 3745 | AB50: Suma anual | AC50: =SUM(AC46:AC49)+AC45 -> 1177.5 | AD50: =SUM(AD46:AD49)+AD45 -> 1257
C52: ALMACEN | T52: Molde 1 | U52: MYPE | V52: NoMype | X52: Maquina de Ensamblado N2 | Y52: MYPE | Z52: NoMype | AB52: Maquina de acabado N2 | AC52: MYPE | AD52: NoMype
D53: Inventario Inicial | E53: Compras | F53: Produccion | G53: Inventario Final | T53: Costo de adquisición | U53: 300 | V53: 300 | X53: Costo de adquisición | Y53: 7500 | Z53: 7500 | AB53: Costo de adquisición | AC53: 4500 | AD53: 4500
C54: Nivel 1 - Cuero sintetico | D54: 0 | E54: =D33 -> 60 | F54: =MIN(E54,H49) -> 60 | G54: =D54+E54-F54 -> 0 | T54: Capacitación | U54: =U53*1% -> 3 | V54: =V53*2% -> 6 | X54: Instalación | Y54: =Y53*3% -> 225 | Z54: =Z53*5% -> 375 | AB54: Instalación | AC54: =AC53*3% -> 135 | AD54: =AD53*5% -> 225
C55: Nivel 2 - Cuero genuino estandar | D55: 0 | E55: =E33 -> 110 | F55: =MIN(E55,H49-F54) -> 107.5 | G55: =D55+E55-F55 -> 2.5 | T55: Mantenimiento anual | U55: =U53*5% -> 15 | V55: =V53*8% -> 24 | X55: Capacitación | Y55: =Y53*2% -> 150 | Z55: =Z53*3% -> 225 | AB55: Capacitación | AC55: =AC53*2% -> 90 | AD55: =AD53*3% -> 135
C56: Nivel 3 - Cuero genuino premium | D56: 0 | E56: =F33 -> 30 | F56: =MIN(E56,H49-F54-F55) -> 0 | G56: =D56+E56-F56 -> 30 | H56: =F56/SUM(F54:F56) -> 0 | T56: Depreciación anual | U56: =-((U53-U53*5%)/5) -> -57 | V56: =-((V53-V53*10%)/5) -> -54 | X56: Mantenimiento anual | Y56: =Y53*5% -> 375 | Z56: =Z53*8% -> 600 | AB56: Mantenimiento anual | AC56: =AC53*5% -> 225 | AD56: =AD53*8% -> 360
C57: Nivel 1 - Aleacion economica | D57: 0 | E57: =G33 -> 200 | F57: =MIN(E57,I49) -> 200 | G57: =D57+E57-F57 -> 0 | T57: Suma anual | U57: =SUM(U54:U56)+U53 -> 261 | V57: =SUM(V54:V56)+V53 -> 276 | X57: Depreciación anual | Y57: =-(Y53-Y53*5%)/10 -> -712.5 | Z57: =-(Z53-Z53*10%)/10 -> -675 | AB57: Depreciación anual | AC57: =-(AC53-AC53*5%)/8 -> -534.375 | AD57: =-(AD53-AD53*10%)/8 -> -506.25
C58: Nivel 2 - Metal premium | D58: 0 | E58: =H33 -> 190 | F58: =MIN(E58,I49-F57) -> 185 | G58: =D58+E58-F58 -> 5 | H58: =F58/SUM(F57:F58) -> 0.48051948 | X58: Suma anual | Y58: =SUM(Y54:Y57)+Y53 -> 7537.5 | Z58: =SUM(Z54:Z57)+Z53 -> 8025 | AB58: Suma anual | AC58: =SUM(AC54:AC57)+AC53 -> 4415.625 | AD58: =SUM(AD54:AD57)+AD53 -> 4713.75
C59: Nivel 1 - Poliester estandar | D59: 0 | E59: =I33 -> 0 | F59: =MIN(E59,J49) -> 0 | G59: =D59+E59-F59 -> 0 | T59: Molde 2 | U59: MYPE | V59: NoMype
C60: Nivel 2 - Encerado reforzado | D60: 0 | E60: =J33 -> 1500 | F60: =MIN(E60,J49-F59) -> 1500 | G60: =D60+E60-F60 -> 0 | T60: Costo de adquisición | U60: 1200 | V60: 1200 | X60: Maquina de Ensamblado N3 | Y60: MYPE | Z60: NoMype | AB60: Maquina de acabado N3 | AC60: MYPE | AD60: NoMype
C61: Nivel 3 - Alta tenacidad (nylon trenzado) | D61: 0 | E61: =K33 -> 1400 | F61: =MIN(E61,J49-F59-F60) -> 1400 | G61: =D61+E61-F61 -> 0 | H61: =F61/(SUM(F60:F61)) -> 0.48275862 | T61: Capacitación | U61: =U60*1% -> 12 | V61: =V60*2% -> 24 | X61: Costo de adquisición | Y61: 15000 | Z61: 15000 | AB61: Costo de adquisición | AC61: 9500 | AD61: 9500
B62: 0 - 10,000(rango en soles) | T62: Mantenimiento anual | U62: =U60*5% -> 60 | V62: =V60*8% -> 96 | X62: Instalación | Y62: =Y61*3% -> 450 | Z62: =Z61*5% -> 750 | AB62: Instalación | AC62: =AC61*3% -> 285 | AD62: =AD61*5% -> 475
A63: Gastos del ciclo en publicidad | B63: 3000 | T63: Depreciación anual | U63: =-((U60-U60*5%)/5) -> -228 | V63: =-((V60-V60*10%)/5) -> -216 | X63: Capacitación | Y63: =Y61*2% -> 300 | Z63: =Z61*3% -> 450 | AB63: Capacitación | AC63: =AC61*2% -> 190 | AD63: =AD61*3% -> 285
T64: Suma anual | U64: =SUM(U61:U63)+U60 -> 1044 | V64: =SUM(V61:V63)+V60 -> 1104 | X64: Mantenimiento anual | Y64: =Y61*5% -> 750 | Z64: =Z61*8% -> 1200 | AB64: Mantenimiento anual | AC64: =AC61*5% -> 475 | AD64: =AD61*8% -> 760
A65: Reputación canónica del catálogo (0–10) | C65: 0 | D65: 0 | E65: 0 | F65: 0 | G65: =Motor_Puntajes!B10 -> 0 | H65: ptos de reputación | X65: Depreciación anual | Y65: =-(Y61-Y61*5%)/10 -> -1425 | Z65: =-(Z61-Z61*10%)/10 -> -1350 | AB65: Depreciación anual | AC65: =-(AC61-AC61*5%)/8 -> -1128.125 | AD65: =-(AD61-AD61*10%)/8 -> -1068.75
C66: Factor de producción | D66: Factor de MO | E66: Factor de MP (utilizacion) | F66: Factor de Publicidad | T66: Moldes 3 | U66: MYPE | V66: NoMype | X66: Suma anual | Y66: =SUM(Y62:Y65)+Y61 -> 15075 | Z66: =SUM(Z62:Z65)+Z61 -> 16050 | AB66: Suma anual | AC66: =SUM(AC62:AC65)+AC61 -> 9321.875 | AD66: =SUM(AD62:AD65)+AD61 -> 9951.25
T67: Costo de adquisición | U67: 3500 | V67: 3500
T68: Capacitación | U68: =U67*1% -> 35 | V68: =V67*2% -> 70
T69: Mantenimiento anual | U69: =U67*5% -> 175 | V69: =V67*8% -> 280
T70: Depreciación anual | U70: =-((U67-U67*5%)/5) -> -665 | V70: =-((V67-V67*10%)/5) -> -630
T71: Suma anual | U71: =SUM(U68:U70)+U67 -> 3045 | V71: =SUM(V68:V70)+V67 -> 3220
B72: EJEMPLO de distribución de Ventas (Bolsos Economicos) | C72: Reputacion | D72: Precio | E72: Puntaje del precio | F72: Puntaje total | G72: Porcentaje parcial | H72: Unidades Vendidas
B73: Empresa A | C73: 7 | D73: 40 | E73: =(MAX($D$73:$D$76)*2-D73)/10 -> 5 | F73: =SUM(C73,E73) -> 12 | G73: =F73/$F$77 -> 0.2238806 | H73: =ROUND(G73*$B$81,0) -> 784 | T73: Costos: MP
B74: Empresa B | C74: 8.3 | D74: 45 | E74: =(MAX($D$73:$D$76)*2-D74)/10 -> 4.5 | F74: =SUM(C74,E74) -> 12.8 | G74: =F74/$F$77 -> 0.23880597 | H74: =ROUND(G74*$B$81,0) -> 836 | T74: Tabla de materia base. | Z74: Lo que sea comprado por un equipo:
B75: Empresa C | C75: 10.2 | D75: 43 | E75: =(MAX($D$73:$D$76)*2-D75)/10 -> 4.7 | F75: =SUM(C75,E75) -> 14.9 | G75: =F75/$F$77 -> 0.27798507 | H75: =ROUND(G75*$B$81,0) -> 973 | T75: Grupo de decisión | U75: Opción/Nivel | V75: Precio de lista | W75: Descontado por cantidad | X75: Unidad | Z75: Grupo de decisión | AA75: Opción/Nivel | AB75: Precio de lista | AC75: Descontado por cantidad | AD75: Unidad
B76: Empresa D | C76: 9 | D76: 41 | E76: =(MAX($D$73:$D$76)*2-D76)/10 -> 4.9 | F76: =SUM(C76,E76) -> 13.9 | G76: =F76/$F$77 -> 0.25932836 | H76: =ROUND(G76*$B$81,0) -> 908 | T76: Calidad del cuero | U76: 1- Cuero sintético | V76: 25 | W76: =V76-V76*8% -> 23 | X76: m² | Z76: Calidad del cuero | AA76: 1- Cuero sintético | AB76: =25*60 -> 1500 | AC76: =AB76-AB76*8% -> 1380 | AD76: 60m²
E77: Total | F77: =SUM(F73:F76) -> 53.6 | H77: =SUM(H73:H76) -> 3501 | T77: Calidad del cuero | U77: 2- Cuero genuino estándar | V77: 45 | W77: =V77-V77*8% -> 41.4 | X77: m² | Z77: Calidad del cuero | AA77: 2- Cuero genuino estándar | AB77: =45*55 -> 2475 | AC77: =AB77-AB77*8% -> 2277 | AD77: 55m²
T78: Calidad del cuero | U78: 3-Cuero genuino premium | V78: 80 | W78: =V78-V78*8% -> 73.6 | X78: m² | Z78: Calidad del cuero | AA78: 3-Cuero genuino premium | AB78: =80*15 -> 1200 | AC78: =AB78-AB78*8% -> 1104 | AD78: 15m²
B79: 7000 | C79: unidades mercado | T79: Calidad de accesorios | U79: 1- Aleación económica | V79: 4 | W79: =V79-V79*8% -> 3.68 | X79: unidad | Z79: Calidad de accesorios | AA79: 1- Aleación económica | AB79: =4*200 -> 800 | AC79: =AB79-AB79*8% -> 736 | AD79: 200 unidad
B80: 0.5 | T80: Calidad de accesorios | U80: 2- Metal premium | V80: 9 | W80: =V80-V80*8% -> 8.28 | X80: unidad | Z80: Calidad de accesorios | AA80: 2- Metal premium | AB80: =9*190 -> 1710 | AC80: =AB80-AB80*8% -> 1573.2 | AD80: 190 unidad
B81: =B79*B80 -> 3500 | C81: unidades mercado real | T81: Calidad del hilo | U81: 1- Poliéster estándar | V81: 2 | W81: =V81-V81*8% -> 1.84 | X81: m | Z81: Calidad del hilo | AA81: 1- Poliéster estándar | AB81: =2*0 -> 0 | AC81: =AB81-AB81*8% -> 0 | AD81: 0 m
T82: Calidad del hilo | U82: 2- Encerado reforzado | V82: 4 | W82: =V82-V82*8% -> 3.68 | X82: m | Z82: Calidad del hilo | AA82: 2- Encerado reforzado | AB82: =4*6 -> 24 | AC82: =AB82-AB82*8% -> 22.08 | AD82: 6 m
T83: Calidad del hilo | U83: 3- Alta tenacidad | V83: 7 | W83: =V83-V83*8% -> 6.44 | X83: m | Z83: Calidad del hilo | AA83: 3- Alta tenacidad | AB83: =7*7 -> 49 | AC83: =AB83-AB83*8% -> 45.08 | AD83: 7 m
Z84: Total | AB84: =SUM(AB76:AB83) -> 7758 | AC84: =SUM(AC76:AC83) -> 7137.36
T85: Inventario Inicial:
B86: EJEMPLO de distribución de Ventas (Bolsos promedio) | C86: Reputacion | D86: Precio | E86: Puntaje del precio | F86: Puntaje total | G86: Porcentaje parcial | H86: Unidades Vendidas | T86: Grupo de decisión | U86: Opción/Nivel | V86: Precio de lista | W86: Descontado por cantidad | X86: Unidad*cant. producida | Z86: Producción:
B87: Empresa A | C87: 7 | D87: 120 | E87: =(MAX($D$87:$D$90)*2-D87)/10 -> 28 | F87: =SUM(C87,E87) -> 35 | G87: =F87/$F$91 -> 0.27237354 | H87: =ROUND(G87*$B$81,0) -> 953 | T87: Calidad del cuero | U87: 1- Cuero sintético | V87: =25*60 -> 1500 | W87: =V87-V87*8% -> 1380 | X87: 60m² | Z87: Grupo de decisión | AA87: Opción/Nivel | AB87: Precio de lista | AC87: Descontado por cantidad | AD87: Unidad*cant. producida
B88: Empresa B | C88: 8.3 | D88: 150 | E88: =(MAX($D$87:$D$90)*2-D88)/10 -> 25 | F88: =SUM(C88,E88) -> 33.3 | G88: =F88/$F$91 -> 0.25914397 | H88: =ROUND(G88*$B$81,0) -> 907 | T88: Calidad del cuero | U88: 2- Cuero genuino estándar | V88: =45*110 -> 4950 | W88: =V88-V88*8% -> 4554 | X88: 110m² | Z88: Calidad del cuero | AA88: 1- Cuero sintético | AB88: =25*60 -> 1500 | AC88: =AB88-AB88*8% -> 1380 | AD88: 60m²
B89: Empresa C | C89: 10.2 | D89: 190 | E89: =(MAX($D$87:$D$90)*2-D89)/10 -> 21 | F89: =SUM(C89,E89) -> 31.2 | G89: =F89/$F$91 -> 0.24280156 | H89: =ROUND(G89*$B$81,0) -> 850 | T89: Calidad del cuero | U89: 3-Cuero genuino premium | V89: =80*30 -> 2400 | W89: =V89-V89*8% -> 2208 | X89: 30m² | Z89: Calidad del cuero | AA89: 2- Cuero genuino estándar | AB89: =45*107 -> 4815 | AC89: =AB89-AB89*8% -> 4429.8 | AD89: 107m²
B90: Empresa D | C90: 9 | D90: 200 | E90: =(MAX($D$87:$D$90)*2-D90)/10 -> 20 | F90: =SUM(C90,E90) -> 29 | G90: =F90/$F$91 -> 0.22568093 | H90: =ROUND(G90*$B$81,0) -> 790 | T90: Calidad de accesorios | U90: 1- Aleación económica | V90: =4*200 -> 800 | W90: =V90-V90*8% -> 736 | X90: 200 unidad | Z90: Calidad del cuero | AA90: 3-Cuero genuino premium | AB90: =80*0 -> 0 | AC90: =AB90-AB90*8% -> 0 | AD90: 0m²
E91: Total | F91: =SUM(F87:F90) -> 128.5 | T91: Calidad de accesorios | U91: 2- Metal premium | V91: =9*190 -> 1710 | W91: =V91-V91*8% -> 1573.2 | X91: 190 unidad | Z91: Calidad de accesorios | AA91: 1- Aleación económica | AB91: =4*200 -> 800 | AC91: =AB91-AB91*8% -> 736 | AD91: 200 unidad
T92: Calidad del hilo | U92: 1- Poliéster estándar | V92: =2*0 -> 0 | W92: =V92-V92*8% -> 0 | X92: 0 m | Z92: Calidad de accesorios | AA92: 2- Metal premium | AB92: =9*185 -> 1665 | AC92: =AB92-AB92*8% -> 1531.8 | AD92: 185 unidad
B93: 5000 | C93: unidades mercado | T93: Calidad del hilo | U93: 2- Encerado reforzado | V93: =4*1500 -> 6000 | W93: =V93-V93*8% -> 5520 | X93: 1500 m | Z93: Calidad del hilo | AA93: 1- Poliéster estándar | AB93: =2*0 -> 0 | AC93: =AB93-AB93*8% -> 0 | AD93: 0 m
B94: 0.7 | T94: Calidad del hilo | U94: 3- Alta tenacidad | V94: =7*1400 -> 9800 | W94: =V94-V94*8% -> 9016 | X94: 1400 m | Z94: Calidad del hilo | AA94: 2- Encerado reforzado | AB94: =4*1500 -> 6000 | AC94: =AB94-AB94*8% -> 5520 | AD94: 1500 m
B95: =B93*B94 -> 3500 | C95: unidades mercado real | T95: Total | V95: =SUM(V87:V94) -> 27160 | W95: =SUM(W87:W94) -> 24987.2 | Z95: Calidad del hilo | AA95: 3- Alta tenacidad | AB95: =7*1400 -> 9800 | AC95: =AB95-AB95*8% -> 9016 | AD95: 1400 m
Z96: Total | AB96: =SUM(AB88:AB95) -> 24580 | AC96: =SUM(AC88:AC95) -> 22613.6
T98: Inventario final: Inventario inicial - Producción
B100: EJEMPLO de distribución de Ventas (Bolsos Premium) | C100: Reputacion | D100: Precio | E100: Puntaje del precio | F100: Puntaje total | G100: Porcentaje parcial | H100: Unidades Vendidas | T100: Total | V100: =V95-AB96 -> 2580 | W100: =W95-AC96 -> 2373.6
B101: Empresa A | C101: 7 | D101: 250 | E101: =(MAX($D$101:$D$104)*2-D101)/10 -> 55 | F101: =SUM(C101,E101) -> 62 | G101: =F101/$F$105 -> 0.26105263 | H101: =ROUND(G101*$B$109,0) -> 209
B102: Empresa B | C102: 8.3 | D102: 300 | E102: =(MAX($D$101:$D$104)*2-D102)/10 -> 50 | F102: =SUM(C102,E102) -> 58.3 | G102: =F102/$F$105 -> 0.24547368 | H102: =ROUND(G102*$B$109,0) -> 196
B103: Empresa C | C103: 10.2 | D103: 220 | E103: =(MAX($D$101:$D$104)*2-D103)/10 -> 58 | F103: =SUM(C103,E103) -> 68.2 | G103: =F103/$F$105 -> 0.28715789 | H103: =ROUND(G103*$B$109,0) -> 230
B104: Empresa D | C104: 9 | D104: 400 | E104: =(MAX($D$101:$D$104)*2-D104)/10 -> 40 | F104: =SUM(C104,E104) -> 49 | G104: =F104/$F$105 -> 0.20631579 | H104: =ROUND(G104*$B$109,0) -> 165
E105: Total | F105: =SUM(F101:F104) -> 237.5
...

Sheet Lotes_Produccion
A1: Lote | B1: Segmento de venta (elige) | C1: Cantidad de unidades (input) | D1: Codigo Cuero (elige) | E1: Codigo Accesorios (elige) | F1: Codigo Hilo (elige) | G1: Codigo Molde (elige) | H1: Costo unitario insumos (auto) | I1: Puntaje Calidad del lote (auto) | J1: Umbral requerido por segmento (auto) | K1: Resultado (auto) | L1: Mensaje para el jugador (auto) | M1: Precio elegido (S/ por unidad) | N1: Validación de precio | O1: Precio efectivo tras consecuencias
A2: Lote 1 | C2: 0 | H2: =IFERROR(INDEX(Catalogo_Decisiones!$G$2:$G$69,MATCH($D2,Catalogo_Decisiones!$A$2:$A$69,0)),0)+IFERROR(INDEX(Catalogo_Decisiones!$G$2:$G$69,MATCH($E2,Catalogo_Decisiones!$A$2:$A$69,0)),0)+IFERROR(INDEX(Catalogo_Decisiones!$G$2:$G$69,MATCH($F2,Catalogo_Decisiones!$A$2:$A$69,0)),0) -> 0 | I2: =MAX(0,MIN(10,IFERROR(INDEX(Catalogo_Decisiones!$H$2:$H$69,MATCH($D2,Catalogo_Decisiones!$A$2:$A$69,0)),0)+IFERROR(INDEX(Catalogo_Decisiones!$H$2:$H$69,MATCH($E2,Catalogo_Decisiones!$A$2:$A$69,0)),0)+IFERROR(INDEX(Catalogo_Decisiones!$H$2:$H$69,MATCH($F2,Catalogo_Decisiones!$A$2:$A$69,0)),0)+IFERROR(INDEX(Catalogo_Decisiones!$H$2:$H$69,MATCH($G2,Catalogo_Decisiones!$A$2:$A$69,0)),0))) -> 0 | J2: =IF(B2="SEG-03",7,IF(B2="SEG-02",4,0)) -> 0 | K2: =IF(B2="","",IF(I2>=J2,"Coherente","No alcanza el segmento")) | L2: =IF(B2="","Elige un segmento y los insumos del lote",IF(K2="Coherente","Este lote cumple con la calidad esperada para su segmento. Los clientes perciben el valor y el precio se sostiene.","Este lote no alcanza la calidad que su segmento promete. Los clientes se sienten enganados: baja el precio efectivo y la reputacion.")) -> Elige un segmento y los insumos del lote | M2: 42.5 | N2: =IF(B2="","",IF(AND(M2>=IF(B2="SEG-01",40,IF(B2="SEG-02",120,220)),M2<=IF(B2="SEG-01",45,IF(B2="SEG-02",200,400))),"Válido","Fuera de rango")) | O2: =M2*IF(B2="SEG-03",IF(I2<7,0.65,1.4),1) -> 42.5
A3: Lote 2 | C3: 0 | H3: =IFERROR(INDEX(Catalogo_Decisiones!$G$2:$G$69,MATCH($D3,Catalogo_Decisiones!$A$2:$A$69,0)),0)+IFERROR(INDEX(Catalogo_Decisiones!$G$2:$G$69,MATCH($E3,Catalogo_Decisiones!$A$2:$A$69,0)),0)+IFERROR(INDEX(Catalogo_Decisiones!$G$2:$G$69,MATCH($F3,Catalogo_Decisiones!$A$2:$A$69,0)),0) -> 0 | I3: =MAX(0,MIN(10,IFERROR(INDEX(Catalogo_Decisiones!$H$2:$H$69,MATCH($D3,Catalogo_Decisiones!$A$2:$A$69,0)),0)+IFERROR(INDEX(Catalogo_Decisiones!$H$2:$H$69,MATCH($E3,Catalogo_Decisiones!$A$2:$A$69,0)),0)+IFERROR(INDEX(Catalogo_Decisiones!$H$2:$H$69,MATCH($F3,Catalogo_Decisiones!$A$2:$A$69,0)),0)+IFERROR(INDEX(Catalogo_Decisiones!$H$2:$H$69,MATCH($G3,Catalogo_Decisiones!$A$2:$A$69,0)),0))) -> 0 | J3: =IF(B3="SEG-03",7,IF(B3="SEG-02",4,0)) -> 0 | K3: =IF(B3="","",IF(I3>=J3,"Coherente","No alcanza el segmento")) | L3: =IF(B3="","Elige un segmento y los insumos del lote",IF(K3="Coherente","Este lote cumple con la calidad esperada para su segmento. Los clientes perciben el valor y el precio se sostiene.","Este lote no alcanza la calidad que su segmento promete. Los clientes se sienten enganados: baja el precio efectivo y la reputacion.")) -> Elige un segmento y los insumos del lote | M3: 160 | N3: =IF(B3="","",IF(AND(M3>=IF(B3="SEG-01",40,IF(B3="SEG-02",120,220)),M3<=IF(B3="SEG-01",45,IF(B3="SEG-02",200,400))),"Válido","Fuera de rango")) | O3: =M3*IF(B3="SEG-03",IF(I3<7,0.65,1.4),1) -> 160
A4: Lote 3 | C4: 0 | H4: =IFERROR(INDEX(Catalogo_Decisiones!$G$2:$G$69,MATCH($D4,Catalogo_Decisiones!$A$2:$A$69,0)),0)+IFERROR(INDEX(Catalogo_Decisiones!$G$2:$G$69,MATCH($E4,Catalogo_Decisiones!$A$2:$A$69,0)),0)+IFERROR(INDEX(Catalogo_Decisiones!$G$2:$G$69,MATCH($F4,Catalogo_Decisiones!$A$2:$A$69,0)),0) -> 0 | I4: =MAX(0,MIN(10,IFERROR(INDEX(Catalogo_Decisiones!$H$2:$H$69,MATCH($D4,Catalogo_Decisiones!$A$2:$A$69,0)),0)+IFERROR(INDEX(Catalogo_Decisiones!$H$2:$H$69,MATCH($E4,Catalogo_Decisiones!$A$2:$A$69,0)),0)+IFERROR(INDEX(Catalogo_Decisiones!$H$2:$H$69,MATCH($F4,Catalogo_Decisiones!$A$2:$A$69,0)),0)+IFERROR(INDEX(Catalogo_Decisiones!$H$2:$H$69,MATCH($G4,Catalogo_Decisiones!$A$2:$A$69,0)),0))) -> 0 | J4: =IF(B4="SEG-03",7,IF(B4="SEG-02",4,0)) -> 0 | K4: =IF(B4="","",IF(I4>=J4,"Coherente","No alcanza el segmento")) | L4: =IF(B4="","Elige un segmento y los insumos del lote",IF(K4="Coherente","Este lote cumple con la calidad esperada para su segmento. Los clientes perciben el valor y el precio se sostiene.","Este lote no alcanza la calidad que su segmento promete. Los clientes se sienten enganados: baja el precio efectivo y la reputacion.")) -> Elige un segmento y los insumos del lote | M4: 250 | N4: =IF(B4="","",IF(AND(M4>=IF(B4="SEG-01",40,IF(B4="SEG-02",120,220)),M4<=IF(B4="SEG-01",45,IF(B4="SEG-02",200,400))),"Válido","Fuera de rango")) | O4: =M4*IF(B4="SEG-03",IF(I4<7,0.65,1.4),1) -> 250
A5: TOTAL CICLO | C5: =SUM(C2:C4) -> 0 | H5: =SUMPRODUCT(C2:C4,H2:H4) -> 0
A7: Nota: cada lote se evalua por separado. El costo unitario de insumos (col H) NO incluye el molde (es inversion fija de Ciclo 0), solo cuero+accesorios+hilo por unidad.

Sheet Motor_Puntajes
A1: Puntaje interno | B1: Valor (suma de aportes) | C1: Escala | D1: Nivel resultante
A2: CALIDAD POR LOTE (detalle)
A3: Puntaje Calidad - Lote 1 | B3: =Lotes_Produccion!I2 -> 0 | C3: =IF(Lotes_Produccion!B2="","","Segmento: "&Lotes_Produccion!B2) | D3: =Lotes_Produccion!K2
A4: Puntaje Calidad - Lote 2 | B4: =Lotes_Produccion!I3 -> 0 | C4: =IF(Lotes_Produccion!B3="","","Segmento: "&Lotes_Produccion!B3) | D4: =Lotes_Produccion!K3
A5: Puntaje Calidad - Lote 3 | B5: =Lotes_Produccion!I4 -> 0 | C5: =IF(Lotes_Produccion!B4="","","Segmento: "&Lotes_Produccion!B4) | D5: =Lotes_Produccion!K4
A6: Puntaje Calidad EMPRESA (promedio ponderado por unidades) | B6: =IFERROR(SUMPRODUCT(Lotes_Produccion!C2:C4,Lotes_Produccion!I2:I4)/SUM(Lotes_Produccion!C2:C4),0) -> 0 | C6: 0 - 10 (referencial) | D6: =IF(B6>=7,"Alto",IF(B6>=4,"Medio","Bajo")) -> Bajo
A8: OTROS PUNTAJES DE EMPRESA
A9: Puntaje de Eficiencia | B9: =MAX(0,MIN(10,SUM(Seleccion_Ciclo0!G2:G15,Seleccion_Ciclo0!G24:G27))) -> 0 | C9: 0 - 10 (referencial) | D9: =IF(B9>=7,"Alto",IF(B9>=4,"Medio","Bajo")) -> Bajo
A10: Puntaje de Reputacion | B10: =MAX(0,MIN(10,SUM(Seleccion_Ciclo0!H2:H15,Seleccion_Ciclo0!H24:H27))) -> 0 | C10: 0 - 10 (referencial) | D10: =IF(B10>=7,"Alto",IF(B10>=4,"Medio","Bajo")) -> Bajo
A11: Puntaje de Salud Financiera | B11: =MAX(0,MIN(10,SUM(Seleccion_Ciclo0!I2:I15,Seleccion_Ciclo0!I24:I27))) -> 0 | C11: 0 - 10 (referencial) | D11: =IF(B11>=7,"Alto",IF(B11>=4,"Medio","Bajo")) -> Bajo
A13: Nota: cada 'Aporte' se define en la hoja Catalogo_Decisiones (columnas H-K) y se suma automaticamente segun lo elegido en Seleccion_Ciclo0.

Sheet Matriz_Consecuencias
A1: ID | B1: Puntaje evaluado | C1: Condicion | D1: Efecto numerico en el juego | E1: Mensaje textual para el jugador
A2: CONS-01 | B2: Calidad | C2: < 7 y Segmento = Premium | D2: Precio de venta -35%, Reputacion -2 | E2: Posicionaste tu marca como premium, pero tus materiales e insumos no lo respaldan. Los clientes se sienten enganados y las devoluciones aumentan.
A3: CONS-02 | B3: Calidad | C3: >= 7 y Segmento = Premium | D3: Precio de venta +40%, Reputacion +2 | E3: Tu producto cumple con los estandares premium. Los clientes perciben el valor y pagan sin problema el precio elevado.
A4: CONS-03 | B4: Eficiencia | C4: < 4 | D4: Produccion real = 70% de lo planeado (retrasos) | E4: Tu equipo no dio abasto con el volumen que planeaste. Hubo retrasos y entregaste menos de lo prometido.
A5: CONS-04 | B5: Reputacion | C5: < 3 durante 2 ciclos seguidos | D5: Demanda -20% | E5: Tu marca empieza a perder terreno. Los clientes prefieren a la competencia.
A6: CONS-05 | B6: Salud Financiera | C6: < 3 | D6: El banco sube la tasa de interes del proximo prestamo | E6: Tu situacion financiera es riesgosa. El banco te ofrece condiciones menos favorables la proxima vez.
A7: CONS-06 | B7: Produccion vs Capacidad | C7: Cantidad producida > capacidad instalada | D7: Retraso de entrega, costo extra por horas extra | E7: Intentaste producir mas de lo que tu planta soporta. Hubo cuellos de botella y tuviste que pagar horas extra para cumplir.
A8: CONS-07 | B8: Produccion vs Demanda | C8: Cantidad producida > demanda real del mercado | D8: Inventario sin vender, costo de almacenaje | E8: Produjiste mas de lo que el mercado te pidio. Te quedaste con inventario sin vender.
A9: CONS-08 | B9: Eficiencia | C9: Jefatura = No y Eficiencia < 5 | D9: Riesgo de descoordinacion: -5% produccion adicional | E9: Sin jefatura que coordine, tu equipo perdio tiempo resolviendo conflictos de tareas.

Sheet Supuestos
A1: ID | B1: Parámetro | C1: Valor / regla | D1: Estado / fundamento
A2: FUENTE | B2: Base autorizada | C2: v16; v18 no disponible | D2: Autorizado por usuario; hash en control
A3: E3 | B3: Precio por segmento | C3: 40–45 /120–200 /220–400; ideales100/250 | D3: Rangos explícitos usuario; defaults42.5/160/250 supuesto
A4: E4 | B4: Mercado | C4: v2; pesos .7/.2/.1,.4/.35/.25,.1/.5/.4;3500/3500/800 | D4: Canónico por usuario
A5: E5 | B5: Empate económico | C5: PrecioScore100 todos; scores acotados0–100 | D5: Regla solicitada
A6: E5e | B6: Demanda no atendida | C6: Se pierde, sin reasignación | D6: Regla solicitada
A7: E5f | B7: Competidores | C7: Solo empresas que produjeron lote en segmento | D7: Regla solicitada; inventario antiguo solo vende si también produce
A8: E6 | B8: Reputación | C8: Catálogo una opción por grupo; clamp0–10, luego CONS01/02 clamp | D8: SUPUESTO para aprobación; publicidad no se cuenta otra vez
A9: E7 | B9: Capacidad | C9: 24d,90%base,+1pp por N3,+4pp jefatura; corte5/7/9,ensamble6/8/12,acabado6/7/10 | D9: Canon CANTIDAD solicitado
A10: E9 | B10: Calidad y puntajes | C10: Tope0–10; Premium<7 CONS01 y>=7 CONS02 | D10: SUPUESTO hueco Premium resuelto
A11: E9 | B11: Personal mixto | C11: Aporte máximo por grupo, no por cada empleado | D11: SUPUESTO para evitar inflar puntajes por volumen
A12: E11 | B12: Canal | C12: Cobertura base1 para física/digital/mixto | D12: SUPUESTO configurable neutral, pendiente aprobación
... A27: REDONDEO | B27: Unidades | C27: ROUND demanda, floor producción; MIN stock; ingresos2decimales | D27: SUPUESTO para consistencia contable

Sheet Oraculo_v19
A1: caso | B1: empresa | C1: segmento | D1: precio | E1: reputacion | F1: calidad0a10 | G1: stock | H1: producido | I1: bajaPrevios | J1: pesoP | K1: pesoR | L1: pesoC | M1: mercado | N1: ideal | O1: precioScore | P1: puntaje | Q1: participacion | R1: demanda | S1: vendidas | T1: factorPrecio | U1: precioEfectivo | V1: ingresos | W1: demandaPerdida | X1: reputacionFinal
A2: normal_economico | B2: A | C2: SEG-01 | D2: 40 | E2: 7 | F2: 8 | G2: 1000 | H2: 100 | I2: 0 | J2: 0.7 | K2: 0.2 | L2: 0.1 | M2: 3500 | N2: 0 | O2: =IF(H2<=0,0,MAX(0,MIN(100,IF(C2="SEG-01",IF(MAX(IF($H$2>0,$D$2,-1E+99),IF($H$3>0,$D$3,-1E+99),IF($H$4>0,$D$4,-1E+99),IF($H$5>0,$D$5,-1E+99))=MIN(IF($H$2>0,$D$2,1E+99),IF($H$3>0,$D$3,1E+99),IF($H$4>0,$D$4,1E+99),IF($H$5>0,$D$5,1E+99)),100,100*(MAX(IF($H$2>0,$D$2,-1E+99),IF($H$3>0,$D$3,-1E+99),IF($H$4>0,$D$4,-1E+99),IF($H$5>0,$D$5,-1E+99))-D2)/(MAX(IF($H$2>0,$D$2,-1E+99),IF($H$3>0,$D$3,-1E+99),IF($H$4>0,$D$4,-1E+99),IF($H$5>0,$D$5,-1E+99))-MIN(IF($H$2>0,$D$2,1E+99),IF($H$3>0,$D$3,1E+99),IF($H$4>0,$D$4,1E+99),IF($H$5>0,$D$5,1E+99)))),100-ABS(D2-N2)/IF(N2=0,1,N2)*100)))) -> 100 | P2: =IF(H2>0,J2*O2+K2*X2*10+L2*MAX(0,MIN(10,F2))*10,0) -> 92 | Q2: =IFERROR(P2/SUM($P$2:$P$5),0) -> 0.4 | R2: =ROUNDDOWN(ROUND(Q2*M2,0)*IF(AND(X2<3,I2>=1),0.8,1),0) -> 1400 | S2: =MIN(G2,R2) -> 1000 | T2: =IF(C2="SEG-03",IF(F2<7,0.65,1.4),1) -> 1 | U2: =D2*T2 -> 40 | V2: =ROUND(S2*U2,2) -> 40000 | W2: =MAX(0,R2-S2) -> 400 | X2: =MAX(0,MIN(10,E2+IF(C2="SEG-03",IF(F2<7,-2,2),0))) -> 7
A3: normal_economico | B3: B | C3: SEG-01 | D3: 42 | E3: 8 | F3: 7 | G3: 1000 | H3: 100 | I3: 0 | J3: 0.7 | K3: 0.2 | L3: 0.1 | M3: 3500 | N3: 0 | O3: =IF(H3<=0,0,MAX(0,MIN(100,IF(C3="SEG-01",IF(MAX(IF($H$2>0,$D$2,-1E+99),IF($H$3>0,$D$3,-1E+99),IF($H$4>0,$D$4,-1E+99),IF($H$5>0,$D$5,-1E+99))=MIN(IF($H$2>0,$D$2,1E+99),IF($H$3>0,$D$3,1E+99),IF($H$4>0,$D$4,1E+99),IF($H$5>0,$D$5,1E+99)),100,100*(MAX(IF($H$2>0,$D$2,-1E+99),IF($H$3>0,$D$3,-1E+99),IF($H$4>0,$D$4,-1E+99),IF($H$5>0,$D$5,-1E+99))-D3)/(MAX(IF($H$2>0,$D$2,-1E+99),IF($H$3>0,$D$3,-1E+99),IF($H$4>0,$D$4,-1E+99),IF($H$5>0,$D$5,-1E+99))-MIN(IF($H$2>0,$D$2,1E+99),IF($H$3>0,$D$3,1E+99),IF($H$4>0,$D$4,1E+99),IF($H$5>0,$D$5,1E+99)))),100-ABS(D3-N3)/IF(N3=0,1,N3)*100)))) -> 60 | P3: =IF(H3>0,J3*O3+K3*X3*10+L3*MAX(0,MIN(10,F3))*10,0) -> 65 | Q3: =IFERROR(P3/SUM($P$2:$P$5),0) -> 0.2826087 | R3: =ROUNDDOWN(ROUND(Q3*M3,0)*IF(AND(X3<3,I3>=1),0.8,1),0) -> 989 | S3: =MIN(G3,R3) -> 989 | T3: =IF(C3="SEG-03",IF(F3<7,0.65,1.4),1) -> 1 | U3: =D3*T3 -> 42 | V3: =ROUND(S3*U3,2) -> 41538 | W3: =MAX(0,R3-S3) -> 0 | X3: =MAX(0,MIN(10,E3+IF(C3="SEG-03",IF(F3<7,-2,2),0))) -> 8
A4: normal_economico | B4: C | C4: SEG-01 | D4: 43 | E4: 9 | F4: 9 | G4: 1000 | H4: 100 | I4: 0 | J4: 0.7 | K4: 0.2 | L4: 0.1 | M4: 3500 | N4: 0 | O4: =IF(H4<=0,0,MAX(0,MIN(100,IF(C4="SEG-01",IF(MAX(IF($H$2>0,$D$2,-1E+99),IF($H$3>0,$D$3,-1E+99),IF($H$4>0,$D$4,-1E+99),IF($H$5>0,$D$5,-1E+99))=MIN(IF($H$2>0,$D$2,1E+99),IF($H$3>0,$D$3,1E+99),IF($H$4>0,$D$4,1E+99),IF($H$5>0,$D$5,1E+99)),100,100*(MAX(IF($H$2>0,$D$2,-1E+99),IF($H$3>0,$D$3,-1E+99),IF($H$4>0,$D$4,-1E+99),IF($H$5>0,$D$5,-1E+99))-D4)/(MAX(IF($H$2>0,$D$2,-1E+99),IF($H$3>0,$D$3,-1E+99),IF($H$4>0,$D$4,-1E+99),IF($H$5>0,$D$5,-1E+99))-MIN(IF($H$2>0,$D$2,1E+99),IF($H$3>0,$D$3,1E+99),IF($H$4>0,$D$4,1E+99),IF($H$5>0,$D$5,1E+99)))),100-ABS(D4-N4)/IF(N4=0,1,N4)*100)))) -> 40 | P4: =IF(H4>0,J4*O4+K4*X4*10+L4*MAX(0,MIN(10,F4))*10,0) -> 55 | Q4: =IFERROR(P4/SUM($P$2:$P$5),0) -> 0.23913043 | R4: =ROUNDDOWN(ROUND(Q4*M4,0)*IF(AND(X4<3,I4>=1),0.8,1),0) -> 837 | S4: =MIN(G4,R4) -> 837 | T4: =IF(C4="SEG-03",IF(F4<7,0.65,1.4),1) -> 1 | U4: =D4*T4 -> 43 | V4: =ROUND(S4*U4,2) -> 35991 | W4: =MAX(0,R4-S4) -> 0 | X4: =MAX(0,MIN(10,E4+IF(C4="SEG-03",IF(F4<7,-2,2),0))) -> 9
A5: normal_economico | B5: D | C5: SEG-01 | D5: 45 | E5: 6 | F5: 6 | G5: 1000 | H5: 100 | I5: 0 | J5: 0.7 | K5: 0.2 | L5: 0.1 | M5: 3500 | N5: 0 | O5: =IF(H5<=0,0,MAX(0,MIN(100,IF(C5="SEG-01",IF(MAX(IF($H$2>0,$D$2,-1E+99),IF($H$3>0,$D$3,-1E+99),IF($H$4>0,$D$4,-1E+99),IF($H$5>0,$D$5,-1E+99))=MIN(IF($H$2>0,$D$2,1E+99),IF($H$3>0,$D$3,1E+99),IF($H$4>0,$D$4,1E+99),IF($H$5>0,$D$5,1E+99)),100,100*(MAX(IF($H$2>0,$D$2,-1E+99),IF($H$3>0,$D$3,-1E+99),IF($H$4>0,$D$4,-1E+99),IF($H$5>0,$D$5,-1E+99))-D5)/(MAX(IF($H$2>0,$D$2,-1E+99),IF($H$3>0,$D$3,-1E+99),IF($H$4>0,$D$4,-1E+99),IF($H$5>0,$D$5,-1E+99))-MIN(IF($H$2>0,$D$2,1E+99),IF($H$3>0,$D$3,1E+99),IF($H$4>0,$D$4,1E+99),IF($H$5>0,$D$5,1E+99)))),100-ABS(D5-N5)/IF(N5=0,1,N5)*100)))) -> 0 | P5: =IF(H5>0,J5*O5+K5*X5*10+L5*MAX(0,MIN(10,F5))*10,0) -> 18 | Q5: =IFERROR(P5/SUM($P$2:$P$5),0) -> 0.07826087 | R5: =ROUNDDOWN(ROUND(Q5*M5,0)*IF(AND(X5<3,I5>=1),0.8,1),0) -> 274 | S5: =MIN(G5,R5) -> 274 | T5: =IF(C5="SEG-03",IF(F5<7,0.65,1.4),1) -> 1 | U5: =D5*T5 -> 45 | V5: =ROUND(S5*U5,2) -> 12330 | W5: =MAX(0,R5-S5) -> 0 | X5: =MAX(0,MIN(10,E5+IF(C5="SEG-03",IF(F5<7,-2,2),0))) -> 6
A6: normal_medio | B6: A | C6: SEG-02 | D6: 120 | E6: 7 | F6: 8 | G6: 1000 | H6: 100 | I6: 0 | J6: 0.4 | K6: 0.35 | L6: 0.25 | M6: 3500 | N6: 100 | O6: =IF(H6<=0,0,MAX(0,MIN(100,IF(C6="SEG-01",IF(MAX(IF($H$6>0,$D$6,-1E+99),IF($H$7>0,$D$7,-1E+99),IF($H$8>0,$D$8,-1E+99),IF($H$9>0,$D$9,-1E+99))=MIN(IF($H$6>0,$D$6,1E+99),IF($H$7>0,$D$7,1E+99),IF($H$8>0,$D$8,1E+99),IF($H$9>0,$D$9,1E+99)),100,100*(MAX(IF($H$6>0,$D$6,-1E+99),IF($H$7>0,$D$7,-1E+99),IF($H$8>0,$D$8,-1E+99),IF($H$9>0,$D$9,-1E+99))-D6)/(MAX(IF($H$6>0,$D$6,-1E+99),IF($H$7>0,$D$7,-1E+99),IF($H$8>0,$D$8,-1E+99),IF($H$9>0,$D$9,-1E+99))-MIN(IF($H$6>0,$D$6,1E+99),IF($H$7>0,$D$7,1E+99),IF($H$8>0,$D$8,1E+99),IF($H$9>0,$D$9,1E+99)))),100-ABS(D6-N6)/IF(N6=0,1,N6)*100)))) -> 80 | P6: =IF(H6>0,J6*O6+K6*X6*10+L6*MAX(0,MIN(10,F6))*10,0) -> 76.5 | Q6: =IFERROR(P6/SUM($P$6:$P$9),0) -> 0.30357143 | R6: =ROUNDDOWN(ROUND(Q6*M6,0)*IF(AND(X6<3,I6>=1),0.8,1),0) -> 1063 | S6: =MIN(G6,R6) -> 1000 | T6: =IF(C6="SEG-03",IF(F6<7,0.65,1.4),1) -> 1 | U6: =D6*T6 -> 120 | V6: =ROUND(S6*U6,2) -> 120000 | W6: =MAX(0,R6-S6) -> 63 | X6: =MAX(0,MIN(10,E6+IF(C6="SEG-03",IF(F6<7,-2,2),0))) -> 7
A7: normal_medio | B7: B | C7: SEG-02 | D7: 140 | E7: 8 | F7: 7 | G7: 1000 | H7: 100 | I7: 0 | J7: 0.4 | K7: 0.35 | L7: 0.25 | M7: 3500 | N7: 100 | O7: =IF(H7<=0,0,MAX(0,MIN(100,IF(C7="SEG-01",IF(MAX(IF($H$6>0,$D$6,-1E+99),IF($H$7>0,$D$7,-1E+99),IF($H$8>0,$D$8,-1E+99),IF($H$9>0,$D$9,-1E+99))=MIN(IF($H$6>0,$D$6,1E+99),IF($H$7>0,$D$7,1E+99),IF($H$8>0,$D$8,1E+99),IF($H$9>0,$D$9,1E+99)),100,100*(MAX(IF($H$6>0,$D$6,-1E+99),IF($H$7>0,$D$7,-1E+99),IF($H$8>0,$D$8,-1E+99),IF($H$9>0,$D$9,-1E+99))-D7)/(MAX(IF($H$6>0,$D$6,-1E+99),IF($H$7>0,$D$7,-1E+99),IF($H$8>0,$D$8,-1E+99),IF($H$9>0,$D$9,-1E+99))-MIN(IF($H$6>0,$D$6,1E+99),IF($H$7>0,$D$7,1E+99),IF($H$8>0,$D$8,1E+99),IF($H$9>0,$D$9,1E+99)))),100-ABS(D7-N7)/IF(N7=0,1,N7)*100)))) -> 60 | P7: =IF(H7>0,J7*O7+K7*X7*10+L7*MAX(0,MIN(10,F7))*10,0) -> 69.5 | Q7: =IFERROR(P7/SUM($P$6:$P$9),0) -> 0.27579365 | R7: =ROUNDDOWN(ROUND(Q7*M7,0)*IF(AND(X7<3,I7>=1),0.8,1),0) -> 965 | S7: =MIN(G7,R7) -> 965 | T7: =IF(C7="SEG-03",IF(F7<7,0.65,1.4),1) -> 1 | U7: =D7*T7 -> 140 | V7: =ROUND(S7*U7,2) -> 135100 | W7: =MAX(0,R7-S7) -> 0 | X7: =MAX(0,MIN(10,E7+IF(C7="SEG-03",IF(F7<7,-2,2),0))) -> 8
A8: normal_medio | B8: C | C8: SEG-02 | D8: 160 | E8: 9 | F8: 9 | G8: 1000 | H8: 100 | I8: 0 | J8: 0.4 | K8: 0.35 | L8: 0.25 | M8: 3500 | N8: 100 | O8: =IF(H8<=0,0,MAX(0,MIN(100,IF(C8="SEG-01",IF(MAX(IF($H$6>0,$D$6,-1E+99),IF($H$7>0,$D$7,-1E+99),IF($H$8>0,$D$8,-1E+99),IF($H$9>0,$D$9,-1E+99))=MIN(IF($H$6>0,$D$6,1E+99),IF($H$7>0,$D$7,1E+99),IF($H$8>0,$D$8,1E+99),IF($H$9>0,$D$9,1E+99)),100,100*(MAX(IF($H$6>0,$D$6,-1E+99),IF($H$7>0,$D$7,-1E+99),IF($H$8>0,$D$8,-1E+99),IF($H$9>0,$D$9,-1E+99))-D8)/(MAX(IF($H$6>0,$D$6,-1E+99),IF($H$7>0,$D$7,-1E+99),IF($H$8>0,$D$8,-1E+99),IF($H$9>0,$D$9,-1E+99))-MIN(IF($H$6>0,$D$6,1E+99),IF($H$7>0,$D$7,1E+99),IF($H$8>0,$D$8,1E+99),IF($H$9>0,$D$9,1E+99)))),100-ABS(D8-N8)/IF(N8=0,1,N8)*100)))) -> 40 | P8: =IF(H8>0,J8*O8+K8*X8*10+L8*MAX(0,MIN(10,F8))*10,0) -> 70 | Q8: =IFERROR(P8/SUM($P$6:$P$9),0) -> 0.27777778 | R8: =ROUNDDOWN(ROUND(Q8*M8,0)*IF(AND(X8<3,I8>=1),0.8,1),0) -> 972 | S8: =MIN(G8,R8) -> 972 | T8: =IF(C8="SEG-03",IF(F8<7,0.65,1.4),1) -> 1 | U8: =D8*T8 -> 160 | V8: =ROUND(S8*U8,2) -> 155520 | W8: =MAX(0,R8-S8) -> 0 | X8: =MAX(0,MIN(10,E8+IF(C8="SEG-03",IF(F8<7,-2,2),0))) -> 9
A9: normal_medio | B9: D | C9: SEG-02 | D9: 200 | E9: 6 | F9: 6 | G9: 1000 | H9: 100 | I9: 0 | J9: 0.4 | K9: 0.35 | L9: 0.25 | M9: 3500 | N9: 100 | O9: =IF(H9<=0,0,MAX(0,MIN(100,IF(C9="SEG-01",IF(MAX(IF($H$6>0,$D$6,-1E+99),IF($H$7>0,$D$7,-1E+99),IF($H$8>0,$D$8,-1E+99),IF($H$9>0,$D$9,-1E+99))=MIN(IF($H$6>0,$D$6,1E+99),IF($H$7>0,$D$7,1E+99),IF($H$8>0,$D$8,1E+99),IF($H$9>0,$D$9,1E+99)),100,100*(MAX(IF($H$6>0,$D$6,-1E+99),IF($H$7>0,$D$7,-1E+99),IF($H$8>0,$D$8,-1E+99),IF($H$9>0,$D$9,-1E+99))-D9)/(MAX(IF($H$6>0,$D$6,-1E+99),IF($H$7>0,$D$7,-1E+99),IF($H$8>0,$D$8,-1E+99),IF($H$9>0,$D$9,-1E+99))-MIN(IF($H$6>0,$D$6,1E+99),IF($H$7>0,$D$7,1E+99),IF($H$8>0,$D$8,1E+99),IF($H$9>0,$D$9,1E+99)))),100-ABS(D9-N9)/IF(N9=0,1,N9)*100)))) -> 0 | P9: =IF(H9>0,J9*O9+K9*X9*10+L9*MAX(0,MIN(10,F9))*10,0) -> 36 | Q9: =IFERROR(P9/SUM($P$6:$P$9),0) -> 0.14285714 | R9: =ROUNDDOWN(ROUND(Q9*M9,0)*IF(AND(X9<3,I9>=1),0.8,1),0) -> 500 | S9: =MIN(G9,R9) -> 500 | T9: =IF(C9="SEG-03",IF(F9<7,0.65,1.4),1) -> 1 | U9: =D9*T9 -> 200 | V9: =ROUND(S9*U9,2) -> 100000 | W9: =MAX(0,R9-S9) -> 0 | X9: =MAX(0,MIN(10,E9+IF(C9="SEG-03",IF(F9<7,-2,2),0))) -> 6
A10: normal_premium | B10: A | C10: SEG-03 | D10: 220 | E10: 7 | F10: 8 | G10: 1000 | H10: 100 | I10: 0 | J10: 0.1 | K10: 0.5 | L10: 0.4 | M10: 800 | N10: 250 | O10: =IF(H10<=0,0,MAX(0,MIN(100,IF(C10="SEG-01",IF(MAX(IF($H$10>0,$D$10,-1E+99),IF($H$11>0,$D$11,-1E+99),IF($H$12>0,$D$12,-1E+99),IF($H$13>0,$D$13,-1E+99))=MIN(IF($H$10>0,$D$10,1E+99),IF($H$11>0,$D$11,1E+99),IF($H$12>0,$D$12,1E+99),IF($H$13>0,$D$13,1E+99)),100,100*(MAX(IF($H$10>0,$D$10,-1E+99),IF($H$11>0,$D$11,-1E+99),IF($H$12>0,$D$12,-1E+99),IF($H$13>0,$D$13,-1E+99))-D10)/(MAX(IF($H$10>0,$D$10,-1E+99),IF($H$11>0,$D$11,-1E+99),IF($H$12>0,$D$12,-1E+99),IF($H$13>0,$D$13,-1E+99))-MIN(IF($H$10>0,$D$10,1E+99),IF($H$11>0,$D$11,1E+99),IF($H$12>0,$D$12,1E+99),IF($H$13>0,$D$13,1E+99)))),100-ABS(D10-N10)/IF(N10=0,1,N10)*100)))) -> 88 | P10: =IF(H10>0,J10*O10+K10*X10*10+L10*MAX(0,MIN(10,F10))*10,0) -> 85.8 | Q10: =IFERROR(P10/SUM($P$10:$P$13),0) -> 0.27169094 | R10: =ROUNDDOWN(ROUND(Q10*M10,0)*IF(AND(X10<3,I10>=1),0.8,1),0) -> 217 | S10: =MIN(G10,R10) -> 217 | T10: =IF(C10="SEG-03",IF(F10<7,0.65,1.4),1) -> 1.4 | U10: =D10*T10 -> 308 | V10: =ROUND(S10*U10,2) -> 66836 | W10: =MAX(0,R10-S10) -> 0 | X10: =MAX(0,MIN(10,E10+IF(C10="SEG-03",IF(F10<7,-2,2),0))) -> 9
A11: normal_premium | B11: B | C11: SEG-03 | D11: 250 | E11: 8 | F11: 7 | G11: 1000 | H11: 100 | I11: 0 | J11: 0.1 | K11: 0.5 | L11: 0.4 | M11: 800 | N11: 250 | O11: =IF(H11<=0,0,MAX(0,MIN(100,IF(C11="SEG-01",IF(MAX(IF($H$10>0,$D$10,-1E+99),IF($H$11>0,$D$11,-1E+99),IF($H$12>0,$D$12,-1E+99),IF($H$13>0,$D$13,-1E+99))=MIN(IF($H$10>0,$D$10,1E+99),IF($H$11>0,$D$11,1E+99),IF($H$12>0,$D$12,1E+99),IF($H$13>0,$D$13,1E+99)),100,100*(MAX(IF($H$10>0,$D$10,-1E+99),IF($H$11>0,$D$11,-1E+99),IF($H$12>0,$D$12,-1E+99),IF($H$13>0,$D$13,-1E+99))-D11)/(MAX(IF($H$10>0,$D$10,-1E+99),IF($H$11>0,$D$11,-1E+99),IF($H$12>0,$D$12,-1E+99),IF($H$13>0,$D$13,-1E+99))-MIN(IF($H$10>0,$D$10,1E+99),IF($H$11>0,$D$11,1E+99),IF($H$12>0,$D$12,1E+99),IF($H$13>0,$D$13,1E+99)))),100-ABS(D11-N11)/IF(N11=0,1,N11)*100)))) -> 100 | P11: =IF(H11>0,J11*O11+K11*X11*10+L11*MAX(0,MIN(10,F11))*10,0) -> 88 | Q11: =IFERROR(P11/SUM($P$10:$P$13),0) -> 0.27865738 | R11: =ROUNDDOWN(ROUND(Q11*M11,0)*IF(AND(X11<3,I11>=1),0.8,1),0) -> 223 | S11: =MIN(G11,R11) -> 223 | T11: =IF(C11="SEG-03",IF(F11<7,0.65,1.4),1) -> 1.4 | U11: =D11*T11 -> 350 | V11: =ROUND(S11*U11,2) -> 78050 | W11: =MAX(0,R11-S11) -> 0 | X11: =MAX(0,MIN(10,E11+IF(C11="SEG-03",IF(F11<7,-2,2),0))) -> 10
A12: normal_premium | B12: C | C12: SEG-03 | D12: 300 | E12: 9 | F12: 9 | G12: 1000 | H12: 100 | I12: 0 | J12: 0.1 | K12: 0.5 | L12: 0.4 | M12: 800 | N12: 250 | O12: =IF(H12<=0,0,MAX(0,MIN(100,IF(C12="SEG-01",IF(MAX(IF($H$10>0,$D$10,-1E+99),IF($H$11>0,$D$11,-1E+99),IF($H$12>0,$D$12,-1E+99),IF($H$13>0,$D$13,-1E+99))=MIN(IF($H$10>0,$D$10,1E+99),IF($H$11>0,$D$11,1E+99),IF($H$12>0,$D$12,1E+99),IF($H$13>0,$D$13,1E+99)),100,100*(MAX(IF($H$10>0,$D$10,-1E+99),IF($H$11>0,$D$11,-1E+99),IF($H$12>0,$D$12,-1E+99),IF($H$13>0,$D$13,-1E+99))-D12)/(MAX(IF($H$10>0,$D$10,-1E+99),IF($H$11>0,$D$11,-1E+99),IF($H$12>0,$D$12,-1E+99),IF($H$13>0,$D$13,-1E+99))-MIN(IF($H$10>0,$D$10,1E+99),IF($H$11>0,$D$11,1E+99),IF($H$12>0,$D$12,1E+99),IF($H$13>0,$D$13,1E+99)))),100-ABS(D12-N12)/IF(N12=0,1,N12)*100)))) -> 80 | P12: =IF(H12>0,J12*O12+K12*X12*10+L12*MAX(0,MIN(10,F12))*10,0) -> 94 | Q12: =IFERROR(P12/SUM($P$10:$P$13),0) -> 0.29765674 | R12: =ROUNDDOWN(ROUND(Q12*M12,0)*IF(AND(X12<3,I12>=1),0.8,1),0) -> 238 | S12: =MIN(G12,R12) -> 238 | T12: =IF(C12="SEG-03",IF(F12<7,0.65,1.4),1) -> 1.4 | U12: =D12*T12 -> 420 | V12: =ROUND(S12*U12,2) -> 99960 | W12: =MAX(0,R12-S12) -> 0 | X12: =MAX(0,MIN(10,E12+IF(C12="SEG-03",IF(F12<7,-2,2),0))) -> 10
A13: normal_premium | B13: D | C13: SEG-03 | D13: 400 | E13: 6 | F13: 6 | G13: 1000 | H13: 100 | I13: 0 | J13: 0.1 | K13: 0.5 | L13: 0.4 | M13: 800 | N13: 250 | O13: =IF(H13<=0,0,MAX(0,MIN(100,IF(C13="SEG-01",IF(MAX(IF($H$10>0,$D$10,-1E+99),IF($H$11>0,$D$11,-1E+99),IF($H$12>0,$D$12,-1E+99),IF($H$13>0,$D$13,-1E+99))=MIN(IF($H$10>0,$D$10,1E+99),IF($H$11>0,$D$11,1E+99),IF($H$12>0,$D$12,1E+99),IF($H$13>0,$D$13,1E+99)),100,100*(MAX(IF($H$10>0,$D$10,-1E+99),IF($H$11>0,$D$11,-1E+99),IF($H$12>0,$D$12,-1E+99),IF($H$13>0,$D$13,-1E+99))-D13)/(MAX(IF($H$10>0,$D$10,-1E+99),IF($H$11>0,$D$11,-1E+99),IF($H$12>0,$D$12,-1E+99),IF($H$13>0,$D$13,-1E+99))-MIN(IF($H$10>0,$D$10,1E+99),IF($H$11>0,$D$11,1E+99),IF($H$12>0,$D$12,1E+99),IF($H$13>0,$D$13,1E+99)))),100-ABS(D13-N13)/IF(N13=0,1,N13)*100)))) -> 40 | P13: =IF(H13>0,J13*O13+K13*X13*10+L13*MAX(0,MIN(10,F13))*10,0) -> 48 | Q13: =IFERROR(P13/SUM($P$10:$P$13),0) -> 0.15199493 | R13: =ROUNDDOWN(ROUND(Q13*M13,0)*IF(AND(X13<3,I13>=1),0.8,1),0) -> 122 | S13: =MIN(G13,R13) -> 122 | T13: =IF(C13="SEG-03",IF(F13<7,0.65,1.4),1) -> 0.65 | U13: =D13*T13 -> 260 | V13: =ROUND(S13*U13,2) -> 31720 | W13: =MAX(0,R13-S13) -> 0 | X13: =MAX(0,MIN(10,E13+IF(C13="SEG-03",IF(F13<7,-2,2),0))) -> 4
A14: empate | B14: A | C14: SEG-01 | D14: 42 | E14: 7 | F14: 8 | G14: 1000 | H14: 100 | I14: 0 | J14: 0.7 | K14: 0.2 | L14: 0.1 | M14: 3500 | N14: 0 | O14: =IF(H14<=0,0,MAX(0,MIN(100,IF(C14="SEG-01",IF(MAX(IF($H$14>0,$D$14,-1E+99),IF($H$15>0,$D$15,-1E+99),IF($H$16>0,$D$16,-1E+99),IF($H$17>0,$D$17,-1E+99))=MIN(IF($H$14>0,$D$14,1E+99),IF($H$15>0,$D$15,1E+99),IF($H$16>0,$D$16,1E+99),IF($H$17>0,$D$17,1E+99)),100,100*(MAX(IF($H$14>0,$D$14,-1E+99),IF($H$15>0,$D$15,-1E+99),IF($H$16>0,$D$16,-1E+99),IF($H$17>0,$D$17,-1E+99))-D14)/(MAX(IF($H$14>0,$D$14,-1E+99),IF($H$15>0,$D$15,-1E+99),IF($H$16>0,$D$16,-1E+99),IF($H$17>0,$D$17,-1E+99))-MIN(IF($H$14>0,$D$14,1E+99),IF($H$15>0,$D$15,1E+99),IF($H$16>0,$D$16,1E+99),IF($H$17>0,$D$17,1E+99)))),100-ABS(D14-N14)/IF(N14=0,1,N14)*100)))) -> 100 | P14: =IF(H14>0,J14*O14+K14*X14*10+L14*MAX(0,MIN(10,F14))*10,0) -> 92 | Q14: =IFERROR(P14/SUM($P$14:$P$17),0) -> 0.24864865 | R14: =ROUNDDOWN(ROUND(Q14*M14,0)*IF(AND(X14<3,I14>=1),0.8,1),0) -> 870 | S14: =MIN(G14,R14) -> 870 | T14: =IF(C14="SEG-03",IF(F14<7,0.65,1.4),1) -> 1 | U14: =D14*T14 -> 42 | V14: =ROUND(S14*U14,2) -> 36540 | W14: =MAX(0,R14-S14) -> 0 | X14: =MAX(0,MIN(10,E14+IF(C14="SEG-03",IF(F14<7,-2,2),0))) -> 7
A15: empate | B15: B | C15: SEG-01 | D15: 42 | E15: 8 | F15: 7 | G15: 1000 | H15: 100 | I15: 0 | J15: 0.7 | K15: 0.2 | L15: 0.1 | M15: 3500 | N15: 0 | O15: =IF(H15<=0,0,MAX(0,MIN(100,IF(C15="SEG-01",IF(MAX(IF($H$14>0,$D$14,-1E+99),IF($H$15>0,$D$15,-1E+99),IF($H$16>0,$D$16,-1E+99),IF($H$17>0,$D$17,-1E+99))=MIN(IF($H$14>0,$D$14,1E+99),IF($H$15>0,$D$15,1E+99),IF($H$16>0,$D$16,1E+99),IF($H$17>0,$D$17,1E+99)),100,100*(MAX(IF($H$14>0,$D$14,-1E+99),IF($H$15>0,$D$15,-1E+99),IF($H$16>0,$D$16,-1E+99),IF($H$17>0,$D$17,-1E+99))-D15)/(MAX(IF($H$14>0,$D$14,-1E+99),IF($H$15>0,$D$15,-1E+99),IF($H$16>0,$D$16,-1E+99),IF($H$17>0,$D$17,-1E+99))-MIN(IF($H$14>0,$D$14,1E+99),IF($H$15>0,$D$15,1E+99),IF($H$16>0,$D$16,1E+99),IF($H$17>0,$D$17,1E+99)))),100-ABS(D15-N15)/IF(N15=0,1,N15)*100)))) -> 100 | P15: =IF(H15>0,J15*O15+K15*X15*10+L15*MAX(0,MIN(10,F15))*10,0) -> 93 | Q15: =IFERROR(P15/SUM($P$14:$P$17),0) -> 0.25135135 | R15: =ROUNDDOWN(ROUND(Q15*M15,0)*IF(AND(X15<3,I15>=1),0.8,1),0) -> 880 | S15: =MIN(G15,R15) -> 880 | T15: =IF(C15="SEG-03",IF(F15<7,0.65,1.4),1) -> 1 | U15: =D15*T15 -> 42 | V15: =ROUND(S15*U15,2) -> 36960 | W15: =MAX(0,R15-S15) -> 0 | X15: =MAX(0,MIN(10,E15+IF(C15="SEG-03",IF(F15<7,-2,2),0))) -> 8
A16: empate | B16: C | C16: SEG-01 | D16: 42 | E16: 9 | F16: 9 | G16: 1000 | H16: 100 | I16: 0 | J16: 0.7 | K16: 0.2 | L16: 0.1 | M16: 3500 | N16: 0 | O16: =IF(H16<=0,0,MAX(0,MIN(100,IF(C16="SEG-01",IF(MAX(IF($H$14>0,$D$14,-1E+99),IF($H$15>0,$D$15,-1E+99),IF($H$16>0,$D$16,-1E+99),IF($H$17>0,$D$17,-1E+99))=MIN(IF($H$14>0,$D$14,1E+99),IF($H$15>0,$D$15,1E+99),IF($H$16>0,$D$16,1E+99),IF($H$17>0,$D$17,1E+99)),100,100*(MAX(IF($H$14>0,$D$14,-1E+99),IF($H$15>0,$D$15,-1E+99),IF($H$16>0,$D$16,-1E+99),IF($H$17>0,$D$17,-1E+99))-D16)/(MAX(IF($H$14>0,$D$14,-1E+99),IF($H$15>0,$D$15,-1E+99),IF($H$16>0,$D$16,-1E+99),IF($H$17>0,$D$17,-1E+99))-MIN(IF($H$14>0,$D$14,1E+99),IF($H$15>0,$D$15,1E+99),IF($H$16>0,$D$16,1E+99),IF($H$17>0,$D$17,1E+99)))),100-ABS(D16-N16)/IF(N16=0,1,N16)*100)))) -> 100 | P16: =IF(H16>0,J16*O16+K16*X16*10+L16*MAX(0,MIN(10,F16))*10,0) -> 97 | Q16: =IFERROR(P16/SUM($P$14:$P$17),0) -> 0.26216216 | R16: =ROUNDDOWN(ROUND(Q16*M16,0)*IF(AND(X16<3,I16>=1),0.8,1),0) -> 918 | S16: =MIN(G16,R16) -> 918 | T16: =IF(C16="SEG-03",IF(F16<7,0.65,1.4),1) -> 1 | U16: =D16*T16 -> 42 | V16: =ROUND(S16*U16,2) -> 38556 | W16: =MAX(0,R16-S16) -> 0 | X16: =MAX(0,MIN(10,E16+IF(C16="SEG-03",IF(F16<7,-2,2),0))) -> 9
A17: empate | B17: D | C17: SEG-01 | D17: 42 | E17: 6 | F17: 6 | G17: 1000 | H17: 100 | I17: 0 | J17: 0.7 | K17: 0.2 | L17: 0.1 | M17: 3500 | N17: 0 | O17: =IF(H17<=0,0,MAX(0,MIN(100,IF(C17="SEG-01",IF(MAX(IF($H$14>0,$D$14,-1E+99),IF($H$15>0,$D$15,-1E+99),IF($H$16>0,$D$16,-1E+99),IF($H$17>0,$D$17,-1E+99))=MIN(IF($H$14>0,$D$14,1E+99),IF($H$15>0,$D$15,1E+99),IF($H$16>0,$D$16,1E+99),IF($H$17>0,$D$17,1E+99)),100,100*(MAX(IF($H$14>0,$D$14,-1E+99),IF($H$15>0,$D$15,-1E+99),IF($H$16>0,$D$16,-1E+99),IF($H$17>0,$D$17,-1E+99))-D17)/(MAX(IF($H$14>0,$D$14,-1E+99),IF($H$15>0,$D$15,-1E+99),IF($H$16>0,$D$16,-1E+99),IF($H$17>0,$D$17,-1E+99))-MIN(IF($H$14>0,$D$14,1E+99),IF($H$15>0,$D$15,1E+99),IF($H$16>0,$D$16,1E+99),IF($H$17>0,$D$17,1E+99)))),100-ABS(D17-N17)/IF(N17=0,1,N17)*100)))) -> 100 | P17: =IF(H17>0,J17*O17+K17*X17*10+L17*MAX(0,MIN(10,F17))*10,0) -> 88 | Q17: =IFERROR(P17/SUM($P$14:$P$17),0) -> 0.23783784 | R17: =ROUNDDOWN(ROUND(Q17*M17,0)*IF(AND(X17<3,I17>=1),0.8,1),0) -> 832 | S17: =MIN(G17,R17) -> 832 | T17: =IF(C17="SEG-03",IF(F17<7,0.65,1.4),1) -> 1 | U17: =D17*T17 -> 42 | V17: =ROUND(S17*U17,2) -> 34944 | W17: =MAX(0,R17-S17) -> 0 | X17: =MAX(0,MIN(10,E17+IF(C17="SEG-03",IF(F17<7,-2,2),0))) -> 6
A18: sin_stock | B18: A | C18: SEG-02 | D18: 120 | E18: 7 | F18: 8 | G18: 0 | H18: 100 | I18: 0 | J18: 0.4 | K18: 0.35 | L18: 0.25 | M18: 3500 | N18: 100 | O18: =IF(H18<=0,0,MAX(0,MIN(100,IF(C18="SEG-01",IF(MAX(IF($H$18>0,$D$18,-1E+99),IF($H$19>0,$D$19,-1E+99),IF($H$20>0,$D$20,-1E+99),IF($H$21>0,$D$21,-1E+99))=MIN(IF($H$18>0,$D$18,1E+99),IF($H$19>0,$D$19,1E+99),IF($H$20>0,$D$20,1E+99),IF($H$21>0,$D$21,1E+99)),100,100*(MAX(IF($H$18>0,$D$18,-1E+99),IF($H$19>0,$D$19,-1E+99),IF($H$20>0,$D$20,-1E+99),IF($H$21>0,$D$21,-1E+99))-D18)/(MAX(IF($H$18>0,$D$18,-1E+99),IF($H$19>0,$D$19,-1E+99),IF($H$20>0,$D$20,-1E+99),IF($H$21>0,$D$21,-1E+99))-MIN(IF($H$18>0,$D$18,1E+99),IF($H$19>0,$D$19,1E+99),IF($H$20>0,$D$20,1E+99),IF($H$21>0,$D$21,1E+99)))),100-ABS(D18-N18)/IF(N18=0,1,N18)*100)))) -> 80 | P18: =IF(H18>0,J18*O18+K18*X18*10+L18*MAX(0,MIN(10,F18))*10,0) -> 76.5 | Q18: =IFERROR(P18/SUM($P$18:$P$21),0) -> 0.30357143 | R18: =ROUNDDOWN(ROUND(Q18*M18,0)*IF(AND(X18<3,I18>=1),0.8,1),0) -> 1063 | S18: =MIN(G18,R18) -> 0 | T18: =IF(C18="SEG-03",IF(F18<7,0.65,1.4),1) -> 1 | U18: =D18*T18 -> 120 | V18: =ROUND(S18*U18,2) -> 0 | W18: =MAX(0,R18-S18) -> 1063 | X18: =MAX(0,MIN(10,E18+IF(C18="SEG-03",IF(F18<7,-2,2),0))) -> 7
A19: sin_stock | B19: B | C19: SEG-02 | D19: 140 | E19: 8 | F19: 7 | G19: 1000 | H19: 100 | I19: 0 | J19: 0.4 | K19: 0.35 | L19: 0.25 | M19: 3500 | N19: 100 | O19: =IF(H19<=0,0,MAX(0,MIN(100,IF(C19="SEG-01",IF(MAX(IF($H$18>0,$D$18,-1E+99),IF($H$19>0,$D$19,-1E+99),IF($H$20>0,$D$20,-1E+99),IF($H$21>0,$D$21,-1E+99))=MIN(IF($H$18>0,$D$18,1E+99),IF($H$19>0,$D$19,1E+99),IF($H$20>0,$D$20,1E+99),IF($H$21>0,$D$21,1E+99)),100,100*(MAX(IF($H$18>0,$D$18,-1E+99),IF($H$19>0,$D$19,-1E+99),IF($H$20>0,$D$20,-1E+99),IF($H$21>0,$D$21,-1E+99))-D19)/(MAX(IF($H$18>0,$D$18,-1E+99),IF($H$19>0,$D$19,-1E+99),IF($H$20>0,$D$20,-1E+99),IF($H$21>0,$D$21,-1E+99))-MIN(IF($H$18>0,$D$18,1E+99),IF($H$19>0,$D$19,1E+99),IF($H$20>0,$D$20,1E+99),IF($H$21>0,$D$21,1E+99)))),100-ABS(D19-N19)/IF(N19=0,1,N19)*100)))) -> 60 | P19: =IF(H19>0,J19*O19+K19*X19*10+L19*MAX(0,MIN(10,F19))*10,0) -> 69.5 | Q19: =IFERROR(P19/SUM($P$18:$P$21),0) -> 0.27579365 | R19: =ROUNDDOWN(ROUND(Q19*M19,0)*IF(AND(X19<3,I19>=1),0.8,1),0) -> 965 | S19: =MIN(G19,R19) -> 965 | T19: =IF(C19="SEG-03",IF(F19<7,0.65,1.4),1) -> 1 | U19: =D19*T19 -> 140 | V19: =ROUND(S19*U19,2) -> 135100 | W19: =MAX(0,R19-S19) -> 0 | X19: =MAX(0,MIN(10,E19+IF(C19="SEG-03",IF(F19<7,-2,2),0))) -> 8
A20: sin_stock | B20: C | C20: SEG-02 | D20: 160 | E20: 9 | F20: 9 | G20: 1000 | H20: 100 | I20: 0 | J20: 0.4 | K20: 0.35 | L20: 0.25 | M20: 3500 | N20: 100 | O20: =IF(H20<=0,0,MAX(0,MIN(100,IF(C20="SEG-01",IF(MAX(IF($H$18>0,$D$18,-1E+99),IF($H$19>0,$D$19,-1E+99),IF($H$20>0,$D$20,-1E+99),IF($H$21>0,$D$21,-1E+99))=MIN(IF($H$18>0,$D$18,1E+99),IF($H$19>0,$D$19,1E+99),IF($H$20>0,$D$20,1E+99),IF($H$21>0,$D$21,1E+99)),100,100*(MAX(IF($H$18>0,$D$18,-1E+99),IF($H$19>0,$D$19,-1E+99),IF($H$20>0,$D$20,-1E+99),IF($H$21>0,$D$21,-1E+99))-D20)/(MAX(IF($H$18>0,$D$18,-1E+99),IF($H$19>0,$D$19,-1E+99),IF($H$20>0,$D$20,-1E+99),IF($H$21>0,$D$21,-1E+99))-MIN(IF($H$18>0,$D$18,1E+99),IF($H$19>0,$D$19,1E+99),IF($H$20>0,$D$20,1E+99),IF($H$21>0,$D$21,1E+99)))),100-ABS(D20-N20)/IF(N20=0,1,N20)*100)))) -> 40 | P20: =IF(H20>0,J20*O20+K20*X20*10+L20*MAX(0,MIN(10,F20))*10,0) -> 70 | Q20: =IFERROR(P20/SUM($P$18:$P$21),0) -> 0.27777778 | R20: =ROUNDDOWN(ROUND(Q20*M20,0)*IF(AND(X20<3,I20>=1),0.8,1),0) -> 972 | S20: =MIN(G20,R20) -> 972 | T20: =IF(C20="SEG-03",IF(F20<7,0.65,1.4),1) -> 1 | U20: =D20*T20 -> 160 | V20: =ROUND(S20*U20,2) -> 155520 | W20: =MAX(0,R20-S20) -> 0 | X20: =MAX(0,MIN(10,E20+IF(C20="SEG-03",IF(F20<7,-2,2),0))) -> 9
A21: sin_stock | B21: D | C21: SEG-02 | D21: 200 | E21: 6 | F21: 6 | G21: 1000 | H21: 100 | I21: 0 | J21: 0.4 | K21: 0.35 | L21: 0.25 | M21: 3500 | N21: 100 | O21: =IF(H21<=0,0,MAX(0,MIN(100,IF(C21="SEG-01",IF(MAX(IF($H$18>0,$D$18,-1E+99),IF($H$19>0,$D$19,-1E+99),IF($H$20>0,$D$20,-1E+99),IF($H$21>0,$D$21,-1E+99))=MIN(IF($H$18>0,$D$18,1E+99),IF($H$19>0,$D$19,1E+99),IF($H$20>0,$D$20,1E+99),IF($H$21>0,$D$21,1E+99)),100,100*(MAX(IF($H$18>0,$D$18,-1E+99),IF($H$19>0,$D$19,-1E+99),IF($H$20>0,$D$20,-1E+99),IF($H$21>0,$D$21,-1E+99))-D21)/(MAX(IF($H$18>0,$D$18,-1E+99),IF($H$19>0,$D$19,-1E+99),IF($H$20>0,$D$20,-1E+99),IF($H$21>0,$D$21,-1E+99))-MIN(IF($H$18>0,$D$18,1E+99),IF($H$19>0,$D$19,1E+99),IF($H$20>0,$D$20,1E+99),IF($H$21>0,$D$21,1E+99)))),100-ABS(D21-N21)/IF(N21=0,1,N21)*100)))) -> 0 | P21: =IF(H21>0,J21*O21+K21*X21*10+L21*MAX(0,MIN(10,F21))*10,0) -> 36 | Q21: =IFERROR(P21/SUM($P$18:$P$21),0) -> 0.14285714 | R21: =ROUNDDOWN(ROUND(Q21*M21,0)*IF(AND(X21<3,I21>=1),0.8,1),0) -> 500 | S21: =MIN(G21,R21) -> 500 | T21: =IF(C21="SEG-03",IF(F21<7,0.65,1.4),1) -> 1 | U21: =D21*T21 -> 200 | V21: =ROUND(S21*U21,2) -> 100000 | W21: =MAX(0,R21-S21) -> 0 | X21: =MAX(0,MIN(10,E21+IF(C21="SEG-03",IF(F21<7,-2,2),0))) -> 6
A22: no_produjo | B22: A | C22: SEG-02 | D22: 120 | E22: 7 | F22: 8 | G22: 1000 | H22: 0 | I22: 0 | J22: 0.4 | K22: 0.35 | L22: 0.25 | M22: 3500 | N22: 100 | O22: =IF(H22<=0,0,MAX(0,MIN(100,IF(C22="SEG-01",IF(MAX(IF($H$22>0,$D$22,-1E+99),IF($H$23>0,$D$23,-1E+99),IF($H$24>0,$D$24,-1E+99),IF($H$25>0,$D$25,-1E+99))=MIN(IF($H$22>0,$D$22,1E+99),IF($H$23>0,$D$23,1E+99),IF($H$24>0,$D$24,1E+99),IF($H$25>0,$D$25,1E+99)),100,100*(MAX(IF($H$22>0,$D$22,-1E+99),IF($H$23>0,$D$23,-1E+99),IF($H$24>0,$D$24,-1E+99),IF($H$25>0,$D$25,-1E+99))-D22)/(MAX(IF($H$22>0,$D$22,-1E+99),IF($H$23>0,$D$23,-1E+99),IF($H$24>0,$D$24,-1E+99),IF($H$25>0,$D$25,-1E+99))-MIN(IF($H$22>0,$D$22,1E+99),IF($H$23>0,$D$23,1E+99),IF($H$24>0,$D$24,1E+99),IF($H$25>0,$D$25,1E+99)))),100-ABS(D22-N22)/IF(N22=0,1,N22)*100)))) -> 0 | P22: =IF(H22>0,J22*O22+K22*X22*10+L22*MAX(0,MIN(10,F22))*10,0) -> 0 | Q22: =IFERROR(P22/SUM($P$22:$P$25),0) -> 0 | R22: =ROUNDDOWN(ROUND(Q22*M22,0)*IF(AND(X22<3,I22>=1),0.8,1),0) -> 0 | S22: =MIN(G22,R22) -> 0 | T22: =IF(C22="SEG-03",IF(F22<7,0.65,1.4),1) -> 1 | U22: =D22*T22 -> 120 | V22: =ROUND(S22*U22,2) -> 0 | W22: =MAX(0,R22-S22) -> 0 | X22: =MAX(0,MIN(10,E22+IF(C22="SEG-03",IF(F22<7,-2,2),0))) -> 7
A23: no_produjo | B23: B | C23: SEG-02 | D23: 140 | E23: 8 | F23: 7 | G23: 1000 | H23: 100 | I23: 0 | J23: 0.4 | K23: 0.35 | L23: 0.25 | M23: 3500 | N23: 100 | O23: =IF(H23<=0,0,MAX(0,MIN(100,IF(C23="SEG-01",IF(MAX(IF($H$22>0,$D$22,-1E+99),IF($H$23>0,$D$23,-1E+99),IF($H$24>0,$D$24,-1E+99),IF($H$25>0,$D$25,-1E+99))=MIN(IF($H$22>0,$D$22,1E+99),IF($H$23>0,$D$23,1E+99),IF($H$24>0,$D$24,1E+99),IF($H$25>0,$D$25,1E+99)),100,100*(MAX(IF($H$22>0,$D$22,-1E+99),IF($H$23>0,$D$23,-1E+99),IF($H$24>0,$D$24,-1E+99),IF($H$25>0,$D$25,-1E+99))-D23)/(MAX(IF($H$22>0,$D$22,-1E+99),IF($H$23>0,$D$23,-1E+99),IF($H$24>0,$D$24,-1E+99),IF($H$25>0,$D$25,-1E+99))-MIN(IF($H$22>0,$D$22,1E+99),IF($H$23>0,$D$23,1E+99),IF($H$24>0,$D$24,1E+99),IF($H$25>0,$D$25,1E+99)))),100-ABS(D23-N23)/IF(N23=0,1,N23)*100)))) -> 60 | P23: =IF(H23>0,J23*O23+K23*X23*10+L23*MAX(0,MIN(10,F23))*10,0) -> 69.5 | Q23: =IFERROR(P23/SUM($P$22:$P$25),0) -> 0.3960114 | R23: =ROUNDDOWN(ROUND(Q23*M23,0)*IF(AND(X23<3,I23>=1),0.8,1),0) -> 1386 | S23: =MIN(G23,R23) -> 1000 | T23: =IF(C23="SEG-03",IF(F23<7,0.65,1.4),1) -> 1 | U23: =D23*T23 -> 140 | V23: =ROUND(S23*U23,2) -> 140000 | W23: =MAX(0,R23-S23) -> 386 | X23: =MAX(0,MIN(10,E23+IF(C23="SEG-03",IF(F23<7,-2,2),0))) -> 8
A24: no_produjo | B24: C | C24: SEG-02 | D24: 160 | E24: 9 | F24: 9 | G24: 1000 | H24: 100 | I24: 0 | J24: 0.4 | K24: 0.35 | L24: 0.25 | M24: 3500 | N24: 100 | O24: =IF(H24<=0,0,MAX(0,MIN(100,IF(C24="SEG-01",IF(MAX(IF($H$22>0,$D$22,-1E+99),IF($H$23>0,$D$23,-1E+99),IF($H$24>0,$D$24,-1E+99),IF($H$25>0,$D$25,-1E+99))=MIN(IF($H$22>0,$D$22,1E+99),IF($H$23>0,$D$23,1E+99),IF($H$24>0,$D$24,1E+99),IF($H$25>0,$D$25,1E+99)),100,100*(MAX(IF($H$22>0,$D$22,-1E+99),IF($H$23>0,$D$23,-1E+99),IF($H$24>0,$D$24,-1E+99),IF($H$25>0,$D$25,-1E+99))-D24)/(MAX(IF($H$22>0,$D$22,-1E+99),IF($H$23>0,$D$23,-1E+99),IF($H$24>0,$D$24,-1E+99),IF($H$25>0,$D$25,-1E+99))-MIN(IF($H$22>0,$D$22,1E+99),IF($H$23>0,$D$23,1E+99),IF($H$24>0,$D$24,1E+99),IF($H$25>0,$D$25,1E+99)))),100-ABS(D24-N24)/IF(N24=0,1,N24)*100)))) -> 40 | P24: =IF(H24>0,J24*O24+K24*X24*10+L24*MAX(0,MIN(10,F24))*10,0) -> 70 | Q24: =IFERROR(P24/SUM($P$22:$P$25),0) -> 0.3988604 | R24: =ROUNDDOWN(ROUND(Q24*M24,0)*IF(AND(X24<3,I24>=1),0.8,1),0) -> 1396 | S24: =MIN(G24,R24) -> 1000 | T24: =IF(C24="SEG-03",IF(F24<7,0.65,1.4),1) -> 1 | U24: =D24*T24 -> 160 | V24: =ROUND(S24*U24,2) -> 160000 | W24: =MAX(0,R24-S24) -> 396 | X24: =MAX(0,MIN(10,E24+IF(C24="SEG-03",IF(F24<7,-2,2),0))) -> 9
A25: no_produjo | B25: D | C25: SEG-02 | D25: 200 | E25: 6 | F25: 6 | G25: 1000 | H25: 100 | I25: 0 | J25: 0.4 | K25: 0.35 | L25: 0.25 | M25: 3500 | N25: 100 | O25: =IF(H25<=0,0,MAX(0,MIN(100,IF(C25="SEG-01",IF(MAX(IF($H$22>0,$D$22,-1E+99),IF($H$23>0,$D$23,-1E+99),IF($H$24>0,$D$24,-1E+99),IF($H$25>0,$D$25,-1E+99))=MIN(IF($H$22>0,$D$22,1E+99),IF($H$23>0,$D$23,1E+99),IF($H$24>0,$D$24,1E+99),IF($H$25>0,$D$25,1E+99)),100,100*(MAX(IF($H$22>0,$D$22,-1E+99),IF($H$23>0,$D$23,-1E+99),IF($H$24>0,$D$24,-1E+99),IF($H$25>0,$D$25,-1E+99))-D25)/(MAX(IF($H$22>0,$D$22,-1E+99),IF($H$23>0,$D$23,-1E+99),IF($H$24>0,$D$24,-1E+99),IF($H$25>0,$D$25,-1E+99))-MIN(IF($H$22>0,$D$22,1E+99),IF($H$23>0,$D$23,1E+99),IF($H$24>0,$D$24,1E+99),IF($H$25>0,$D$25,1E+99)))),100-ABS(D25-N25)/IF(N25=0,1,N25)*100)))) -> 0 | P25: =IF(H25>0,J25*O25+K25*X25*10+L25*MAX(0,MIN(10,F25))*10,0) -> 36 | Q25: =IFERROR(P25/SUM($P$22:$P$25),0) -> 0.20512821 | R25: =ROUNDDOWN(ROUND(Q25*M25,0)*IF(AND(X25<3,I25>=1),0.8,1),0) -> 718 | S25: =MIN(G25,R25) -> 718 | T25: =IF(C25="SEG-03",IF(F25<7,0.65,1.4),1) -> 1 | U25: =D25*T25 -> 200 | V25: =ROUND(S25*U25,2) -> 143600 | W25: =MAX(0,R25-S25) -> 0 | X25: =MAX(0,MIN(10,E25+IF(C25="SEG-03",IF(F25<7,-2,2),0))) -> 6
A26: premium_incoherente | B26: A | C26: SEG-03 | D26: 220 | E26: 7 | F26: 5 | G26: 1000 | H26: 100 | I26: 0 | J26: 0.1 | K26: 0.5 | L26: 0.4 | M26: 800 | N26: 250 | O26: =IF(H26<=0,0,MAX(0,MIN(100,IF(C26="SEG-01",IF(MAX(IF($H$26>0,$D$26,-1E+99),IF($H$27>0,$D$27,-1E+99),IF($H$28>0,$D$28,-1E+99),IF($H$29>0,$D$29,-1E+99))=MIN(IF($H$26>0,$D$26,1E+99),IF($H$27>0,$D$27,1E+99),IF($H$28>0,$D$28,1E+99),IF($H$29>0,$D$29,1E+99)),100,100*(MAX(IF($H$26>0,$D$26,-1E+99),IF($H$27>0,$D$27,-1E+99),IF($H$28>0,$D$28,-1E+99),IF($H$29>0,$D$29,-1E+99))-D26)/(MAX(IF($H$26>0,$D$26,-1E+99),IF($H$27>0,$D$27,-1E+99),IF($H$28>0,$D$28,-1E+99),IF($H$29>0,$D$29,-1E+99))-MIN(IF($H$26>0,$D$26,1E+99),IF($H$27>0,$D$27,1E+99),IF($H$28>0,$D$28,1E+99),IF($H$29>0,$D$29,1E+99)))),100-ABS(D26-N26)/IF(N26=0,1,N26)*100)))) -> 88 | P26: =IF(H26>0,J26*O26+K26*X26*10+L26*MAX(0,MIN(10,F26))*10,0) -> 53.8 | Q26: =IFERROR(P26/SUM($P$26:$P$29),0) -> 0.18957012 | R26: =ROUNDDOWN(ROUND(Q26*M26,0)*IF(AND(X26<3,I26>=1),0.8,1),0) -> 152 | S26: =MIN(G26,R26) -> 152 | T26: =IF(C26="SEG-03",IF(F26<7,0.65,1.4),1) -> 0.65 | U26: =D26*T26 -> 143 | V26: =ROUND(S26*U26,2) -> 21736 | W26: =MAX(0,R26-S26) -> 0 | X26: =MAX(0,MIN(10,E26+IF(C26="SEG-03",IF(F26<7,-2,2),0))) -> 5
A27: premium_incoherente | B27: B | C27: SEG-03 | D27: 250 | E27: 8 | F27: 7 | G27: 1000 | H27: 100 | I27: 0 | J27: 0.1 | K27: 0.5 | L27: 0.4 | M27: 800 | N27: 250 | O27: =IF(H27<=0,0,MAX(0,MIN(100,IF(C27="SEG-01",IF(MAX(IF($H$26>0,$D$26,-1E+99),IF($H$27>0,$D$27,-1E+99),IF($H$28>0,$D$28,-1E+99),IF($H$29>0,$D$29,-1E+99))=MIN(IF($H$26>0,$D$26,1E+99),IF($H$27>0,$D$27,1E+99),IF($H$28>0,$D$28,1E+99),IF($H$29>0,$D$29,1E+99)),100,100*(MAX(IF($H$26>0,$D$26,-1E+99),IF($H$27>0,$D$27,-1E+99),IF($H$28>0,$D$28,-1E+99),IF($H$29>0,$D$29,-1E+99))-D27)/(MAX(IF($H$26>0,$D$26,-1E+99),IF($H$27>0,$D$27,-1E+99),IF($H$28>0,$D$28,-1E+99),IF($H$29>0,$D$29,-1E+99))-MIN(IF($H$26>0,$D$26,1E+99),IF($H$27>0,$D$27,1E+99),IF($H$28>0,$D$28,1E+99),IF($H$29>0,$D$29,1E+99)))),100-ABS(D27-N27)/IF(N27=0,1,N27)*100)))) -> 100 | P27: =IF(H27>0,J27*O27+K27*X27*10+L27*MAX(0,MIN(10,F27))*10,0) -> 88 | Q27: =IFERROR(P27/SUM($P$26:$P$29),0) -> 0.31007752 | R27: =ROUNDDOWN(ROUND(Q27*M27,0)*IF(AND(X27<3,I27>=1),0.8,1),0) -> 248 | S27: =MIN(G27,R27) -> 248 | T27: =IF(C27="SEG-03",IF(F27<7,0.65,1.4),1) -> 1.4 | U27: =D27*T27 -> 350 | V27: =ROUND(S27*U27,2) -> 86800 | W27: =MAX(0,R27-S27) -> 0 | X27: =MAX(0,MIN(10,E27+IF(C27="SEG-03",IF(F27<7,-2,2),0))) -> 10
A28: premium_incoherente | B28: C | C28: SEG-03 | D28: 300 | E28: 9 | F28: 9 | G28: 1000 | H28: 100 | I28: 0 | J28: 0.1 | K28: 0.5 | L28: 0.4 | M28: 800 | N28: 250 | O28: =IF(H28<=0,0,MAX(0,MIN(100,IF(C28="SEG-01",IF(MAX(IF($H$26>0,$D$26,-1E+99),IF($H$27>0,$D$27,-1E+99),IF($H$28>0,$D$28,-1E+99),IF($H$29>0,$D$29,-1E+99))=MIN(IF($H$26>0,$D$26,1E+99),IF($H$27>0,$D$27,1E+99),IF($H$28>0,$D$28,1E+99),IF($H$29>0,$D$29,1E+99)),100,100*(MAX(IF($H$26>0,$D$26,-1E+99),IF($H$27>0,$D$27,-1E+99),IF($H$28>0,$D$28,-1E+99),IF($H$29>0,$D$29,-1E+99))-D28)/(MAX(IF($H$26>0,$D$26,-1E+99),IF($H$27>0,$D$27,-1E+99),IF($H$28>0,$D$28,-1E+99),IF($H$29>0,$D$29,-1E+99))-MIN(IF($H$26>0,$D$26,1E+99),IF($H$27>0,$D$27,1E+99),IF($H$28>0,$D$28,1E+99),IF($H$29>0,$D$29,1E+99)))),100-ABS(D28-N28)/IF(N28=0,1,N28)*100)))) -> 80 | P28: =IF(H28>0,J28*O28+K28*X28*10+L28*MAX(0,MIN(10,F28))*10,0) -> 94 | Q28: =IFERROR(P28/SUM($P$26:$P$29),0) -> 0.33121917 | R28: =ROUNDDOWN(ROUND(Q28*M28,0)*IF(AND(X28<3,I28>=1),0.8,1),0) -> 265 | S28: =MIN(G28,R28) -> 265 | T28: =IF(C28="SEG-03",IF(F28<7,0.65,1.4),1) -> 1.4 | U28: =D28*T28 -> 420 | V28: =ROUND(S28*U28,2) -> 111300 | W28: =MAX(0,R28-S28) -> 0 | X28: =MAX(0,MIN(10,E28+IF(C28="SEG-03",IF(F28<7,-2,2),0))) -> 10
A29: premium_incoherente | B29: D | C29: SEG-03 | D29: 400 | E29: 6 | F29: 6 | G29: 1000 | H29: 100 | I29: 0 | J29: 0.1 | K29: 0.5 | L29: 0.4 | M29: 800 | N29: 250 | O29: =IF(H29<=0,0,MAX(0,MIN(100,IF(C29="SEG-01",IF(MAX(IF($H$26>0,$D$26,-1E+99),IF($H$27>0,$D$27,-1E+99),IF($H$28>0,$D$28,-1E+99),IF($H$29>0,$D$29,-1E+99))=MIN(IF($H$26>0,$D$26,1E+99),IF($H$27>0,$D$27,1E+99),IF($H$28>0,$D$28,1E+99),IF($H$29>0,$D$29,1E+99)),100,100*(MAX(IF($H$26>0,$D$26,-1E+99),IF($H$27>0,$D$27,-1E+99),IF($H$28>0,$D$28,-1E+99),IF($H$29>0,$D$29,-1E+99))-D29)/(MAX(IF($H$26>0,$D$26,-1E+99),IF($H$27>0,$D$27,-1E+99),IF($H$28>0,$D$28,-1E+99),IF($H$29>0,$D$29,-1E+99))-MIN(IF($H$26>0,$D$26,1E+99),IF($H$27>0,$D$27,1E+99),IF($H$28>0,$D$28,1E+99),IF($H$29>0,$D$29,1E+99)))),100-ABS(D29-N29)/IF(N29=0,1,N29)*100)))) -> 40 | P29: =IF(H29>0,J29*O29+K29*X29*10+L29*MAX(0,MIN(10,F29))*10,0) -> 48 | Q29: =IFERROR(P29/SUM($P$26:$P$29),0) -> 0.16913319 | R29: =ROUNDDOWN(ROUND(Q29*M29,0)*IF(AND(X29<3,I29>=1),0.8,1),0) -> 135 | S29: =MIN(G29,R29) -> 135 | T29: =IF(C29="SEG-03",IF(F29<7,0.65,1.4),1) -> 0.65 | U29: =D29*T29 -> 260 | V29: =ROUND(S29*U29,2) -> 35100 | W29: =MAX(0,R29-S29) -> 0 | X29: =MAX(0,MIN(10,E29+IF(C29="SEG-03",IF(F29<7,-2,2),0))) -> 4
A30: demanda_no_atendida | B30: A | C30: SEG-01 | D30: 40 | E30: 7 | F30: 8 | G30: 10 | H30: 100 | I30: 0 | J30: 0.7 | K30: 0.2 | L30: 0.1 | M30: 3500 | N30: 0 | O30: =IF(H30<=0,0,MAX(0,MIN(100,IF(C30="SEG-01",IF(MAX(IF($H$30>0,$D$30,-1E+99),IF($H$31>0,$D$31,-1E+99),IF($H$32>0,$D$32,-1E+99),IF($H$33>0,$D$33,-1E+99))=MIN(IF($H$30>0,$D$30,1E+99),IF($H$31>0,$D$31,1E+99),IF($H$32>0,$D$32,1E+99),IF($H$33>0,$D$33,1E+99)),100,100*(MAX(IF($H$30>0,$D$30,-1E+99),IF($H$31>0,$D$31,-1E+99),IF($H$32>0,$D$32,-1E+99),IF($H$33>0,$D$33,-1E+99))-D30)/(MAX(IF($H$30>0,$D$30,-1E+99),IF($H$31>0,$D$31,-1E+99),IF($H$32>0,$D$32,-1E+99),IF($H$33>0,$D$33,-1E+99))-MIN(IF($H$30>0,$D$30,1E+99),IF($H$31>0,$D$31,1E+99),IF($H$32>0,$D$32,1E+99),IF($H$33>0,$D$33,1E+99)))),100-ABS(D30-N30)/IF(N30=0,1,N30)*100)))) -> 100 | P30: =IF(H30>0,J30*O30+K30*X30*10+L30*MAX(0,MIN(10,F30))*10,0) -> 92 | Q30: =IFERROR(P30/SUM($P$30:$P$33),0) -> 0.4 | R30: =ROUNDDOWN(ROUND(Q30*M30,0)*IF(AND(X30<3,I30>=1),0.8,1),0) -> 1400 | S30: =MIN(G30,R30) -> 10 | T30: =IF(C30="SEG-03",IF(F30<7,0.65,1.4),1) -> 1 | U30: =D30*T30 -> 40 | V30: =ROUND(S30*U30,2) -> 400 | W30: =MAX(0,R30-S30) -> 1390 | X30: =MAX(0,MIN(10,E30+IF(C30="SEG-03",IF(F30<7,-2,2),0))) -> 7
A31: demanda_no_atendida | B31: B | C31: SEG-01 | D31: 42 | E31: 8 | F31: 7 | G31: 10 | H31: 100 | I31: 0 | J31: 0.7 | K31: 0.2 | L31: 0.1 | M31: 3500 | N31: 0 | O31: =IF(H31<=0,0,MAX(0,MIN(100,IF(C31="SEG-01",IF(MAX(IF($H$30>0,$D$30,-1E+99),IF($H$31>0,$D$31,-1E+99),IF($H$32>0,$D$32,-1E+99),IF($H$33>0,$D$33,-1E+99))=MIN(IF($H$30>0,$D$30,1E+99),IF($H$31>0,$D$31,1E+99),IF($H$32>0,$D$32,1E+99),IF($H$33>0,$D$33,1E+99)),100,100*(MAX(IF($H$30>0,$D$30,-1E+99),IF($H$31>0,$D$31,-1E+99),IF($H$32>0,$D$32,-1E+99),IF($H$33>0,$D$33,-1E+99))-D31)/(MAX(IF($H$30>0,$D$30,-1E+99),IF($H$31>0,$D$31,-1E+99),IF($H$32>0,$D$32,-1E+99),IF($H$33>0,$D$33,-1E+99))-MIN(IF($H$30>0,$D$30,1E+99),IF($H$31>0,$D$31,1E+99),IF($H$32>0,$D$32,1E+99),IF($H$33>0,$D$33,1E+99)))),100-ABS(D31-N31)/IF(N31=0,1,N31)*100)))) -> 60 | P31: =IF(H31>0,J31*O31+K31*X31*10+L31*MAX(0,MIN(10,F31))*10,0) -> 65 | Q31: =IFERROR(P31/SUM($P$30:$P$33),0) -> 0.2826087 | R31: =ROUNDDOWN(ROUND(Q31*M31,0)*IF(AND(X31<3,I31>=1),0.8,1),0) -> 989 | S31: =MIN(G31,R31) -> 10 | T31: =IF(C31="SEG-03",IF(F31<7,0.65,1.4),1) -> 1 | U31: =D31*T31 -> 42 | V31: =ROUND(S31*U31,2) -> 420 | W31: =MAX(0,R31-S31) -> 979 | X31: =MAX(0,MIN(10,E31+IF(C31="SEG-03",IF(F31<7,-2,2),0))) -> 8
A32: demanda_no_atendida | B32: C | C32: SEG-01 | D32: 43 | E32: 9 | F32: 9 | G32: 10 | H32: 100 | I32: 0 | J32: 0.7 | K32: 0.2 | L32: 0.1 | M32: 3500 | N32: 0 | O32: =IF(H32<=0,0,MAX(0,MIN(100,IF(C32="SEG-01",IF(MAX(IF($H$30>0,$D$30,-1E+99),IF($H$31>0,$D$31,-1E+99),IF($H$32>0,$D$32,-1E+99),IF($H$33>0,$D$33,-1E+99))=MIN(IF($H$30>0,$D$30,1E+99),IF($H$31>0,$D$31,1E+99),IF($H$32>0,$D$32,1E+99),IF($H$33>0,$D$33,1E+99)),100,100*(MAX(IF($H$30>0,$D$30,-1E+99),IF($H$31>0,$D$31,-1E+99),IF($H$32>0,$D$32,-1E+99),IF($H$33>0,$D$33,-1E+99))-D32)/(MAX(IF($H$30>0,$D$30,-1E+99),IF($H$31>0,$D$31,-1E+99),IF($H$32>0,$D$32,-1E+99),IF($H$33>0,$D$33,-1E+99))-MIN(IF($H$30>0,$D$30,1E+99),IF($H$31>0,$D$31,1E+99),IF($H$32>0,$D$32,1E+99),IF($H$33>0,$D$33,1E+99)))),100-ABS(D32-N32)/IF(N32=0,1,N32)*100)))) -> 40 | P32: =IF(H32>0,J32*O32+K32*X32*10+L32*MAX(0,MIN(10,F32))*10,0) -> 55 | Q32: =IFERROR(P32/SUM($P$30:$P$33),0) -> 0.23913043 | R32: =ROUNDDOWN(ROUND(Q32*M32,0)*IF(AND(X32<3,I32>=1),0.8,1),0) -> 837 | S32: =MIN(G32,R32) -> 10 | T32: =IF(C32="SEG-03",IF(F32<7,0.65,1.4),1) -> 1 | U32: =D32*T32 -> 43 | V32: =ROUND(S32*U32,2) -> 430 | W32: =MAX(0,R32-S32) -> 827 | X32: =MAX(0,MIN(10,E32+IF(C32="SEG-03",IF(F32<7,-2,2),0))) -> 9
A33: demanda_no_atendida | B33: D | C33: SEG-01 | D33: 45 | E33: 6 | F33: 6 | G33: 10 | H33: 100 | I33: 0 | J33: 0.7 | K33: 0.2 | L33: 0.1 | M33: 3500 | N33: 0 | O33: =IF(H33<=0,0,MAX(0,MIN(100,IF(C33="SEG-01",IF(MAX(IF($H$30>0,$D$30,-1E+99),IF($H$31>0,$D$31,-1E+99),IF($H$32>0,$D$32,-1E+99),IF($H$33>0,$D$33,-1E+99))=MIN(IF($H$30>0,$D$30,1E+99),IF($H$31>0,$D$31,1E+99),IF($H$32>0,$D$32,1E+99),IF($H$33>0,$D$33,1E+99)),100,100*(MAX(IF($H$30>0,$D$30,-1E+99),IF($H$31>0,$D$31,-1E+99),IF($H$32>0,$D$32,-1E+99),IF($H$33>0,$D$33,-1E+99))-D33)/(MAX(IF($H$30>0,$D$30,-1E+99),IF($H$31>0,$D$31,-1E+99),IF($H$32>0,$D$32,-1E+99),IF($H$33>0,$D$33,-1E+99))-MIN(IF($H$30>0,$D$30,1E+99),IF($H$31>0,$D$31,1E+99),IF($H$32>0,$D$32,1E+99),IF($H$33>0,$D$33,1E+99)))),100-ABS(D33-N33)/IF(N33=0,1,N33)*100)))) -> 0 | P33: =IF(H33>0,J33*O33+K33*X33*10+L33*MAX(0,MIN(10,F33))*10,0) -> 18 | Q33: =IFERROR(P33/SUM($P$30:$P$33),0) -> 0.07826087 | R33: =ROUNDDOWN(ROUND(Q33*M33,0)*IF(AND(X33<3,I33>=1),0.8,1),0) -> 274 | S33: =MIN(G33,R33) -> 10 | T33: =IF(C33="SEG-03",IF(F33<7,0.65,1.4),1) -> 1 | U33: =D33*T33 -> 45 | V33: =ROUND(S33*U33,2) -> 450 | W33: =MAX(0,R33-S33) -> 264 | X33: =MAX(0,MIN(10,E33+IF(C33="SEG-03",IF(F33<7,-2,2),0))) -> 6
A34: reputacion_baja_2c | B34: A | C34: SEG-02 | D34: 120 | E34: 2 | F34: 8 | G34: 1000 | H34: 100 | I34: 1 | J34: 0.4 | K34: 0.35 | L34: 0.25 | M34: 3500 | N34: 100 | O34: =IF(H34<=0,0,MAX(0,MIN(100,IF(C34="SEG-01",IF(MAX(IF($H$34>0,$D$34,-1E+99),IF($H$35>0,$D$35,-1E+99),IF($H$36>0,$D$36,-1E+99),IF($H$37>0,$D$37,-1E+99))=MIN(IF($H$34>0,$D$34,1E+99),IF($H$35>0,$D$35,1E+99),IF($H$36>0,$D$36,1E+99),IF($H$37>0,$D$37,1E+99)),100,100*(MAX(IF($H$34>0,$D$34,-1E+99),IF($H$35>0,$D$35,-1E+99),IF($H$36>0,$D$36,-1E+99),IF($H$37>0,$D$37,-1E+99))-D34)/(MAX(IF($H$34>0,$D$34,-1E+99),IF($H$35>0,$D$35,-1E+99),IF($H$36>0,$D$36,-1E+99),IF($H$37>0,$D$37,-1E+99))-MIN(IF($H$34>0,$D$34,1E+99),IF($H$35>0,$D$35,1E+99),IF($H$36>0,$D$36,1E+99),IF($H$37>0,$D$37,1E+99)))),100-ABS(D34-N34)/IF(N34=0,1,N34)*100)))) -> 80 | P34: =IF(H34>0,J34*O34+K34*X34*10+L34*MAX(0,MIN(10,F34))*10,0) -> 59 | Q34: =IFERROR(P34/SUM($P$34:$P$37),0) -> 0.25159915 | R34: =ROUNDDOWN(ROUND(Q34*M34,0)*IF(AND(X34<3,I34>=1),0.8,1),0) -> 704 | S34: =MIN(G34,R34) -> 704 | T34: =IF(C34="SEG-03",IF(F34<7,0.65,1.4),1) -> 1 | U34: =D34*T34 -> 120 | V34: =ROUND(S34*U34,2) -> 84480 | W34: =MAX(0,R34-S34) -> 0 | X34: =MAX(0,MIN(10,E34+IF(C34="SEG-03",IF(F34<7,-2,2),0))) -> 2
A35: reputacion_baja_2c | B35: B | C35: SEG-02 | D35: 140 | E35: 8 | F35: 7 | G35: 1000 | H35: 100 | I35: 1 | J35: 0.4 | K35: 0.35 | L35: 0.25 | M35: 3500 | N35: 100 | O35: =IF(H35<=0,0,MAX(0,MIN(100,IF(C35="SEG-01",IF(MAX(IF($H$34>0,$D$34,-1E+99),IF($H$35>0,$D$35,-1E+99),IF($H$36>0,$D$36,-1E+99),IF($H$37>0,$D$37,-1E+99))=MIN(IF($H$34>0,$D$34,1E+99),IF($H$35>0,$D$35,1E+99),IF($H$36>0,$D$36,1E+99),IF($H$37>0,$D$37,1E+99)),100,100*(MAX(IF($H$34>0,$D$34,-1E+99),IF($H$35>0,$D$35,-1E+99),IF($H$36>0,$D$36,-1E+99),IF($H$37>0,$D$37,-1E+99))-D35)/(MAX(IF($H$34>0,$D$34,-1E+99),IF($H$35>0,$D$35,-1E+99),IF($H$36>0,$D$36,-1E+99),IF($H$37>0,$D$37,-1E+99))-MIN(IF($H$34>0,$D$34,1E+99),IF($H$35>0,$D$35,1E+99),IF($H$36>0,$D$36,1E+99),IF($H$37>0,$D$37,1E+99)))),100-ABS(D35-N35)/IF(N35=0,1,N35)*100)))) -> 60 | P35: =IF(H35>0,J35*O35+K35*X35*10+L35*MAX(0,MIN(10,F35))*10,0) -> 69.5 | Q35: =IFERROR(P35/SUM($P$34:$P$37),0) -> 0.29637527 | R35: =ROUNDDOWN(ROUND(Q35*M35,0)*IF(AND(X35<3,I35>=1),0.8,1),0) -> 1037 | S35: =MIN(G35,R35) -> 1000 | T35: =IF(C35="SEG-03",IF(F35<7,0.65,1.4),1) -> 1 | U35: =D35*T35 -> 140 | V35: =ROUND(S35*U35,2) -> 140000 | W35: =MAX(0,R35-S35) -> 37 | X35: =MAX(0,MIN(10,E35+IF(C35="SEG-03",IF(F35<7,-2,2),0))) -> 8
A36: reputacion_baja_2c | B36: C | C36: SEG-02 | D36: 160 | E36: 9 | F36: 9 | G36: 1000 | H36: 100 | I36: 1 | J36: 0.4 | K36: 0.35 | L36: 0.25 | M36: 3500 | N36: 100 | O36: =IF(H36<=0,0,MAX(0,MIN(100,IF(C36="SEG-01",IF(MAX(IF($H$34>0,$D$34,-1E+99),IF($H$35>0,$D$35,-1E+99),IF($H$36>0,$D$36,-1E+99),IF($H$37>0,$D$37,-1E+99))=MIN(IF($H$34>0,$D$34,1E+99),IF($H$35>0,$D$35,1E+99),IF($H$36>0,$D$36,1E+99),IF($H$37>0,$D$37,1E+99)),100,100*(MAX(IF($H$34>0,$D$34,-1E+99),IF($H$35>0,$D$35,-1E+99),IF($H$36>0,$D$36,-1E+99),IF($H$37>0,$D$37,-1E+99))-D36)/(MAX(IF($H$34>0,$D$34,-1E+99),IF($H$35>0,$D$35,-1E+99),IF($H$36>0,$D$36,-1E+99),IF($H$37>0,$D$37,-1E+99))-MIN(IF($H$34>0,$D$34,1E+99),IF($H$35>0,$D$35,1E+99),IF($H$36>0,$D$36,1E+99),IF($H$37>0,$D$37,1E+99)))),100-ABS(D36-N36)/IF(N36=0,1,N36)*100)))) -> 40 | P36: =IF(H36>0,J36*O36+K36*X36*10+L36*MAX(0,MIN(10,F36))*10,0) -> 70 | Q36: =IFERROR(P36/SUM($P$34:$P$37),0) -> 0.29850746 | R36: =ROUNDDOWN(ROUND(Q36*M36,0)*IF(AND(X36<3,I36>=1),0.8,1),0) -> 1045 | S36: =MIN(G36,R36) -> 1000 | T36: =IF(C36="SEG-03",IF(F36<7,0.65,1.4),1) -> 1 | U36: =D36*T36 -> 160 | V36: =ROUND(S36*U36,2) -> 160000 | W36: =MAX(0,R36-S36) -> 45 | X36: =MAX(0,MIN(10,E36+IF(C36="SEG-03",IF(F36<7,-2,2),0))) -> 9
A37: reputacion_baja_2c | B37: D | C37: SEG-02 | D37: 200 | E37: 6 | F37: 6 | G37: 1000 | H37: 100 | I37: 1 | J37: 0.4 | K37: 0.35 | L37: 0.25 | M37: 3500 | N37: 100 | O37: =IF(H37<=0,0,MAX(0,MIN(100,IF(C37="SEG-01",IF(MAX(IF($H$34>0,$D$34,-1E+99),IF($H$35>0,$D$35,-1E+99),IF($H$36>0,$D$36,-1E+99),IF($H$37>0,$D$37,-1E+99))=MIN(IF($H$34>0,$D$34,1E+99),IF($H$35>0,$D$35,1E+99),IF($H$36>0,$D$36,1E+99),IF($H$37>0,$D$37,1E+99)),100,100*(MAX(IF($H$34>0,$D$34,-1E+99),IF($H$35>0,$D$35,-1E+99),IF($H$36>0,$D$36,-1E+99),IF($H$37>0,$D$37,-1E+99))-D37)/(MAX(IF($H$34>0,$D$34,-1E+99),IF($H$35>0,$D$35,-1E+99),IF($H$36>0,$D$36,-1E+99),IF($H$37>0,$D$37,-1E+99))-MIN(IF($H$34>0,$D$34,1E+99),IF($H$35>0,$D$35,1E+99),IF($H$36>0,$D$36,1E+99),IF($H$37>0,$D$37,1E+99)))),100-ABS(D37-N37)/IF(N37=0,1,N37)*100)))) -> 0 | P37: =IF(H37>0,J37*O37+K37*X37*10+L37*MAX(0,MIN(10,F37))*10,0) -> 36 | Q37: =IFERROR(P37/SUM($P$34:$P$37),0) -> 0.15351812 | R37: =ROUNDDOWN(ROUND(Q37*M37,0)*IF(AND(X37<3,I37>=1),0.8,1),0) -> 537 | S37: =MIN(G37,R37) -> 537 | T37: =IF(C37="SEG-03",IF(F37<7,0.65,1.4),1) -> 1 | U37: =D37*T37 -> 200 | V37: =ROUND(S37*U37,2) -> 107400 | W37: =MAX(0,R37-S37) -> 0 | X37: =MAX(0,MIN(10,E37+IF(C37="SEG-03",IF(F37<7,-2,2),0))) -> 6

Sheet Componentes_v19
A1: bloque | B1: nombre | C1: valor_formula | D1: fuente
A2: capacidad | B2: corte_nivel1 | C2: ='CANTIDAD DE PRODUCCIÓN'!E5 -> 5 | D2: CANTIDAD DE PRODUCCIÓN!E5
A3: capacidad | B3: corte_nivel2 | C3: ='CANTIDAD DE PRODUCCIÓN'!E6 -> 7 | D3: CANTIDAD DE PRODUCCIÓN!E6
A4: capacidad | B4: corte_nivel3 | C4: ='CANTIDAD DE PRODUCCIÓN'!E7 -> 9 | D4: CANTIDAD DE PRODUCCIÓN!E7
A5: capacidad | B5: ensamble_nivel1 | C5: ='CANTIDAD DE PRODUCCIÓN'!E11 -> 6 | D5: CANTIDAD DE PRODUCCIÓN!E11
A6: capacidad | B6: ensamble_nivel2 | C6: ='CANTIDAD DE PRODUCCIÓN'!E12 -> 8 | D6: CANTIDAD DE PRODUCCIÓN!E12
A7: capacidad | B7: ensamble_nivel3 | C7: ='CANTIDAD DE PRODUCCIÓN'!E13 -> 12 | D7: CANTIDAD DE PRODUCCIÓN!E13
A8: capacidad | B8: acabado_nivel1 | C8: ='CANTIDAD DE PRODUCCIÓN'!E17 -> 6 | D8: CANTIDAD DE PRODUCCIÓN!E17
A9: capacidad | B9: acabado_nivel2 | C9: ='CANTIDAD DE PRODUCCIÓN'!E18 -> 7 | D9: CANTIDAD DE PRODUCCIÓN!E18
A10: capacidad | B10: acabado_nivel3 | C10: ='CANTIDAD DE PRODUCCIÓN'!E19 -> 10 | D10: CANTIDAD DE PRODUCCIÓN!E19
A11: produccion | B11: eficiencia | C11: ='CANTIDAD DE PRODUCCIÓN'!M5 -> 0.97 | D11: CANTIDAD DE PRODUCCIÓN!M5
A12: produccion | B12: capacidad | C12: ='CANTIDAD DE PRODUCCIÓN'!N5 -> 400 | D12: CANTIDAD DE PRODUCCIÓN!N5
A13: produccion | B13: produccion_lote1 | C13: ='CANTIDAD DE PRODUCCIÓN'!E56 -> 192 | D13: CANTIDAD DE PRODUCCIÓN!E56
A14: produccion | B14: produccion_lote2 | C14: ='CANTIDAD DE PRODUCCIÓN'!E57 -> 125 | D14: CANTIDAD DE PRODUCCIÓN!E57
A15: produccion | B15: produccion_lote3 | C15: ='CANTIDAD DE PRODUCCIÓN'!E58 -> 50 | D15: CANTIDAD DE PRODUCCIÓN!E58
A16: puntajes | B16: calidad1 | C16: =Motor_Puntajes!B3 -> 0 | D16: Motor_Puntajes!B3
A17: puntajes | B17: calidad2 | C17: =Motor_Puntajes!B4 -> 0 | D17: Motor_Puntajes!B4
A18: puntajes | B18: calidad3 | C18: =Motor_Puntajes!B5 -> 0 | D18: Motor_Puntajes!B5
A19: puntajes | B19: calidadEmpresa | C19: =Motor_Puntajes!B6 -> 0 | D19: Motor_Puntajes!B6
A20: puntajes | B20: eficienciaPuntaje | C20: =Motor_Puntajes!B9 -> 0 | D20: Motor_Puntajes!B9
A21: puntajes | B21: reputacion | C21: =Motor_Puntajes!B10 -> 0 | D21: Motor_Puntajes!B10
A22: puntajes | B22: saludFinanciera | C22: =Motor_Puntajes!B11 -> 0 | D22: Motor_Puntajes!B11
A23: capacidad | B23: nivel1_capacidad | C23: =ROUND(MIN(4*'CANTIDAD DE PRODUCCIÓN'!E5,4*'CANTIDAD DE PRODUCCIÓN'!E11*1.5,4*'CANTIDAD DE PRODUCCIÓN'!E17*1.5)*24*MIN(1,0.9+0*0.01+0.04),0) -> 451 | D23: 4operarios/área,4máquinas,ensamble/acabado industriales,jefatura
A24: capacidad | B24: nivel2_capacidad | C24: =ROUND(MIN(4*'CANTIDAD DE PRODUCCIÓN'!E6,4*'CANTIDAD DE PRODUCCIÓN'!E12*1.5,4*'CANTIDAD DE PRODUCCIÓN'!E18*1.5)*24*MIN(1,0.9+0*0.01+0.04),0) -> 632 | D24: 4operarios/área,4máquinas,ensamble/acabado industriales,jefatura
A25: capacidad | B25: nivel3_capacidad | C25: =ROUND(MIN(4*'CANTIDAD DE PRODUCCIÓN'!E7,4*'CANTIDAD DE PRODUCCIÓN'!E13*1.5,4*'CANTIDAD DE PRODUCCIÓN'!E19*1.5)*24*MIN(1,0.9+12*0.01+0.04),0) -> 864 | D25: 4operarios/área,4máquinas,ensamble/acabado industriales,jefatura

Sheet Cierre_oraculo_v19
A1: empresa | B1: segmento | C1: objetivo | D1: capacidad | E1: producido | F1: calidad | G1: reputacion | H1: precio | I1: precioScore | J1: puntaje | K1: participacion | L1: asignado | M1: vendido | N1: precioEfectivo | O1: ingresos | P1: consumoCuero | Q1: consumoAccesorios | R1: consumoHilo | S1: ingresoEmpresa | T1: cuentasCobrar | U1: ingresoCaja | V1: almacenaje | W1: eficiencia | X1: saludFinanciera | AA1: Códigos de entradas del fixture; no resultados JS
A2: 0 | B2: SEG-01 | C2: 90 | D2: =ROUND(MIN(4*'CANTIDAD DE PRODUCCIÓN'!E7,4*'CANTIDAD DE PRODUCCIÓN'!E13*1.5,4*'CANTIDAD DE PRODUCCIÓN'!E19*1.5)*24*MIN(1,0.9+12*0.01+0.04),0) -> 864 | E2: =MIN(C2,D2,ROUNDDOWN(250/0.3,0),1000,ROUNDDOWN(10000/6,0)) -> 90 | F2: =MAX(0,MIN(10,SUMIF(Catalogo_Decisiones!$A$2:$A$69,"INS-03",Catalogo_Decisiones!$H$2:$H$69)+SUMIF(Catalogo_Decisiones!$A$2:$A$69,"INS-05",Catalogo_Decisiones!$H$2:$H$69)+SUMIF(Catalogo_Decisiones!$A$2:$A$69,"INS-08",Catalogo_Decisiones!$H$2:$H$69)+SUMIF(Catalogo_Decisiones!$A$2:$A$69,"INF-08",Catalogo_Decisiones!$H$2:$H$69))) -> 9 | G2: =MAX(0,MIN(10,$AC$2+IF($C$4>0,2,0))) -> 6 | H2: 42.5 | I2: 100 | J2: =IF(E2>0,0.7*I2+0.2*G2*10+0.1*F2*10,0) -> 91 | K2: =IFERROR(J2/SUMIF($B$2:$B$13,B2,$J$2:$J$13),0) -> 0.48924731 | L2: =ROUND(K2*3500,0) -> 1712 | M2: =MIN(E2,L2) -> 90 | N2: =H2*1 -> 42.5 | O2: =ROUND(M2*N2,2) -> 3825 | P2: =E2*0.3 -> 27 | Q2: =E2*1 -> 90 | R2: =E2*6 -> 540 | S2: =SUM(O2:O4) -> 3825 | T2: =ROUND(S2*0.2,2) -> 765 | U2: =S2-T2 -> 3060 | V2: =SUM(E2:E4)*2-SUM(M2:M4)*2 -> 0 | W2: =$AB$2 -> 10 | X2: =$AD$2 -> 1 | AA2: INF-04 | AB2: =MAX(0,MIN(10,SUMIF(Catalogo_Decisiones!$A$2:$A$69,$AA$2,Catalogo_Decisiones!$I$2:$I$69)+SUMIF(Catalogo_Decisiones!$A$2:$A$69,$AA$3,Catalogo_Decisiones!$I$2:$I$69)+SUMIF(Catalogo_Decisiones!$A$2:$A$69,$AA$4,Catalogo_Decisiones!$I$2:$I$69)+SUMIF(Catalogo_Decisiones!$A$2:$A$69,$AA$5,Catalogo_Decisiones!$I$2:$I$69)+SUMIF(Catalogo_Decisiones!$A$2:$A$69,$AA$6,Catalogo_Decisiones!$I$2:$I$69)+SUMIF(Catalogo_Decisiones!$A$2:$A$69,$AA$7,Catalogo_Decisiones!$I$2:$I$69)+SUMIF(Catalogo_Decisiones!$A$2:$A$69,$AA$8,Catalogo_Decisiones!$I$2:$I$69)+SUMIF(Catalogo_Decisiones!$A$2:$A$69,$AA$9,Catalogo_Decisiones!$I$2:$I$69)+SUMIF(Catalogo_Decisiones!$A$2:$A$69,$AA$10,Catalogo_Decisiones!$I$2:$I$69))) -> 10 | AC2: =MAX(0,MIN(10,SUMIF(Catalogo_Decisiones!$A$2:$A$69,$AA$2,Catalogo_Decisiones!$J$2:$J$69)+SUMIF(Catalogo_Decisiones!$A$2:$A$69,$AA$3,Catalogo_Decisiones!$J$2:$J$69)+SUMIF(Catalogo_Decisiones!$A$2:$A$69,$AA$4,Catalogo_Decisiones!$J$2:$J$69)+SUMIF(Catalogo_Decisiones!$A$2:$A$69,$AA$5,Catalogo_Decisiones!$J$2:$J$69)+SUMIF(Catalogo_Decisiones!$A$2:$A$69,$AA$6,Catalogo_Decisiones!$J$2:$J$69)+SUMIF(Catalogo_Decisiones!$A$2:$A$69,$AA$7,Catalogo_Decisiones!$J$2:$J$69)+SUMIF(Catalogo_Decisiones!$A$2:$A$69,$AA$8,Catalogo_Decisiones!$J$2:$J$69)+SUMIF(Catalogo_Decisiones!$A$2:$A$69,$AA$9,Catalogo_Decisiones!$J$2:$J$69)+SUMIF(Catalogo_Decisiones!$A$2:$A$69,$AA$10,Catalogo_Decisiones!$J$2:$J$69))) -> 6 | AD2: =MAX(0,MIN(10,SUMIF(Catalogo_Decisiones!$A$2:$A$69,$AA$2,Catalogo_Decisiones!$K$2:$K$69)+SUMIF(Catalogo_Decisiones!$A$2:$A$69,$AA$3,Catalogo_Decisiones!$K$2:$K$69)+SUMIF(Catalogo_Decisiones!$A$2:$A$69,$AA$4,Catalogo_Decisiones!$K$2:$K$69)+SUMIF(Catalogo_Decisiones!$A$2:$A$69,$AA$5,Catalogo_Decisiones!$K$2:$K$69)+SUMIF(Catalogo_Decisiones!$A$2:$A$69,$AA$6,Catalogo_Decisiones!$K$2:$K$69)+SUMIF(Catalogo_Decisiones!$A$2:$A$69,$AA$7,Catalogo_Decisiones!$K$2:$K$69)+SUMIF(Catalogo_Decisiones!$A$2:$A$69,$AA$8,Catalogo_Decisiones!$K$2:$K$69)+SUMIF(Catalogo_Decisiones!$A$2:$A$69,$AA$9,Catalogo_Decisiones!$K$2:$K$69)+SUMIF(Catalogo_Decisiones!$A$2:$A$69,$AA$10,Catalogo_Decisiones!$K$2:$K$69))) -> 1
A3: 0 | B3: SEG-02 | C3: 0 | D3: =ROUND(MIN(4*'CANTIDAD DE PRODUCCIÓN'!E7,4*'CANTIDAD DE PRODUCCIÓN'!E13*1.5,4*'CANTIDAD DE PRODUCCIÓN'!E19*1.5)*24*MIN(1,0.9+12*0.01+0.04),0) -> 864 | E3: =MIN(C3,D3,ROUNDDOWN(250/0.4,0),1000,ROUNDDOWN(10000/7,0)) -> 0 | F3: =MAX(0,MIN(10,SUMIF(Catalogo_Decisiones!$A$2:$A$69,"INS-03",Catalogo_Decisiones!$H$2:$H$69)+SUMIF(Catalogo_Decisiones!$A$2:$A$69,"INS-05",Catalogo_Decisiones!$H$2:$H$69)+SUMIF(Catalogo_Decisiones!$A$2:$A$69,"INS-08",Catalogo_Decisiones!$H$2:$H$69)+SUMIF(Catalogo_Decisiones!$A$2:$A$69,"INF-09",Catalogo_Decisiones!$H$2:$H$69))) -> 10 | G3: =MAX(0,MIN(10,$AC$2+IF($C$4>0,2,0))) -> 6 | H3: 160 | I3: =MAX(0,MIN(100,100-ABS(H3-100)/100*100)) -> 40 | J3: =IF(E3>0,0.4*I3+0.35*G3*10+0.25*F3*10,0) -> 0 | K3: =IFERROR(J3/SUMIF($B$2:$B$13,B3,$J$2:$J$13),0) -> 0 | L3: =ROUND(K3*3500,0) -> 0 | M3: =MIN(E3,L3) -> 0 | N3: =H3*1 -> 160 | O3: =ROUND(M3*N3,2) -> 0 | P3: =E3*0.4 -> 0 | Q3: =E3*1 -> 0 | R3: =E3*7 -> 0 | S3: =SUM(O2:O4) -> 3825 | T3: =ROUND(S3*0.2,2) -> 765 | U3: =S3-T3 -> 3060 | V3: =SUM(E2:E4)*2-SUM(M2:M4)*2 -> 0 | W3: =$AB$2 -> 10 | X3: =$AD$2 -> 1 | AA3: INF-07
A4: 0 | B4: SEG-03 | C4: 0 | D4: =ROUND(MIN(4*'CANTIDAD DE PRODUCCIÓN'!E7,4*'CANTIDAD DE PRODUCCIÓN'!E13*1.5,4*'CANTIDAD DE PRODUCCIÓN'!E19*1.5)*24*MIN(1,0.9+12*0.01+0.04),0) -> 864 | E4: =MIN(C4,D4,ROUNDDOWN(250/0.7,0),1000,ROUNDDOWN(10000/13,0)) -> 0 | F4: =MAX(0,MIN(10,SUMIF(Catalogo_Decisiones!$A$2:$A$69,"INS-03",Catalogo_Decisiones!$H$2:$H$69)+SUMIF(Catalogo_Decisiones!$A$2:$A$69,"INS-05",Catalogo_Decisiones!$H$2:$H$69)+SUMIF(Catalogo_Decisiones!$A$2:$A$69,"INS-08",Catalogo_Decisiones!$H$2:$H$69)+SUMIF(Catalogo_Decisiones!$A$2:$A$69,"INF-10",Catalogo_Decisiones!$H$2:$H$69))) -> 10 | G4: =MAX(0,MIN(10,$AC$2+IF($C$4>0,2,0))) -> 6 | H4: 250 | I4: =MAX(0,MIN(100,100-ABS(H4-250)/250*100)) -> 100 | J4: =IF(E4>0,0.1*I4+0.5*G4*10+0.4*F4*10,0) -> 0 | K4: =IFERROR(J4/SUMIF($B$2:$B$13,B4,$J$2:$J$13),0) -> 0 | L4: =ROUND(K4*800,0) -> 0 | M4: =MIN(E4,L4) -> 0 | N4: =H4*IF(E4>0,IF(F4<7,0.65,1.4),1) -> 250 | O4: =ROUND(M4*N4,2) -> 0 | P4: =E4*0.7 -> 0 | Q4: =E4*1 -> 0 | R4: =E4*13 -> 0 | S4: =SUM(O2:O4) -> 3825 | T4: =ROUND(S4*0.2,2) -> 765 | U4: =S4-T4 -> 3060 | V4: =SUM(E2:E4)*2-SUM(M2:M4)*2 -> 0 | W4: =$AB$2 -> 10 | X4: =$AD$2 -> 1 | AA4: INF-09
A5: 1 | B5: SEG-01 | C5: 0 | D5: =ROUND(MIN(4*'CANTIDAD DE PRODUCCIÓN'!E7,4*'CANTIDAD DE PRODUCCIÓN'!E13*1.5,4*'CANTIDAD DE PRODUCCIÓN'!E19*1.5)*24*MIN(1,0.9+12*0.01+0.04),0) -> 864 | E5: =MIN(C5,D5,ROUNDDOWN(250/0.3,0),1000,ROUNDDOWN(10000/6,0)) -> 0 | F5: =MAX(0,MIN(10,SUMIF(Catalogo_Decisiones!$A$2:$A$69,"INS-03",Catalogo_Decisiones!$H$2:$H$69)+SUMIF(Catalogo_Decisiones!$A$2:$A$69,"INS-05",Catalogo_Decisiones!$H$2:$H$69)+SUMIF(Catalogo_Decisiones!$A$2:$A$69,"INS-08",Catalogo_Decisiones!$H$2:$H$69)+SUMIF(Catalogo_Decisiones!$A$2:$A$69,"INF-08",Catalogo_Decisiones!$H$2:$H$69))) -> 9 | G5: =MAX(0,MIN(10,$AC$2+IF($C$7>0,2,0))) -> 6 | H5: 42.5 | I5: 100 | J5: =IF(E5>0,0.7*I5+0.2*G5*10+0.1*F5*10,0) -> 0 | K5: =IFERROR(J5/SUMIF($B$2:$B$13,B5,$J$2:$J$13),0) -> 0 | L5: =ROUND(K5*3500,0) -> 0 | M5: =MIN(E5,L5) -> 0 | N5: =H5*1 -> 42.5 | O5: =ROUND(M5*N5,2) -> 0 | P5: =E5*0.3 -> 0 | Q5: =E5*1 -> 0 | R5: =E5*6 -> 0 | S5: =SUM(O5:O7) -> 14400 | T5: =ROUND(S5*0.2,2) -> 2880 | U5: =S5-T5 -> 11520 | V5: =SUM(E5:E7)*2-SUM(M5:M7)*2 -> 0 | W5: =$AB$2 -> 10 | X5: =$AD$2 -> 1 | AA5: RH-03
A6: 1 | B6: SEG-02 | C6: 90 | D6: =ROUND(MIN(4*'CANTIDAD DE PRODUCCIÓN'!E7,4*'CANTIDAD DE PRODUCCIÓN'!E13*1.5,4*'CANTIDAD DE PRODUCCIÓN'!E19*1.5)*24*MIN(1,0.9+12*0.01+0.04),0) -> 864 | E6: =MIN(C6,D6,ROUNDDOWN(250/0.4,0),1000,ROUNDDOWN(10000/7,0)) -> 90 | F6: =MAX(0,MIN(10,SUMIF(Catalogo_Decisiones!$A$2:$A$69,"INS-03",Catalogo_Decisiones!$H$2:$H$69)+SUMIF(Catalogo_Decisiones!$A$2:$A$69,"INS-05",Catalogo_Decisiones!$H$2:$H$69)+SUMIF(Catalogo_Decisiones!$A$2:$A$69,"INS-08",Catalogo_Decisiones!$H$2:$H$69)+SUMIF(Catalogo_Decisiones!$A$2:$A$69,"INF-09",Catalogo_Decisiones!$H$2:$H$69))) -> 10 | G6: =MAX(0,MIN(10,$AC$2+IF($C$7>0,2,0))) -> 6 | H6: 160 | I6: =MAX(0,MIN(100,100-ABS(H6-100)/100*100)) -> 40 | J6: =IF(E6>0,0.4*I6+0.35*G6*10+0.25*F6*10,0) -> 62 | K6: =IFERROR(J6/SUMIF($B$2:$B$13,B6,$J$2:$J$13),0) -> 0.47328244 | L6: =ROUND(K6*3500,0) -> 1656 | M6: =MIN(E6,L6) -> 90 | N6: =H6*1 -> 160 | O6: =ROUND(M6*N6,2) -> 14400 | P6: =E6*0.4 -> 36 | Q6: =E6*1 -> 90 | R6: =E6*7 -> 630 | S6: =SUM(O5:O7) -> 14400 | T6: =ROUND(S6*0.2,2) -> 2880 | U6: =S6-T6 -> 11520 | V6: =SUM(E5:E7)*2-SUM(M5:M7)*2 -> 0 | W6: =$AB$2 -> 10 | X6: =$AD$2 -> 1 | AA6: RH-06
A7: 1 | B7: SEG-03 | C7: 0 | D7: =ROUND(MIN(4*'CANTIDAD DE PRODUCCIÓN'!E7,4*'CANTIDAD DE PRODUCCIÓN'!E13*1.5,4*'CANTIDAD DE PRODUCCIÓN'!E19*1.5)*24*MIN(1,0.9+12*0.01+0.04),0) -> 864 | E7: =MIN(C7,D7,ROUNDDOWN(250/0.7,0),1000,ROUNDDOWN(10000/13,0)) -> 0 | F7: =MAX(0,MIN(10,SUMIF(Catalogo_Decisiones!$A$2:$A$69,"INS-03",Catalogo_Decisiones!$H$2:$H$69)+SUMIF(Catalogo_Decisiones!$A$2:$A$69,"INS-05",Catalogo_Decisiones!$H$2:$H$69)+SUMIF(Catalogo_Decisiones!$A$2:$A$69,"INS-08",Catalogo_Decisiones!$H$2:$H$69)+SUMIF(Catalogo_Decisiones!$A$2:$A$69,"INF-10",Catalogo_Decisiones!$H$2:$H$69))) -> 10 | G7: =MAX(0,MIN(10,$AC$2+IF($C$7>0,2,0))) -> 6 | H7: 250 | I7: =MAX(0,MIN(100,100-ABS(H7-250)/250*100)) -> 100 | J7: =IF(E7>0,0.1*I7+0.5*G7*10+0.4*F7*10,0) -> 0 | K7: =IFERROR(J7/SUMIF($B$2:$B$13,B7,$J$2:$J$13),0) -> 0 | L7: =ROUND(K7*800,0) -> 0 | M7: =MIN(E7,L7) -> 0 | N7: =H7*IF(E7>0,IF(F7<7,0.65,1.4),1) -> 250 | O7: =ROUND(M7*N7,2) -> 0 | P7: =E7*0.7 -> 0 | Q7: =E7*1 -> 0 | R7: =E7*13 -> 0 | S7: =SUM(O5:O7) -> 14400 | T7: =ROUND(S7*0.2,2) -> 2880 | U7: =S7-T7 -> 11520 | V7: =SUM(E5:E7)*2-SUM(M5:M7)*2 -> 0 | W7: =$AB$2 -> 10 | X7: =$AD$2 -> 1 | AA7: RH-09
A8: 2 | B8: SEG-01 | C8: 0 | D8: =ROUND(MIN(4*'CANTIDAD DE PRODUCCIÓN'!E7,4*'CANTIDAD DE PRODUCCIÓN'!E13*1.5,4*'CANTIDAD DE PRODUCCIÓN'!E19*1.5)*24*MIN(1,0.9+12*0.01+0.04),0) -> 864 | E8: =MIN(C8,D8,ROUNDDOWN(250/0.3,0),1000,ROUNDDOWN(10000/6,0)) -> 0 | F8: =MAX(0,MIN(10,SUMIF(Catalogo_Decisiones!$A$2:$A$69,"INS-03",Catalogo_Decisiones!$H$2:$H$69)+SUMIF(Catalogo_Decisiones!$A$2:$A$69,"INS-05",Catalogo_Decisiones!$H$2:$H$69)+SUMIF(Catalogo_Decisiones!$A$2:$A$69,"INS-08",Catalogo_Decisiones!$H$2:$H$69)+SUMIF(Catalogo_Decisiones!$A$2:$A$69,"INF-08",Catalogo_Decisiones!$H$2:$H$69))) -> 9 | G8: =MAX(0,MIN(10,$AC$2+IF($C$10>0,2,0))) -> 8 | H8: 42.5 | I8: 100 | J8: =IF(E8>0,0.7*I8+0.2*G8*10+0.1*F8*10,0) -> 0 | K8: =IFERROR(J8/SUMIF($B$2:$B$13,B8,$J$2:$J$13),0) -> 0 | L8: =ROUND(K8*3500,0) -> 0 | M8: =MIN(E8,L8) -> 0 | N8: =H8*1 -> 42.5 | O8: =ROUND(M8*N8,2) -> 0 | P8: =E8*0.3 -> 0 | Q8: =E8*1 -> 0 | R8: =E8*6 -> 0 | S8: =SUM(O8:O10) -> 31500 | T8: =ROUND(S8*0.2,2) -> 6300 | U8: =S8-T8 -> 25200 | V8: =SUM(E8:E10)*2-SUM(M8:M10)*2 -> 0 | W8: =$AB$2 -> 10 | X8: =$AD$2 -> 1 | AA8: RH-10A
A9: 2 | B9: SEG-02 | C9: 0 | D9: =ROUND(MIN(4*'CANTIDAD DE PRODUCCIÓN'!E7,4*'CANTIDAD DE PRODUCCIÓN'!E13*1.5,4*'CANTIDAD DE PRODUCCIÓN'!E19*1.5)*24*MIN(1,0.9+12*0.01+0.04),0) -> 864 | E9: =MIN(C9,D9,ROUNDDOWN(250/0.4,0),1000,ROUNDDOWN(10000/7,0)) -> 0 | F9: =MAX(0,MIN(10,SUMIF(Catalogo_Decisiones!$A$2:$A$69,"INS-03",Catalogo_Decisiones!$H$2:$H$69)+SUMIF(Catalogo_Decisiones!$A$2:$A$69,"INS-05",Catalogo_Decisiones!$H$2:$H$69)+SUMIF(Catalogo_Decisiones!$A$2:$A$69,"INS-08",Catalogo_Decisiones!$H$2:$H$69)+SUMIF(Catalogo_Decisiones!$A$2:$A$69,"INF-09",Catalogo_Decisiones!$H$2:$H$69))) -> 10 | G9: =MAX(0,MIN(10,$AC$2+IF($C$10>0,2,0))) -> 8 | H9: 160 | I9: =MAX(0,MIN(100,100-ABS(H9-100)/100*100)) -> 40 | J9: =IF(E9>0,0.4*I9+0.35*G9*10+0.25*F9*10,0) -> 0 | K9: =IFERROR(J9/SUMIF($B$2:$B$13,B9,$J$2:$J$13),0) -> 0 | L9: =ROUND(K9*3500,0) -> 0 | M9: =MIN(E9,L9) -> 0 | N9: =H9*1 -> 160 | O9: =ROUND(M9*N9,2) -> 0 | P9: =E9*0.4 -> 0 | Q9: =E9*1 -> 0 | R9: =E9*7 -> 0 | S9: =SUM(O8:O10) -> 31500 | T9: =ROUND(S9*0.2,2) -> 6300 | U9: =S9-T9 -> 25200 | V9: =SUM(E8:E10)*2-SUM(M8:M10)*2 -> 0 | W9: =$AB$2 -> 10 | X9: =$AD$2 -> 1 | AA9: COM-01B
A10: 2 | B10: SEG-03 | C10: 90 | D10: =ROUND(MIN(4*'CANTIDAD DE PRODUCCIÓN'!E7,4*'CANTIDAD DE PRODUCCIÓN'!E13*1.5,4*'CANTIDAD DE PRODUCCIÓN'!E19*1.5)*24*MIN(1,0.9+12*0.01+0.04),0) -> 864 | E10: =MIN(C10,D10,ROUNDDOWN(250/0.7,0),1000,ROUNDDOWN(10000/13,0)) -> 90 | F10: =MAX(0,MIN(10,SUMIF(Catalogo_Decisiones!$A$2:$A$69,"INS-03",Catalogo_Decisiones!$H$2:$H$69)+SUMIF(Catalogo_Decisiones!$A$2:$A$69,"INS-05",Catalogo_Decisiones!$H$2:$H$69)+SUMIF(Catalogo_Decisiones!$A$2:$A$69,"INS-08",Catalogo_Decisiones!$H$2:$H$69)+SUMIF(Catalogo_Decisiones!$A$2:$A$69,"INF-10",Catalogo_Decisiones!$H$2:$H$69))) -> 10 | G10: =MAX(0,MIN(10,$AC$2+IF($C$10>0,2,0))) -> 8 | H10: 250 | I10: =MAX(0,MIN(100,100-ABS(H10-250)/250*100)) -> 100 | J10: =IF(E10>0,0.1*I10+0.5*G10*10+0.4*F10*10,0) -> 90 | K10: =IFERROR(J10/SUMIF($B$2:$B$13,B10,$J$2:$J$13),0) -> 0.5 | L10: =ROUND(K10*800,0) -> 400 | M10: =MIN(E10,L10) -> 90 | N10: =H10*IF(E10>0,IF(F10<7,0.65,1.4),1) -> 350 | O10: =ROUND(M10*N10,2) -> 31500 | P10: =E10*0.7 -> 63 | Q10: =E10*1 -> 90 | R10: =E10*13 -> 1170 | S10: =SUM(O8:O10) -> 31500 | T10: =ROUND(S10*0.2,2) -> 6300 | U10: =S10-T10 -> 25200 | V10: =SUM(E8:E10)*2-SUM(M8:M10)*2 -> 0 | W10: =$AB$2 -> 10 | X10: =$AD$2 -> 1 | AA10: FIN-01B
A11: 3 | B11: SEG-01 | C11: 30 | D11: =ROUND(MIN(4*'CANTIDAD DE PRODUCCIÓN'!E7,4*'CANTIDAD DE PRODUCCIÓN'!E13*1.5,4*'CANTIDAD DE PRODUCCIÓN'!E19*1.5)*24*MIN(1,0.9+12*0.01+0.04),0) -> 864 | E11: =MIN(C11,D11,ROUNDDOWN(250/0.3,0),1000,ROUNDDOWN(10000/6,0)) -> 30 | F11: =MAX(0,MIN(10,SUMIF(Catalogo_Decisiones!$A$2:$A$69,"INS-03",Catalogo_Decisiones!$H$2:$H$69)+SUMIF(Catalogo_Decisiones!$A$2:$A$69,"INS-05",Catalogo_Decisiones!$H$2:$H$69)+SUMIF(Catalogo_Decisiones!$A$2:$A$69,"INS-08",Catalogo_Decisiones!$H$2:$H$69)+SUMIF(Catalogo_Decisiones!$A$2:$A$69,"INF-08",Catalogo_Decisiones!$H$2:$H$69))) -> 9 | G11: =MAX(0,MIN(10,$AC$2+IF($C$13>0,2,0))) -> 8 | H11: 42.5 | I11: 100 | J11: =IF(E11>0,0.7*I11+0.2*G11*10+0.1*F11*10,0) -> 95 | K11: =IFERROR(J11/SUMIF($B$2:$B$13,B11,$J$2:$J$13),0) -> 0.51075269 | L11: =ROUND(K11*3500,0) -> 1788 | M11: =MIN(E11,L11) -> 30 | N11: =H11*1 -> 42.5 | O11: =ROUND(M11*N11,2) -> 1275 | P11: =E11*0.3 -> 9 | Q11: =E11*1 -> 30 | R11: =E11*6 -> 180 | S11: =SUM(O11:O13) -> 16575 | T11: =ROUND(S11*0.2,2) -> 3315 | U11: =S11-T11 -> 13260 | V11: =SUM(E11:E13)*2-SUM(M11:M13)*2 -> 0 | W11: =$AB$2 -> 10 | X11: =$AD$2 -> 1
A12: 3 | B12: SEG-02 | C12: 30 | D12: =ROUND(MIN(4*'CANTIDAD DE PRODUCCIÓN'!E7,4*'CANTIDAD DE PRODUCCIÓN'!E13*1.5,4*'CANTIDAD DE PRODUCCIÓN'!E19*1.5)*24*MIN(1,0.9+12*0.01+0.04),0) -> 864 | E12: =MIN(C12,D12,ROUNDDOWN(250/0.4,0),1000,ROUNDDOWN(10000/7,0)) -> 30 | F12: =MAX(0,MIN(10,SUMIF(Catalogo_Decisiones!$A$2:$A$69,"INS-03",Catalogo_Decisiones!$H$2:$H$69)+SUMIF(Catalogo_Decisiones!$A$2:$A$69,"INS-05",Catalogo_Decisiones!$H$2:$H$69)+SUMIF(Catalogo_Decisiones!$A$2:$A$69,"INS-08",Catalogo_Decisiones!$H$2:$H$69)+SUMIF(Catalogo_Decisiones!$A$2:$A$69,"INF-09",Catalogo_Decisiones!$H$2:$H$69))) -> 10 | G12: =MAX(0,MIN(10,$AC$2+IF($C$13>0,2,0))) -> 8 | H12: 160 | I12: =MAX(0,MIN(100,100-ABS(H12-100)/100*100)) -> 40 | J12: =IF(E12>0,0.4*I12+0.35*G12*10+0.25*F12*10,0) -> 69 | K12: =IFERROR(J12/SUMIF($B$2:$B$13,B12,$J$2:$J$13),0) -> 0.52671756 | L12: =ROUND(K12*3500,0) -> 1844 | M12: =MIN(E12,L12) -> 30 | N12: =H12*1 -> 160 | O12: =ROUND(M12*N12,2) -> 4800 | P12: =E12*0.4 -> 12 | Q12: =E12*1 -> 30 | R12: =E12*7 -> 210 | S12: =SUM(O11:O13) -> 16575 | T12: =ROUND(S12*0.2,2) -> 3315 | U12: =S12-T12 -> 13260 | V12: =SUM(E11:E13)*2-SUM(M11:M13)*2 -> 0 | W12: =$AB$2 -> 10 | X12: =$AD$2 -> 1
A13: 3 | B13: SEG-03 | C13: 30 | D13: =ROUND(MIN(4*'CANTIDAD DE PRODUCCIÓN'!E7,4*'CANTIDAD DE PRODUCCIÓN'!E13*1.5,4*'CANTIDAD DE PRODUCCIÓN'!E19*1.5)*24*MIN(1,0.9+12*0.01+0.04),0) -> 864 | E13: =MIN(C13,D13,ROUNDDOWN(250/0.7,0),1000,ROUNDDOWN(10000/13,0)) -> 30 | F13: =MAX(0,MIN(10,SUMIF(Catalogo_Decisiones!$A$2:$A$69,"INS-03",Catalogo_Decisiones!$H$2:$H$69)+SUMIF(Catalogo_Decisiones!$A$2:$A$69,"INS-05",Catalogo_Decisiones!$H$2:$H$69)+SUMIF(Catalogo_Decisiones!$A$2:$A$69,"INS-08",Catalogo_Decisiones!$H$2:$H$69)+SUMIF(Catalogo_Decisiones!$A$2:$A$69,"INF-10",Catalogo_Decisiones!$H$2:$H$69))) -> 10 | G13: =MAX(0,MIN(10,$AC$2+IF($C$13>0,2,0))) -> 8 | H13: 250 | I13: =MAX(0,MIN(100,100-ABS(H13-250)/250*100)) -> 100 | J13: =IF(E13>0,0.1*I13+0.5*G13*10+0.4*F13*10,0) -> 90 | K13: =IFERROR(J13/SUMIF($B$2:$B$13,B13,$J$2:$J$13),0) -> 0.5 | L13: =ROUND(K13*800,0) -> 400 | M13: =MIN(E13,L13) -> 30 | N13: =H13*IF(E13>0,IF(F13<7,0.65,1.4),1) -> 350 | O13: =ROUND(M13*N13,2) -> 10500 | P13: =E13*0.7 -> 21 | Q13: =E13*1 -> 30 | R13: =E13*13 -> 390 | S13: =SUM(O11:O13) -> 16575 | T13: =ROUND(S13*0.2,2) -> 3315 | U13: =S13-T13 -> 13260 | V13: =SUM(E11:E13)*2-SUM(M11:M13)*2 -> 0 | W13: =$AB$2 -> 10 | X13: =$AD$2 -> 1

Sheet Control_de_cambios
A1: Hoja | B1: Celda | C1: Antes | D1: Después | E1: Motivo
A2: FUENTE | B2: SHA256 | C2: .codex-work\DECISIONES_SIDE_16.xlsx | D2: 3b6b42bbbc56a2534ce7e241c607d572dd38dcf02311683609497df36a0c1eb1 | E2: Base v16 autorizada; no se encontró v18; original intacto
A3: Seleccion_Ciclo0 | B3: C2 | C3: '=IFERROR(INDEX(Catalogo_Decisiones!$D$2:$D$57,MATCH($B2,Catalogo_Decisiones!$A$2:$A$57,0)),"") | D3: '=IFERROR(INDEX(Catalogo_Decisiones!$D$2:$D$69,MATCH($B2,Catalogo_Decisiones!$A$2:$A$69,0)),"") | E3: E1: incluir las 68 opciones
A4: Seleccion_Ciclo0 | B4: D2 | C4: '=IFERROR(INDEX(Catalogo_Decisiones!$F$2:$F$57,MATCH($B2,Catalogo_Decisiones!$A$2:$A$57,0)),"") | D4: '=IFERROR(INDEX(Catalogo_Decisiones!$F$2:$F$69,MATCH($B2,Catalogo_Decisiones!$A$2:$A$69,0)),"") | E4: E1: incluir las 68 opciones
A5: Seleccion_Ciclo0 | B5: E2 | C5: '=IFERROR(INDEX(Catalogo_Decisiones!$G$2:$G$57,MATCH($B2,Catalogo_Decisiones!$A$2:$A$57,0)),0) | D5: '=IFERROR(INDEX(Catalogo_Decisiones!$G$2:$G$69,MATCH($B2,Catalogo_Decisiones!$A$2:$A$69,0)),0) | E5: E1: incluir las 68 opciones
A6: Seleccion_Ciclo0 | B6: F2 | C6: '=IFERROR(INDEX(Catalogo_Decisiones!$H$2:$H$57,MATCH($B2,Catalogo_Decisiones!$A$2:$A$57,0)),0) | D6: '=IFERROR(INDEX(Catalogo_Decisiones!$H$2:$H$69,MATCH($B2,Catalogo_Decisiones!$A$2:$A$69,0)),0) | E6: E1: incluir las 68 opciones
A7: Seleccion_Ciclo0 | B7: G2 | C7: '=IFERROR(INDEX(Catalogo_Decisiones!$I$2:$I$57,MATCH($B2,Catalogo_Decisiones!$A$2:$A$57,0)),0) | D7: '=IFERROR(INDEX(Catalogo_Decisiones!$I$2:$I$69,MATCH($B2,Catalogo_Decisiones!$A$2:$A$69,0)),0) | E7: E1: incluir las 68 opciones
A8: Seleccion_Ciclo0 | B8: H2 | C8: '=IFERROR(INDEX(Catalogo_Decisiones!$J$2:$J$57,MATCH($B2,Catalogo_Decisiones!$A$2:$A$57,0)),0) | D8: '=IFERROR(INDEX(Catalogo_Decisiones!$J$2:$J$69,MATCH($B2,Catalogo_Decisiones!$A$2:$A$69,0)),0) | E8: E1: incluir las 68 opciones
A9: Seleccion_Ciclo0 | B9: I2 | C9: '=IFERROR(INDEX(Catalogo_Decisiones!$K$2:$K$57,MATCH($B2,Catalogo_Decisiones!$A$2:$A$57,0)),0) | D9: '=IFERROR(INDEX(Catalogo_Decisiones!$K$2:$K$69,MATCH($B2,Catalogo_Decisiones!$A$2:$A$69,0)),0) | E9: E1: incluir las 68 opciones
A10: Seleccion_Ciclo0 | B10: C3 | C10: '=IFERROR(INDEX(Catalogo_Decisiones!$D$2:$D$57,MATCH($B3,Catalogo_Decisiones!$A$2:$A$57,0)),"") | D10: '=IFERROR(INDEX(Catalogo_Decisiones!$D$2:$D$69,MATCH($B3,Catalogo_Decisiones!$A$2:$A$69,0)),"") | E10: E1: incluir las 68 opciones
A11: Seleccion_Ciclo0 | B11: D3 | C11: '=IFERROR(INDEX(Catalogo_Decisiones!$F$2:$F$57,MATCH($B3,Catalogo_Decisiones!$A$2:$A$57,0)),"") | D11: '=IFERROR(INDEX(Catalogo_Decisiones!$F$2:$F$69,MATCH($B3,Catalogo_Decisiones!$A$2:$A$69,0)),"") | E11: E1: incluir las 68 opciones
A12: Seleccion_Ciclo0 | B12: E3 | C12: '=IFERROR(INDEX(Catalogo_Decisiones!$G$2:$G$57,MATCH($B3,Catalogo_Decisiones!$A$2:$A$57,0)),0) | D12: '=IFERROR(INDEX(Catalogo_Decisiones!$G$2:$G$69,MATCH($B3,Catalogo_Decisiones!$A$2:$A$69,0)),0) | E12: E1: incluir las 68 opciones
... A106: Lotes_Produccion | B106: I4 | C106: '=IFERROR(INDEX(Catalogo_Decisiones!$H$2:$H$57,MATCH($D4,Catalogo_Decisiones!$A$2:$A$57,0)),0)+IFERROR(INDEX(Catalogo_Decisiones!$H$2:$H$57,MATCH($E4,Catalogo_Decisiones!$A$2:$A$57,0)),0)+IFERROR(INDEX(Catalogo_Decisiones!$H$2:$H$57,MATCH($F4,Catalogo_Decisiones!$A$2:$A$57,0)),0)+IFERROR(INDEX(Catalogo_Decisiones!$H$2:$H$57,MATCH($G4,Catalogo_Decisiones!$A$2:$A$57,0)),0) | D106: '=IFERROR(INDEX(Catalogo_Decisiones!$H$2:$H$69,MATCH($D4,Catalogo_Decisiones!$A$2:$A$69,0)),0)+IFERROR(INDEX(Catalogo_Decisiones!$H$2:$H$69,MATCH($E4,Catalogo_Decisiones!$A$2:$A$69,0)),0)+IFERROR(INDEX(Catalogo_Decisiones!$H$2:$H$69,MATCH($F4,Catalogo_Decisiones!$A$2:$A$69,0)),0)+IFERROR(INDEX(Catalogo_Decisiones!$H$2:$H$69,MATCH($G4,Catalogo_Decisiones!$A$2:$A$69,0)),0) | E106: E1: incluir las 68 opciones
A107: Catalogo_Decisiones | B107: G58 | C107: S/0 | D107: 0 | E107: E2: moneda textual a número, formato monetario
A108: Catalogo_Decisiones | B108: G59 | C108: S/0 | D108: 0 | E108: E2: moneda textual a número, formato monetario
A109: Catalogo_Decisiones | B109: K59 | C109: '=+1 | D109: 1 | E109: E2: fórmula constante a literal numérico; original sí evaluaba como número
A110: Catalogo_Decisiones | B110: G60 | C110: S/0 | D110: 0 | E110: E2: moneda textual a número, formato monetario
A111: Catalogo_Decisiones | B111: G61 | C111: S/0 | D111: 0 | E111: E2: moneda textual a número, formato monetario
A112: Catalogo_Decisiones | B112: K61 | C112: '=+1 | D112: 1 | E112: E2: fórmula constante a literal numérico; original sí evaluaba como número
A113: Catalogo_Decisiones | B113: G62 | C113: S/5 | D113: 5 | E113: E2: moneda textual a número, formato monetario
A114: Catalogo_Decisiones | B114: J62 | C114: '=+1 | D114: 1 | E114: E2: fórmula constante a literal numérico; original sí evaluaba como número
A115: Catalogo_Decisiones | B115: G63 | C115: S/10 | D115: 10 | E115: E2: moneda textual a número, formato monetario
A116: Catalogo_Decisiones | B116: J63 | C116: '=+2 | D116: 2 | E116: E2: fórmula constante a literal numérico; original sí evaluaba como número
A117: Catalogo_Decisiones | B117: G64 | C117: S/0 | D117: 0 | E117: E2: moneda textual a número, formato monetario
A118: Catalogo_Decisiones | B118: K64 | C118: '=+1 | D118: 1 | E118: E2: fórmula constante a literal numérico; original sí evaluaba como número
... A129: Catalogo_Decisiones | B129: I69 | C129: '=+2 | D129: 2 | E129: E2: fórmula constante a literal numérico; original sí evaluaba como número
A130: Seleccion_Ciclo0 | B130: A24 | D130: Método de depreciación | E130: E1: exponer grupo existente del catálogo, sin decisión nueva
A131: Seleccion_Ciclo0 | B131: C24 | D131: '=IFERROR(INDEX(Catalogo_Decisiones!$D$2:$D$69,MATCH($B24,Catalogo_Decisiones!$A$2:$A$69,0)),"") | E131: E1: búsqueda de grupos existentes
A132: Seleccion_Ciclo0 | B132: D24 | D132: '=IFERROR(INDEX(Catalogo_Decisiones!$F$2:$F$69,MATCH($B24,Catalogo_Decisiones!$A$2:$A$69,0)),"") | E132: E1: búsqueda de grupos existentes
A133: Seleccion_Ciclo0 | B133: E24 | D133: '=IFERROR(INDEX(Catalogo_Decisiones!$G$2:$G$69,MATCH($B24,Catalogo_Decisiones!$A$2:$A$69,0)),0) | E133: E1: búsqueda de grupos existentes
A134: Seleccion_Ciclo0 | B134: F24 | D134: '=IFERROR(INDEX(Catalogo_Decisiones!$H$2:$H$69,MATCH($B24,Catalogo_Decisiones!$A$2:$A$69,0)),0) | E134: E1: búsqueda de grupos existentes
A135: Seleccion_Ciclo0 | B135: G24 | D135: '=IFERROR(INDEX(Catalogo_Decisiones!$I$2:$I$69,MATCH($B24,Catalogo_Decisiones!$A$2:$A$69,0)),0) | E135: E1: búsqueda de grupos existentes
A136: Seleccion_Ciclo0 | B136: H24 | D136: '=IFERROR(INDEX(Catalogo_Decisiones!$J$2:$J$69,MATCH($B24,Catalogo_Decisiones!$A$2:$A$69,0)),0) | E136: E1: búsqueda de grupos existentes
A137: Seleccion_Ciclo0 | B137: I24 | D137: '=IFERROR(INDEX(Catalogo_Decisiones!$K$2:$K$69,MATCH($B24,Catalogo_Decisiones!$A$2:$A$69,0)),0) | E137: E1: búsqueda de grupos existentes
A138: Seleccion_Ciclo0 | B138: A25 | D138: Garantía | E138: E1: exponer grupo existente del catálogo, sin decisión nueva
A139: Seleccion_Ciclo0 | B139: C25 | D139: '=IFERROR(INDEX(Catalogo_Decisiones!$D$2:$D$69,MATCH($B25,Catalogo_Decisiones!$A$2:$A$69,0)),"") | E139: E1: búsqueda de grupos existentes
A140: Seleccion_Ciclo0 | B140: D25 | D140: '=IFERROR(INDEX(Catalogo_Decisiones!$F$2:$F$69,MATCH($B25,Catalogo_Decisiones!$A$2:$A$69,0)),"") | E140: E1: búsqueda de grupos existentes
A141: Seleccion_Ciclo0 | B141: E25 | D141: '=IFERROR(INDEX(Catalogo_Decisiones!$G$2:$G$69,MATCH($B25,Catalogo_Decisiones!$A$2:$A$69,0)),0) | E141: E1: búsqueda de grupos existentes
... A161: Seleccion_Ciclo0 | B161: I27 | D161: '=IFERROR(INDEX(Catalogo_Decisiones!$K$2:$K$69,MATCH($B27,Catalogo_Decisiones!$A$2:$A$69,0)),0) | E161: E1: búsqueda de grupos existentes
A162: Lotes_Produccion | B162: I2 | C162: '=IFERROR(INDEX(Catalogo_Decisiones!$H$2:$H$69,MATCH($D2,Catalogo_Decisiones!$A$2:$A$69,0)),0)+IFERROR(INDEX(Catalogo_Decisiones!$H$2:$H$69,MATCH($E2,Catalogo_Decisiones!$A$2:$A$69,0)),0)+IFERROR(INDEX(Catalogo_Decisiones!$H$2:$H$69,MATCH($F2,Catalogo_Decisiones!$A$2:$A$69,0)),0)+IFERROR(INDEX(Catalogo_Decisiones!$H$2:$H$69,MATCH($G2,Catalogo_Decisiones!$A$2:$A$69,0)),0) | D162: '=MAX(0,MIN(10,IFERROR(INDEX(Catalogo_Decisiones!$H$2:$H$69,MATCH($D2,Catalogo_Decisiones!$A$2:$A$69,0)),0)+IFERROR(INDEX(Catalogo_Decisiones!$H$2:$H$69,MATCH($E2,Catalogo_Decisiones!$A$2:$A$69,0)),0)+IFERROR(INDEX(Catalogo_Decisiones!$H$2:$H$69,MATCH($F2,Catalogo_Decisiones!$A$2:$A$69,0)),0)+IFERROR(INDEX(Catalogo_Decisiones!$H$2:$H$69,MATCH($G2,Catalogo_Decisiones!$A$2:$A$69,0)),0))) | E162: E9: calidad acotada 0–10
A163: Lotes_Produccion | B163: J2 | C163: '=IFS($B2="SEG-01",0,$B2="SEG-02",4,$B2="SEG-03",7,TRUE(),0) | D163: '=IF(B2="SEG-03",7,IF(B2="SEG-02",4,0)) | E163: Compatibilidad: IF anidado en vez de IFS sin prefijo
A164: Lotes_Produccion | B164: M2 | D164: 42.5 | E164: E3: precio elegido; supuesto inicial por segmento, editable
A165: Lotes_Produccion | B165: N2 | D165: '=IF(B2="","",IF(AND(M2>=IF(B2="SEG-01",40,IF(B2="SEG-02",120,220)),M2<=IF(B2="SEG-01",45,400)),"Válido","Fuera de rango")) | E165: E3: validación visible de precio
A166: Lotes_Produccion | B166: N2 | C166: '=IF(B2="","",IF(AND(M2>=IF(B2="SEG-01",40,IF(B2="SEG-02",120,220)),M2<=IF(B2="SEG-01",45,400)),"Válido","Fuera de rango")) | D166: '=IF(B2="","",IF(AND(M2>=IF(B2="SEG-01",40,IF(B2="SEG-02",120,220)),M2<=IF(B2="SEG-01",45,IF(B2="SEG-02",200,400))),"Válido","Fuera de rango")) | E166: E3: límites económicos40–45,medio120–200,premium220–400
A167: Lotes_Produccion | B167: O2 | D167: '=M2*IF(B2="SEG-03",IF(I2<7,0.65,1.4),1) | E167: E9: Premium<7 penaliza, >=7 premia
A168: Lotes_Produccion | B168: I3 | C168: '=IFERROR(INDEX(Catalogo_Decisiones!$H$2:$H$69,MATCH($D3,Catalogo_Decisiones!$A$2:$A$69,0)),0)+IFERROR(INDEX(Catalogo_Decisiones!$H$2:$H$69,MATCH($E3,Catalogo_Decisiones!$A$2:$A$69,0)),0)+IFERROR(INDEX(Catalogo_Decisiones!$H$2:$H$69,MATCH($F3,Catalogo_Decisiones!$A$2:$A$69,0)),0)+IFERROR(INDEX(Catalogo_Decisiones!$H$2:$H$69,MATCH($G3,Catalogo_Decisiones!$A$2:$A$69,0)),0) | D168: '=MAX(0,MIN(10,IFERROR(INDEX(Catalogo_Decisiones!$H$2:$H$69,MATCH($D3,Catalogo_Decisiones!$A$2:$A$69,0)),0)+IFERROR(INDEX(Catalogo_Decisiones!$H$2:$H$69,MATCH($E3,Catalogo_Decisiones!$A$2:$A$69,0)),0)+IFERROR(INDEX(Catalogo_Decisiones!$H$2:$H$69,MATCH($F3,Catalogo_Decisiones!$A$2:$A$69,0)),0)+IFERROR(INDEX(Catalogo_Decisiones!$H$2:$H$69,MATCH($G3,Catalogo_Decisiones!$A$2:$A$69,0)),0))) | E168: E9: calidad acotada 0–10
A169: Lotes_Produccion | B169: J3 | C169: '=IFS($B3="SEG-01",0,$B3="SEG-02",4,$B3="SEG-03",7,TRUE(),0) | D169: '=IF(B3="SEG-03",7,IF(B3="SEG-02",4,0)) | E169: Compatibilidad: IF anidado en vez de IFS sin prefijo
A170: Lotes_Produccion | B170: M3 | D170: 160 | E170: E3: precio elegido; supuesto inicial por segmento, editable
A171: Lotes_Produccion | B171: N3 | D171: '=IF(B3="","",IF(AND(M3>=IF(B3="SEG-01",40,IF(B3="SEG-02",120,220)),M3<=IF(B3="SEG-01",45,400)),"Válido","Fuera de rango")) | E171: E3: validación visible de precio
A172: Lotes_Produccion | B172: N3 | C172: '=IF(B3="","",IF(AND(M3>=IF(B3="SEG-01",40,IF(B3="SEG-02",120,220)),M3<=IF(B3="SEG-01",45,400)),"Válido","Fuera de rango")) | D172: '=IF(B3="","",IF(AND(M3>=IF(B3="SEG-01",40,IF(B3="SEG-02",120,220)),M3<=IF(B3="SEG-01",45,IF(B3="SEG-02",200,400))),"Válido","Fuera de rango")) | E172: E3: límites económicos40–45,medio120–200,premium220–400
A173: Lotes_Produccion | B173: O3 | D173: '=M3*IF(B3="SEG-03",IF(I3<7,0.65,1.4),1) | E173: E9: Premium<7 penaliza, >=7 premia
A174: Lotes_Produccion | B174: I4 | C174: '=IFERROR(INDEX(Catalogo_Decisiones!$H$2:$H$69,MATCH($D4,Catalogo_Decisiones!$A$2:$A$69,0)),0)+IFERROR(INDEX(Catalogo_Decisiones!$H$2:$H$69,MATCH($E4,Catalogo_Decisiones!$A$2:$A$69,0)),0)+IFERROR(INDEX(Catalogo_Decisiones!$H$2:$H$69,MATCH($F4,Catalogo_Decisiones!$A$2:$A$69,0)),0)+IFERROR(INDEX(Catalogo_Decisiones!$H$2:$H$69,MATCH($G4,Catalogo_Decisiones!$A$2:$A$69,0)),0) | D174: '=MAX(0,MIN(10,IFERROR(INDEX(Catalogo_Decisiones!$H$2:$H$69,MATCH($D4,Catalogo_Decisiones!$A$2:$A$69,0)),0)+IFERROR(INDEX(Catalogo_Decisiones!$H$2:$H$69,MATCH($E4,Catalogo_Decisiones!$A$2:$A$69,0)),0)+IFERROR(INDEX(Catalogo_Decisiones!$H$2:$H$69,MATCH($F4,Catalogo_Decisiones!$A$2:$A$69,0)),0)+IFERROR(INDEX(Catalogo_Decisiones!$H$2:$H$69,MATCH($G4,Catalogo_Decisiones!$A$2:$A$69,0)),0))) | E174: E9: calidad acotada 0–10
A175: Lotes_Produccion | B175: J4 | C175: '=IFS($B4="SEG-01",0,$B4="SEG-02",4,$B4="SEG-03",7,TRUE(),0) | D175: '=IF(B4="SEG-03",7,IF(B4="SEG-02",4,0)) | E175: Compatibilidad: IF anidado en vez de IFS sin prefijo
A176: Lotes_Produccion | B176: M4 | D176: 250 | E176: E3: precio elegido; supuesto inicial por segmento, editable
A177: Lotes_Produccion | B177: N4 | D177: '=IF(B4="","",IF(AND(M4>=IF(B4="SEG-01",40,IF(B4="SEG-02",120,220)),M4<=IF(B4="SEG-01",45,400)),"Válido","Fuera de rango")) | E177: E3: validación visible de precio
A178: Lotes_Produccion | B178: N4 | C178: '=IF(B4="","",IF(AND(M4>=IF(B4="SEG-01",40,IF(B4="SEG-02",120,220)),M4<=IF(B4="SEG-01",45,400)),"Válido","Fuera de rango")) | D178: '=IF(B4="","",IF(AND(M4>=IF(B4="SEG-01",40,IF(B4="SEG-02",120,220)),M4<=IF(B4="SEG-01",45,IF(B4="SEG-02",200,400))),"Válido","Fuera de rango")) | E178: E3: límites económicos40–45,medio120–200,premium220–400
A179: Lotes_Produccion | B179: O4 | D179: '=M4*IF(B4="SEG-03",IF(I4<7,0.65,1.4),1) | E179: E9: Premium<7 penaliza, >=7 premia
A180: Lotes_Produccion | B180: M1 | D180: Precio elegido (S/ por unidad) | E180: E3: único campo nuevo permitido
A181: Lotes_Produccion | B181: N1 | D181: Validación de precio | E181: E3
A182: Lotes_Produccion | B182: O1 | D182: Precio efectivo tras consecuencias | E182: E9/CONS01/02
A183: Motor_Puntajes | B183: B9 | C183: '=SUM(Seleccion_Ciclo0!G2:G15) | D183: '=MAX(0,MIN(10,SUM(Seleccion_Ciclo0!G2:G15,Seleccion_Ciclo0!G24:G27))) | E183: E6/E9: catálogo única fuente, tope0–10
A184: Motor_Puntajes | B184: B10 | C184: '=SUM(Seleccion_Ciclo0!H2:H15) | D184: '=MAX(0,MIN(10,SUM(Seleccion_Ciclo0!H2:H15,Seleccion_Ciclo0!H24:H27))) | E184: E6/E9: catálogo única fuente, tope0–10
A185: Motor_Puntajes | B185: B11 | C185: '=SUM(Seleccion_Ciclo0!I2:I15) | D185: '=MAX(0,MIN(10,SUM(Seleccion_Ciclo0!I2:I15,Seleccion_Ciclo0!I24:I27))) | E185: E6/E9: catálogo única fuente, tope0–10
A186: Matriz_Consecuencias | B186: C2 | C186: < 4 y Segmento = Premium | D186: < 7 y Segmento = Premium | E186: E9: cerrar hueco4–6.99; supuesto documentado
A187: CANTIDAD DE PRODUCCIÓN | B187: A75 | C187: Calculo de Reputacion | D187: Reputación canónica del catálogo (0–10) | E187: E6: retirar mezcla producción/publicidad/puntajes
A188: CANTIDAD DE PRODUCCIÓN | B188: C75 | C188: '=F51*10 | D188: 0 | E188: E6: componente histórico obsoleto, sin doble publicidad
A189: CANTIDAD DE PRODUCCIÓN | B189: D75 | C189: '=M10*10 | D189: 0 | E189: E6: componente histórico obsoleto, sin doble publicidad
A190: CANTIDAD DE PRODUCCIÓN | B190: E75 | C190: '=AVERAGE(H65,H68,H71)*10 | D190: 0 | E190: E6: componente histórico obsoleto, sin doble publicidad
A191: CANTIDAD DE PRODUCCIÓN | B191: F75 | C191: '=B73/10000*10 | D191: 0 | E191: E6: componente histórico obsoleto, sin doble publicidad
A192: CANTIDAD DE PRODUCCIÓN | B192: G75 | C192: '=SUM(C75:F75) | D192: '=Motor_Puntajes!B10 | E192: E6: única reputación de decisiones, acotada
A193: CANTIDAD DE PRODUCCIÓN | B193: A123 | C193: Calculo de Reputacion | D193: Reputación canónica del catálogo (0–10) | E193: E6: retirar mezcla producción/publicidad/puntajes
A194: CANTIDAD DE PRODUCCIÓN | B194: C123 | C194: '=F51*10 | D194: 0 | E194: E6: componente histórico obsoleto, sin doble publicidad
A195: CANTIDAD DE PRODUCCIÓN | B195: D123 | C195: '=M10*10 | D195: 0 | E195: E6: componente histórico obsoleto, sin doble publicidad
A196: CANTIDAD DE PRODUCCIÓN | B196: E123 | C196: '=AVERAGE(H65,H68,H71)*10 | D196: 0 | E196: E6: componente histórico obsoleto, sin doble publicidad
A197: CANTIDAD DE PRODUCCIÓN | B197: F123 | C197: '=B73/10000*10 | D197: 0 | E197: E6: componente histórico obsoleto, sin doble publicidad
A198: CANTIDAD DE PRODUCCIÓN | B198: G123 | C198: '=SUM(C123:F123) | D198: '=Motor_Puntajes!B10 | E198: E6: única reputación de decisiones, acotada
A199: CANTIDAD DE PRODUCCIÓN | B199: M10 | C199: '=L10/L9 | D199: '=IFERROR(L10/L9,0) | E199: Proteger ausencia de personal
A200: CANTIDAD DE PRODUCCIÓN | B200: M5 | C200: '=K7+(F7+F13+F19)/100+4%*F21 | D200: '=MIN(1,K7+SUM(F7,F13:H13,F19:H19)/100+4%*F21) | E200: E7: bono por TODOS N3; SUPUESTO eficiencia máxima100%
A201: Costos De Producción | B201: A65 | C201: Calculo de Reputacion | D201: Reputación canónica del catálogo (0–10) | E201: E6: retirar mezcla producción/publicidad/puntajes
A202: Costos De Producción | B202: C65 | C202: '=F48*10 | D202: 0 | E202: E6: componente histórico obsoleto, sin doble publicidad
A203: Costos De Producción | B203: D65 | C203: '=M10*10 | D203: 0 | E203: E6: componente histórico obsoleto, sin doble publicidad
A204: Costos De Producción | B204: E65 | C204: '=AVERAGE(H56,H58,H61)*10 | D204: 0 | E204: E6: componente histórico obsoleto, sin doble publicidad
A205: Costos De Producción | B205: F65 | C205: '=B63/10000*10 | D205: 0 | E205: E6: componente histórico obsoleto, sin doble publicidad
A206: Costos De Producción | B206: G65 | C206: '=SUM(C65:F65) | D206: '=Motor_Puntajes!B10 | E206: E6: única reputación de decisiones, acotada
A207: Costos De Producción | B207: A113 | C207: Calculo de Reputacion | D207: Reputación canónica del catálogo (0–10) | E207: E6: retirar mezcla producción/publicidad/puntajes
A208: Costos De Producción | B208: C113 | C208: '=F48*10 | D208: 0 | E208: E6: componente histórico obsoleto, sin doble publicidad
A209: Costos De Producción | B209: D113 | C209: '=M10*10 | D209: 0 | E209: E6: componente histórico obsoleto, sin doble publicidad
A210: Costos De Producción | B210: E113 | C210: '=AVERAGE(H56,H58,H61)*10 | D210: 0 | E210: E6: componente histórico obsoleto, sin doble publicidad
A211: Costos De Producción | B211: F113 | C211: '=B63/10000*10 | D211: 0 | E211: E6: componente histórico obsoleto, sin doble publicidad
A212: Costos De Producción | B212: G113 | C212: '=SUM(C113:F113) | D212: '=Motor_Puntajes!B10 | E212: E6: única reputación de decisiones, acotada
A213: Costos De Producción | B213: M10 | C213: '=L10/L9 | D213: '=IFERROR(L10/L9,0) | E213: Proteger ausencia de personal
A214: Costos De Producción | B214: M5 | C214: '=K7+(F7+F13+F19)/100+4%*F21 | D214: '=MIN(1,K7+SUM(F7,F13:H13,F19:H19)/100+4%*F21) | E214: E7: bono por TODOS N3; SUPUESTO eficiencia máxima100%
A215: Costos De Producción | B215: E5 | C215: 6 | D215: '='CANTIDAD DE PRODUCCIÓN'!E5 | E215: E7: productividad canónica CANTIDAD
A216: Costos De Producción | B216: E6 | C216: 8 | D216: '='CANTIDAD DE PRODUCCIÓN'!E6 | E216: E7: productividad canónica CANTIDAD
A217: Costos De Producción | B217: E7 | C217: 12 | D217: '='CANTIDAD DE PRODUCCIÓN'!E7 | E217: E7: productividad canónica CANTIDAD
A218: Costos De Producción | B218: E11 | C218: 6 | D218: '='CANTIDAD DE PRODUCCIÓN'!E11 | E218: E7: productividad canónica CANTIDAD
A219: Costos De Producción | B219: E12 | C219: 8 | D219: '='CANTIDAD DE PRODUCCIÓN'!E12 | E219: E7: productividad canónica CANTIDAD
A220: Costos De Producción | B220: E13 | C220: 12 | D220: '='CANTIDAD DE PRODUCCIÓN'!E13 | E220: E7: productividad canónica CANTIDAD
A221: Costos De Producción | B221: E17 | C221: 6 | D221: '='CANTIDAD DE PRODUCCIÓN'!E17 | E221: E7: productividad canónica CANTIDAD
A222: Costos De Producción | B222: E18 | C222: 8 | D222: '='CANTIDAD DE PRODUCCIÓN'!E18 | E222: E7: productividad canónica CANTIDAD
...
